Workbook

Sheet Birbank Ştat
A1: New | B1: Cəmi | C1: İşçi sayı | D1: müvəqqəti | E1: vakant | F1: Non agile, agile, filial | G1: qeyd | H1: Vertical | I1: Pashapay | J1: Birmarket | K1: Paşa holding | L1: Future lab | M1: Cəmi keçid sayı
A2: Data governance ekspert mərkəzi | B2: 19 | C2: 20 | D2: 0 | E2: =B2-C2+D2 -> -1 | F2: Agile | G2: mənfilər-atrən səfərli HRBP məlumat verilib-04.10.2026 mail | H2: Ekosistem | I2: =COUNTIFS('baza-04.10.2026'!C:C,'Birbank Ştat'!A:A,'baza-04.10.2026'!I:I,"Bir Payment") -> 0 | J2: =COUNTIFS('baza-04.10.2026'!C:C,'Birbank Ştat'!A:A,'baza-04.10.2026'!I:I,"BirMarket") -> 5 | K2: =COUNTIFS('baza-04.10.2026'!C:C,'Birbank Ştat'!A:A,'baza-04.10.2026'!I:I,"Paşa Holding") -> 1 | L2: =COUNTIFS('baza-04.10.2026'!C:C,'Birbank Ştat'!A:A,'baza-04.10.2026'!I:I,"Future lab") -> 0 | M2: =Table2[[#This Row],[Pashapay]]+Table2[[#This Row],[Birmarket]]+Table2[[#This Row],[Paşa holding]]+Table2[[#This Row],[Future lab]] -> 6
A3: Ekvayrinq texnologiyaları sahəsi | B3: 3 | C3: 4 | D3: 0 | E3: =B3-C3+D3 -> -1 | F3: Agile | G3: mənfilər-atrən səfərli HRBP məlumat verilib-04.10.2026 mail | H3: Payment | I3: =COUNTIFS('baza-04.10.2026'!C:C,'Birbank Ştat'!A:A,'baza-04.10.2026'!I:I,"Bir Payment") -> 0 | J3: =COUNTIFS('baza-04.10.2026'!C:C,'Birbank Ştat'!A:A,'baza-04.10.2026'!I:I,"BirMarket") -> 0 | K3: =COUNTIFS('baza-04.10.2026'!C:C,'Birbank Ştat'!A:A,'baza-04.10.2026'!I:I,"Paşa Holding") -> 0 | L3: =COUNTIFS('baza-04.10.2026'!C:C,'Birbank Ştat'!A:A,'baza-04.10.2026'!I:I,"Future lab") -> 0 | M3: =Table2[[#This Row],[Pashapay]]+Table2[[#This Row],[Birmarket]]+Table2[[#This Row],[Paşa holding]]+Table2[[#This Row],[Future lab]] -> 0
A4: Maliyyə hesabatlığı və mühasibatlıq departamenti | B4: 38 | C4: 38 | D4: 0 | E4: =B4-C4+D4 -> 0 | F4: Non-Agile | H4: Fintech | I4: =COUNTIFS('baza-04.10.2026'!C:C,'Birbank Ştat'!A:A,'baza-04.10.2026'!I:I,"Bir Payment") -> 3 | J4: =COUNTIFS('baza-04.10.2026'!C:C,'Birbank Ştat'!A:A,'baza-04.10.2026'!I:I,"BirMarket") -> 1 | K4: =COUNTIFS('baza-04.10.2026'!C:C,'Birbank Ştat'!A:A,'baza-04.10.2026'!I:I,"Paşa Holding") -> 0 | L4: =COUNTIFS('baza-04.10.2026'!C:C,'Birbank Ştat'!A:A,'baza-04.10.2026'!I:I,"Future lab") -> 0 | M4: =Table2[[#This Row],[Pashapay]]+Table2[[#This Row],[Birmarket]]+Table2[[#This Row],[Paşa holding]]+Table2[[#This Row],[Future lab]] -> 4
A5: Komplayens departamenti | B5: 53 | C5: 54 | D5: 2 | E5: =B5-C5+D5 -> 1 | F5: Non-Agile | G5: 1 hüquqdan | H5: Fintech | I5: =COUNTIFS('baza-04.10.2026'!C:C,'Birbank Ştat'!A:A,'baza-04.10.2026'!I:I,"Bir Payment") -> 3 | J5: =COUNTIFS('baza-04.10.2026'!C:C,'Birbank Ştat'!A:A,'baza-04.10.2026'!I:I,"BirMarket") -> 1 | K5: =COUNTIFS('baza-04.10.2026'!C:C,'Birbank Ştat'!A:A,'baza-04.10.2026'!I:I,"Paşa Holding") -> 0 | L5: =COUNTIFS('baza-04.10.2026'!C:C,'Birbank Ştat'!A:A,'baza-04.10.2026'!I:I,"Future lab") -> 0 | M5: =Table2[[#This Row],[Pashapay]]+Table2[[#This Row],[Birmarket]]+Table2[[#This Row],[Paşa holding]]+Table2[[#This Row],[Future lab]] -> 4
A6: Kart biznesi ekspert mərkəzi | B6: 12 | C6: 12 | D6: 0 | E6: =B6-C6+D6 -> 0 | F6: Agile | H6: Payment | I6: =COUNTIFS('baza-04.10.2026'!C:C,'Birbank Ştat'!A:A,'baza-04.10.2026'!I:I,"Bir Payment") -> 0 | J6: =COUNTIFS('baza-04.10.2026'!C:C,'Birbank Ştat'!A:A,'baza-04.10.2026'!I:I,"BirMarket") -> 0 | K6: =COUNTIFS('baza-04.10.2026'!C:C,'Birbank Ştat'!A:A,'baza-04.10.2026'!I:I,"Paşa Holding") -> 0 | L6: =COUNTIFS('baza-04.10.2026'!C:C,'Birbank Ştat'!A:A,'baza-04.10.2026'!I:I,"Future lab") -> 0 | M6: =Table2[[#This Row],[Pashapay]]+Table2[[#This Row],[Birmarket]]+Table2[[#This Row],[Paşa holding]]+Table2[[#This Row],[Future lab]] -> 0
A7: Rəqəmsal həllər sahəsi | B7: 6 | C7: 6 | D7: 0 | E7: =B7-C7+D7 -> 0 | F7: Agile | H7: Fintech | I7: =COUNTIFS('baza-04.10.2026'!C:C,'Birbank Ştat'!A:A,'baza-04.10.2026'!I:I,"Bir Payment") -> 0 | J7: =COUNTIFS('baza-04.10.2026'!C:C,'Birbank Ştat'!A:A,'baza-04.10.2026'!I:I,"BirMarket") -> 0 | K7: =COUNTIFS('baza-04.10.2026'!C:C,'Birbank Ştat'!A:A,'baza-04.10.2026'!I:I,"Paşa Holding") -> 0 | L7: =COUNTIFS('baza-04.10.2026'!C:C,'Birbank Ştat'!A:A,'baza-04.10.2026'!I:I,"Future lab") -> 0 | M7: =Table2[[#This Row],[Pashapay]]+Table2[[#This Row],[Birmarket]]+Table2[[#This Row],[Paşa holding]]+Table2[[#This Row],[Future lab]] -> 0
A8: Beynəlxalq hesabatlıq və MİS departamenti | B8: 15 | C8: 14 | D8: 1 | E8: =B8-C8+D8 -> 2 | F8: Non-Agile | G8: 1 elave pashapaydan, 1 elave yaz İH-tamilla x | H8: Ekosistem | I8: =COUNTIFS('baza-04.10.2026'!C:C,'Birbank Ştat'!A:A,'baza-04.10.2026'!I:I,"Bir Payment") -> 0 | J8: =COUNTIFS('baza-04.10.2026'!C:C,'Birbank Ştat'!A:A,'baza-04.10.2026'!I:I,"BirMarket") -> 0 | K8: =COUNTIFS('baza-04.10.2026'!C:C,'Birbank Ştat'!A:A,'baza-04.10.2026'!I:I,"Paşa Holding") -> 0 | L8: =COUNTIFS('baza-04.10.2026'!C:C,'Birbank Ştat'!A:A,'baza-04.10.2026'!I:I,"Future lab") -> 0 | M8: =Table2[[#This Row],[Pashapay]]+Table2[[#This Row],[Birmarket]]+Table2[[#This Row],[Paşa holding]]+Table2[[#This Row],[Future lab]] -> 0
A9: FinTech arxitektura və İT idarəetmə prosesi | B9: 3 | C9: 3 | D9: 0 | E9: =B9-C9+D9 -> 0 | F9: Agile | H9: Fintech | I9: =COUNTIFS('baza-04.10.2026'!C:C,'Birbank Ştat'!A:A,'baza-04.10.2026'!I:I,"Bir Payment") -> 0 | J9: =COUNTIFS('baza-04.10.2026'!C:C,'Birbank Ştat'!A:A,'baza-04.10.2026'!I:I,"BirMarket") -> 0 | K9: =COUNTIFS('baza-04.10.2026'!C:C,'Birbank Ştat'!A:A,'baza-04.10.2026'!I:I,"Paşa Holding") -> 0 | L9: =COUNTIFS('baza-04.10.2026'!C:C,'Birbank Ştat'!A:A,'baza-04.10.2026'!I:I,"Future lab") -> 0 | M9: =Table2[[#This Row],[Pashapay]]+Table2[[#This Row],[Birmarket]]+Table2[[#This Row],[Paşa holding]]+Table2[[#This Row],[Future lab]] -> 0
A10: Prosessinq sahəsi | B10: 3 | C10: 3 | D10: 0 | E10: =B10-C10+D10 -> 0 | F10: Agile | H10: Payment | I10: =COUNTIFS('baza-04.10.2026'!C:C,'Birbank Ştat'!A:A,'baza-04.10.2026'!I:I,"Bir Payment") -> 0 | J10: =COUNTIFS('baza-04.10.2026'!C:C,'Birbank Ştat'!A:A,'baza-04.10.2026'!I:I,"BirMarket") -> 0 | K10: =COUNTIFS('baza-04.10.2026'!C:C,'Birbank Ştat'!A:A,'baza-04.10.2026'!I:I,"Paşa Holding") -> 0 | L10: =COUNTIFS('baza-04.10.2026'!C:C,'Birbank Ştat'!A:A,'baza-04.10.2026'!I:I,"Future lab") -> 0 | M10: =Table2[[#This Row],[Pashapay]]+Table2[[#This Row],[Birmarket]]+Table2[[#This Row],[Paşa holding]]+Table2[[#This Row],[Future lab]] -> 0
A11: FinTech platformalar sahəsi | B11: 3 | C11: 3 | D11: 0 | E11: =B11-C11+D11 -> 0 | F11: Agile | H11: Fintech | I11: =COUNTIFS('baza-04.10.2026'!C:C,'Birbank Ştat'!A:A,'baza-04.10.2026'!I:I,"Bir Payment") -> 0 | J11: =COUNTIFS('baza-04.10.2026'!C:C,'Birbank Ştat'!A:A,'baza-04.10.2026'!I:I,"BirMarket") -> 0 | K11: =COUNTIFS('baza-04.10.2026'!C:C,'Birbank Ştat'!A:A,'baza-04.10.2026'!I:I,"Paşa Holding") -> 0 | L11: =COUNTIFS('baza-04.10.2026'!C:C,'Birbank Ştat'!A:A,'baza-04.10.2026'!I:I,"Future lab") -> 0 | M11: =Table2[[#This Row],[Pashapay]]+Table2[[#This Row],[Birmarket]]+Table2[[#This Row],[Paşa holding]]+Table2[[#This Row],[Future lab]] -> 0
A12: Ödəniş və transferlər sahəsi | B12: 3 | C12: 3 | D12: 0 | E12: =B12-C12+D12 -> 0 | F12: Agile | H12: Payment | I12: =COUNTIFS('baza-04.10.2026'!C:C,'Birbank Ştat'!A:A,'baza-04.10.2026'!I:I,"Bir Payment") -> 0 | J12: =COUNTIFS('baza-04.10.2026'!C:C,'Birbank Ştat'!A:A,'baza-04.10.2026'!I:I,"BirMarket") -> 0 | K12: =COUNTIFS('baza-04.10.2026'!C:C,'Birbank Ştat'!A:A,'baza-04.10.2026'!I:I,"Paşa Holding") -> 0 | L12: =COUNTIFS('baza-04.10.2026'!C:C,'Birbank Ştat'!A:A,'baza-04.10.2026'!I:I,"Future lab") -> 0 | M12: =Table2[[#This Row],[Pashapay]]+Table2[[#This Row],[Birmarket]]+Table2[[#This Row],[Paşa holding]]+Table2[[#This Row],[Future lab]] -> 0
A13: Özünəxidmət terminalları sahəsi | B13: 2 | C13: 2 | D13: 0 | E13: =B13-C13+D13 -> 0 | F13: Agile | H13: Payment | I13: =COUNTIFS('baza-04.10.2026'!C:C,'Birbank Ştat'!A:A,'baza-04.10.2026'!I:I,"Bir Payment") -> 1 | J13: =COUNTIFS('baza-04.10.2026'!C:C,'Birbank Ştat'!A:A,'baza-04.10.2026'!I:I,"BirMarket") -> 0 | K13: =COUNTIFS('baza-04.10.2026'!C:C,'Birbank Ştat'!A:A,'baza-04.10.2026'!I:I,"Paşa Holding") -> 0 | L13: =COUNTIFS('baza-04.10.2026'!C:C,'Birbank Ştat'!A:A,'baza-04.10.2026'!I:I,"Future lab") -> 0 | M13: =Table2[[#This Row],[Pashapay]]+Table2[[#This Row],[Birmarket]]+Table2[[#This Row],[Paşa holding]]+Table2[[#This Row],[Future lab]] -> 1
A14: Kart klirinqi və hesablaşmalar şöbəsi | B14: 12 | C14: 11 | D14: 0 | E14: =B14-C14+D14 -> 1 | F14: Non-Agile | H14: Payment | I14: =COUNTIFS('baza-04.10.2026'!C:C,'Birbank Ştat'!A:A,'baza-04.10.2026'!I:I,"Bir Payment") -> 0 | J14: =COUNTIFS('baza-04.10.2026'!C:C,'Birbank Ştat'!A:A,'baza-04.10.2026'!I:I,"BirMarket") -> 0 | K14: =COUNTIFS('baza-04.10.2026'!C:C,'Birbank Ştat'!A:A,'baza-04.10.2026'!I:I,"Paşa Holding") -> 0 | L14: =COUNTIFS('baza-04.10.2026'!C:C,'Birbank Ştat'!A:A,'baza-04.10.2026'!I:I,"Future lab") -> 0 | M14: =Table2[[#This Row],[Pashapay]]+Table2[[#This Row],[Birmarket]]+Table2[[#This Row],[Paşa holding]]+Table2[[#This Row],[Future lab]] -> 0
A15: Ödəniş platformaları sahəsi | B15: 4 | C15: 4 | D15: 0 | E15: =B15-C15+D15 -> 0 | F15: Agile | H15: Payment | I15: =COUNTIFS('baza-04.10.2026'!C:C,'Birbank Ştat'!A:A,'baza-04.10.2026'!I:I,"Bir Payment") -> 0 | J15: =COUNTIFS('baza-04.10.2026'!C:C,'Birbank Ştat'!A:A,'baza-04.10.2026'!I:I,"BirMarket") -> 0 | K15: =COUNTIFS('baza-04.10.2026'!C:C,'Birbank Ştat'!A:A,'baza-04.10.2026'!I:I,"Paşa Holding") -> 0 | L15: =COUNTIFS('baza-04.10.2026'!C:C,'Birbank Ştat'!A:A,'baza-04.10.2026'!I:I,"Future lab") -> 0 | M15: =Table2[[#This Row],[Pashapay]]+Table2[[#This Row],[Birmarket]]+Table2[[#This Row],[Paşa holding]]+Table2[[#This Row],[Future lab]] -> 0
A16: Əməliyyatlar ofisi | B16: 1 | C16: 1 | D16: 0 | E16: =B16-C16+D16 -> 0 | F16: Non-Agile | H16: Fintech | I16: =COUNTIFS('baza-04.10.2026'!C:C,'Birbank Ştat'!A:A,'baza-04.10.2026'!I:I,"Bir Payment") -> 0 | J16: =COUNTIFS('baza-04.10.2026'!C:C,'Birbank Ştat'!A:A,'baza-04.10.2026'!I:I,"BirMarket") -> 0 | K16: =COUNTIFS('baza-04.10.2026'!C:C,'Birbank Ştat'!A:A,'baza-04.10.2026'!I:I,"Paşa Holding") -> 0 | L16: =COUNTIFS('baza-04.10.2026'!C:C,'Birbank Ştat'!A:A,'baza-04.10.2026'!I:I,"Future lab") -> 0 | M16: =Table2[[#This Row],[Pashapay]]+Table2[[#This Row],[Birmarket]]+Table2[[#This Row],[Paşa holding]]+Table2[[#This Row],[Future lab]] -> 0
A17: İnformasiya texnologiyaları idarəsi | B17: 2 | C17: 2 | D17: 0 | E17: =B17-C17+D17 -> 0 | F17: Agile | H17: Ekosistem | I17: =COUNTIFS('baza-04.10.2026'!C:C,'Birbank Ştat'!A:A,'baza-04.10.2026'!I:I,"Bir Payment") -> 0 | J17: =COUNTIFS('baza-04.10.2026'!C:C,'Birbank Ştat'!A:A,'baza-04.10.2026'!I:I,"BirMarket") -> 0 | K17: =COUNTIFS('baza-04.10.2026'!C:C,'Birbank Ştat'!A:A,'baza-04.10.2026'!I:I,"Paşa Holding") -> 0 | L17: =COUNTIFS('baza-04.10.2026'!C:C,'Birbank Ştat'!A:A,'baza-04.10.2026'!I:I,"Future lab") -> 0 | M17: =Table2[[#This Row],[Pashapay]]+Table2[[#This Row],[Birmarket]]+Table2[[#This Row],[Paşa holding]]+Table2[[#This Row],[Future lab]] -> 0
A18: Rəhbərlik | B18: 15 | C18: 15 | D18: 0 | E18: =B18-C18+D18 -> 0 | F18: Non-Agile | H18: Ekosistem | I18: =COUNTIFS('baza-04.10.2026'!C:C,'Birbank Ştat'!A:A,'baza-04.10.2026'!I:I,"Bir Payment") -> 1 | J18: =COUNTIFS('baza-04.10.2026'!C:C,'Birbank Ştat'!A:A,'baza-04.10.2026'!I:I,"BirMarket") -> 2 | K18: =COUNTIFS('baza-04.10.2026'!C:C,'Birbank Ştat'!A:A,'baza-04.10.2026'!I:I,"Paşa Holding") -> 0 | L18: =COUNTIFS('baza-04.10.2026'!C:C,'Birbank Ştat'!A:A,'baza-04.10.2026'!I:I,"Future lab") -> 0 | M18: =Table2[[#This Row],[Pashapay]]+Table2[[#This Row],[Birmarket]]+Table2[[#This Row],[Paşa holding]]+Table2[[#This Row],[Future lab]] -> 3
A19: Maliyyə risklərinin idarə edilməsi ofisi | B19: 1 | C19: 1 | D19: 0 | E19: =B19-C19+D19 -> 0 | F19: Non-Agile | H19: Fintech | I19: =COUNTIFS('baza-04.10.2026'!C:C,'Birbank Ştat'!A:A,'baza-04.10.2026'!I:I,"Bir Payment") -> 0 | J19: =COUNTIFS('baza-04.10.2026'!C:C,'Birbank Ştat'!A:A,'baza-04.10.2026'!I:I,"BirMarket") -> 0 | K19: =COUNTIFS('baza-04.10.2026'!C:C,'Birbank Ştat'!A:A,'baza-04.10.2026'!I:I,"Paşa Holding") -> 0 | L19: =COUNTIFS('baza-04.10.2026'!C:C,'Birbank Ştat'!A:A,'baza-04.10.2026'!I:I,"Future lab") -> 0 | M19: =Table2[[#This Row],[Pashapay]]+Table2[[#This Row],[Birmarket]]+Table2[[#This Row],[Paşa holding]]+Table2[[#This Row],[Future lab]] -> 0
A20: Strategiya idarəsi | B20: 1 | C20: 1 | D20: 0 | E20: =B20-C20+D20 -> 0 | F20: Non-Agile | H20: Ekosistem | I20: =COUNTIFS('baza-04.10.2026'!C:C,'Birbank Ştat'!A:A,'baza-04.10.2026'!I:I,"Bir Payment") -> 0 | J20: =COUNTIFS('baza-04.10.2026'!C:C,'Birbank Ştat'!A:A,'baza-04.10.2026'!I:I,"BirMarket") -> 0 | K20: =COUNTIFS('baza-04.10.2026'!C:C,'Birbank Ştat'!A:A,'baza-04.10.2026'!I:I,"Paşa Holding") -> 1 | L20: =COUNTIFS('baza-04.10.2026'!C:C,'Birbank Ştat'!A:A,'baza-04.10.2026'!I:I,"Future lab") -> 0 | M20: =Table2[[#This Row],[Pashapay]]+Table2[[#This Row],[Birmarket]]+Table2[[#This Row],[Paşa holding]]+Table2[[#This Row],[Future lab]] -> 1
... A24: Ödəniş texnologiyaları ofisi | B24: 1 | C24: 1 | D24: 0 | E24: =B24-C24+D24 -> 0 | F24: Agile | H24: Payment | I24: =COUNTIFS('baza-04.10.2026'!C:C,'Birbank Ştat'!A:A,'baza-04.10.2026'!I:I,"Bir Payment") -> 0 | J24: =COUNTIFS('baza-04.10.2026'!C:C,'Birbank Ştat'!A:A,'baza-04.10.2026'!I:I,"BirMarket") -> 0 | K24: =COUNTIFS('baza-04.10.2026'!C:C,'Birbank Ştat'!A:A,'baza-04.10.2026'!I:I,"Paşa Holding") -> 0 | L24: =COUNTIFS('baza-04.10.2026'!C:C,'Birbank Ştat'!A:A,'baza-04.10.2026'!I:I,"Future lab") -> 0 | M24: =Table2[[#This Row],[Pashapay]]+Table2[[#This Row],[Birmarket]]+Table2[[#This Row],[Paşa holding]]+Table2[[#This Row],[Future lab]] -> 0
A25: Analitika ekspert mərkəzi | B25: 2 | C25: 4 | D25: 0 | E25: 0 | F25: Agile | G25: köhnə strukturda qalan. 1-ini ilqar ocaqovda nəzərə almışam(əzizli yunis), 1 ni fintech analitika naildə, qaldı 2 ştat | H25: Payment | I25: =COUNTIFS('baza-04.10.2026'!C:C,'Birbank Ştat'!A:A,'baza-04.10.2026'!I:I,"Bir Payment") -> 0 | J25: =COUNTIFS('baza-04.10.2026'!C:C,'Birbank Ştat'!A:A,'baza-04.10.2026'!I:I,"BirMarket") -> 0 | K25: =COUNTIFS('baza-04.10.2026'!C:C,'Birbank Ştat'!A:A,'baza-04.10.2026'!I:I,"Paşa Holding") -> 0 | L25: =COUNTIFS('baza-04.10.2026'!C:C,'Birbank Ştat'!A:A,'baza-04.10.2026'!I:I,"Future lab") -> 0 | M25: =Table2[[#This Row],[Pashapay]]+Table2[[#This Row],[Birmarket]]+Table2[[#This Row],[Paşa holding]]+Table2[[#This Row],[Future lab]] -> 0
A26: Aİ və Data elmi ekspert mərkəzi | B26: 5 | C26: 5 | D26: 0 | E26: 0 | F26: Agile | G26: köhnə strukturda qalan | H26: Ekosistem | I26: =COUNTIFS('baza-04.10.2026'!C:C,'Birbank Ştat'!A:A,'baza-04.10.2026'!I:I,"Bir Payment") -> 0 | J26: =COUNTIFS('baza-04.10.2026'!C:C,'Birbank Ştat'!A:A,'baza-04.10.2026'!I:I,"BirMarket") -> 0 | K26: =COUNTIFS('baza-04.10.2026'!C:C,'Birbank Ştat'!A:A,'baza-04.10.2026'!I:I,"Paşa Holding") -> 0 | L26: =COUNTIFS('baza-04.10.2026'!C:C,'Birbank Ştat'!A:A,'baza-04.10.2026'!I:I,"Future lab") -> 0 | M26: =Table2[[#This Row],[Pashapay]]+Table2[[#This Row],[Birmarket]]+Table2[[#This Row],[Paşa holding]]+Table2[[#This Row],[Future lab]] -> 0
A27: Loyallıq məhsulları sahəsi | B27: 1 | C27: 1 | D27: 0 | E27: 0 | F27: Agile | G27: köhnə strukturda qalan | H27: Payment | I27: =COUNTIFS('baza-04.10.2026'!C:C,'Birbank Ştat'!A:A,'baza-04.10.2026'!I:I,"Bir Payment") -> 0 | J27: =COUNTIFS('baza-04.10.2026'!C:C,'Birbank Ştat'!A:A,'baza-04.10.2026'!I:I,"BirMarket") -> 0 | K27: =COUNTIFS('baza-04.10.2026'!C:C,'Birbank Ştat'!A:A,'baza-04.10.2026'!I:I,"Paşa Holding") -> 0 | L27: =COUNTIFS('baza-04.10.2026'!C:C,'Birbank Ştat'!A:A,'baza-04.10.2026'!I:I,"Future lab") -> 0 | M27: =Table2[[#This Row],[Pashapay]]+Table2[[#This Row],[Birmarket]]+Table2[[#This Row],[Paşa holding]]+Table2[[#This Row],[Future lab]] -> 0
A28: Data menecment ofisi | B28: 1 | C28: 0 | D28: 0 | E28: 0 | F28: Agile | G28: köhnə strukturda qalan-Shabanlı Seymur-ştatı hara verilməli | H28: Ekosistem | I28: =COUNTIFS('baza-04.10.2026'!C:C,'Birbank Ştat'!A:A,'baza-04.10.2026'!I:I,"Bir Payment") -> 0 | J28: =COUNTIFS('baza-04.10.2026'!C:C,'Birbank Ştat'!A:A,'baza-04.10.2026'!I:I,"BirMarket") -> 0 | K28: =COUNTIFS('baza-04.10.2026'!C:C,'Birbank Ştat'!A:A,'baza-04.10.2026'!I:I,"Paşa Holding") -> 0 | L28: =COUNTIFS('baza-04.10.2026'!C:C,'Birbank Ştat'!A:A,'baza-04.10.2026'!I:I,"Future lab") -> 0 | M28: =Table2[[#This Row],[Pashapay]]+Table2[[#This Row],[Birmarket]]+Table2[[#This Row],[Paşa holding]]+Table2[[#This Row],[Future lab]] -> 0
A29: Birbonus sahəsi | B29: 5 | C29: 4 | D29: 0 | E29: =B29-C29+D29 -> 1 | F29: Agile | H29: Payment | I29: =COUNTIFS('baza-04.10.2026'!C:C,'Birbank Ştat'!A:A,'baza-04.10.2026'!I:I,"Bir Payment") -> 0 | J29: =COUNTIFS('baza-04.10.2026'!C:C,'Birbank Ştat'!A:A,'baza-04.10.2026'!I:I,"BirMarket") -> 0 | K29: =COUNTIFS('baza-04.10.2026'!C:C,'Birbank Ştat'!A:A,'baza-04.10.2026'!I:I,"Paşa Holding") -> 0 | L29: =COUNTIFS('baza-04.10.2026'!C:C,'Birbank Ştat'!A:A,'baza-04.10.2026'!I:I,"Future lab") -> 0 | M29: =Table2[[#This Row],[Pashapay]]+Table2[[#This Row],[Birmarket]]+Table2[[#This Row],[Paşa holding]]+Table2[[#This Row],[Future lab]] -> 0
A30: Arxitektura ekspert mərkəzi | B30: 8 | C30: 7 | D30: 0 | E30: =B30-C30+D30 -> 1 | F30: Agile | H30: Ekosistem | I30: =COUNTIFS('baza-04.10.2026'!C:C,'Birbank Ştat'!A:A,'baza-04.10.2026'!I:I,"Bir Payment") -> 0 | J30: =COUNTIFS('baza-04.10.2026'!C:C,'Birbank Ştat'!A:A,'baza-04.10.2026'!I:I,"BirMarket") -> 0 | K30: =COUNTIFS('baza-04.10.2026'!C:C,'Birbank Ştat'!A:A,'baza-04.10.2026'!I:I,"Paşa Holding") -> 0 | L30: =COUNTIFS('baza-04.10.2026'!C:C,'Birbank Ştat'!A:A,'baza-04.10.2026'!I:I,"Future lab") -> 0 | M30: =Table2[[#This Row],[Pashapay]]+Table2[[#This Row],[Birmarket]]+Table2[[#This Row],[Paşa holding]]+Table2[[#This Row],[Future lab]] -> 0
A31: Məhsulların rəsmiləşdirilməsi sahəsi | B31: 5 | C31: 4 | D31: 0 | E31: =B31-C31+D31 -> 1 | F31: Agile | H31: Fintech | I31: =COUNTIFS('baza-04.10.2026'!C:C,'Birbank Ştat'!A:A,'baza-04.10.2026'!I:I,"Bir Payment") -> 0 | J31: =COUNTIFS('baza-04.10.2026'!C:C,'Birbank Ştat'!A:A,'baza-04.10.2026'!I:I,"BirMarket") -> 0 | K31: =COUNTIFS('baza-04.10.2026'!C:C,'Birbank Ştat'!A:A,'baza-04.10.2026'!I:I,"Paşa Holding") -> 0 | L31: =COUNTIFS('baza-04.10.2026'!C:C,'Birbank Ştat'!A:A,'baza-04.10.2026'!I:I,"Future lab") -> 0 | M31: =Table2[[#This Row],[Pashapay]]+Table2[[#This Row],[Birmarket]]+Table2[[#This Row],[Paşa holding]]+Table2[[#This Row],[Future lab]] -> 0
A32: İT proseslərinin idarə edilməsi funksional sahəsi | B32: 5 | C32: 4 | D32: 0 | E32: =B32-C32+D32 -> 1 | F32: Agile | H32: Ekosistem | I32: =COUNTIFS('baza-04.10.2026'!C:C,'Birbank Ştat'!A:A,'baza-04.10.2026'!I:I,"Bir Payment") -> 0 | J32: =COUNTIFS('baza-04.10.2026'!C:C,'Birbank Ştat'!A:A,'baza-04.10.2026'!I:I,"BirMarket") -> 0 | K32: =COUNTIFS('baza-04.10.2026'!C:C,'Birbank Ştat'!A:A,'baza-04.10.2026'!I:I,"Paşa Holding") -> 0 | L32: =COUNTIFS('baza-04.10.2026'!C:C,'Birbank Ştat'!A:A,'baza-04.10.2026'!I:I,"Future lab") -> 0 | M32: =Table2[[#This Row],[Pashapay]]+Table2[[#This Row],[Birmarket]]+Table2[[#This Row],[Paşa holding]]+Table2[[#This Row],[Future lab]] -> 0
A33: Ekosistem platforma və İD sahəsi | B33: 5 | C33: 4 | D33: 0 | E33: =B33-C33+D33 -> 1 | F33: Agile | H33: Ekosistem | I33: =COUNTIFS('baza-04.10.2026'!C:C,'Birbank Ştat'!A:A,'baza-04.10.2026'!I:I,"Bir Payment") -> 0 | J33: =COUNTIFS('baza-04.10.2026'!C:C,'Birbank Ştat'!A:A,'baza-04.10.2026'!I:I,"BirMarket") -> 0 | K33: =COUNTIFS('baza-04.10.2026'!C:C,'Birbank Ştat'!A:A,'baza-04.10.2026'!I:I,"Paşa Holding") -> 0 | L33: =COUNTIFS('baza-04.10.2026'!C:C,'Birbank Ştat'!A:A,'baza-04.10.2026'!I:I,"Future lab") -> 0 | M33: =Table2[[#This Row],[Pashapay]]+Table2[[#This Row],[Birmarket]]+Table2[[#This Row],[Paşa holding]]+Table2[[#This Row],[Future lab]] -> 0
A34: Xəzinədarlıq departamenti | B34: 21 | C34: 20 | D34: 0 | E34: =B34-C34+D34 -> 1 | F34: Non-Agile | H34: Fintech | I34: =COUNTIFS('baza-04.10.2026'!C:C,'Birbank Ştat'!A:A,'baza-04.10.2026'!I:I,"Bir Payment") -> 0 | J34: =COUNTIFS('baza-04.10.2026'!C:C,'Birbank Ştat'!A:A,'baza-04.10.2026'!I:I,"BirMarket") -> 0 | K34: =COUNTIFS('baza-04.10.2026'!C:C,'Birbank Ştat'!A:A,'baza-04.10.2026'!I:I,"Paşa Holding") -> 0 | L34: =COUNTIFS('baza-04.10.2026'!C:C,'Birbank Ştat'!A:A,'baza-04.10.2026'!I:I,"Future lab") -> 0 | M34: =Table2[[#This Row],[Pashapay]]+Table2[[#This Row],[Birmarket]]+Table2[[#This Row],[Paşa holding]]+Table2[[#This Row],[Future lab]] -> 0
A35: Kreditlərin hüquqi təqibi departamenti | B35: 58 | C35: 57 | D35: 0 | E35: =B35-C35+D35 -> 1 | F35: Non-Agile | H35: Fintech | I35: =COUNTIFS('baza-04.10.2026'!C:C,'Birbank Ştat'!A:A,'baza-04.10.2026'!I:I,"Bir Payment") -> 0 | J35: =COUNTIFS('baza-04.10.2026'!C:C,'Birbank Ştat'!A:A,'baza-04.10.2026'!I:I,"BirMarket") -> 0 | K35: =COUNTIFS('baza-04.10.2026'!C:C,'Birbank Ştat'!A:A,'baza-04.10.2026'!I:I,"Paşa Holding") -> 0 | L35: =COUNTIFS('baza-04.10.2026'!C:C,'Birbank Ştat'!A:A,'baza-04.10.2026'!I:I,"Future lab") -> 0 | M35: =Table2[[#This Row],[Pashapay]]+Table2[[#This Row],[Birmarket]]+Table2[[#This Row],[Paşa holding]]+Table2[[#This Row],[Future lab]] -> 0
A36: Model risklərinin idarəedilməsi ekspert mərkəzi | B36: 12 | C36: 11 | D36: 0 | E36: =B36-C36+D36 -> 1 | F36: Agile | H36: Ekosistem | I36: =COUNTIFS('baza-04.10.2026'!C:C,'Birbank Ştat'!A:A,'baza-04.10.2026'!I:I,"Bir Payment") -> 0 | J36: =COUNTIFS('baza-04.10.2026'!C:C,'Birbank Ştat'!A:A,'baza-04.10.2026'!I:I,"BirMarket") -> 0 | K36: =COUNTIFS('baza-04.10.2026'!C:C,'Birbank Ştat'!A:A,'baza-04.10.2026'!I:I,"Paşa Holding") -> 0 | L36: =COUNTIFS('baza-04.10.2026'!C:C,'Birbank Ştat'!A:A,'baza-04.10.2026'!I:I,"Future lab") -> 0 | M36: =Table2[[#This Row],[Pashapay]]+Table2[[#This Row],[Birmarket]]+Table2[[#This Row],[Paşa holding]]+Table2[[#This Row],[Future lab]] -> 0
A37: VİP müştərilərlə iş şöbəsi | B37: 9 | C37: 8 | D37: 0 | E37: =B37-C37+D37 -> 1 | F37: Non-Agile | H37: Fintech | I37: =COUNTIFS('baza-04.10.2026'!C:C,'Birbank Ştat'!A:A,'baza-04.10.2026'!I:I,"Bir Payment") -> 0 | J37: =COUNTIFS('baza-04.10.2026'!C:C,'Birbank Ştat'!A:A,'baza-04.10.2026'!I:I,"BirMarket") -> 0 | K37: =COUNTIFS('baza-04.10.2026'!C:C,'Birbank Ştat'!A:A,'baza-04.10.2026'!I:I,"Paşa Holding") -> 0 | L37: =COUNTIFS('baza-04.10.2026'!C:C,'Birbank Ştat'!A:A,'baza-04.10.2026'!I:I,"Future lab") -> 0 | M37: =Table2[[#This Row],[Pashapay]]+Table2[[#This Row],[Birmarket]]+Table2[[#This Row],[Paşa holding]]+Table2[[#This Row],[Future lab]] -> 0
A38: Aİ governance ekspert mərkəzi | B38: 15 | C38: 16 | D38: 3 | E38: =B38-C38+D38 -> 2 | F38: Agile | G38: 1 dene müşteri tecrubesinden | H38: Ekosistem | I38: =COUNTIFS('baza-04.10.2026'!C:C,'Birbank Ştat'!A:A,'baza-04.10.2026'!I:I,"Bir Payment") -> 0 | J38: =COUNTIFS('baza-04.10.2026'!C:C,'Birbank Ştat'!A:A,'baza-04.10.2026'!I:I,"BirMarket") -> 0 | K38: =COUNTIFS('baza-04.10.2026'!C:C,'Birbank Ştat'!A:A,'baza-04.10.2026'!I:I,"Paşa Holding") -> 0 | L38: =COUNTIFS('baza-04.10.2026'!C:C,'Birbank Ştat'!A:A,'baza-04.10.2026'!I:I,"Future lab") -> 1 | M38: =Table2[[#This Row],[Pashapay]]+Table2[[#This Row],[Birmarket]]+Table2[[#This Row],[Paşa holding]]+Table2[[#This Row],[Future lab]] -> 1
A39: Mikro biznes departamenti | B39: 19 | C39: 18 | D39: 0 | E39: =B39-C39+D39 -> 1 | F39: Non-Agile | H39: Fintech | I39: =COUNTIFS('baza-04.10.2026'!C:C,'Birbank Ştat'!A:A,'baza-04.10.2026'!I:I,"Bir Payment") -> 0 | J39: =COUNTIFS('baza-04.10.2026'!C:C,'Birbank Ştat'!A:A,'baza-04.10.2026'!I:I,"BirMarket") -> 0 | K39: =COUNTIFS('baza-04.10.2026'!C:C,'Birbank Ştat'!A:A,'baza-04.10.2026'!I:I,"Paşa Holding") -> 0 | L39: =COUNTIFS('baza-04.10.2026'!C:C,'Birbank Ştat'!A:A,'baza-04.10.2026'!I:I,"Future lab") -> 0 | M39: =Table2[[#This Row],[Pashapay]]+Table2[[#This Row],[Birmarket]]+Table2[[#This Row],[Paşa holding]]+Table2[[#This Row],[Future lab]] -> 0
A40: BirApp texnologiyası sahəsi | B40: 3 | C40: 2 | D40: 0 | E40: =B40-C40+D40 -> 1 | F40: Agile | H40: Ekosistem | I40: =COUNTIFS('baza-04.10.2026'!C:C,'Birbank Ştat'!A:A,'baza-04.10.2026'!I:I,"Bir Payment") -> 0 | J40: =COUNTIFS('baza-04.10.2026'!C:C,'Birbank Ştat'!A:A,'baza-04.10.2026'!I:I,"BirMarket") -> 0 | K40: =COUNTIFS('baza-04.10.2026'!C:C,'Birbank Ştat'!A:A,'baza-04.10.2026'!I:I,"Paşa Holding") -> 0 | L40: =COUNTIFS('baza-04.10.2026'!C:C,'Birbank Ştat'!A:A,'baza-04.10.2026'!I:I,"Future lab") -> 0 | M40: =Table2[[#This Row],[Pashapay]]+Table2[[#This Row],[Birmarket]]+Table2[[#This Row],[Paşa holding]]+Table2[[#This Row],[Future lab]] -> 0
A41: BirApp sahəsi | B41: 7 | C41: 6 | D41: 0 | E41: =B41-C41+D41 -> 1 | F41: Agile | H41: Ekosistem | I41: =COUNTIFS('baza-04.10.2026'!C:C,'Birbank Ştat'!A:A,'baza-04.10.2026'!I:I,"Bir Payment") -> 1 | J41: =COUNTIFS('baza-04.10.2026'!C:C,'Birbank Ştat'!A:A,'baza-04.10.2026'!I:I,"BirMarket") -> 0 | K41: =COUNTIFS('baza-04.10.2026'!C:C,'Birbank Ştat'!A:A,'baza-04.10.2026'!I:I,"Paşa Holding") -> 0 | L41: =COUNTIFS('baza-04.10.2026'!C:C,'Birbank Ştat'!A:A,'baza-04.10.2026'!I:I,"Future lab") -> 0 | M41: =Table2[[#This Row],[Pashapay]]+Table2[[#This Row],[Birmarket]]+Table2[[#This Row],[Paşa holding]]+Table2[[#This Row],[Future lab]] -> 1
A42: Məhsul və marketinq idarəsi | B42: 2 | C42: 1 | D42: 0 | E42: =B42-C42+D42 -> 1 | F42: Agile | H42: Ekosistem | I42: =COUNTIFS('baza-04.10.2026'!C:C,'Birbank Ştat'!A:A,'baza-04.10.2026'!I:I,"Bir Payment") -> 0 | J42: =COUNTIFS('baza-04.10.2026'!C:C,'Birbank Ştat'!A:A,'baza-04.10.2026'!I:I,"BirMarket") -> 0 | K42: =COUNTIFS('baza-04.10.2026'!C:C,'Birbank Ştat'!A:A,'baza-04.10.2026'!I:I,"Paşa Holding") -> 0 | L42: =COUNTIFS('baza-04.10.2026'!C:C,'Birbank Ştat'!A:A,'baza-04.10.2026'!I:I,"Future lab") -> 0 | M42: =Table2[[#This Row],[Pashapay]]+Table2[[#This Row],[Birmarket]]+Table2[[#This Row],[Paşa holding]]+Table2[[#This Row],[Future lab]] -> 0
A43: Pərakəndə məhsullar ofisi | B43: 1 | C43: 0 | D43: 0 | E43: =B43-C43+D43 -> 1 | F43: Agile | H43: Fintech | I43: =COUNTIFS('baza-04.10.2026'!C:C,'Birbank Ştat'!A:A,'baza-04.10.2026'!I:I,"Bir Payment") -> 0 | J43: =COUNTIFS('baza-04.10.2026'!C:C,'Birbank Ştat'!A:A,'baza-04.10.2026'!I:I,"BirMarket") -> 0 | K43: =COUNTIFS('baza-04.10.2026'!C:C,'Birbank Ştat'!A:A,'baza-04.10.2026'!I:I,"Paşa Holding") -> 0 | L43: =COUNTIFS('baza-04.10.2026'!C:C,'Birbank Ştat'!A:A,'baza-04.10.2026'!I:I,"Future lab") -> 0 | M43: =Table2[[#This Row],[Pashapay]]+Table2[[#This Row],[Birmarket]]+Table2[[#This Row],[Paşa holding]]+Table2[[#This Row],[Future lab]] -> 0
A44: Ödəniş əməliyyatları ofisi | B44: 2 | C44: 1 | D44: 0 | E44: =B44-C44+D44 -> 1 | F44: Agile | H44: Payment | I44: =COUNTIFS('baza-04.10.2026'!C:C,'Birbank Ştat'!A:A,'baza-04.10.2026'!I:I,"Bir Payment") -> 0 | J44: =COUNTIFS('baza-04.10.2026'!C:C,'Birbank Ştat'!A:A,'baza-04.10.2026'!I:I,"BirMarket") -> 0 | K44: =COUNTIFS('baza-04.10.2026'!C:C,'Birbank Ştat'!A:A,'baza-04.10.2026'!I:I,"Paşa Holding") -> 0 | L44: =COUNTIFS('baza-04.10.2026'!C:C,'Birbank Ştat'!A:A,'baza-04.10.2026'!I:I,"Future lab") -> 0 | M44: =Table2[[#This Row],[Pashapay]]+Table2[[#This Row],[Birmarket]]+Table2[[#This Row],[Paşa holding]]+Table2[[#This Row],[Future lab]] -> 0
A45: Müştəri təcrübəsi ekspert mərkəzi | B45: 26 | C45: 25 | D45: 0 | E45: =B45-C45+D45 -> 1 | F45: Agile | G45: 1 i getdi ai governance | H45: Ekosistem | I45: =COUNTIFS('baza-04.10.2026'!C:C,'Birbank Ştat'!A:A,'baza-04.10.2026'!I:I,"Bir Payment") -> 7 | J45: =COUNTIFS('baza-04.10.2026'!C:C,'Birbank Ştat'!A:A,'baza-04.10.2026'!I:I,"BirMarket") -> 2 | K45: =COUNTIFS('baza-04.10.2026'!C:C,'Birbank Ştat'!A:A,'baza-04.10.2026'!I:I,"Paşa Holding") -> 0 | L45: =COUNTIFS('baza-04.10.2026'!C:C,'Birbank Ştat'!A:A,'baza-04.10.2026'!I:I,"Future lab") -> 2 | M45: =Table2[[#This Row],[Pashapay]]+Table2[[#This Row],[Birmarket]]+Table2[[#This Row],[Paşa holding]]+Table2[[#This Row],[Future lab]] -> 11
A46: FinTech TechOps funksional sahəsi | B46: 16 | C46: 14 | D46: 0 | E46: =B46-C46+D46 -> 2 | F46: Agile | H46: Fintech | I46: =COUNTIFS('baza-04.10.2026'!C:C,'Birbank Ştat'!A:A,'baza-04.10.2026'!I:I,"Bir Payment") -> 0 | J46: =COUNTIFS('baza-04.10.2026'!C:C,'Birbank Ştat'!A:A,'baza-04.10.2026'!I:I,"BirMarket") -> 0 | K46: =COUNTIFS('baza-04.10.2026'!C:C,'Birbank Ştat'!A:A,'baza-04.10.2026'!I:I,"Paşa Holding") -> 0 | L46: =COUNTIFS('baza-04.10.2026'!C:C,'Birbank Ştat'!A:A,'baza-04.10.2026'!I:I,"Future lab") -> 0 | M46: =Table2[[#This Row],[Pashapay]]+Table2[[#This Row],[Birmarket]]+Table2[[#This Row],[Paşa holding]]+Table2[[#This Row],[Future lab]] -> 0
A47: Pərakəndə biznes platformaları sahəsi | B47: 7 | C47: 5 | D47: 0 | E47: =B47-C47+D47 -> 2 | F47: Agile | H47: Fintech | I47: =COUNTIFS('baza-04.10.2026'!C:C,'Birbank Ştat'!A:A,'baza-04.10.2026'!I:I,"Bir Payment") -> 0 | J47: =COUNTIFS('baza-04.10.2026'!C:C,'Birbank Ştat'!A:A,'baza-04.10.2026'!I:I,"BirMarket") -> 0 | K47: =COUNTIFS('baza-04.10.2026'!C:C,'Birbank Ştat'!A:A,'baza-04.10.2026'!I:I,"Paşa Holding") -> 0 | L47: =COUNTIFS('baza-04.10.2026'!C:C,'Birbank Ştat'!A:A,'baza-04.10.2026'!I:I,"Future lab") -> 0 | M47: =Table2[[#This Row],[Pashapay]]+Table2[[#This Row],[Birmarket]]+Table2[[#This Row],[Paşa holding]]+Table2[[#This Row],[Future lab]] -> 0
A48: Ekosistemin inkişafı və analitikası departamenti | B48: 10 | C48: 9 | D48: 0 | E48: =B48-C48+D48 -> 1 | F48: Non-Agile | G48: 1i verildi strategiya | H48: Ekosistem | I48: =COUNTIFS('baza-04.10.2026'!C:C,'Birbank Ştat'!A:A,'baza-04.10.2026'!I:I,"Bir Payment") -> 1 | J48: =COUNTIFS('baza-04.10.2026'!C:C,'Birbank Ştat'!A:A,'baza-04.10.2026'!I:I,"BirMarket") -> 0 | K48: =COUNTIFS('baza-04.10.2026'!C:C,'Birbank Ştat'!A:A,'baza-04.10.2026'!I:I,"Paşa Holding") -> 8 | L48: =COUNTIFS('baza-04.10.2026'!C:C,'Birbank Ştat'!A:A,'baza-04.10.2026'!I:I,"Future lab") -> 0 | M48: =Table2[[#This Row],[Pashapay]]+Table2[[#This Row],[Birmarket]]+Table2[[#This Row],[Paşa holding]]+Table2[[#This Row],[Future lab]] -> 9
A49: Ödəniş biznesinin arxitektura və İT idarəetmə prosesi | B49: 5 | C49: 4 | D49: 0 | E49: =B49-C49+D49 -> 1 | F49: Agile | H49: Payment | I49: =COUNTIFS('baza-04.10.2026'!C:C,'Birbank Ştat'!A:A,'baza-04.10.2026'!I:I,"Bir Payment") -> 0 | J49: =COUNTIFS('baza-04.10.2026'!C:C,'Birbank Ştat'!A:A,'baza-04.10.2026'!I:I,"BirMarket") -> 0 | K49: =COUNTIFS('baza-04.10.2026'!C:C,'Birbank Ştat'!A:A,'baza-04.10.2026'!I:I,"Paşa Holding") -> 0 | L49: =COUNTIFS('baza-04.10.2026'!C:C,'Birbank Ştat'!A:A,'baza-04.10.2026'!I:I,"Future lab") -> 0 | M49: =Table2[[#This Row],[Pashapay]]+Table2[[#This Row],[Birmarket]]+Table2[[#This Row],[Paşa holding]]+Table2[[#This Row],[Future lab]] -> 0
A50: İstedadların idarə edilməsi departamenti | B50: 23 | C50: 22 | D50: 1 | E50: =B50-C50+D50 -> 2 | F50: Non-Agile | H50: Fintech | I50: =COUNTIFS('baza-04.10.2026'!C:C,'Birbank Ştat'!A:A,'baza-04.10.2026'!I:I,"Bir Payment") -> 0 | J50: =COUNTIFS('baza-04.10.2026'!C:C,'Birbank Ştat'!A:A,'baza-04.10.2026'!I:I,"BirMarket") -> 1 | K50: =COUNTIFS('baza-04.10.2026'!C:C,'Birbank Ştat'!A:A,'baza-04.10.2026'!I:I,"Paşa Holding") -> 0 | L50: =COUNTIFS('baza-04.10.2026'!C:C,'Birbank Ştat'!A:A,'baza-04.10.2026'!I:I,"Future lab") -> 0 | M50: =Table2[[#This Row],[Pashapay]]+Table2[[#This Row],[Birmarket]]+Table2[[#This Row],[Paşa holding]]+Table2[[#This Row],[Future lab]] -> 1
A51: Data mühəndisliyi və texnologiyaları ekspert mərkəzi | B51: 27 | C51: 23 | D51: 0 | E51: =B51-C51+D51 -> 4 | F51: Agile | H51: Ekosistem | I51: =COUNTIFS('baza-04.10.2026'!C:C,'Birbank Ştat'!A:A,'baza-04.10.2026'!I:I,"Bir Payment") -> 4 | J51: =COUNTIFS('baza-04.10.2026'!C:C,'Birbank Ştat'!A:A,'baza-04.10.2026'!I:I,"BirMarket") -> 0 | K51: =COUNTIFS('baza-04.10.2026'!C:C,'Birbank Ştat'!A:A,'baza-04.10.2026'!I:I,"Paşa Holding") -> 0 | L51: =COUNTIFS('baza-04.10.2026'!C:C,'Birbank Ştat'!A:A,'baza-04.10.2026'!I:I,"Future lab") -> 0 | M51: =Table2[[#This Row],[Pashapay]]+Table2[[#This Row],[Birmarket]]+Table2[[#This Row],[Paşa holding]]+Table2[[#This Row],[Future lab]] -> 4
A52: Müştəri dəyərləri sahəsi | B52: 7 | C52: 5 | D52: 0 | E52: =B52-C52+D52 -> 2 | F52: Agile | H52: Fintech | I52: =COUNTIFS('baza-04.10.2026'!C:C,'Birbank Ştat'!A:A,'baza-04.10.2026'!I:I,"Bir Payment") -> 0 | J52: =COUNTIFS('baza-04.10.2026'!C:C,'Birbank Ştat'!A:A,'baza-04.10.2026'!I:I,"BirMarket") -> 0 | K52: =COUNTIFS('baza-04.10.2026'!C:C,'Birbank Ştat'!A:A,'baza-04.10.2026'!I:I,"Paşa Holding") -> 0 | L52: =COUNTIFS('baza-04.10.2026'!C:C,'Birbank Ştat'!A:A,'baza-04.10.2026'!I:I,"Future lab") -> 0 | M52: =Table2[[#This Row],[Pashapay]]+Table2[[#This Row],[Birmarket]]+Table2[[#This Row],[Paşa holding]]+Table2[[#This Row],[Future lab]] -> 0
A53: Kart məhsulları sahəsi | B53: 6 | C53: 5 | D53: 0 | E53: =B53-C53+D53 -> 1 | F53: Agile | G53: 1 i Ödəniş biznesi müh İTBA verildi | H53: Payment | I53: =COUNTIFS('baza-04.10.2026'!C:C,'Birbank Ştat'!A:A,'baza-04.10.2026'!I:I,"Bir Payment") -> 0 | J53: =COUNTIFS('baza-04.10.2026'!C:C,'Birbank Ştat'!A:A,'baza-04.10.2026'!I:I,"BirMarket") -> 0 | K53: =COUNTIFS('baza-04.10.2026'!C:C,'Birbank Ştat'!A:A,'baza-04.10.2026'!I:I,"Paşa Holding") -> 0 | L53: =COUNTIFS('baza-04.10.2026'!C:C,'Birbank Ştat'!A:A,'baza-04.10.2026'!I:I,"Future lab") -> 0 | M53: =Table2[[#This Row],[Pashapay]]+Table2[[#This Row],[Birmarket]]+Table2[[#This Row],[Paşa holding]]+Table2[[#This Row],[Future lab]] -> 0
A54: Audit komitəsi | B54: 2 | C54: 0 | D54: 0 | E54: =B54-C54+D54 -> 2 | F54: Non-Agile | H54: Fintech | I54: =COUNTIFS('baza-04.10.2026'!C:C,'Birbank Ştat'!A:A,'baza-04.10.2026'!I:I,"Bir Payment") -> 0 | J54: =COUNTIFS('baza-04.10.2026'!C:C,'Birbank Ştat'!A:A,'baza-04.10.2026'!I:I,"BirMarket") -> 0 | K54: =COUNTIFS('baza-04.10.2026'!C:C,'Birbank Ştat'!A:A,'baza-04.10.2026'!I:I,"Paşa Holding") -> 0 | L54: =COUNTIFS('baza-04.10.2026'!C:C,'Birbank Ştat'!A:A,'baza-04.10.2026'!I:I,"Future lab") -> 0 | M54: =Table2[[#This Row],[Pashapay]]+Table2[[#This Row],[Birmarket]]+Table2[[#This Row],[Paşa holding]]+Table2[[#This Row],[Future lab]] -> 0
A55: Müşahidə şurası | B55: 4 | C55: 2 | D55: 0 | E55: =B55-C55+D55 -> 2 | F55: Non-Agile | H55: Ekosistem | I55: =COUNTIFS('baza-04.10.2026'!C:C,'Birbank Ştat'!A:A,'baza-04.10.2026'!I:I,"Bir Payment") -> 0 | J55: =COUNTIFS('baza-04.10.2026'!C:C,'Birbank Ştat'!A:A,'baza-04.10.2026'!I:I,"BirMarket") -> 0 | K55: =COUNTIFS('baza-04.10.2026'!C:C,'Birbank Ştat'!A:A,'baza-04.10.2026'!I:I,"Paşa Holding") -> 0 | L55: =COUNTIFS('baza-04.10.2026'!C:C,'Birbank Ştat'!A:A,'baza-04.10.2026'!I:I,"Future lab") -> 0 | M55: =Table2[[#This Row],[Pashapay]]+Table2[[#This Row],[Birmarket]]+Table2[[#This Row],[Paşa holding]]+Table2[[#This Row],[Future lab]] -> 0
A56: Kredit portfelinə nəzarət departamenti | B56: 34 | C56: 31 | D56: 0 | E56: =B56-C56+D56 -> 3 | F56: Agile | H56: Fintech | I56: =COUNTIFS('baza-04.10.2026'!C:C,'Birbank Ştat'!A:A,'baza-04.10.2026'!I:I,"Bir Payment") -> 0 | J56: =COUNTIFS('baza-04.10.2026'!C:C,'Birbank Ştat'!A:A,'baza-04.10.2026'!I:I,"BirMarket") -> 0 | K56: =COUNTIFS('baza-04.10.2026'!C:C,'Birbank Ştat'!A:A,'baza-04.10.2026'!I:I,"Paşa Holding") -> 0 | L56: =COUNTIFS('baza-04.10.2026'!C:C,'Birbank Ştat'!A:A,'baza-04.10.2026'!I:I,"Future lab") -> 0 | M56: =Table2[[#This Row],[Pashapay]]+Table2[[#This Row],[Birmarket]]+Table2[[#This Row],[Paşa holding]]+Table2[[#This Row],[Future lab]] -> 0
A57: Korporativ satışlar departamenti | B57: 29 | C57: 26 | D57: 0 | E57: =B57-C57+D57 -> 3 | F57: Non-Agile | H57: Fintech | I57: =COUNTIFS('baza-04.10.2026'!C:C,'Birbank Ştat'!A:A,'baza-04.10.2026'!I:I,"Bir Payment") -> 0 | J57: =COUNTIFS('baza-04.10.2026'!C:C,'Birbank Ştat'!A:A,'baza-04.10.2026'!I:I,"BirMarket") -> 0 | K57: =COUNTIFS('baza-04.10.2026'!C:C,'Birbank Ştat'!A:A,'baza-04.10.2026'!I:I,"Paşa Holding") -> 0 | L57: =COUNTIFS('baza-04.10.2026'!C:C,'Birbank Ştat'!A:A,'baza-04.10.2026'!I:I,"Future lab") -> 0 | M57: =Table2[[#This Row],[Pashapay]]+Table2[[#This Row],[Birmarket]]+Table2[[#This Row],[Paşa holding]]+Table2[[#This Row],[Future lab]] -> 0
A58: Maliyyə menecmenti departamenti | B58: 26 | C58: 25 | D58: 0 | E58: =B58-C58+D58 -> 1 | F58: Non-Agile | G58: 2si strategiyaya | H58: Fintech | I58: =COUNTIFS('baza-04.10.2026'!C:C,'Birbank Ştat'!A:A,'baza-04.10.2026'!I:I,"Bir Payment") -> 0 | J58: =COUNTIFS('baza-04.10.2026'!C:C,'Birbank Ştat'!A:A,'baza-04.10.2026'!I:I,"BirMarket") -> 0 | K58: =COUNTIFS('baza-04.10.2026'!C:C,'Birbank Ştat'!A:A,'baza-04.10.2026'!I:I,"Paşa Holding") -> 0 | L58: =COUNTIFS('baza-04.10.2026'!C:C,'Birbank Ştat'!A:A,'baza-04.10.2026'!I:I,"Future lab") -> 0 | M58: =Table2[[#This Row],[Pashapay]]+Table2[[#This Row],[Birmarket]]+Table2[[#This Row],[Paşa holding]]+Table2[[#This Row],[Future lab]] -> 0
A59: Təşkilati və qeyri-maliyyə risklərinin idarə edilməsi departamenti | B59: 57 | C59: 54 | D59: 0 | E59: =B59-C59+D59 -> 3 | F59: Agile | H59: Ekosistem | I59: =COUNTIFS('baza-04.10.2026'!C:C,'Birbank Ştat'!A:A,'baza-04.10.2026'!I:I,"Bir Payment") -> 2 | J59: =COUNTIFS('baza-04.10.2026'!C:C,'Birbank Ştat'!A:A,'baza-04.10.2026'!I:I,"BirMarket") -> 0 | K59: =COUNTIFS('baza-04.10.2026'!C:C,'Birbank Ştat'!A:A,'baza-04.10.2026'!I:I,"Paşa Holding") -> 0 | L59: =COUNTIFS('baza-04.10.2026'!C:C,'Birbank Ştat'!A:A,'baza-04.10.2026'!I:I,"Future lab") -> 0 | M59: =Table2[[#This Row],[Pashapay]]+Table2[[#This Row],[Birmarket]]+Table2[[#This Row],[Paşa holding]]+Table2[[#This Row],[Future lab]] -> 2
A60: Nağd pulların idarə edilməsi departamenti | B60: 41 | C60: 38 | D60: 0 | E60: =B60-C60+D60 -> 3 | G60: 1 çıxdı ödəniş biz analitika və ai ya | H60: Payment | I60: =COUNTIFS('baza-04.10.2026'!C:C,'Birbank Ştat'!A:A,'baza-04.10.2026'!I:I,"Bir Payment") -> 1 | J60: =COUNTIFS('baza-04.10.2026'!C:C,'Birbank Ştat'!A:A,'baza-04.10.2026'!I:I,"BirMarket") -> 0 | K60: =COUNTIFS('baza-04.10.2026'!C:C,'Birbank Ştat'!A:A,'baza-04.10.2026'!I:I,"Paşa Holding") -> 0 | L60: =COUNTIFS('baza-04.10.2026'!C:C,'Birbank Ştat'!A:A,'baza-04.10.2026'!I:I,"Future lab") -> 0 | M60: =Table2[[#This Row],[Pashapay]]+Table2[[#This Row],[Birmarket]]+Table2[[#This Row],[Paşa holding]]+Table2[[#This Row],[Future lab]] -> 1
A61: Texniki dəstək departamenti | B61: 59 | C61: 58 | D61: 0 | E61: =B61-C61+D61 -> 1 | F61: Non-Agile | G61: 2 sini ləğv | H61: Payment | I61: =COUNTIFS('baza-04.10.2026'!C:C,'Birbank Ştat'!A:A,'baza-04.10.2026'!I:I,"Bir Payment") -> 31 | J61: =COUNTIFS('baza-04.10.2026'!C:C,'Birbank Ştat'!A:A,'baza-04.10.2026'!I:I,"BirMarket") -> 0 | K61: =COUNTIFS('baza-04.10.2026'!C:C,'Birbank Ştat'!A:A,'baza-04.10.2026'!I:I,"Paşa Holding") -> 0 | L61: =COUNTIFS('baza-04.10.2026'!C:C,'Birbank Ştat'!A:A,'baza-04.10.2026'!I:I,"Future lab") -> 0 | M61: =Table2[[#This Row],[Pashapay]]+Table2[[#This Row],[Birmarket]]+Table2[[#This Row],[Paşa holding]]+Table2[[#This Row],[Future lab]] -> 31
A62: Agile və məhsul ekspert mərkəzi | B62: 25 | C62: 25 | D62: 1 | E62: =B62-C62+D62 -> 1 | F62: Agile | G62: Fintech agile və ödəniş biznesi agile birgə nəzərə alınıb | H62: Ekosistem | I62: 3 | J62: =COUNTIFS('baza-04.10.2026'!C:C,'Birbank Ştat'!A:A,'baza-04.10.2026'!I:I,"BirMarket") -> 0 | K62: =COUNTIFS('baza-04.10.2026'!C:C,'Birbank Ştat'!A:A,'baza-04.10.2026'!I:I,"Paşa Holding") -> 0 | L62: =COUNTIFS('baza-04.10.2026'!C:C,'Birbank Ştat'!A:A,'baza-04.10.2026'!I:I,"Future lab") -> 0 | M62: =Table2[[#This Row],[Pashapay]]+Table2[[#This Row],[Birmarket]]+Table2[[#This Row],[Paşa holding]]+Table2[[#This Row],[Future lab]] -> 3
A63: Korporativ inkişaf və investor əlaqələri departamenti | B63: 6 | C63: 2 | D63: 0 | E63: =B63-C63+D63 -> 4 | F63: Non-Agile | H63: Ekosistem | I63: =COUNTIFS('baza-04.10.2026'!C:C,'Birbank Ştat'!A:A,'baza-04.10.2026'!I:I,"Bir Payment") -> 0 | J63: =COUNTIFS('baza-04.10.2026'!C:C,'Birbank Ştat'!A:A,'baza-04.10.2026'!I:I,"BirMarket") -> 0 | K63: =COUNTIFS('baza-04.10.2026'!C:C,'Birbank Ştat'!A:A,'baza-04.10.2026'!I:I,"Paşa Holding") -> 0 | L63: =COUNTIFS('baza-04.10.2026'!C:C,'Birbank Ştat'!A:A,'baza-04.10.2026'!I:I,"Future lab") -> 0 | M63: =Table2[[#This Row],[Pashapay]]+Table2[[#This Row],[Birmarket]]+Table2[[#This Row],[Paşa holding]]+Table2[[#This Row],[Future lab]] -> 0
A64: Təşkilati inkişaf və HR texnologiyaları departamenti | B64: 83 | C64: 80 | D64: 3 | E64: =B64-C64+D64 -> 6 | F64: Non-Agile | H64: Ekosistem | I64: =COUNTIFS('baza-04.10.2026'!C:C,'Birbank Ştat'!A:A,'baza-04.10.2026'!I:I,"Bir Payment") -> 9 | J64: =COUNTIFS('baza-04.10.2026'!C:C,'Birbank Ştat'!A:A,'baza-04.10.2026'!I:I,"BirMarket") -> 12 | K64: =COUNTIFS('baza-04.10.2026'!C:C,'Birbank Ştat'!A:A,'baza-04.10.2026'!I:I,"Paşa Holding") -> 2 | L64: =COUNTIFS('baza-04.10.2026'!C:C,'Birbank Ştat'!A:A,'baza-04.10.2026'!I:I,"Future lab") -> 1 | M64: =Table2[[#This Row],[Pashapay]]+Table2[[#This Row],[Birmarket]]+Table2[[#This Row],[Paşa holding]]+Table2[[#This Row],[Future lab]] -> 24
A65: Maliyyə risklərinin idarə edilməsi departamenti | B65: 42 | C65: 37 | D65: 1 | E65: =B65-C65+D65 -> 6 | F65: Non-Agile | G65: 1 elave kredit ilkin teqibinden | H65: Fintech | I65: =COUNTIFS('baza-04.10.2026'!C:C,'Birbank Ştat'!A:A,'baza-04.10.2026'!I:I,"Bir Payment") -> 1 | J65: =COUNTIFS('baza-04.10.2026'!C:C,'Birbank Ştat'!A:A,'baza-04.10.2026'!I:I,"BirMarket") -> 0 | K65: =COUNTIFS('baza-04.10.2026'!C:C,'Birbank Ştat'!A:A,'baza-04.10.2026'!I:I,"Paşa Holding") -> 0 | L65: =COUNTIFS('baza-04.10.2026'!C:C,'Birbank Ştat'!A:A,'baza-04.10.2026'!I:I,"Future lab") -> 0 | M65: =Table2[[#This Row],[Pashapay]]+Table2[[#This Row],[Birmarket]]+Table2[[#This Row],[Paşa holding]]+Table2[[#This Row],[Future lab]] -> 1
A66: Birbank biznes sahəsi | B66: =12-1 -> 11 | C66: 8 | D66: 0 | E66: =B66-C66+D66 -> 3 | F66: Agile | G66: 1i bdd yə po | H66: Fintech | I66: =COUNTIFS('baza-04.10.2026'!C:C,'Birbank Ştat'!A:A,'baza-04.10.2026'!I:I,"Bir Payment") -> 0 | J66: =COUNTIFS('baza-04.10.2026'!C:C,'Birbank Ştat'!A:A,'baza-04.10.2026'!I:I,"BirMarket") -> 0 | K66: =COUNTIFS('baza-04.10.2026'!C:C,'Birbank Ştat'!A:A,'baza-04.10.2026'!I:I,"Paşa Holding") -> 0 | L66: =COUNTIFS('baza-04.10.2026'!C:C,'Birbank Ştat'!A:A,'baza-04.10.2026'!I:I,"Future lab") -> 0 | M66: =Table2[[#This Row],[Pashapay]]+Table2[[#This Row],[Birmarket]]+Table2[[#This Row],[Paşa holding]]+Table2[[#This Row],[Future lab]] -> 0
A67: Risk texnologiyaları sahəsi | B67: 9 | C67: 5 | D67: 0 | E67: =B67-C67+D67 -> 4 | F67: Agile | H67: Fintech | I67: =COUNTIFS('baza-04.10.2026'!C:C,'Birbank Ştat'!A:A,'baza-04.10.2026'!I:I,"Bir Payment") -> 0 | J67: =COUNTIFS('baza-04.10.2026'!C:C,'Birbank Ştat'!A:A,'baza-04.10.2026'!I:I,"BirMarket") -> 0 | K67: =COUNTIFS('baza-04.10.2026'!C:C,'Birbank Ştat'!A:A,'baza-04.10.2026'!I:I,"Paşa Holding") -> 0 | L67: =COUNTIFS('baza-04.10.2026'!C:C,'Birbank Ştat'!A:A,'baza-04.10.2026'!I:I,"Future lab") -> 0 | M67: =Table2[[#This Row],[Pashapay]]+Table2[[#This Row],[Birmarket]]+Table2[[#This Row],[Paşa holding]]+Table2[[#This Row],[Future lab]] -> 0
A68: Korporativ katiblik şöbəsi | B68: 35.5 | C68: 30 | D68: 0 | E68: =B68-C68+D68 -> 5.5 | F68: Non-Agile | G68: 2i ixtisar | H68: Fintech | I68: 1 | J68: 1 | K68: =COUNTIFS('baza-04.10.2026'!C:C,'Birbank Ştat'!A:A,'baza-04.10.2026'!I:I,"Paşa Holding") -> 0 | L68: 1 | M68: =Table2[[#This Row],[Pashapay]]+Table2[[#This Row],[Birmarket]]+Table2[[#This Row],[Paşa holding]]+Table2[[#This Row],[Future lab]] -> 3
A69: Təhlükəsizlik departamenti | B69: =79-1 -> 78 | C69: 75 | D69: 0 | E69: =B69-C69+D69 -> 3 | F69: Non-Agile | G69: 1 i rəqəmsal dələduzluğa verildi | H69: Fintech | I69: =COUNTIFS('baza-04.10.2026'!C:C,'Birbank Ştat'!A:A,'baza-04.10.2026'!I:I,"Bir Payment") -> 3 | J69: =COUNTIFS('baza-04.10.2026'!C:C,'Birbank Ştat'!A:A,'baza-04.10.2026'!I:I,"BirMarket") -> 4 | K69: =COUNTIFS('baza-04.10.2026'!C:C,'Birbank Ştat'!A:A,'baza-04.10.2026'!I:I,"Paşa Holding") -> 0 | L69: =COUNTIFS('baza-04.10.2026'!C:C,'Birbank Ştat'!A:A,'baza-04.10.2026'!I:I,"Future lab") -> 0 | M69: =Table2[[#This Row],[Pashapay]]+Table2[[#This Row],[Birmarket]]+Table2[[#This Row],[Paşa holding]]+Table2[[#This Row],[Future lab]] -> 7
A70: Strategiya və layihələrin idarə edilməsi departamenti | B70: 31 | C70: 23 | D70: 0 | E70: =B70-C70+D70 -> 8 | F70: Non-Agile | G70: 3 əlavə | H70: Ekosistem | I70: =COUNTIFS('baza-04.10.2026'!C:C,'Birbank Ştat'!A:A,'baza-04.10.2026'!I:I,"Bir Payment") -> 3 | J70: =COUNTIFS('baza-04.10.2026'!C:C,'Birbank Ştat'!A:A,'baza-04.10.2026'!I:I,"BirMarket") -> 0 | K70: =COUNTIFS('baza-04.10.2026'!C:C,'Birbank Ştat'!A:A,'baza-04.10.2026'!I:I,"Paşa Holding") -> 4 | L70: =COUNTIFS('baza-04.10.2026'!C:C,'Birbank Ştat'!A:A,'baza-04.10.2026'!I:I,"Future lab") -> 0 | M70: =Table2[[#This Row],[Pashapay]]+Table2[[#This Row],[Birmarket]]+Table2[[#This Row],[Paşa holding]]+Table2[[#This Row],[Future lab]] -> 7
A71: Kiçik və orta sahibkarlarla iş departamenti | B71: 94 | C71: 88 | D71: 0 | E71: =B71-C71+D71 -> 6 | F71: Non-Agile | H71: Fintech | I71: =COUNTIFS('baza-04.10.2026'!C:C,'Birbank Ştat'!A:A,'baza-04.10.2026'!I:I,"Bir Payment") -> 0 | J71: =COUNTIFS('baza-04.10.2026'!C:C,'Birbank Ştat'!A:A,'baza-04.10.2026'!I:I,"BirMarket") -> 0 | K71: =COUNTIFS('baza-04.10.2026'!C:C,'Birbank Ştat'!A:A,'baza-04.10.2026'!I:I,"Paşa Holding") -> 0 | L71: =COUNTIFS('baza-04.10.2026'!C:C,'Birbank Ştat'!A:A,'baza-04.10.2026'!I:I,"Future lab") -> 0 | M71: =Table2[[#This Row],[Pashapay]]+Table2[[#This Row],[Birmarket]]+Table2[[#This Row],[Paşa holding]]+Table2[[#This Row],[Future lab]] -> 0
A72: Marketinq ekspert mərkəzi | B72: 93 | C72: 86 | D72: 0 | E72: =B72-C72+D72 -> 7 | F72: Agile | G72: 91 idi, 1 elave yazdiq-amma daxilden elemek lazimdi cavid m kurasyasindan tamilla x hell edecek, 1 əlavə aygün x ok Holdinq məsələsi | H72: Ekosistem | I72: =COUNTIFS('baza-04.10.2026'!C:C,'Birbank Ştat'!A:A,'baza-04.10.2026'!I:I,"Bir Payment") -> 22 | J72: =COUNTIFS('baza-04.10.2026'!C:C,'Birbank Ştat'!A:A,'baza-04.10.2026'!I:I,"BirMarket") -> 13 | K72: =COUNTIFS('baza-04.10.2026'!C:C,'Birbank Ştat'!A:A,'baza-04.10.2026'!I:I,"Paşa Holding") -> 0 | L72: =COUNTIFS('baza-04.10.2026'!C:C,'Birbank Ştat'!A:A,'baza-04.10.2026'!I:I,"Future lab") -> 0 | M72: =Table2[[#This Row],[Pashapay]]+Table2[[#This Row],[Birmarket]]+Table2[[#This Row],[Paşa holding]]+Table2[[#This Row],[Future lab]] -> 35
A73: Ödəniş biznesinin TechOps funksional sahəsi | B73: =22+1 -> 23 | C73: 17 | D73: 0 | E73: =B73-C73+D73 -> 6 | F73: Agile | G73: 1i pashapaydan verildi bura | H73: Payment | I73: =COUNTIFS('baza-04.10.2026'!C:C,'Birbank Ştat'!A:A,'baza-04.10.2026'!I:I,"Bir Payment") -> 4 | J73: =COUNTIFS('baza-04.10.2026'!C:C,'Birbank Ştat'!A:A,'baza-04.10.2026'!I:I,"BirMarket") -> 0 | K73: =COUNTIFS('baza-04.10.2026'!C:C,'Birbank Ştat'!A:A,'baza-04.10.2026'!I:I,"Paşa Holding") -> 0 | L73: =COUNTIFS('baza-04.10.2026'!C:C,'Birbank Ştat'!A:A,'baza-04.10.2026'!I:I,"Future lab") -> 0 | M73: =Table2[[#This Row],[Pashapay]]+Table2[[#This Row],[Birmarket]]+Table2[[#This Row],[Paşa holding]]+Table2[[#This Row],[Future lab]] -> 4
A74: Hüquq departamenti | B74: 70.5 | C74: 67 | D74: 2 | E74: =B74-C74+D74 -> 5.5 | F74: Non-Agile | G74: 1 komplayense verildi | H74: Fintech | I74: =COUNTIFS('baza-04.10.2026'!C:C,'Birbank Ştat'!A:A,'baza-04.10.2026'!I:I,"Bir Payment") -> 7 | J74: =COUNTIFS('baza-04.10.2026'!C:C,'Birbank Ştat'!A:A,'baza-04.10.2026'!I:I,"BirMarket") -> 8 | K74: =COUNTIFS('baza-04.10.2026'!C:C,'Birbank Ştat'!A:A,'baza-04.10.2026'!I:I,"Paşa Holding") -> 0 | L74: =COUNTIFS('baza-04.10.2026'!C:C,'Birbank Ştat'!A:A,'baza-04.10.2026'!I:I,"Future lab") -> 0 | M74: =Table2[[#This Row],[Pashapay]]+Table2[[#This Row],[Birmarket]]+Table2[[#This Row],[Paşa holding]]+Table2[[#This Row],[Future lab]] -> 15
A75: Dizayn ekspert mərkəzi | B75: 63 | C75: 57 | D75: 0 | E75: =B75-C75+D75 -> 6 | F75: Agile | H75: Ekosistem | I75: =COUNTIFS('baza-04.10.2026'!C:C,'Birbank Ştat'!A:A,'baza-04.10.2026'!I:I,"Bir Payment") -> 10 | J75: =COUNTIFS('baza-04.10.2026'!C:C,'Birbank Ştat'!A:A,'baza-04.10.2026'!I:I,"BirMarket") -> 6 | K75: =COUNTIFS('baza-04.10.2026'!C:C,'Birbank Ştat'!A:A,'baza-04.10.2026'!I:I,"Paşa Holding") -> 0 | L75: =COUNTIFS('baza-04.10.2026'!C:C,'Birbank Ştat'!A:A,'baza-04.10.2026'!I:I,"Future lab") -> 3 | M75: =Table2[[#This Row],[Pashapay]]+Table2[[#This Row],[Birmarket]]+Table2[[#This Row],[Paşa holding]]+Table2[[#This Row],[Future lab]] -> 19
A76: İnzibati idarəetmə departamenti | B76: 162 | C76: 158 | D76: 2 | E76: =B76-C76+D76 -> 6 | F76: Non-Agile | H76: Fintech | I76: =COUNTIFS('baza-04.10.2026'!C:C,'Birbank Ştat'!A:A,'baza-04.10.2026'!I:I,"Bir Payment") -> 16 | J76: =COUNTIFS('baza-04.10.2026'!C:C,'Birbank Ştat'!A:A,'baza-04.10.2026'!I:I,"BirMarket") -> 2 | K76: =COUNTIFS('baza-04.10.2026'!C:C,'Birbank Ştat'!A:A,'baza-04.10.2026'!I:I,"Paşa Holding") -> 0 | L76: =COUNTIFS('baza-04.10.2026'!C:C,'Birbank Ştat'!A:A,'baza-04.10.2026'!I:I,"Future lab") -> 0 | M76: =Table2[[#This Row],[Pashapay]]+Table2[[#This Row],[Birmarket]]+Table2[[#This Row],[Paşa holding]]+Table2[[#This Row],[Future lab]] -> 18
A77: Rəqəmsal dələduzluğa qarşı mübarizə departamenti | B77: =22+1 -> 23 | C77: 16 | D77: 0 | E77: =B77-C77+D77 -> 7 | F77: Agile | G77: 1 i təhlükəsizlikdən | H77: Payment | I77: =COUNTIFS('baza-04.10.2026'!C:C,'Birbank Ştat'!A:A,'baza-04.10.2026'!I:I,"Bir Payment") -> 2 | J77: =COUNTIFS('baza-04.10.2026'!C:C,'Birbank Ştat'!A:A,'baza-04.10.2026'!I:I,"BirMarket") -> 0 | K77: =COUNTIFS('baza-04.10.2026'!C:C,'Birbank Ştat'!A:A,'baza-04.10.2026'!I:I,"Paşa Holding") -> 0 | L77: =COUNTIFS('baza-04.10.2026'!C:C,'Birbank Ştat'!A:A,'baza-04.10.2026'!I:I,"Future lab") -> 0 | M77: =Table2[[#This Row],[Pashapay]]+Table2[[#This Row],[Birmarket]]+Table2[[#This Row],[Paşa holding]]+Table2[[#This Row],[Future lab]] -> 2
A78: Biznesə dəstək departamenti | B78: =116+1 -> 117 | C78: 108 | D78: 0 | E78: =B78-C78+D78 -> 9 | F78: Non-Agile | G78: 1- i birbank biznesdən | H78: Fintech | I78: =COUNTIFS('baza-04.10.2026'!C:C,'Birbank Ştat'!A:A,'baza-04.10.2026'!I:I,"Bir Payment") -> 0 | J78: =COUNTIFS('baza-04.10.2026'!C:C,'Birbank Ştat'!A:A,'baza-04.10.2026'!I:I,"BirMarket") -> 0 | K78: =COUNTIFS('baza-04.10.2026'!C:C,'Birbank Ştat'!A:A,'baza-04.10.2026'!I:I,"Paşa Holding") -> 0 | L78: =COUNTIFS('baza-04.10.2026'!C:C,'Birbank Ştat'!A:A,'baza-04.10.2026'!I:I,"Future lab") -> 0 | M78: =Table2[[#This Row],[Pashapay]]+Table2[[#This Row],[Birmarket]]+Table2[[#This Row],[Paşa holding]]+Table2[[#This Row],[Future lab]] -> 0
A79: Ödəniş biznesinin Analitika və Aİ ekspert mərkəzi | B79: 50 | C79: 40 | D79: 0 | E79: =B79-C79+D79 -> 10 | F79: Agile | G79: 3 əlavə, 1 əlavə nağd pull id ed, 1 pashapay | H79: Payment | I79: =COUNTIFS('baza-04.10.2026'!C:C,'Birbank Ştat'!A:A,'baza-04.10.2026'!I:I,"Bir Payment") -> 10 | J79: =COUNTIFS('baza-04.10.2026'!C:C,'Birbank Ştat'!A:A,'baza-04.10.2026'!I:I,"BirMarket") -> 0 | K79: =COUNTIFS('baza-04.10.2026'!C:C,'Birbank Ştat'!A:A,'baza-04.10.2026'!I:I,"Paşa Holding") -> 0 | L79: =COUNTIFS('baza-04.10.2026'!C:C,'Birbank Ştat'!A:A,'baza-04.10.2026'!I:I,"Future lab") -> 0 | M79: =Table2[[#This Row],[Pashapay]]+Table2[[#This Row],[Birmarket]]+Table2[[#This Row],[Paşa holding]]+Table2[[#This Row],[Future lab]] -> 10
A80: Kassa və inkassasiya prosesləri departamenti | B80: 456 | C80: 442 | D80: 0 | E80: =B80-C80+D80 -> 14 | F80: Non-Agile | G80: 211 keçid, +3 pashapaydan | H80: Payment | I80: =COUNTIFS('baza-04.10.2026'!C:C,'Birbank Ştat'!A:A,'baza-04.10.2026'!I:I,"Bir Payment") -> 211 | J80: =COUNTIFS('baza-04.10.2026'!C:C,'Birbank Ştat'!A:A,'baza-04.10.2026'!I:I,"BirMarket") -> 0 | K80: =COUNTIFS('baza-04.10.2026'!C:C,'Birbank Ştat'!A:A,'baza-04.10.2026'!I:I,"Paşa Holding") -> 0 | L80: =COUNTIFS('baza-04.10.2026'!C:C,'Birbank Ştat'!A:A,'baza-04.10.2026'!I:I,"Future lab") -> 0 | M80: =Table2[[#This Row],[Pashapay]]+Table2[[#This Row],[Birmarket]]+Table2[[#This Row],[Paşa holding]]+Table2[[#This Row],[Future lab]] -> 211
A81: İnformasiya təhlükəsizliyi departamenti | B81: 70 | C81: 62 | D81: 0 | E81: =B81-C81+D81 -> 8 | F81: Non-Agile | H81: Ekosistem | I81: =COUNTIFS('baza-04.10.2026'!C:C,'Birbank Ştat'!A:A,'baza-04.10.2026'!I:I,"Bir Payment") -> 5 | J81: =COUNTIFS('baza-04.10.2026'!C:C,'Birbank Ştat'!A:A,'baza-04.10.2026'!I:I,"BirMarket") -> 1 | K81: =COUNTIFS('baza-04.10.2026'!C:C,'Birbank Ştat'!A:A,'baza-04.10.2026'!I:I,"Paşa Holding") -> 0 | L81: =COUNTIFS('baza-04.10.2026'!C:C,'Birbank Ştat'!A:A,'baza-04.10.2026'!I:I,"Future lab") -> 0 | M81: =Table2[[#This Row],[Pashapay]]+Table2[[#This Row],[Birmarket]]+Table2[[#This Row],[Paşa holding]]+Table2[[#This Row],[Future lab]] -> 6
A82: Daxili audit departamenti | B82: 55 | C82: 42 | D82: 0 | E82: =B82-C82+D82 -> 13 | F82: Non-Agile | H82: Fintech | I82: =COUNTIFS('baza-04.10.2026'!C:C,'Birbank Ştat'!A:A,'baza-04.10.2026'!I:I,"Bir Payment") -> 0 | J82: =COUNTIFS('baza-04.10.2026'!C:C,'Birbank Ştat'!A:A,'baza-04.10.2026'!I:I,"BirMarket") -> 0 | K82: =COUNTIFS('baza-04.10.2026'!C:C,'Birbank Ştat'!A:A,'baza-04.10.2026'!I:I,"Paşa Holding") -> 0 | L82: =COUNTIFS('baza-04.10.2026'!C:C,'Birbank Ştat'!A:A,'baza-04.10.2026'!I:I,"Future lab") -> 0 | M82: =Table2[[#This Row],[Pashapay]]+Table2[[#This Row],[Birmarket]]+Table2[[#This Row],[Paşa holding]]+Table2[[#This Row],[Future lab]] -> 0
A83: Xidmət keyfiyyətinin idarə edilməsi departamenti | B83: 152 | C83: 153 | D83: 8 | E83: =B83-C83+D83 -> 7 | F83: Non-Agile | H83: Fintech | I83: =COUNTIFS('baza-04.10.2026'!C:C,'Birbank Ştat'!A:A,'baza-04.10.2026'!I:I,"Bir Payment") -> 1 | J83: =COUNTIFS('baza-04.10.2026'!C:C,'Birbank Ştat'!A:A,'baza-04.10.2026'!I:I,"BirMarket") -> 0 | K83: =COUNTIFS('baza-04.10.2026'!C:C,'Birbank Ştat'!A:A,'baza-04.10.2026'!I:I,"Paşa Holding") -> 0 | L83: =COUNTIFS('baza-04.10.2026'!C:C,'Birbank Ştat'!A:A,'baza-04.10.2026'!I:I,"Future lab") -> 0 | M83: =Table2[[#This Row],[Pashapay]]+Table2[[#This Row],[Birmarket]]+Table2[[#This Row],[Paşa holding]]+Table2[[#This Row],[Future lab]] -> 1
A84: İT infrastruktur departamenti | B84: 99 | C84: 89 | D84: 0 | E84: =B84-C84+D84 -> 10 | F84: Agile | H84: Ekosistem | I84: =COUNTIFS('baza-04.10.2026'!C:C,'Birbank Ştat'!A:A,'baza-04.10.2026'!I:I,"Bir Payment") -> 4 | J84: =COUNTIFS('baza-04.10.2026'!C:C,'Birbank Ştat'!A:A,'baza-04.10.2026'!I:I,"BirMarket") -> 1 | K84: =COUNTIFS('baza-04.10.2026'!C:C,'Birbank Ştat'!A:A,'baza-04.10.2026'!I:I,"Paşa Holding") -> 0 | L84: =COUNTIFS('baza-04.10.2026'!C:C,'Birbank Ştat'!A:A,'baza-04.10.2026'!I:I,"Future lab") -> 0 | M84: =Table2[[#This Row],[Pashapay]]+Table2[[#This Row],[Birmarket]]+Table2[[#This Row],[Paşa holding]]+Table2[[#This Row],[Future lab]] -> 5
A85: Biznes sahələrinin inkişafı və partnyor şəbəkəsi departamenti | B85: 99 | C85: 84 | D85: 0 | E85: =B85-C85+D85 -> 15 | F85: Non-Agile | H85: Payment | I85: =COUNTIFS('baza-04.10.2026'!C:C,'Birbank Ştat'!A:A,'baza-04.10.2026'!I:I,"Bir Payment") -> 24 | J85: =COUNTIFS('baza-04.10.2026'!C:C,'Birbank Ştat'!A:A,'baza-04.10.2026'!I:I,"BirMarket") -> 1 | K85: =COUNTIFS('baza-04.10.2026'!C:C,'Birbank Ştat'!A:A,'baza-04.10.2026'!I:I,"Paşa Holding") -> 1 | L85: =COUNTIFS('baza-04.10.2026'!C:C,'Birbank Ştat'!A:A,'baza-04.10.2026'!I:I,"Future lab") -> 0 | M85: =Table2[[#This Row],[Pashapay]]+Table2[[#This Row],[Birmarket]]+Table2[[#This Row],[Paşa holding]]+Table2[[#This Row],[Future lab]] -> 26
A86: FinTech Analitika və Aİ ekspert mərkəzi | B86: 155 | C86: 139 | D86: 2 | E86: =B86-C86+D86 -> 18 | F86: Agile | G86: 1 vüsal şükürov ştatı | H86: Fintech | I86: =COUNTIFS('baza-04.10.2026'!C:C,'Birbank Ştat'!A:A,'baza-04.10.2026'!I:I,"Bir Payment") -> 0 | J86: =COUNTIFS('baza-04.10.2026'!C:C,'Birbank Ştat'!A:A,'baza-04.10.2026'!I:I,"BirMarket") -> 0 | K86: =COUNTIFS('baza-04.10.2026'!C:C,'Birbank Ştat'!A:A,'baza-04.10.2026'!I:I,"Paşa Holding") -> 1 | L86: =COUNTIFS('baza-04.10.2026'!C:C,'Birbank Ştat'!A:A,'baza-04.10.2026'!I:I,"Future lab") -> 0 | M86: =Table2[[#This Row],[Pashapay]]+Table2[[#This Row],[Birmarket]]+Table2[[#This Row],[Paşa holding]]+Table2[[#This Row],[Future lab]] -> 1
A87: Kredit risklərinin təhlili departamenti | B87: 116 | C87: 111 | D87: 0 | E87: =B87-C87+D87 -> 5 | F87: Non-Agile | H87: Fintech | I87: =COUNTIFS('baza-04.10.2026'!C:C,'Birbank Ştat'!A:A,'baza-04.10.2026'!I:I,"Bir Payment") -> 0 | J87: =COUNTIFS('baza-04.10.2026'!C:C,'Birbank Ştat'!A:A,'baza-04.10.2026'!I:I,"BirMarket") -> 0 | K87: =COUNTIFS('baza-04.10.2026'!C:C,'Birbank Ştat'!A:A,'baza-04.10.2026'!I:I,"Paşa Holding") -> 0 | L87: =COUNTIFS('baza-04.10.2026'!C:C,'Birbank Ştat'!A:A,'baza-04.10.2026'!I:I,"Future lab") -> 0 | M87: =Table2[[#This Row],[Pashapay]]+Table2[[#This Row],[Birmarket]]+Table2[[#This Row],[Paşa holding]]+Table2[[#This Row],[Future lab]] -> 0
A88: Kreditlərin ilkin təqibi departamenti | B88: 203 | C88: 183 | D88: 0 | E88: =B88-C88+D88 -> 20 | F88: Non-Agile | G88: 1 verildi maliyye risklerine | H88: Fintech | I88: =COUNTIFS('baza-04.10.2026'!C:C,'Birbank Ştat'!A:A,'baza-04.10.2026'!I:I,"Bir Payment") -> 0 | J88: =COUNTIFS('baza-04.10.2026'!C:C,'Birbank Ştat'!A:A,'baza-04.10.2026'!I:I,"BirMarket") -> 0 | K88: =COUNTIFS('baza-04.10.2026'!C:C,'Birbank Ştat'!A:A,'baza-04.10.2026'!I:I,"Paşa Holding") -> 0 | L88: =COUNTIFS('baza-04.10.2026'!C:C,'Birbank Ştat'!A:A,'baza-04.10.2026'!I:I,"Future lab") -> 0 | M88: =Table2[[#This Row],[Pashapay]]+Table2[[#This Row],[Birmarket]]+Table2[[#This Row],[Paşa holding]]+Table2[[#This Row],[Future lab]] -> 0
A89: Ödəniş biznesinin mühəndislik ekspert mərkəzi | B89: 274 | C89: 248 | D89: 1 | E89: =B89-C89+D89 -> 27 | F89: Agile | G89: relokasiyalar pashapay, 1 əlavə aylin 05.10.2026, 2 əlavə QA andersen aytan , +1 aylin kart mehsullari | H89: Payment | I89: =COUNTIFS('baza-04.10.2026'!C:C,'Birbank Ştat'!A:A,'baza-04.10.2026'!I:I,"Bir Payment") -> 16 | J89: =COUNTIFS('baza-04.10.2026'!C:C,'Birbank Ştat'!A:A,'baza-04.10.2026'!I:I,"BirMarket") -> 0 | K89: =COUNTIFS('baza-04.10.2026'!C:C,'Birbank Ştat'!A:A,'baza-04.10.2026'!I:I,"Paşa Holding") -> 0 | L89: =COUNTIFS('baza-04.10.2026'!C:C,'Birbank Ştat'!A:A,'baza-04.10.2026'!I:I,"Future lab") -> 0 | M89: =Table2[[#This Row],[Pashapay]]+Table2[[#This Row],[Birmarket]]+Table2[[#This Row],[Paşa holding]]+Table2[[#This Row],[Future lab]] -> 16
A90: Mühəndislik və texnoloji platformalar ekspert mərkəzi | B90: 170 | C90: 145 | D90: 1 | E90: =B90-C90+D90 -> 26 | F90: Agile | G90: 1 əlavə orxan | H90: Ekosistem | I90: =COUNTIFS('baza-04.10.2026'!C:C,'Birbank Ştat'!A:A,'baza-04.10.2026'!I:I,"Bir Payment") -> 1 | J90: =COUNTIFS('baza-04.10.2026'!C:C,'Birbank Ştat'!A:A,'baza-04.10.2026'!I:I,"BirMarket") -> 2 | K90: =COUNTIFS('baza-04.10.2026'!C:C,'Birbank Ştat'!A:A,'baza-04.10.2026'!I:I,"Paşa Holding") -> 0 | L90: =COUNTIFS('baza-04.10.2026'!C:C,'Birbank Ştat'!A:A,'baza-04.10.2026'!I:I,"Future lab") -> 0 | M90: =Table2[[#This Row],[Pashapay]]+Table2[[#This Row],[Birmarket]]+Table2[[#This Row],[Paşa holding]]+Table2[[#This Row],[Future lab]] -> 3
A91: FinTech mühəndislik ekspert mərkəzi | B91: 357 | C91: 323 | D91: 2 | E91: =B91-C91+D91 -> 36 | F91: Agile | G91: 1i artıq idi, 1 verildi bura mikro b d skd den, 9 sildik ixtisar | H91: Fintech | I91: =COUNTIFS('baza-04.10.2026'!C:C,'Birbank Ştat'!A:A,'baza-04.10.2026'!I:I,"Bir Payment") -> 1 | J91: =COUNTIFS('baza-04.10.2026'!C:C,'Birbank Ştat'!A:A,'baza-04.10.2026'!I:I,"BirMarket") -> 0 | K91: =COUNTIFS('baza-04.10.2026'!C:C,'Birbank Ştat'!A:A,'baza-04.10.2026'!I:I,"Paşa Holding") -> 0 | L91: =COUNTIFS('baza-04.10.2026'!C:C,'Birbank Ştat'!A:A,'baza-04.10.2026'!I:I,"Future lab") -> 0 | M91: =Table2[[#This Row],[Pashapay]]+Table2[[#This Row],[Birmarket]]+Table2[[#This Row],[Paşa holding]]+Table2[[#This Row],[Future lab]] -> 1
A92: Filial | B92: 1950 | C92: 1965 | D92: 64 | E92: =B92-C92+D92 -> 49 | F92: Filial | H92: Fintech | I92: =COUNTIFS('baza-04.10.2026'!C:C,'Birbank Ştat'!A:A,'baza-04.10.2026'!I:I,"Bir Payment") -> 0 | J92: =COUNTIFS('baza-04.10.2026'!C:C,'Birbank Ştat'!A:A,'baza-04.10.2026'!I:I,"BirMarket") -> 0 | K92: =COUNTIFS('baza-04.10.2026'!C:C,'Birbank Ştat'!A:A,'baza-04.10.2026'!I:I,"Paşa Holding") -> 0 | L92: =COUNTIFS('baza-04.10.2026'!C:C,'Birbank Ştat'!A:A,'baza-04.10.2026'!I:I,"Future lab") -> 0 | M92: =Table2[[#This Row],[Pashapay]]+Table2[[#This Row],[Birmarket]]+Table2[[#This Row],[Paşa holding]]+Table2[[#This Row],[Future lab]] -> 0
A93: Satış kanalları departamenti | B93: 668 | C93: 658 | D93: 51 | E93: =B93-C93+D93 -> 61 | F93: Non-Agile | G93: 1 i fintech müh | H93: Fintech | I93: =COUNTIFS('baza-04.10.2026'!C:C,'Birbank Ştat'!A:A,'baza-04.10.2026'!I:I,"Bir Payment") -> 0 | J93: =COUNTIFS('baza-04.10.2026'!C:C,'Birbank Ştat'!A:A,'baza-04.10.2026'!I:I,"BirMarket") -> 0 | K93: =COUNTIFS('baza-04.10.2026'!C:C,'Birbank Ştat'!A:A,'baza-04.10.2026'!I:I,"Paşa Holding") -> 0 | L93: =COUNTIFS('baza-04.10.2026'!C:C,'Birbank Ştat'!A:A,'baza-04.10.2026'!I:I,"Future lab") -> 0 | M93: =Table2[[#This Row],[Pashapay]]+Table2[[#This Row],[Birmarket]]+Table2[[#This Row],[Paşa holding]]+Table2[[#This Row],[Future lab]] -> 0
A94: CƏM | B94: =SUBTOTAL(9,B2:B93) -> 6605 | C94: =SUBTOTAL(9,C2:C93) -> 6286 | D94: =SUBTOTAL(9,D2:D93) -> 145 | E94: =SUBTOTAL(9,E2:E93) -> 465 | I94: =SUM(I2:I93) -> 409 | J94: =SUM(J2:J93) -> 63 | K94: =SUM(K2:K93) -> 19 | L94: =SUM(L2:L93) -> 8 | M94: =SUM(I94:L94) -> 499

Sheet baza-04.10.2026
A1: Personal kod | B1: Soyadı, adı və ata adı (Surname, name, father name) | C1: Departament (Department) | D1: Şöbə (Section) | E1: Bölmə (Subsection) | F1: Vəzifə (Position) | G1: Aktiv, Passiv, HX, SM (Active, Passive,Social vacation) | H1: Status | I1: Keçid etdiyi şirkət | J1: Kapital Banka işə qəbul olunduğu tarix (Hire date) | K1: Non agile filial | L1: İşdən çıxma tarixi | M1: Qeyd
A2: 16457 | B2: Məmmədov Fərid Usad oğlu | C2: Müşahidə Şurası | D2: # | E2: # | F2: Müşahidə şurasının sədri (əvəzçilik qaydasında) | G2: A | H2: Daimi | J2: 45405 | K2: Non-Agile
A3: 10843 | B3: Həsənov Oqtay Arif oğlu | C3: Müşahidə Şurası | D3: # | E3: # | F3: Müşahidə şurasının üzvü, Audit komitəsinin sədri (əvəzçilik qaydasında) | G3: A | H3: Daimi | J3: 41654 | K3: Non-Agile
A4: 10925 | B4: Hüseynov Fərid Arif oğlu | C4: Rəhbərlik | D4: # | E4: # | F4: İdarə Heyətinin sədri, Baş icraçı direktor | G4: A | H4: Daimi | J4: 42125 | K4: Non-Agile
A5: 10722 | B5: Mirzəyev Cavid Akif oğlu | C5: Rəhbərlik | D5: # | E5: # | F5: İdarə Heyəti sədrinin I müavini | G5: A | H5: Daimi | J5: 41736 | K5: Non-Agile
A6: 10610 | B6: Hidayətzadə Fərid Səbuhi oğlu | C6: Rəhbərlik | D6: # | E6: # | F6: İdarə Heyəti sədrinin müavini, Baş Korporativ satış inzibatçısı | G6: A | H6: Daimi | J6: 41484 | K6: Non-Agile
A7: 18167 | B7: Orucov Calal Cümşüd oğlu | C7: Rəhbərlik | D7: # | E7: # | F7: İdarə Heyəti sədrinin müavini | G7: A | H7: Daimi | J7: 46027 | K7: Non-Agile | M7: 84 N-19.12.2025, 08 N-Emin M yerinə olması 30.01.2026
A8: 10002 | B8: Məmmədov Yaşar Zeynalabdı oğlu | C8: Rəhbərlik | D8: # | E8: # | F8: İdarə Heyəti sədrinin müavini | G8: A | H8: Daimi | J8: 37893 | K8: Non-Agile
A9: 10611 | B9: Abdullayev Kamal Nadir oğlu | C9: Rəhbərlik | D9: # | E9: # | F9: Baş komplayens inzibatçısı | G9: A | H9: Daimi | J9: 41484 | K9: Non-Agile
A10: 10963 | B10: Baxşiyev Ağarza Yaşar oğlu | C10: Rəhbərlik | D10: # | E10: # | F10: Baş Risk inzibatçısı | G10: A | H10: Daimi | J10: 42219 | K10: Non-Agile
A11: 18369 | B11: Atakişiyev Rauf Surxay oğlu | C11: Rəhbərlik | D11: # | E11: # | F11: Baş Maliyyə inzibatçısı | G11: A | H11: Daimi | J11: 46113 | K11: Non-Agile | M11: 23N-19.03.2026
A12: 10658 | B12: Məmmədov Emin Ağaverdi oğlu | C12: Rəhbərlik | D12: # | E12: # | F12: İdarə Heyəti sədrinin müşaviri | G12: A | H12: Daimi | J12: 41611 | K12: Non-Agile
A13: 18916 | B13: SZCZEPANSKI LUKASZ | C13: Rəhbərlik | D13: # | E13: # | F13: İdarə Heyəti sədrinin müşaviri | G13: A | H13: Daimi | J13: 46237 | K13: Non-Agile | M13: 58N-23.07.2026
A14: 18890 | B14: Qulaməliyev Rauf İlham oğlu | C14: Rəhbərlik | D14: # | E14: # | F14: İdarə Heyəti sədrinin müşaviri | G14: A | H14: Daimi | I14: BirMarket | J14: 46241 | K14: Non-Agile | M14: 58N-23.07.2026
A15: 18188 | B15: Məmmədov Samir Sabir oğlu | C15: Rəhbərlik | D15: # | E15: # | F15: İdarə Heyəti sədrinin müşaviri (əvəzçilik qaydasında) | G15: A | H15: Daimi | I15: BirMarket | J15: 46034 | K15: Non-Agile | M15: 02 N-12.01.2026
A16: 15131 | B16: Aslanov Mehti İsfəndiyar oğlu | C16: Rəhbərlik | D16: # | E16: # | F16: Müşavir (İdarə Heyətinin sədri/baş icraçı direktorun ekosistem üzrə) (əvəzçilik üzrə) | G16: A | H16: Daimi | J16: 44958 | K16: Non-Agile
A17: 11584 | B17: İslamov Fərid Abbas oğlu | C17: Rəhbərlik | D17: # | E17: # | F17: Ofis lideri | G17: A | H17: Daimi | J17: 42877 | K17: Agile
A18: 19018 | B18: VASILEVA EVGENIIA | C18: Rəhbərlik | D18: # | E18: # | F18: Aparat rəhbəri | G18: A | H18: Daimi | I18: Bir Payment | J18: 46254 | K18: Agile
A19: 15541 | B19: GROMOV MIKHAIL | C19: İnformasiya texnologiyaları idarəsi | D19: # | E19: # | F19: Baş direktor | G19: A | H19: Daimi | J19: 45114 | K19: Agile
A20: 16327 | B20: EVDOKIMOV MAKSIM | C20: Məhsul və marketinq idarəsi | D20: # | E20: # | F20: Baş direktor | G20: A | H20: Daimi | J20: 45344 | K20: Agile
A21: 18522 | B21: Nəbiyev Valeh Valeh oğlu | C21: Data və Aİ idarəsi | D21: # | E21: # | F21: Baş direktor | G21: A | H21: Daimi | I21: Paşa Holding | J21: 46143 | K21: Agile
A22: 18523 | B22: Məmmədov Ruslan Nəsir oğlu | C22: Strategiya idarəsi | D22: # | E22: # | F22: Baş direktor | G22: A | H22: Daimi | I22: Paşa Holding | J22: 46143 | K22: Non-Agile
A23: 160032 | B23: İbrahimov Məhəmməd Əhməd oğlu | C23: Əməliyyatlar ofisi | D23: # | E23: # | F23: Ofis lideri | G23: A | H23: Daimi | J23: 42311 | K23: Non-Agile
A24: 10431 | B24: Xan-Məmmədov Zakir Akif oğlu | C24: Ödəniş məhsulları ofisi | D24: # | E24: # | F24: Ofis lideri | G24: A | H24: Daimi | J24: 40253 | K24: Agile
A25: 10967 | B25: Səmədov Fərid Sirac oğlu | C25: Ödəniş texnologiyaları ofisi | D25: # | E25: # | F25: Ofis lideri | G25: A | H25: Daimi | J25: 42222 | K25: Agile
A26: 10516 | B26: Məmmədov Pərvin Zahid oğlu | C26: Maliyyə ofisi | D26: # | E26: # | F26: Ofis lideri | G26: A | H26: Daimi | J26: 41022 | K26: Non-Agile
A27: 13059 | B27: Mahmudxanov Xıdır Asif oğlu | C27: Maliyyə risklərinin idarə edilməsi ofisi | D27: # | E27: # | F27: Ofis lideri | G27: A | H27: Daimi | J27: 44228 | K27: Non-Agile
A28: 16326 | B28: IAKUBOV AIRAT | C28: İnformasiya texnologiyaları idarəsi | D28: # | E28: # | F28: Tribe tech lead | G28: A | H28: Daimi | J28: 45344 | K28: Agile
A29: 16075 | B29: Şükürov Elvin Elçin oğlu | C29: Ödəniş biznesinin mühəndislik ekspert mərkəzi | D29: # | E29: # | F29: Tribe tech lead | G29: A | H29: Daimi | J29: 45278 | K29: Agile
A30: 18483 | B30: İbrahimxanlı Murad Zeynal oğlu | C30: Ödəniş biznesinin mühəndislik ekspert mərkəzi | D30: Software chapter | E30: # | F30: Tech lead | G30: A | H30: Daimi | J30: 46146 | K30: Agile
A31: 18815 | B31: Məmmədzadə Samir Səfər oğlu | C31: Ödəniş biznesinin mühəndislik ekspert mərkəzi | D31: Software chapter | E31: # | F31: Tech lead (0,5 ştat vahidi üzrə əvəzçilik qaydasında) | G31: A | H31: Daimi | I31: Bir Payment | J31: 46213 | K31: Agile
A32: 18182 | B32: Əhmədov Kənan Fəxrəddin oğlu | C32: Kart məhsulları sahəsi | D32: # | E32: # | F32: Tribe tech lead | G32: A | H32: Daimi | J32: 46035 | K32: Agile
A33: 11886 | B33: Lətifov Fariz Məmməd oğlu | C33: FinTech mühəndislik ekspert mərkəzi | D33: # | E33: # | F33: Tribe tech lead | G33: A | H33: Daimi | J33: 43242 | K33: Agile
A34: 17254 | B34: Məmmədov İlqar Camal oğlu | C34: Ödəniş biznesinin mühəndislik ekspert mərkəzi | D34: # | E34: # | F34: Ekspert mərkəzinin lideri | G34: A | H34: Daimi | J34: 45691 | K34: Agile
A35: 16234 | B35: Əlizadə Teymur Vladimiroviç | C35: Ödəniş biznesinin TechOps funksional sahəsi | D35: # | E35: # | F35: Servis dayanıqlığı üzrə mühəndis | G35: A | H35: Daimi | J35: 45323 | K35: Agile
A36: 17485 | B36: SHATUNOV MAKSIM | C36: BirApp texnologiyası sahəsi | D36: # | E36: # | F36: Tribe tech lead | G36: A | H36: Daimi | J36: 45762 | K36: Agile
A37: 11527 | B37: Rəcəbova Samirə Fuad qızı | C37: BirApp texnologiyası sahəsi | D37: Birbank Platform | E37: # | F37: Məhsul sahibi | G37: A | H37: Daimi | J37: 42797 | K37: Agile
A38: 11536 | B38: Seyfullayev Şahmar Asəf oğlu | C38: Ödəniş biznesinin mühəndislik ekspert mərkəzi | D38: # | E38: # | F38: Tribe tech lead | G38: A | H38: Daimi | J38: 42808 | K38: Agile
A39: 18202 | B39: Mustafayev Kamran Çingiz oğlu | C39: Korporativ inkişaf və investor əlaqələri departamenti | D39: # | E39: # | F39: Menecer | G39: A | H39: Daimi | J39: 46055 | K39: Non-Agile
A40: 18268 | B40: RIZVANOV RUSTAM | C40: Korporativ inkişaf və investor əlaqələri departamenti | D40: # | E40: # | F40: Direktor müavini | G40: A | H40: Daimi | J40: 46084 | K40: Non-Agile
A41: 10944 | B41: Ağayeva Aysel Babakişi qızı | C41: # | D41: Korporativ katiblik şöbəsi | E41: # | F41: Şöbə müdiri | G41: A | H41: Daimi | J41: 42171 | K41: Non-Agile
A42: 10568 | B42: Bayramova Aynur Zirəddin qızı | C42: # | D42: Korporativ katiblik şöbəsi | E42: İdarəetmə orqanları və komitələrlə iş bölməsi | F42: Menecer | G42: A | H42: Daimi | J42: 41246 | K42: Non-Agile
A43: 13399 | B43: Qasımlı Nəsibə Etibar qızı | C43: # | D43: Korporativ katiblik şöbəsi | E43: İdarəetmə orqanları və komitələrlə iş bölməsi | F43: Aparıcı mütəxəssis | G43: A | H43: Daimi | J43: 44425 | K43: Non-Agile
... A56: 15659 | B56: İsmayılova Şükufə Muxalif qızı | C56: # | D56: Korporativ katiblik şöbəsi | E56: Katiblik bölməsi | F56: Şəxsi köməkçi | G56: A | H56: Daimi | J56: 45154 | K56: Non-Agile
A57: 19126 | B57: Məmmədova Xumar Elşən qızı | C57: # | D57: Korporativ katiblik şöbəsi | E57: Katiblik bölməsi | F57: Şəxsi köməkçi | G57: A | H57: Daimi | I57: Future lab | J57: 46268 | K57: Non-Agile
A58: 17763 | B58: Yahyayeva Emiliya Rasim qızı | C58: # | D58: Korporativ katiblik şöbəsi | E58: Katiblik bölməsi | F58: Şəxsi köməkçi | G58: A | H58: Daimi | J58: 45873 | K58: Non-Agile
A59: 17835 | B59: Məmmədova Nərgiz Aydın qızı | C59: # | D59: Korporativ katiblik şöbəsi | E59: Katiblik bölməsi | F59: Şəxsi köməkçi | G59: A | H59: Daimi | J59: 45888 | K59: Non-Agile
A60: 12584 | B60: Vəlili İranə İlmas qızı | C60: # | D60: Korporativ katiblik şöbəsi | E60: Katiblik bölməsi | F60: Şəxsi köməkçi | G60: A | H60: Daimi | J60: 43827 | K60: Non-Agile
A61: 10603 | B61: Məmmədova Fidan Tahir qızı | C61: # | D61: Korporativ katiblik şöbəsi | E61: Katiblik bölməsi | F61: Şəxsi köməkçi (əvəzçilik qaydasında) | G61: A | H61: Daimi | J61: 39727 | K61: Non-Agile
A62: 10015 | B62: Kərimova Mehparə Məmmədsadıq qızı | C62: # | D62: Korporativ katiblik şöbəsi | E62: Sənədlərin qeydiyyatı və dövriyyəsi bölməsi | F62: Menecer | G62: A | H62: Daimi | J62: 36714 | K62: Non-Agile
A63: 13006 | B63: Rzayeva Ülkər Bəhram qızı | C63: # | D63: Korporativ katiblik şöbəsi | E63: Sənədlərin qeydiyyatı və dövriyyəsi bölməsi | F63: Aparıcı mütəxəssis | G63: A | H63: Daimi | J63: 44187 | K63: Non-Agile
A64: 14147 | B64: Məmmədova Ramilə Vaqif qızı | C64: # | D64: Korporativ katiblik şöbəsi | E64: Sənədlərin qeydiyyatı və dövriyyəsi bölməsi | F64: Aparıcı mütəxəssis | G64: A | H64: Daimi | J64: 44673 | K64: Non-Agile
A65: 18467 | B65: Səfərli Vüsalə Novruz qızı | C65: # | D65: Korporativ katiblik şöbəsi | E65: Sənədlərin qeydiyyatı və dövriyyəsi bölməsi | F65: Aparıcı mütəxəssis | G65: A | H65: Daimi | J65: 46134 | K65: Non-Agile
A66: 13414 | B66: Aslanlı Tərlan Yusif oğlu | C66: # | D66: Korporativ katiblik şöbəsi | E66: Sənədlərin qeydiyyatı və dövriyyəsi bölməsi | F66: Mütəxəssis | G66: A | H66: Daimi | J66: 44431 | K66: Non-Agile
A67: 16636 | B67: İsmayılova Aysel Qələmdar qızı | C67: # | D67: Korporativ katiblik şöbəsi | E67: Sənədlərin qeydiyyatı və dövriyyəsi bölməsi | F67: Mütəxəssis | G67: A | H67: Daimi | J67: 45505 | K67: Non-Agile
A68: 17180 | B68: Şeydayeva Ceyla Zəki qızı | C68: # | D68: Korporativ katiblik şöbəsi | E68: Sənədlərin qeydiyyatı və dövriyyəsi bölməsi | F68: Mütəxəssis | G68: A | H68: Daimi | J68: 45670 | K68: Non-Agile
A69: 17316 | B69: Raşimov Süleyman Rafik oğlu | C69: # | D69: Korporativ katiblik şöbəsi | E69: Sənədlərin qeydiyyatı və dövriyyəsi bölməsi | F69: Mütəxəssis | G69: A | H69: Daimi | J69: 45709 | K69: Non-Agile
... A71: 16969 | B71: Həsənzadə Aynur Abasqulu qızı | C71: Təşkilati inkişaf və HR texnologiyaları departamenti | D71: İşəgötürən brendi və KSM funksional sahəsi | E71: # | F71: Funksional sahə lideri | G71: A | H71: Daimi | J71: 45580 | K71: Non-Agile
A72: 18277 | B72: İmanova Nigar Rövşən qızı | C72: Təşkilati inkişaf və HR texnologiyaları departamenti | D72: İşəgötürən brendi və KSM funksional sahəsi | E72: # | F72: Menecer | G72: A | H72: Daimi | I72: BirMarket | J72: 46072 | K72: Non-Agile
A73: 18281 | B73: Tağiyeva Şahidə Namiq qızı | C73: Təşkilati inkişaf və HR texnologiyaları departamenti | D73: İşəgötürən brendi və KSM funksional sahəsi | E73: İnternal communications function | F73: Menecer | G73: A | H73: Daimi | I73: BirMarket | J73: 46072 | K73: Non-Agile
A74: 18362 | B74: Əhmədova Kəmalə Calalətdin qızı | C74: Təşkilati inkişaf və HR texnologiyaları departamenti | D74: İşəgötürən brendi və KSM funksional sahəsi | E74: # | F74: Baş mütəxəssis | G74: A | H74: Daimi | J74: 46113 | K74: Non-Agile
A75: 19206 | B75: Hümmətova Aytən Şamil qızı | C75: Təşkilati inkişaf və HR texnologiyaları departamenti | D75: İşəgötürən brendi və KSM funksional sahəsi | E75: # | F75: Baş mütəxəssis | G75: A | H75: Daimi | I75: Future lab | J75: 46276 | K75: Non-Agile
A76: 15580 | B76: Abdullazadə Fidan Bəxtiyar qızı | C76: Təşkilati inkişaf və HR texnologiyaları departamenti | D76: İşəgötürən brendi və KSM funksional sahəsi | E76: İnternal communications function | F76: Aparıcı mütəxəssis | G76: A | H76: Daimi | J76: 45124 | K76: Non-Agile
A77: 19232 | B77: Qasımzadə Nigar Asif qızı | C77: Təşkilati inkişaf və HR texnologiyaları departamenti | D77: İşəgötürən brendi və KSM funksional sahəsi | E77: İnternal communications function | F77: Aparıcı mütəxəssis | G77: A | H77: Daimi | J77: 46281 | K77: Non-Agile
A78: 17948 | B78: İsayeva Fəridə Seymur qızı | C78: Təşkilati inkişaf və HR texnologiyaları departamenti | D78: İşəgötürən brendi və KSM funksional sahəsi | E78: # | F78: Mütəxəssis | G78: A | H78: Daimi | J78: 45933 | K78: Non-Agile
A79: 13116 | B79: Poladov Yusif Canəli oğlu | C79: Təşkilati inkişaf və HR texnologiyaları departamenti | D79: İşəgötürən brendi və KSM funksional sahəsi | E79: # | F79: Baş mütəxəssis | G79: A | H79: Daimi | J79: 44265 | K79: Non-Agile
A80: 17466 | B80: Əli Fəxrəddin Fuad oğlu | C80: Təşkilati inkişaf və HR texnologiyaları departamenti | D80: İşəgötürən brendi və KSM funksional sahəsi | E80: # | F80: Mütəxəssis | G80: A | H80: Daimi | J80: 45758 | K80: Non-Agile
A81: 17978 | B81: Əhmədova Nərmin Həsən qızı | C81: Təşkilati inkişaf və HR texnologiyaları departamenti | D81: İşəgötürən brendi və KSM funksional sahəsi | E81: # | F81: Mütəxəssis | G81: A | H81: Daimi | J81: 45944 | K81: Non-Agile
A82: 18399 | B82: İsayev Maksim Maarif oğlu | C82: Təşkilati inkişaf və HR texnologiyaları departamenti | D82: İşəgötürən brendi və KSM funksional sahəsi | E82: # | F82: Aparıcı mütəxəssis | G82: A | H82: Daimi | I82: BirMarket | J82: 46120 | K82: Non-Agile
A83: 12835 | B83: Əliyev Səttar Bayram oğlu | C83: # | D83: VİP müştərilərlə iş şöbəsi | E83: # | F83: Şöbə müdiri | G83: A | H83: Daimi | J83: 44004 | K83: Non-Agile
A84: 600034 | B84: Əfəndiyev Fərid Məcid oğlu | C84: # | D84: VİP müştərilərlə iş şöbəsi | E84: # | F84: Menecer | G84: A | H84: Daimi | J84: 42676 | K84: Non-Agile
A85: 770021 | B85: Tivrizov Rəcəb Məmməd oğlu | C85: # | D85: VİP müştərilərlə iş şöbəsi | E85: # | F85: Baş mütəxəssis | G85: A | H85: Daimi | J85: 42731 | K85: Non-Agile
A86: 12638 | B86: Tağıyev Orxan Rafael oğlu | C86: # | D86: VİP müştərilərlə iş şöbəsi | E86: # | F86: Baş mütəxəssis | G86: A | H86: Daimi | J86: 43847 | K86: Non-Agile
A87: 12738 | B87: Cəbrayılzadə Vüsal Rəfail oğlu | C87: # | D87: VİP müştərilərlə iş şöbəsi | E87: # | F87: Baş mütəxəssis | G87: A | H87: Daimi | J87: 43885 | K87: Non-Agile
A88: 300223 | B88: Qasımov Emin Tahir oğlu | C88: # | D88: VİP müştərilərlə iş şöbəsi | E88: # | F88: Aparıcı mütəxəssis | G88: A | H88: Daimi | J88: 44203 | K88: Non-Agile
A89: 13285 | B89: Əminzadə Nicat İlqar oğlu | C89: # | D89: VİP müştərilərlə iş şöbəsi | E89: # | F89: Aparıcı mütəxəssis | G89: A | H89: Daimi | J89: 44368 | K89: Non-Agile
A90: 18961 | B90: Məhərrəmli Elnur Firdovsi oğlu | C90: # | D90: VİP müştərilərlə iş şöbəsi | E90: # | F90: Kiçik mütəxəssis | G90: A | H90: Daimi | J90: 46248 | K90: Non-Agile
A91: 17215 | B91: Kazımov Rauf Sabir oğlu | C91: Daxili audit departamenti | D91: # | E91: # | F91: Direktor | G91: A | H91: Daimi | J91: 45663 | K91: Non-Agile
A92: 210029 | B92: Əhmədov Abil Mirqabil oğlu | C92: Daxili audit departamenti | D92: Əməliyyat,komplayens və davamlı audit üzrə ekspert mərkəzi | E92: # | F92: Audit meneceri | G92: A | H92: Daimi | J92: 42075 | K92: Non-Agile
A93: 10765 | B93: Əhmədzadə Elvin İlqar oğlu | C93: Daxili audit departamenti | D93: Əməliyyat,komplayens və davamlı audit üzrə ekspert mərkəzi | E93: # | F93: Audit meneceri | G93: A | H93: Daimi | J93: 41841 | K93: Non-Agile
A94: 10338 | B94: Novruzov Yalçın Əzizağa oğlu | C94: Daxili audit departamenti | D94: Əməliyyat,komplayens və davamlı audit üzrə ekspert mərkəzi | E94: # | F94: Audit meneceri | G94: A | H94: Daimi | J94: 38783 | K94: Non-Agile
... A144: 15499 | B144: Hacıyev Cavidan Natiq oğlu | C144: Hüquq departamenti | D144: Məhkəmələr və hüquqi təminat şöbəsi | E144: # | F144: Aparıcı hüquqşünas | G144: A | H144: Daimi | J144: 45099 | K144: Non-Agile
A145: 18318 | B145: Əhmədzadə Orxan Fərman oğlu | C145: Hüquq departamenti | D145: Məhkəmələr və hüquqi təminat şöbəsi | E145: # | F145: Hüquqşünas (əvəzçilik qaydasında) | G145: A | H145: Daimi | I145: BirMarket | J145: 46084 | K145: Non-Agile
A146: 18319 | B146: Şirəliyeva Şəms Əsgər qızı | C146: Hüquq departamenti | D146: Məhkəmələr və hüquqi təminat şöbəsi | E146: # | F146: Mütəxəssis(əvəzçilik qaydasında) | G146: A | H146: Daimi | I146: Bir Payment | J146: 46084 | K146: Non-Agile
A147: 18335 | B147: Nəsirova Könül Məzahir qızı | C147: Hüquq departamenti | D147: Məhkəmələr və hüquqi təminat şöbəsi | E147: # | F147: Mütəxəssis | G147: A | H147: Daimi | I147: Bir Payment | J147: 46091 | K147: Non-Agile
A148: 14355 | B148: Məmişova Elnarə Cəfər qızı | C148: Hüquq departamenti | D148: Məhkəmələr və hüquqi təminat şöbəsi | E148: # | F148: Mütəxəssis | G148: A | H148: Daimi | J148: 44743 | K148: Non-Agile
A149: 17456 | B149: Məhərrəmova İlahə Vaqif qızı | C149: Hüquq departamenti | D149: Məhkəmələr və hüquqi təminat şöbəsi | E149: # | F149: Aparıcı hüquqşünas | G149: A | H149: Daimi | J149: 45757 | K149: Non-Agile
A150: 18375 | B150: Muradova Nərgiz Fəxrəddin qızı | C150: Hüquq departamenti | D150: Ödəniş biznesinə hüquqi dəstək şöbəsi | E150: # | F150: Şöbə müdiri | G150: A | H150: Daimi | I150: Bir Payment | J150: 46113 | K150: Non-Agile
A151: 18376 | B151: Rzayeva Gülnar Fazil qızı | C151: Hüquq departamenti | D151: Ödəniş biznesinə hüquqi dəstək şöbəsi | E151: # | F151: Baş hüquqşünas | G151: A | H151: Daimi | I151: Bir Payment | J151: 46113 | K151: Non-Agile
A152: 18379 | B152: Pirqasimova Esmira Alxanovna | C152: Hüquq departamenti | D152: Ödəniş biznesinə hüquqi dəstək şöbəsi | E152: # | F152: Baş hüquqşünas | G152: A | H152: Daimi | I152: Bir Payment | J152: 46113 | K152: Non-Agile
A153: 18377 | B153: Ağasərkari Selcan Naqif qızı | C153: Hüquq departamenti | D153: Ödəniş biznesinə hüquqi dəstək şöbəsi | E153: # | F153: Aparıcı hüquqşünas | G153: A | H153: Daimi | I153: Bir Payment | J153: 46113 | K153: Non-Agile
A154: 18381 | B154: Ağamedov Nadir Nizamoviç oğlu | C154: Hüquq departamenti | D154: E-ticarət biznesinə hüquqi dəstək şöbəsi | E154: # | F154: Baş hüquqşünas | G154: A | H154: Daimi | I154: BirMarket | J154: 46113 | K154: Non-Agile
A155: 18382 | B155: Qarayev Anar Çingiz oğlu | C155: Hüquq departamenti | D155: E-ticarət biznesinə hüquqi dəstək şöbəsi | E155: # | F155: Baş hüquqşünas (0,5 ştat vahidi üzrə) | G155: A | H155: Daimi | I155: BirMarket | J155: 46113 | K155: Non-Agile
A156: 18380 | B156: Ömərli Turxan Müsəllim oğlu | C156: Hüquq departamenti | D156: E-ticarət biznesinə hüquqi dəstək şöbəsi | E156: # | F156: Aparıcı hüquqşünas | G156: A | H156: Daimi | I156: BirMarket | J156: 46113 | K156: Non-Agile
A157: 18384 | B157: Tağiyeva Zahidə Əli qızı | C157: Hüquq departamenti | D157: E-ticarət biznesinə hüquqi dəstək şöbəsi | E157: # | F157: Baş mütəxəssis | G157: HX | H157: Daimi | I157: BirMarket | J157: 46113 | K157: Non-Agile
A158: 18383 | B158: Aslanova Tamara Mehman qızı | C158: Hüquq departamenti | D158: E-ticarət biznesinə hüquqi dəstək şöbəsi | E158: # | F158: Mütəxəssis | G158: A | H158: Daimi | I158: BirMarket | J158: 46113 | K158: Non-Agile
A159: 18378 | B159: Cabbarli Ləman İlqar qızı | C159: Hüquq departamenti | D159: E-ticarət biznesinə hüquqi dəstək şöbəsi | E159: # | F159: Hüquqşunas | G159: A | H159: Daimi | I159: BirMarket | J159: 46113 | K159: Non-Agile
A160: 12207 | B160: Səfərəliyeva Tahirə Mahmud qızı | C160: Hüquq departamenti | D160: Arxiv şöbəsi | E160: # | F160: Şöbə müdiri | G160: A | H160: Daimi | J160: 43587 | K160: Non-Agile
A161: 13124 | B161: Xəlilova Şəhanə Natiq qızı | C161: Hüquq departamenti | D161: Arxiv şöbəsi | E161: # | F161: Menecer | G161: A | H161: Daimi | J161: 44270 | K161: Non-Agile
A162: 13020 | B162: Ağayev Nicat İlqar oğlu | C162: Hüquq departamenti | D162: Arxiv şöbəsi | E162: # | F162: Baş mütəxəssis | G162: A | H162: Daimi | J162: 44203 | K162: Non-Agile
...

Sheet İxtisar
A1: Sahə | B1: Əvvəlki təsdiqlənən ştat sayı | C1: İxtisardan sonra təsdiqlənəcək ştat sayı | D1: İxtisar olunan ştat sayı | E1: İxtisardan əvvəlki vakant | F1: İxtisardan sonrakı vakant | G1: Status
A2: Filial | B2: 2007 | C2: 1950 | D2: 57 | E2: 106 | F2: =Table1[[#This Row],[İxtisardan əvvəlki vakant]]-Table1[[#This Row],[İxtisar olunan ştat sayı]] -> 49 | G2: Şifahi bildirilib ki yenə ixtisar olacaq
A3: FinTech mühəndislik ekspert mərkəzi | B3: 366 | C3: 357 | D3: 9 | E3: 45 | F3: =Table1[[#This Row],[İxtisardan əvvəlki vakant]]-Table1[[#This Row],[İxtisar olunan ştat sayı]] -> 36 | G3: Yeni layihələrə görə reserved saxlayır
A4: Korporativ katiblik şöbəsi | B4: 37.5 | C4: 35.5 | D4: 2 | E4: 7.5 | F4: =Table1[[#This Row],[İxtisardan əvvəlki vakant]]-Table1[[#This Row],[İxtisar olunan ştat sayı]] -> 5.5
A5: Texniki dəstək departamenti | B5: 61 | C5: 59 | D5: 2 | E5: 3 | F5: =Table1[[#This Row],[İxtisardan əvvəlki vakant]]-Table1[[#This Row],[İxtisar olunan ştat sayı]] -> 1
A6: Kredit risklərinin təhlili departamenti | B6: 133 | C6: =Table1[[#This Row],[Əvvəlki təsdiqlənən ştat sayı]]-17 -> 116 | D6: 17 | E6: 22 | F6: =Table1[[#This Row],[İxtisardan əvvəlki vakant]]-Table1[[#This Row],[İxtisar olunan ştat sayı]] -> 5
A7: CƏMİ | D7: =SUM(Table1[İxtisar olunan ştat sayı]) -> 87 | E7: =SUM(Table1[İxtisardan əvvəlki vakant]) -> 183.5 | F7: =SUM(Table1[İxtisardan sonrakı vakant]) -> 96.5

Sheet HR
A1: Sahə | B1: Struktur dəyişikliyindən əvvəl | C1: Hardan gəlib | D1: Say | E1: Struktur dəyişikliyindən sonra | F1: Faktiki işçi sayı | G1: Müvəqqəti işçi sayı | H1: Vakant ştat | J1: Ştat ixtisar-HR | K1: Strukturu | L1: İşdən çıxma tarixi
A2: Təşkilati inkişaf və HR texnologiyaları departamenti | B2: 0 | C2: İstedadların idarə edilməsi departamenti | D2: 48 | E2: =SUM(D2:D9) -> 84 | F2: 82 | G2: 3 | H2: 5 | J2: Abdullayeva Sugra | K2: İnsanlar və korporativ mədəniyyət departamenti-İnsan Resursları əməliyyatları və əmək haqqı hesablanması şöbəsi-İnsan Resursları üzrə baş mütəxəssis | L2: 46203 | M2: Birmarket
C3: Daxili kommunikasiya və Korporativ Sosial Məsuliyyət şöbəsi | D3: 8 | J3: Muradova Kəmalə | K3: İnsanlar və korporativ mədəniyyət departamenti-İnsan Resursları əməliyyatları və əmək haqqı hesablanması şöbəsi-İnsan Resursları üzrə mütəxəssis | L3: ştatı ixtisar edilib, özünü birmarketdə CC boş vakanta keçiriblər-08.06.2026
C4: Pashapay | D4: =5+4 -> 9 | J4: Kərimova Nəzrin | K4: İstedadların idarə edilməsi departamenti, Performansın idarə edilməsi və işçi bağlılığı şöbəsi, İnsan resursları üzrə mütəxəssis | L4: 46205 | M4: Pashapay
C5: BirMarket | D5: =7+5 -> 12 | J5: Məmmədova Səmidə | K5: İstedadların idarə edilməsi departamenti, İstedadların cəlbi və biznes partnyorluq şöbəsi,İnsan Resursları üzrə Biznes tərəfdaş | L5: 46224
C6: Pasha holding | D6: 2
C7: İstedadların idarə edilməsi departamenti(Xuraman H, Mujgan R) | D7: 2
C8: Pashapay(Zabeta) | D8: 1
C9: Future lab | D9: 2
A11: Vakantlar | B11: Şöbə | C11: Bölmə | D11: Vəzifə | E11: Yeni qəbul | F11: İşə başlama tarixi | G11: Status | H11: Qeyd
A12: 1 | B12: Təşkilati inkişaf və işçi bağlılığı funksional sahəsi | C12: - | D12: Aparıcı mütəxəssis | E12: Zeynalova Leyla Bəxtiyar | F12: 46307 | G12: İşə qəbul | H12: Elmira Hacıyeva
A13: 2 | B13: HR TechOps, performans və data funksional sahəsi | C13: Ecosystem HR data | D13: Mütəxəssis | E13: Əzizov Emil Müslət | F13: - | H13: Abdullayeva Gülşən
A14: 3 | B14: HR TechOps, performans və data funksional sahəsi | C14: Ecosystem HR operations & Service delivery | D14: Menecer | E14: Oktaylı İqrar Oktay | F14: 46310 | H14: Sunqarova Bikə Hacirabadan qızı
A15: 4 | B15: İşəgötürən brendi və KSM funksional sahəsi, İnternal communications function | C15: - | D15: Aparıcı mütəxəssis | H15: Abbasova Jalə Ceyhun qızı
A16: 5 | B16: Təşkilati inkişaf və işçi bağlılığı funksional sahəsi | C16: Learning & Development | D16: Menecer | G16: Vakant | H16: Mansurova Nərmin Şahin qızı
A21: Vakant olmalıdır amma ştat yoxdur | B21: Hansı şöbə | C21: Kimin yerinə | D21: Qeyd
A22: 1 | B22: Learning & Development | C22: Mujgan Rustəmli
A23: 2 | B23: Təşkilati inkişaf və işçi bağlılığı funksional sahəsi | C23: Nərmin Əhmədova
A24: 3 | B24: HR TechOps, performans və data funksional sahəsi | C24: George Bakhtin | D24: Ştatı Ayrat verməli
A25: 4 | B25: HRBP və istedad cəlbi funksional sahəsi | C25: Əliyeva Zəhra Abasəli qızı
A26: 5 | B26: HRBP və istedad cəlbi funksional sahəsi | C26: Əsgərova Mətanət Vaqif qızı
A27: 6 | B27: İşəgötürən brendi və KSM funksional sahəsi | C27: Baloğlanlı Ziyafət Seymur oğlu
A30: Sual altında olan məsələlər | B30: Hansı şöbə | C30: Ştat | D30: Qeyd
A31: 1 | B31: HRBP | C31: Cəbrayılov Fehruz Nizami oğlu | D31: Aygün xanımın şifahi razılığı əsasında işə götürülüb
C32: Şəfiyeva Nəzrin Fikrət qızı
A33: 3 | B33: İşəgötürən brendi və KSM funksional sahəsi | C33: Əhmədova Kəmalə Calalətdin qızı | D33: HR ştatından götürülüb
C34: Abbasova Jalə Ceyhun qızı | D34: HR ştatından götürülüb
C35: Rüstəmova Vəfa Elbrus qızı | D35: HR ştatından götürülüb

Sheet Pashapay ştat
A1: Row Labels | B1: Staff | C1: Vakant | F1: 46294
A2: None structure | B2: 30 | C2: 0
A3: Biznesin optimallaşdırılması şöbəsi | B3: 1 | C3: 0
A4: Daxili nəzarət şöbəsi | B4: 3 | C4: 0
A5: Frauda qarşı mübarizə şöbəsi | B5: 10 | C5: 0
A6: Hüquq Şöbəsi | B6: 3 | C6: 1
A7: İnformasiya təhlükəsizliyi şöbəsi | B7: 3 | C7: 0
A8: İnkassasiya Şöbəsi | B8: 165 | C8: 24
A9: İT şöbəsi | B9: 11 | C9: 0
A10: Kross-sərhəd və satış sahəsi | B10: 11 | C10: 3
A11: Məhsullar Şöbəsi | B11: 18 | C11: 5
A12: Audit komitəsi | B12: 3 | C12: 1
A13: Baş Komplayens inzibatçısı | B13: 1 | C13: 0
... A22: Terminal və ATM şəbəkəsinin idarə edilməsi departamenti | B22: 27 | C22: 0
A23: Grand Total | B23: =SUM(B2:B22) -> 591 | C23: =SUM(C2:C22) -> 55

Sheet birmarket ştat
A1: 46301
A2: Sahə adı | B2: İşçi sayı-əmək müqaviləsi | C2: Vakant sayı-əmək müqaviləsi | D2: İşçi sayı-xidməti müqavilə(expat) | E2: İşçi sayı-xidməti müqavilə(yerli) | F2: Vakant sayı-xidməti müqavilə(yerli)
A3: Kommersiya bloku | B3: 1 | C3: 2 | D3: 2
A4: Kommersiya blok/Elektronika sahəsi | B4: 11 | C4: 1
A5: Kommersiya bloku/Gözəllik sahəsi | B5: 6
A6: Kommersiya bloku/Ev əşyaları sahəsi | B6: 8
A7: Kommersiya blok/Gündəlik təlabat üçün istehlak sahəsi | B7: 8 | C7: 1
A8: Kommersiya bloku/Satışların təkmilləşdirilməsi departamenti | B8: 46
A9: Kommersiya bloku/Məzmun əməliyyatları şöbəsi | B9: 37
A10: Kommersiya bloku/Satıcı Məhsul departamenti | B10: 3 | D10: 1
A11: Təchizat Zənciri bloku | B11: 1
A12: Təchizat zənciri bloku/Logistika əməliyyatları departamenti | B12: 192 | C12: 6 | D12: 2 | E12: 455 | F12: 80
A13: Texnologiya şöbəsi | B13: 1 | C13: 1
A14: Monitorinq şöbəsi | B14: 3
A15: Məhsulun qaytarılması şöbəsi | B15: 9
A16: Kütləvi sərhəd keçidi şöbəsi | B16: 5
A17: Texniki xidmət və inzibati təsərrüfat şöbəsi | B17: 20
A18: Təchizat Zənciri bloku/Logistika Məhsul departamenti | B18: 3 | D18: 4
A19: İnkişaf bloku | B19: 2 | C19: 1 | D19: 5
A20: İnkişaf qrupu | B20: 2 | C20: 1 | D20: 1
A21: Data və analitika departamenti | B21: 11 | D21: 10
A22: Aİ və modelləşdirmə departamenti | B22: 8
A23: Məhsul və Texnologiyalar bloku | B23: 12 | D23: 7
A24: Məhsul və Texnologiyalar bloku/Mühəndislik departamenti | B24: 23 | D24: 103
A25: Maliyyə bloku
A26: Maliyyə bloku/Maliyyə hesabatları və mühasibatlıq departamenti | B26: 29
A27: Maliyyə planlaması və analitika departamenti | B27: 8 | C27: 2
A28: Maliyyə bloku/Hüquq, komplayens və sənədlərə nəzarət şöbəsi | B28: 2
A29: Maliyyə bloku/Satınalma və təchizat şöbəsi | B29: 2
A30: Maliyyə bloku/Maliyyə Xidmətləri və Ekosistem İnteqrasiyası bölməsi | B30: 1 | C30: 1
A31: İnsanlar və korporativ mədəniyyət bloku
A32: HR Biznes Tərəfdaşlığı şöbəsi | B32: 2
A33: İstedadların İdarə Edilməsi şöbəsi | B33: 3 | D33: 1
A34: Ümumi inzibati şöbəsi | B34: 7
A35: İdarəetmə və rəhbərlik | B35: 1
A36: Layihələrin idarə edilməsi departamenti | B36: 1
A37: Müştəri xidməti və marketpleys əməliyyatları departamenti | B37: 167 | C37: 10
A38: İşçi Performansının Təkmilləşdirilməsi Departamenti | B38: 2 | C38: 1 | D38: 3
A39: Sağlamlıq, əməyin təhlükəsizliyi və ətraf mühitin mühafizəsi şöbəsi | B39: 1
A40: Cəmi | B40: =SUM(B3:B39) -> 638 | C40: =SUM(C3:C39) -> 27 | D40: =SUM(D3:D39) -> 139 | E40: =SUM(E3:E39) -> 455 | F40: =SUM(F3:F39) -> 80

Sheet Pashapay işçi siyahısı
A1: Status | B1: ID | C1: Category (Main) | D1: Name Surname | E1: Soyad, Ad, Ata adı | F1: Department | G1: Departament | H1: Division | I1: Şöbə | J1: Position | K1: Mövcud Yeni Vəzifə | L1: Reporting to (Need Update) | M1: İşə qəbul tarixi | N1: Müqavilə bitmə tarixi | O1: Müqavilə müddəti | P1: RİM | Q1: Doğum tarixi | R1: Yaş | S1: FIN | T1: Vətəndaşlıq | U1: Seriya nömrəsi | V1: Ş.V bitmə tarixi | W1: İş rejimi | X1: Təhsil səv. | Y1: Cins | Z1: Əlaqə nömrəsi | AB1: Korporativ emai | AC1: Personal e-mail | AD1: Address of Registration | AE1: Residency Address | AF1: Familiy status | AG1: Children | AH1: Termination | AI1: Location
A2: Active | B2: ID-01 | C2: H | D2: Ilaha Zeynalova, Aflatun | E2: Zeynalova İlahə Əflatun qızı | F2: Terminal and ATM department | G2: Terminal və ATM şəbəkəsinin idarə edilməsi departamenti | H2: - | I2: - | J2: Head of Terminals Network Management | K2: Direktor | L2: Tağıyev Camal İlham oğlu | M2: 39819 | O2: Indefinite | Q2: 28620 | R2: 48.435616 | S2: 12P0418 | T2: Azerbaijan | U2: AZE 17622290 | W2: Full time | X2: Bachelor | Y2: Female | Z2: +994555050823 | AA2: +994555050823 | AB2: ilaha.zeynalova@pashapay.az | AD2: Bakı Şəh, A.İsgəndərov Küç ,Ev 1, M 12 | AE2: Bakı Şəh, A.İsgəndərov Küç ,Ev 1, M 12 | AF2: single | AG2: 0 | AI2: Port Baku 2
A3: Active | B3: ID-04 | C3: A | D3: Asim Bayramov, Sahib | E3: Bayramov Asim Sahib oğlu | F3: - | G3: - | H3: Encashment division | I3: İnkassasiya Şöbəsi | J3: Driver Incasator | K3: Sürücü inkassator | L3: Abbasova Nurlana Ramiz qızı | M3: 40508 | O3: Indefinite | P3: Baki | Q3: 31870 | R3: 39.531507 | S3: 385BR9W | T3: Azerbaijan | U3: AZE 15356388 | W3: Full time | Y3: Male | Z3: +994552801009 | AB3: - | AD3: Bakı Şəh.,Nərimanov Ray., Ş. Mustafayev Küç., Ev 5 M.16 | AE3: Bakı Şəh., Ş. Mustafayev Küç., Ev 5 M.16 | AF3: married | AG3: 2 | AI3: Sabail rayonu, Gülbala Əliyev 54C
A4: Active | B4: ID-05 | C4: TL | D4: Nurlan Mahmudov, Valeh | E4: Mahmudov Nurlan Valeh oğlu | F4: Terminal business support department | G4: Terminal biznesinə dəstək departamenti | H4: Encashment processes support division | I4: İnkassasiya proseslərinə dəstək şöbəsi | J4: Team Lead | K4: Qrup Rəhbəri | L4: Rüstəmzadə İlqar Vilayət oğlu | M4: 40592 | O4: Indefinite | Q4: 32181 | R4: 38.679452 | S4: 2CJ6GL0 | T4: Azerbaijan | U4: AZE 16433572 | W4: Full time | Y4: Male | Z4: +994555050888 | AA4: +994555050888 | AB4: nurlan.mahmudov@pashapay.az | AD4: Ağdam Ray., Saybalı K. | AE4: Bakı Şəh., Nəsimi R. Tbilisi Pr. 1058-Ci Məh, Bina 36A, M.56 | AF4: married | AG4: 1 | AI4: Sabail rayonu, Gülbala Əliyev 54C
A5: Active | B5: ID-06 | C5: M | D5: Shirinbika Mahmudova, Mushvig | E5: Mahmudova Şirinbikə Müşviq qızı | F5: Financial management department | G5: Maliyyə menecmenti departamenti | H5: Budget control division | I5: Büdcəyə nəzarət şöbəsi | J5: Manager | K5: Menecer | L5: Ağayev Mirşahin Mircəfər oğlu | M5: 40620 | O5: Indefinite | Q5: 33246 | R5: 35.761644 | S5: 54RXPZ2 | T5: Azerbaijan | U5: AZE 15972901 | W5: Full time | Y5: Female | Z5: +994502906868 | AA5: +994502906868 | AB5: shirin.makhmudova@pashapay.az | AD5: Bakı Şəh., Nəsimi R. Tbilisi Pr. 1058-Ci Məh, Bina 36A, M.56 | AE5: Bakı Şəh., Nəsimi R. Tbilisi Pr. 1058-Ci Məh, Bina 36A, M.56 | AF5: married | AG5: 1 | AI5: Port Baku 2
A6: Active | B6: ID-07 | C6: TL | D6: Bakhtiyar Abdul-Ahadov, Shahid | E6: Abdul-Əhədov Bəxtiyar Şahid oğlu | F6: Terminal business support department | G6: Terminal biznesinə dəstək departamenti | H6: Terminal maintenance division | I6: Texniki təmir şöbəsi | J6: Team Lead | K6: Qrup Rəhbəri | L6: Nəbiyev Namiq Şahbəddin oğlu | M6: 40833 | O6: Indefinite | Q6: 26583 | R6: 54.016438 | S6: 5Z2EVQX | T6: Azerbaijan | U6: AZE 16149326 | W6: Full time | Y6: Male | Z6: +994555050880 | AA6: +994555050880 | AB6: bakhtiyar.abdul-ahadov@pashapay.az | AD6: Bakı Şəh., Babək Pr-Ti. Ev. 13, M. 15 | AE6: Bakı Şəh., Babək Pr-Ti. Ev. 13, M. 15 | AF6: married | AG6: 2 | AI6: Sabail rayonu, Gülbala Əliyev 54C
A7: Active | B7: ID-08 | C7: S | D7: Saida Najafova, Ali | E7: Nəcəfova Səidə Əli qızı | F7: Customer excellence department | G7: Müştəri mükəmməlliyi departamenti | H7: Customer care division | I7: Müştəri xidmətləri şöbəsi | J7: Senior Front Office Specialist | K7: Ön Masa üzrə Baş Mütəxəssis | L7: Əmirov Savalan İsrəfil oğlu | M7: 40841 | O7: Indefinite | Q7: 32461 | R7: 37.912329 | S7: 3FYUDSZ | T7: Azerbaijan | U7: AZE 16880009 | W7: Full time | Y7: Female | Z7: +994555050859 | AA7: +994555050859 | AB7: saida.nacafova@pashapay.az | AD7: Sumqayıt Şəh., Corat Qəs.,2-Məhəllə.133A | AE7: Sumqayıt Şəh., 1 Mr, Ev. 5B\9, M. 46 | AF7: married | AG7: 1 | AI7: Xırdalan
A8: Disabled | B8: ID-09 | C8: S | D8: Shahin Jabbarov, Arif | E8: Cabbarov Şahin Arif oğlu | F8: Terminal business support department | G8: Terminal biznesinə dəstək departamenti | H8: Terminal maintenance division | I8: Texniki təmir şöbəsi | J8: Technician Specialist | K8: Texniki İşlər üzrə Mütəxəssis | L8: Nəbiyev Namiq Şahbəddin oğlu | M8: 40858 | O8: Indefinite | Q8: 30281 | R8: 43.884932 | S8: 123F2UX | T8: Azerbaijan | U8: AZE 17738710 | W8: Full time | Y8: Male | Z8: +994555050882 | AB8: - | AD8: Bakı Şəh., Ə.Cavad, Ev. 37 | AE8: Bakı Şəh., Ə.Cavad, Ev. 37 | AF8: married | AG8: 2 | AI8: Sabail rayonu, Gülbala Əliyev 54C
A9: Active | B9: ID-14 | C9: TL | D9: Parviz Mayilov, Anvar | E9: Mayılov Pərviz Ənvər oğlu | F9: Terminal business support department | G9: Terminal biznesinə dəstək departamenti | H9: Terminal maintenance division | I9: Texniki təmir şöbəsi | J9: Team Lead | K9: Qrup Rəhbəri | L9: Nəbiyev Namiq Şahbəddin oğlu | M9: 41052 | O9: Indefinite | Q9: 32226 | R9: 38.556164 | S9: 27R7T84 | T9: Azerbaijan | U9: AZE 13532074 | W9: Full time | Y9: Male | Z9: +994555050868 | AA9: +994555050868 | AB9: parviz.mayilov@pashapay.az | AD9: Bakı Şəh., Əmircan Qəs., E.Həsənov Küç., Ev 95.,M.67/68 | AE9: Bakı Şəh., Əmircan Qəs., E.Həsənov Küç., Ev 95.,M.67/68 | AF9: married | AG9: 3 | AI9: Sabail rayonu, Gülbala Əliyev 54C
A10: Active | B10: ID-15 | C10: A | D10: Azer Afandiyev, Dadash | E10: Əfəndiyev Azər Dadaş oğlu | F10: Terminal business support department | G10: Terminal biznesinə dəstək departamenti | H10: Terminal technical support division | I10: Terminallara texniki dəstək şöbəsi | J10: Technical worker on terminal payments | K10: Terminal ödənişləri üzrə texniki işçi | L10: Əlizadə Nicat Əşrəf oğlu | M10: 41309 | O10: Indefinite | Q10: 31043 | R10: 41.79726 | S10: 2C5U6NR | T10: Azerbaijan | U10: AA 1276075 | W10: Full time | Y10: Male | Z10: +994555050877 | AB10: - | AD10: Bakı Şəh.,Nərimanov Ray.,Azadlıq Pr.,Ev.116,M.146 | AE10: Bakı Şəh.,Azadlıq Pr., Ev.116.,M.146 | AF10: married | AG10: 2 | AI10: Sabail rayonu, Gülbala Əliyev 54C
A11: Active | B11: ID-16 | C11: A | D11: Samir Zeynalov, Nizami | E11: Zeynalov Samir Nizami oğlu | F11: Terminal business support department | G11: Terminal biznesinə dəstək departamenti | H11: Terminal technical support division | I11: Terminallara texniki dəstək şöbəsi | J11: Technical worker on terminal payments | K11: Terminal ödənişləri üzrə texniki işçi | L11: Əlizadə Nicat Əşrəf oğlu | M11: 41421 | O11: Indefinite | Q11: 28198 | R11: 49.591781 | S11: 3JVXJS3 | T11: Azerbaijan | U11: AZE 13516551 | W11: Full time | Y11: Male | Z11: +994555050856 | AB11: - | AD11: Gəncə Şəh.,Nizami Küç.,12-Dal.,Ev 17A | AE11: Gəncə Şəh.,Nizami Küç.,12-Dal.,Ev 17A | AF11: married | AG11: 2 | AI11: Gəncə RİM
A12: Active | B12: ID-20 | C12: A | D12: Gismat Mammadov, Ali | E12: Məmmədov Qismət Əli oğlu | F12: - | G12: - | H12: Encashment division | I12: İnkassasiya Şöbəsi | J12: Driver Incasator | K12: Sürücü inkassator | L12: Abbasova Nurlana Ramiz qızı | M12: 41487 | O12: Indefinite | P12: Sumqayıt RİM | Q12: 24196 | R12: 60.556164 | S12: 3DRGLDR | T12: Azerbaijan | U12: AZE 15772995 | W12: Full time | Y12: Male | Z12: +994555050732 | AB12: - | AD12: Sumqayıt Şəh.,Mik-13, Ev.40, M.8 | AE12: Sumqayıt Şəh.,Mik-13, Ev.4 , M.8 | AF12: married | AG12: 2 | AI12: Sumqayıt RİM
A13: Active | B13: ID-19 | C13: A | D13: Elvin Mukhtarov, Yagub | E13: Muxtarov Elvin Yaqub oğlu | F13: - | G13: - | H13: Encashment division | I13: İnkassasiya Şöbəsi | J13: Cash Collector | K13: Kassir inkassator | L13: Abbasova Nurlana Ramiz qızı | M13: 41487 | O13: Indefinite | P13: Baki | Q13: 31933 | R13: 39.358904 | S13: 2TR9LZV | T13: Azerbaijan | U13: AZE 16939587 | W13: Full time | Y13: Male | Z13: +994555050881 | AB13: - | AD13: Bakı Şəh.,Sabunçu Ray.,Bakıxanov Qəs.,Y.Əliyev Küç.,Ev 3/51 | AE13: Bakı Şəh.,Bakıxanov Qəs.,Y.Əliyev Küç.,Ev 3/51 | AF13: married | AG13: 2 | AI13: Sabail rayonu, Gülbala Əliyev 54C
A14: Active | B14: ID-22 | C14: A | D14: Vasif Garibli, Hafiz | E14: Qəribli Vasif Hafiz oğlu | F14: Terminal business support department | G14: Terminal biznesinə dəstək departamenti | H14: Terminal technical support division | I14: Terminallara texniki dəstək şöbəsi | J14: Technical worker on terminal payments | K14: Terminal ödənişləri üzrə texniki işçi | L14: Əlizadə Nicat Əşrəf oğlu | M14: 41673 | O14: Indefinite | Q14: 33608 | R14: 34.769863 | S14: 4U72XH4 | T14: Azerbaijan | U14: AZE 16693991 | W14: Full time | Y14: Male | Z14: +994555050729 | AB14: - | AD14: İmişli Şəh., Ş.Qurbanov Küç., Ev.1 | AE14: Bakı Şəh.,Yasamal R-Nu, 2-Ci Alatava Ev 6A | AF14: married | AG14: 0 | AI14: Şirvan RİM
A15: Active | B15: ID-21 | C15: S | D15: Nijat Soltanov, Zulfigar | E15: Soltanov Nicat Zülfiqar oğlu | F15: Terminal business support department | G15: Terminal biznesinə dəstək departamenti | H15: Terminal business support division | I15: Terminal biznesinə dəstək şöbəsi | J15: Leading Warehouseman | K15: Aparıcı Anbardar | L15: Fərzəliyev Zaur Tofiq oğlu | M15: 41673 | O15: Indefinite | Q15: 31799 | R15: 39.726027 | S15: 1G7BF52 | T15: Azerbaijan | U15: AZE 13601703 | W15: Full time | Y15: Male | Z15: +994555050854 | AA15: +994555050854 | AB15: nicat.soltanov@pashapay.az | AD15: Bakı Şəh., Balandin- 42 | AE15: Bakı Şəh.,Suraxanı R-Nu Qaraçuxur Qəs.,Zaur Şərifov Küç., Ev.6, M. 5 | AF15: married | AG15: 2 | AI15: Sabail rayonu, Gülbala Əliyev 54C
A16: Active | B16: ID-23 | C16: M | D16: Nijat Alizade, Ashraf | E16: Əlizadə Nicat Əşrəf oğlu | F16: Terminal business support department | G16: Terminal biznesinə dəstək departamenti | H16: Terminal technical support division | I16: Terminallara texniki dəstək şöbəsi | J16: Technical Support Division Manager | K16: Texniki Dəstək üzrə Menecer | L16: Abbasov Toğrul Vaqif oğlu | M16: 41682 | O16: Indefinite | Q16: 32621 | R16: 37.473973 | S16: 4TARMCF | T16: Azerbaijan | U16: AZE 14910111 | W16: Full time | Y16: Male | Z16: +994555050885 | AA16: +994555050885 | AB16: nicat.alizade@pashapay.az | AD16: Füzuli Şəh., H.Hacıyev Küç.,Ev.17 | AE16: Bakı Şəh.,Sabunçu R-Nu Bakıxanov Qəs., Y.Əliyev Küç., Ev.1, M.41 | AF16: married | AG16: 1 | AI16: Sabail rayonu, Gülbala Əliyev 54C
A17: Active | B17: ID-24 | C17: A | D17: Emil Huseynov, Vagif | E17: Hüseynov Emil Vaqif oğlu | F17: - | G17: - | H17: Encashment division | I17: İnkassasiya Şöbəsi | J17: Cash Collector | K17: Kassir inkassator | L17: Abbasova Nurlana Ramiz qızı | M17: 41745 | O17: Indefinite | P17: Gəncə RİM | Q17: 31979 | R17: 39.232877 | S17: 26VBFGM | T17: Azerbaijan | U17: AA3901744 | V17: 48428 | W17: Full time | Y17: Male | Z17: +994555050829 | AB17: - | AD17: Gəncə Şəh.,Gülüstan Qəs.,Ev 47V,Mənzil 10 | AE17: Gəncə Şəh., M.Hacıyev Küç.,Ev 17 , M. 79 | AF17: married | AG17: 2 | AI17: Gəncə RİM
A18: Active | B18: ID-27 | C18: A | D18: Farid Ramazanov, Tanriverdi | E18: Ramazanov Fərid Tanrıverdi oğlu | F18: Terminal business support department | G18: Terminal biznesinə dəstək departamenti | H18: Terminal technical support division | I18: Terminallara texniki dəstək şöbəsi | J18: Technical worker on terminal payments | K18: Terminal ödənişləri üzrə texniki işçi | L18: Əlizadə Nicat Əşrəf oğlu | M18: 41792 | O18: Indefinite | Q18: 32432 | R18: 37.991781 | S18: 2K8WVV2 | T18: Azerbaijan | U18: AA3681121 | V18: 48265 | W18: Full time | Y18: Male | Z18: +994555050725 | AB18: - | AD18: Gəncə Şəh.,Nizami Ray.,Nizami Küç.,12-Dal.,Ev.22 | AE18: Gəncə Şəh.,Nizami Ray.,Nizami Küç.,12-Dal.,Ev.22 | AF18: single | AG18: 0 | AI18: Gəncə RİM
A19: Active | B19: ID-28 | C19: A | D19: Ilkin Aghazade, Ilgar | E19: Ağazadə İlkin İlqar oğlu | F19: - | G19: - | H19: Encashment division | I19: İnkassasiya Şöbəsi | J19: Cash Collector | K19: Kassir inkassator | L19: Abbasova Nurlana Ramiz qızı | M19: 41815 | O19: Indefinite | P19: Sumqayıt RİM | Q19: 34093 | R19: 33.441096 | S19: 5KH5LQE | T19: Azerbaijan | U19: AZE 17486581 | W19: Full time | Y19: Male | Z19: +994555050837 | AB19: - | AD19: Bakı Şəh.,Binəqədi Qəs.,Mədən-2 Kor-94, Ev.7 | AE19: Bakı Şəh.,Binəqədi Qəs.,Mədən-2 Kor-94, Ev.7 | AF19: single | AG19: 0 | AI19: Sumqayıt RİM
A20: Active | B20: ID-29 | C20: TL | D20: Sarkhan Mahmudov, Bakhtijamal | E20: Mahmudov Sərxan Bəxticamal oğlu | F20: - | G20: - | H20: Encashment division | I20: İnkassasiya Şöbəsi | J20: Cash Team Leader | K20: Kassa üzrə Qrup Rəhbəri | L20: Abbasova Nurlana Ramiz qızı | M20: 41834 | O20: Indefinite | Q20: 34190 | R20: 33.175342 | S20: 5QNKESL | T20: Azerbaijan | U20: AZE 07794353 | W20: Full time | Y20: Male | Z20: +994555050713 | AA20: +994555050713 | AB20: sarxan.mahmudov@pashapay.az | AD20: Gəncə Şəh.,Ordubadi Küç.,Ev.52 | AE20: Gəncə Şəh.,Ordubadi Küç.,Ev.52 | AF20: single | AG20: 0 | AI20: Tovuz RİM
A21: Active | B21: ID-31 | C21: A | D21: Samir Mammadov, Rafig | E21: Məmmədov Samir Rafiq oğlu | F21: Terminal business support department | G21: Terminal biznesinə dəstək departamenti | H21: Terminal business support division | I21: Terminal biznesinə dəstək şöbəsi | J21: Labourer | K21: Fəhlə | L21: Fərzəliyev Zaur Tofiq oğlu | M21: 41900 | O21: Indefinite | Q21: 31001 | R21: 41.912329 | S21: 5N6TJJ2 | T21: Azerbaijan | U21: AA 1564987 | W21: Full time | Y21: Male | Z21: +994775413114 | AB21: - | AD21: Bakı Şəh., Binəqədi Ray.,Xocəsən Qəs.F.Ağazadə Küç., Ev.9. | AE21: Bakı Şəh., Xocəsən Qəs.F.Ağazadə Küç., Ev.9. | AF21: married | AG21: 2 | AI21: Sabail rayonu, Gülbala Əliyev 54C
A22: Active | B22: ID-32 | C22: A | D22: Novruz Aliyev, Gardashkhan | E22: Əliyev Novruz Qardaşxan oğlu | F22: - | G22: - | H22: Encashment division | I22: İnkassasiya Şöbəsi | J22: Driver Incasator | K22: Sürücü inkassator | L22: Abbasova Nurlana Ramiz qızı | M22: 41913 | O22: Indefinite | P22: Baki | Q22: 21253 | R22: 68.619178 | S22: 0XWH4TN | T22: Azerbaijan | U22: AZE 07490998 | W22: Full time | Y22: Male | Z22: +994554305274 | AB22: - | AD22: Bakı Şəh., Y/Günəşli Qəs., V Y/S., Ev.6., M. 64 | AE22: Bakı Şəh., Y/Günəşli Qəs., V Y/S., Ev.6., M. 64 | AF22: married | AG22: 2 | AI22: Sabail rayonu, Gülbala Əliyev 54C
A23: Active | B23: ID-38 | C23: A | D23: Elvin Rzayev, Anvar | E23: Rzayev Elvin Ənvər oğlu | F23: - | G23: - | H23: Encashment division | I23: İnkassasiya Şöbəsi | J23: Cash Collector | K23: Kassir inkassator | L23: Abbasova Nurlana Ramiz qızı | M23: 41975 | O23: Indefinite | P23: Lənkaran RİM | Q23: 31329 | R23: 41.013699 | S23: 1SDS8RN | T23: Azerbaijan | U23: AZE 13790923 | W23: Full time | Y23: Male | Z23: +994555050886 | AB23: - | AD23: Astara Ray., Maşxan Kəndi | AE23: Astara Ray., Maşxan Kəndi | AF23: married | AG23: 3 | AI23: Lənkaran RİM
A24: Active | B24: ID-39 | C24: S | D24: Amina Mammadli, Tahir | E24: Məmmədli Əminə Tahir qızı | F24: Customer excellence department | G24: Müştəri mükəmməlliyi departamenti | H24: Customer care division | I24: Müştəri xidmətləri şöbəsi | J24: Leading Front Office Specialist | K24: Ön Masa üzrə Aparıcı Mütəxəssis | L24: Əmirov Savalan İsrəfil oğlu | M24: 41984 | O24: Indefinite | Q24: 33528 | R24: 34.989041 | S24: 5B32QXX | T24: Azerbaijan | U24: AZE 16698689 | W24: Full time | Y24: Female | Z24: +994555050827 | AA24: +994555050827 | AB24: amina.karimli@pashapay.az | AD24: Lənkəran Şəh., S. Bayramov Küç., Ev.15 | AE24: Lənkəran Şəh., S. Bayramov Küç., Ev.15 | AF24: married | AG24: 1 | AI24: Lənkaran RİM
A25: Active | B25: ID-40 | C25: A | D25: Yegana Hajiyeva, Safar | E25: Hacıyeva Yeganə Səfər qızı | F25: - | G25: - | H25: - | I25: - | J25: Cleaning Lady | K25: Xidmətçi | L25: KB-yə Kassa və inkassasiya prosesləri departamentinə keçirilir, rəsmiləşmədədirlər. | M25: 42010 | O25: Indefinite | Q25: 26712 | R25: 53.663014 | S25: 2H535C8 | T25: Azerbaijan | U25: AZE 15009421 | W25: Full time | Y25: Female | Z25: +994514914125 | AB25: - | AD25: Lənkəran Ray., İstisu Qəs. | AE25: Lənkəran Ray., İstisu Qəs. | AF25: married | AG25: 2 | AI25: Lənkaran RİM
A26: Disabled | B26: ID-41 | C26: S | D26: Akif Salmanov, Israfil | E26: Salmanov Akif İsrafil oğlu | F26: Terminal business support department | G26: Terminal biznesinə dəstək departamenti | H26: Terminal maintenance division | I26: Texniki təmir şöbəsi | J26: Technician Specialist | K26: Texniki İşlər üzrə Mütəxəssis | L26: Nəbiyev Namiq Şahbəddin oğlu | M26: 42061 | O26: Indefinite | Q26: 22369 | R26: 65.561644 | S26: 2KD6A24 | T26: Azerbaijan | U26: AZE 09241005 | W26: Full time | Y26: Male | Z26: +994505475742 | AB26: - | AD26: Abşeron Ray., Masazır Kəndi, Yolaltı 1 Küç. | AE26: Abşeron Ray., Əliağa Vahid Küç.14 | AF26: married | AG26: 2 | AI26: Distant
A27: Active | B27: ID-43 | C27: A | D27: Iltimas Guliyeva, Mammadali | E27: Quliyeva İltimas Məmmədəli qızı | F27: - | G27: - | H27: - | I27: - | J27: Cleaning Lady | K27: Xidmətçi | L27: KB-yə Kassa və inkassasiya prosesləri departamentinə keçirilir, rəsmiləşmədədirlər. | M27: 42074 | O27: Indefinite | Q27: 22255 | R27: 65.873973 | S27: 3N5CSXL | T27: Azerbaijan | U27: AZE 09191323 | W27: Full time | Y27: Female | Z27: +994558204812 | AB27: - | AD27: Gəncə Şəh., Qaçaq Nəbi Küç., Ev.18 | AE27: Gəncə Şəh., Qaçaq Nəbi Küç., Ev.18 | AF27: married | AG27: 2 | AI27: Gəncə RİM
A28: Disabled | B28: ID-44 | C28: S | D28: Jamaladdin Karimov, Tapdig | E28: Kərimov Cəmaləddin Tapdıq oğlu | F28: Terminal business support department | G28: Terminal biznesinə dəstək departamenti | H28: Terminal maintenance division | I28: Texniki təmir şöbəsi | J28: Technician Specialist | K28: Texniki İşlər üzrə Mütəxəssis | L28: Nəbiyev Namiq Şahbəddin oğlu | M28: 42095 | O28: Indefinite | Q28: 25756 | R28: 56.282192 | S28: 2D48PV0 | T28: Azerbaijan | U28: AA 0175241 | W28: Full time | Y28: Male | Z28: +994503490308 | AB28: - | AD28: Ağdam Şəh., Ağdamkənd Sahəsi | AE28: Sumqayıt Şəh., 3 Mkr., Ev..11/8, M.1 | AF28: married | AG28: 2 | AI28: Distant
A29: Active | B29: ID-46 | C29: S | D29: Anar Huseynov, Telman | E29: Hüseynov Anar Telman oğlu | F29: Terminal business support department | G29: Terminal biznesinə dəstək departamenti | H29: Encashment processes support division | I29: İnkassasiya proseslərinə dəstək şöbəsi | J29: Leading Specialist | K29: Aparıcı mütəxəssis | L29: Rüstəmzadə İlqar Vilayət oğlu | M29: 42101 | O29: Indefinite | Q29: 33044 | R29: 36.315068 | S29: 5A6CGR7 | T29: Azerbaijan | U29: AZE 15477512 | W29: Full time | Y29: Male | Z29: +994555050734 | AA29: +994555050734 | AB29: anar.huseynov@pashapay.az | AD29: Ağdam Şəh.,S.Vurğun Küç., Ev.9 | AE29: Bakı Şəh.,Binəqədi Ray., Dərnəgül Qəs.,K.Rəhimov 7 , 9 Saylı Bpl-Nin Yataqxanası | AF29: married | AG29: 2 | AI29: Sabail rayonu, Gülbala Əliyev 54C
A30: Active | B30: ID-47 | C30: S | D30: Rena Umudova, Valeh | E30: Umudova Rəna Valeh qızı | F30: - | G30: - | H30: - | I30: - | J30: Accountant | K30: Mühasib | L30: Piriyev Abdulla Vaqif oğlu | M30: 42125 | O30: Indefinite | Q30: 29538 | R30: 45.920548 | S30: 1KU2PJK | T30: Azerbaijan | U30: AZE 17192707 | W30: Full time | Y30: Female | Z30: +994555050743 | AA30: +994555050743 | AB30: rena.umudova@pashapay.az | AD30: Ağdam Ray.,T.İsmayılov Küç.,Ev.,32 | AE30: Bakı Şəh.,Nəsimi R-Nu, Hüseynzadə Küç.,Ev.1 M.7 | AF30: single | AG30: 2 | AI30: Port Baku 2
A31: Active | B31: ID-49 | C31: A | D31: Igbal Aslanov, Aliheydar | E31: Aslanov İqbal Əliheydər oğlu | F31: - | G31: - | H31: Encashment division | I31: İnkassasiya Şöbəsi | J31: Driver Incasator | K31: Sürücü inkassator | L31: Abbasova Nurlana Ramiz qızı | M31: 42136 | O31: Indefinite | P31: Xaçmaz RİM | Q31: 27762 | R31: 50.786301 | S31: 25D4LW2 | T31: Azerbaijan | U31: AZE 08865483 | W31: Full time | Y31: Male | Z31: +994554168014 | AB31: - | AD31: Lənkəran Şəh., S.Bayramov Küç., Ev.2 | AE31: Lənkəran Şəh., S.Bayramov Küç., Ev.2 | AF31: single | AG31: 2 | AI31: Xaçmaz RİM
A32: Active | B32: ID-50 | C32: A | D32: Aykhan Mammadov, Ali | E32: Məmmədov Ayxan Əli oğlu | F32: Terminal business support department | G32: Terminal biznesinə dəstək departamenti | H32: Terminal technical support division | I32: Terminallara texniki dəstək şöbəsi | J32: Technical worker on terminal payments | K32: Terminal ödənişləri üzrə texniki işçi | L32: Əlizadə Nicat Əşrəf oğlu | M32: 42137 | O32: Indefinite | Q32: 34351 | R32: 32.734247 | S32: 5R23NUV | T32: Azerbaijan | U32: AA 0111581 | W32: Full time | Y32: Male | Z32: +994509929200 | AB32: - | AD32: Bakı Şəh.,6 Mkr., Üzeyir Hacıbəyov Küç., Ev 2/10, M.36 | AE32: Bakı Şəh.,6 Mkr., Ü.Hacıbəyov Küç., Ev 2/1 , M.36 | AF32: single | AG32: 0 | AI32: Sabail rayonu, Gülbala Əliyev 54C
A33: Active | B33: ID-52 | C33: A | D33: Ajdar Isgandarov, Elshan | E33: İsgəndərov Əjdər Elşən oğlu | F33: - | G33: - | H33: Encashment division | I33: İnkassasiya Şöbəsi | J33: Driver Incasator | K33: Sürücü inkassator | L33: Abbasova Nurlana Ramiz qızı | M33: 42137 | O33: Indefinite | P33: Sumqayıt RİM | Q33: 31355 | R33: 40.942466 | S33: 16ZBZDA | T33: Azerbaijan | U33: AA 0969761 | W33: Full time | Y33: Male | Z33: +994554667470 | AB33: - | AD33: Bakı.,Mirzağa Əliyev | AE33: Bakı Şəh., M.A.Əliyev , Ev.6 A | AF33: married | AG33: 1 | AI33: Sumqayıt RİM
A34: Active | B34: ID-53 | C34: M | D34: Ilgar Rustamzade, Vilayat | E34: Rüstəmzadə İlqar Vilayət oğlu | F34: Terminal business support department | G34: Terminal biznesinə dəstək departamenti | H34: Encashment processes support division | I34: İnkassasiya proseslərinə dəstək şöbəsi | J34: Transportation Manager | K34: Nəqliyyat üzrə Menecer | L34: Abbasov Toğrul Vaqif oğlu | M34: 42160 | O34: Indefinite | Q34: 26315 | R34: 54.750685 | S34: 22W7SDV | T34: Azerbaijan | U34: AZE 05582474 | W34: Full time | Y34: Male | Z34: +994555050803 | AA34: +994555050803 | AB34: ilgar.rustamzade@pashapay.az | AD34: Bakı Şəh., Rəsulzadə Qəs., S.Bəhlulzadə Küç.,Dön-1, Ev.49/184 | AE34: Bakı Şəh., Rəsulzadə Qəs., S.Bəhlulzadə Küç.,Dön-1, Ev.49/184 | AF34: married | AG34: 2 | AI34: Sabail rayonu, Gülbala Əliyev 54C
A35: Active | B35: ID-54 | C35: S | D35: Samir Hajiyev, Mehman | E35: Hacıyev Samir Mehman oğlu | F35: Terminal business support department | G35: Terminal biznesinə dəstək departamenti | H35: Encashment processes and cash centers monitoring division | I35: İnkassasiya prosesi və kassa mərkəzlərinin monitorinqi şöbəsi | J35: Leading Specialist | K35: Aparıcı mütəxəssis | L35: Ramaldanov Şıxbala Şair oğlu | M35: 42171 | O35: Indefinite | Q35: 32136 | R35: 38.80274 | S35: 23HSLEQ | T35: Azerbaijan | U35: AZE 14699821 | W35: Full time | Y35: Male | Z35: +994555050726 | AA35: +994555050726 | AB35: samir.haciyev@pashapay.az | AD35: Bakı Şəh.,Xətai Ray.,Q.Məmmədov Küç., Ev.4 Yat. | AE35: Bakı Şəh.,Abşeron R-Nu.,Masazır Qəs., R.Dünyamalıyev Küç., Dal.4, Ev.7 | AF35: married | AG35: 2 | AI35: Sabail rayonu, Gülbala Əliyev 54C
A36: Active | B36: ID-56 | C36: TL | D36: Azer Guliyev, Shaban | E36: Quliyev Azər Şaban oğlu | F36: Security department | G36: Təhlükəsizlik departamenti | H36: - | I36: - | J36: Security Team Leader | K36: Təhlükəsizlik üzrə Qrup Rəhbəri | L36: Məmmədov Kənan Eldar oğlu | M36: 42177 | O36: Indefinite | Q36: 23384 | R36: 62.780822 | S36: 14NYKYW | T36: Azerbaijan | U36: AZE 14574856 | W36: Full time | Y36: Male | Z36: +994555050735 | AA36: +994512771060 | AB36: azer.quliyev@pashapay.az | AD36: Bakı Şəh.,Yasamal Ray., Şərifzadə Küç., Ev.10A, M.20 | AE36: Bakı Şəh.,Yasamal Ray., Şərifzadə Küç., Ev.1 A, M.2 | AF36: married | AG36: 2 | AI36: Sabail rayonu, Gülbala Əliyev 54C
A37: Active | B37: ID-57 | C37: A | D37: Nurlan Sultanov, Nariman | E37: Sultanov Nurlan Nəriman oğlu | F37: Terminal business support department | G37: Terminal biznesinə dəstək departamenti | H37: Terminal technical support division | I37: Terminallara texniki dəstək şöbəsi | J37: Technical worker on terminal payments | K37: Terminal ödənişləri üzrə texniki işçi | L37: Əlizadə Nicat Əşrəf oğlu | M37: 42222 | O37: Indefinite | Q37: 33348 | R37: 35.482192 | S37: 4YVX18T | T37: Azerbaijan | U37: AZE 16216923 | W37: Full time | Y37: Male | Z37: +994555050893 | AB37: - | AD37: Dəvəçi Şəh.,Nizami Küç., Ev.9 | AE37: Dəvəçi Şəh.,Nizami Küç., Ev.9 | AF37: married | AG37: 2 | AI37: Sabail rayonu, Gülbala Əliyev 54C
A38: Active | B38: ID-58 | C38: TL | D38: Ilkin Ahmadzade, Azer | E38: Əhmədzadə İlkin Azər oğlu | F38: - | G38: - | H38: Encashment division | I38: İnkassasiya Şöbəsi | J38: Cash Team Leader | K38: Kassa üzrə Qrup Rəhbəri | L38: Abbasova Nurlana Ramiz qızı | M38: 42234 | O38: Indefinite | Q38: 33886 | R38: 34.008219 | S38: 5HUWPET | T38: Azerbaijan | U38: AZE 17345823 | W38: Full time | Y38: Male | Z38: +994706690042 | AB38: ilkin.ahmadzade@pashapay.az | AD38: Lənkəran Şəh., Akademik Z.Əliyeva Küç., Ev.78/10, M.62 | AE38: Lənkəran Şəh., Akademik Z.Əliyeva Küç., Ev.78/1 , M.62 | AF38: married | AG38: 1 | AI38: Bilasuvar RİM
A39: Active | B39: ID-59 | C39: M | D39: Khalil Khanabadskiy, Elkhan | E39: Xanabadskiy Xəlil Elxan oğlu | F39: Settlements department | G39: Hesablaşmalar departamenti | H39: Payment system division | I39: Ödəniş Sistemləri | J39: Payment System Manager | K39: Ödəniş Sistemləri Şöbəsinin Meneceri | L39: Usubova Sevinc Cəfər qızı | M39: 42269 | O39: Indefinite | Q39: 33840 | R39: 34.134247 | S39: 5F4RJN9 | T39: Azerbaijan | U39: AZE 17134907 | W39: Full time | Y39: Male | Z39: +994555050819 | AA39: +994555050819 | AB39: khalil.khanabadski@pashapay.az | AD39: Bakı Şəh.,Binəqədi Ray.,S.S.Axundov Küç.,Ev 4A,M.37 | AE39: Bakı Şəh.,Binəqədi Ray.,S.S.Axundov Küç.,Ev 4A,M.37 | AF39: married | AG39: 0 | AI39: Port Baku 2
A40: Active | B40: ID-61 | C40: A | D40: Ismayil Aliyev, Hasan | E40: Əliyev İsmayıl Həsən oğlu | F40: - | G40: - | H40: Encashment division | I40: İnkassasiya Şöbəsi | J40: Driver Incasator | K40: Sürücü inkassator | L40: Abbasova Nurlana Ramiz qızı | M40: 42391 | O40: Indefinite | P40: Gəncə RİM | Q40: 32761 | R40: 37.090411 | S40: 4L67635 | T40: Azerbaijan | U40: AZE 14073970 | W40: Full time | Y40: Male | Z40: +994558438858 | AB40: - | AD40: Gəncə Şəh., Nizami Ray., H.Əliyev Pr. Ev.147, M.89 | AE40: Gəncə Şəh., Nizami Ray., H.Əliyev Pr. Ev.147, M.89 | AF40: married | AG40: 1 | AI40: Gəncə RİM
A41: Active | B41: ID-62 | C41: A | D41: Famil Abasov, Mirmahammad | E41: Abasov Famil Mirməhəmməd oğlu | F41: Terminal business support department | G41: Terminal biznesinə dəstək departamenti | H41: Terminal technical support division | I41: Terminallara texniki dəstək şöbəsi | J41: Technical worker on terminal payments | K41: Terminal ödənişləri üzrə texniki işçi | L41: Əlizadə Nicat Əşrəf oğlu | M41: 42391 | O41: Indefinite | Q41: 30918 | R41: 42.139726 | S41: 0ZAADZN | T41: Azerbaijan | U41: AZE 08045401 | W41: Full time | Y41: Male | Z41: +994555050891 | AB41: - | AD41: Bakı Şəh., Gen.Mehmandarov Küç., Ev 2, M.82 | AE41: Masallı Rayonu, Rüdəkənar Kəndi | AF41: married | AG41: 2 | AI41: Lənkaran RİM
A42: Active | B42: ID-64 | C42: TL | D42: Zaur Bakhshiyev, Tofig | E42: Baxşıyev Zaur Tofiq oğlu | F42: Terminal business support department | G42: Terminal biznesinə dəstək departamenti | H42: Encashment processes support division | I42: İnkassasiya proseslərinə dəstək şöbəsi | J42: Transportation Team Leader | K42: Nəqliyyat üzrə Qrup Rəhbəri | L42: Rüstəmzadə İlqar Vilayət oğlu | M42: 42527 | O42: Indefinite | Q42: 27610 | R42: 51.20274 | S42: 3G7RMPY | T42: Azerbaijan | U42: AA 7300093 | W42: Full time | Y42: Male | Z42: +994506129733 | AA42: +994506129733 | AB42: zaur.baxshiyev@pashapay.az | AD42: Bakı Şəh.,A.M. Şərifzadə Küç.,Ev 138,M 42 | AE42: Yasamal Ray.,Kamal Rəhimov Küç.,15 Mənzil 14 | AF42: married | AG42: 2 | AI42: Sabail rayonu, Gülbala Əliyev 54C
A43: Active | B43: ID-65 | C43: A | D43: Beytulla Mammadov, Vugar | E43: Məmmədov Beytulla Vüqar oğlu | F43: - | G43: - | H43: Encashment division | I43: İnkassasiya Şöbəsi | J43: Cash Collector | K43: Kassir inkassator | L43: Abbasova Nurlana Ramiz qızı | M43: 42528 | O43: Indefinite | P43: Lənkaran RİM | Q43: 33138 | R43: 36.057534 | S43: 4WRLAQK | T43: Azerbaijan | U43: AZE 15327798 | W43: Full time | Y43: Male | Z43: +994555050719 | AB43: - | AD43: Lənkəran Şəh.,M.Əsədov Küç.,Ev 2/14 | AE43: Lənkəran Şəh.,Şəhidlər Xiyabanı Ev 46/1 , M.11 | AF43: married | AG43: 2 | AI43: Lənkaran RİM
A44: Active | B44: ID-66 | C44: A | D44: Arzu Hasanov, Humbat | E44: Həsənov Arzu Hümbət oğlu | F44: - | G44: - | H44: Encashment division | I44: İnkassasiya Şöbəsi | J44: Driver Incasator | K44: Sürücü inkassator | L44: Abbasova Nurlana Ramiz qızı | M44: 42552 | O44: Indefinite | P44: Tovuz RİM | Q44: 30737 | R44: 42.635616 | S44: 2GGJ5VV | T44: Azerbaijan | U44: AA 0553408 | W44: Full time | Y44: Male | Z44: +994555171020 | AB44: - | AD44: Gəncə Şəh.,Gənclər Küç.,Ev 27 | AE44: Gəncə Şəh.,Kəpəz Ray.,Gənclər Küç.,Ev 27 | AF44: married | AG44: 2 | AI44: Tovuz RİM
A45: Active | B45: ID-67 | C45: A | D45: Farid Babayev, Sokrat | E45: Babayev Fərid Sokrat oğlu | F45: Terminal business support department | G45: Terminal biznesinə dəstək departamenti | H45: Terminal technical support division | I45: Terminallara texniki dəstək şöbəsi | J45: Technical worker on terminal payments | K45: Terminal ödənişləri üzrə texniki işçi | L45: Əlizadə Nicat Əşrəf oğlu | M45: 42640 | O45: Indefinite | Q45: 33301 | R45: 35.610959 | S45: 52Y06RK | T45: Azerbaijan | U45: AZE 15292453 | W45: Full time | Y45: Male | Z45: +994555050878 | AB45: - | AD45: Bakı Ş.,N.Nərimanov Ray.,Y.Nəsirov Küç.,Məh.1921,M.42 | AE45: Bakı Ş.,N.Nərimanov Ray.,Y.Nəsirov Küç.,Məh.1921,M.42 | AF45: single | AG45: 0 | AI45: Sabail rayonu, Gülbala Əliyev 54C
A46: Active | B46: ID-68 | C46: TL | D46: Gulnaz Javanshirli (Rajabova), Chingiz | E46: Cavanşirli (Rəcəbova) Gülnaz Çingiz qızı | F46: Customer excellence department | G46: Müştəri mükəmməlliyi departamenti | H46: Customer care division | I46: Müştəri xidmətləri şöbəsi | J46: Customer Relations Team Lead | K46: Müştəri Xidmətləri üzrə Qrup Rəhbəri | L46: Əmirov Savalan İsrəfil oğlu | M46: 42675 | O46: Indefinite | Q46: 34586 | R46: 32.090411 | S46: 5VSSKJZ | T46: Azerbaijan | U46: AA4348012 | V46: 48423 | W46: Full time | Y46: Female | Z46: +994555050831 | AA46: +994506658595 | AB46: gulnaz.javanshirli@pashapay.az | AD46: Bakı Şəh.,1-Ci Alatava | AE46: Bakı Şəh.,Yasamal Ray.,Akademik Qarayev 2 | AF46: single | AG46: 0 | AI46: Azure
A47: Active | B47: ID-69 | C47: A | D47: Fizuli Imanov, Maharram | E47: İmanov Fizuli Məhərrəm oğlu | F47: Terminal business support department | G47: Terminal biznesinə dəstək departamenti | H47: Encashment processes support division | I47: İnkassasiya proseslərinə dəstək şöbəsi | J47: Driver | K47: Sürücü | L47: Rüstəmzadə İlqar Vilayət oğlu | M47: 42678 | O47: Indefinite | Q47: 31566 | R47: 40.364384 | S47: 1KCA5GK | T47: Azerbaijan | U47: AZE 09766254 | W47: Full time | Y47: Male | Z47: +994555050867 | AB47: - | AD47: Bakı Şəh.,Şüvəlan Qəs.,Gülçülük Sovxozu,Ev 6,M.2 | AE47: Bakı Şəh.,Şüvəlan Qəs.,Gülçülük Sovxozu,Ev 6,M.2 | AF47: married | AG47: 0 | AI47: Sabail rayonu, Gülbala Əliyev 54C
A48: Disabled | B48: ID-70 | C48: TL | D48: Aghali Ahmadov, Siyasat | E48: Əhmədov Ağali Siyasət oğlu | F48: Terminal business support department | G48: Terminal biznesinə dəstək departamenti | H48: Terminal business support division | I48: Terminal biznesinə dəstək şöbəsi | J48: Team Lead | K48: Qrup Rəhbəri | L48: Fərzəliyev Zaur Tofiq oğlu | M48: 42709 | O48: Indefinite | Q48: 29920 | R48: 44.873973 | S48: 4CJAKHD | T48: Azerbaijan | U48: AZE 16534767 | W48: Full time | Y48: Male | Z48: +994555050813 | AA48: +994555050813 | AB48: agali.akhmadov@pashapay.az | AD48: Neftçala Şəh.,M.Ə.Rəsulzadə Küç.,Ev.16,M.14 | AE48: Bakı Şəh.,Nəsimi R-Nu, 2 Mkr.Cavadxan(Gəncə Xanı) Küç.6 ,Ev 54 | AF48: married | AG48: 2 | AI48: Sabail rayonu, Gülbala Əliyev 54C
A49: Active | B49: ID-73 | C49: S | D49: Adila Mammadova, Adalat | E49: Məmmədova Ədilə Ədalət qızı | F49: Customer excellence department | G49: Müştəri mükəmməlliyi departamenti | H49: Customer complaints division | I49: Müştəri şikayətləri şöbəsi | J49: Senior Customer Complaints Specialist | K49: Müştəri Şikayətləri üzrə Baş Mütəxəssis | L49: Ağazadə Bəhmən Zeynal oğli | M49: 42752 | O49: Indefinite | Q49: 34007 | R49: 33.676712 | S49: 5NJ9FVZ | T49: Azerbaijan | U49: AZE 17828756 | W49: Full time | Y49: Female | Z49: +994555050847 | AA49: +994555050847 | AB49: adelya.mammadova@pashapay.az | AD49: Bakı Ş.,Niyazi Küç.,Ev.32 | AE49: S.Orucov Küç.Ev 2,M. 3 | AF49: single | AG49: 0 | AI49: Azure
A50: Active | B50: ID-75 | C50: A | D50: Turan Abdullayev, Galib | E50: Abdullayev Turan Qalib oğlu | F50: - | G50: - | H50: Encashment division | I50: İnkassasiya Şöbəsi | J50: Cash Collector | K50: Kassir inkassator | L50: Abbasova Nurlana Ramiz qızı | M50: 42780 | O50: Indefinite | P50: Gəncə RİM | Q50: 28252 | R50: 49.443836 | S50: 1EJ80FT | T50: Azerbaijan | U50: AA5043243 | V50: 48775 | W50: Full time | Y50: Male | Z50: +994555050845 | AB50: - | AD50: Gəncə Şəh.,Nizami Ray.,Gülüstan Qəs.,Ev.15,M.34 | AE50: Gəncə Şəh.,Nizami Ray.,Gülüstan Qəs.,Ev.15,M.34 | AF50: married | AG50: 2 | AI50: Gəncə RİM
A51: Active | B51: ID-76 | C51: S | D51: Shams Jalilova (Ismayilova), Hakim | E51: Cəlilova Şəms (İsmayılova) Hakim | F51: Settlements department | G51: Hesablaşmalar departamenti | H51: Payment system division | I51: Ödəniş Sistemləri | J51: Senior Settlements Specialist | K51: Hesablaşmalar üzrə Baş Mütəxəssis | L51: Xanabadskiy Xəlil Elxan oğlu | M51: 42811 | O51: Indefinite | Q51: 33892 | R51: 33.991781 | S51: 5NP2VJF | T51: Azerbaijan | U51: AZE 17512020 | W51: Full time | Y51: Female | Z51: +994555050730 | AA51: +994506306116 | AB51: shams.ismayilova@pashapay.az | AD51: Bakı Şəh.Nərimanov Ray.,Atatürk Pr.,Ev.2A,M.35 | AE51: Xətai Ray.,Gəncə Pr.,2 A | AF51: single | AG51: 0 | AI51: Port Baku 2
A52: Active | B52: ID-77 | C52: A | D52: Zaur Asgarov, Aydin | E52: Əsgərov Zaur Aydın oğlu | F52: - | G52: - | H52: Encashment division | I52: İnkassasiya Şöbəsi | J52: Driver Incasator | K52: Sürücü inkassator | L52: Abbasova Nurlana Ramiz qızı | M52: 42839 | O52: Indefinite | P52: Tovuz RİM | Q52: 28141 | R52: 49.747945 | S52: 2B6664D | T52: Azerbaijan | U52: AZE 09207640 | W52: Full time | Y52: Male | Z52: +994707145323 | AB52: - | AD52: Gəncə Şəh.,H.Şəh-83,Ev.402,M.37 | AE52: Gəncə Şəh.,H.Şəh-83,Ev.4 2,M.37 | AF52: married | AG52: 2 | AI52: Tovuz RİM
A53: Active | B53: ID-79 | C53: A | D53: Tofig Allahverdiyev, Natig | E53: Allahverdiyev Tofiq Natiq oğlu | F53: Terminal business support department | G53: Terminal biznesinə dəstək departamenti | H53: Terminal technical support division | I53: Terminallara texniki dəstək şöbəsi | J53: Technical worker on terminal payments | K53: Terminal ödənişləri üzrə texniki işçi | L53: Əlizadə Nicat Əşrəf oğlu | M53: 42898 | O53: Indefinite | Q53: 34663 | R53: 31.879452 | S53: 5VM8DS4 | T53: Azerbaijan | U53: AZE 08539233 | W53: Full time | Y53: Male | Z53: +994555050883 | AB53: - | AD53: Gəncə Şəh.,Atatürk Pr.,Ev 245 | AE53: Gəncə Şəh.,Atatürk Pr.,Ev 245 | AF53: married | AG53: 1 | AI53: Gəncə RİM
A54: Active | B54: ID-82 | C54: TL | D54: Nuran Mammadzade, Zafar | E54: Məmmədzadə Nuran Zəfər oğlu | F54: Terminal and ATM department | G54: Terminal və ATM şəbəkəsinin idarə edilməsi departamenti | H54: Terminal and ATM distibution division | I54: Terminal və ATM-lərin yerləşdirilməsi | J54: Terminal Installation Team Lead | K54: Terminalların Yerləşdirilməsi üzrə Qrup Rəhbəri | L54: Ramazanov Rəşad Cəfər oğlu | M54: 42964 | O54: Indefinite | Q54: 31323 | R54: 41.030137 | S54: 1AS38YY | T54: Azerbaijan | U54: AZE 08133837 | W54: Full time | X54: Bachelor | Y54: Male | Z54: +994555050814 | AA54: +994555050814 | AB54: nuran.mammadzade@pashapay.az | AD54: Bakı Şəh.,Ə.Hüseynzadə Küç.,Ev8, M.39 | AE54: Bakı Şəh.,Ə.Hüseynzadə Küç.,Ev8, M.39 | AF54: married | AG54: 1 | AI54: Port Baku 2
A55: Active | B55: ID-84 | C55: TL | D55: Rafig Aliyev, Ilgar | E55: Əliyev Rafiq İlqar oğlu | F55: Terminal and ATM department | G55: Terminal və ATM şəbəkəsinin idarə edilməsi departamenti | H55: Terminal and ATM distibution division | I55: Terminal və ATM-lərin yerləşdirilməsi | J55: Sales Representative Team Lead | K55: Satış Təmsilçiləri üzrə Qrup Rəhbəri | L55: Ramazanov Rəşad Cəfər oğlu | M55: 42989 | O55: Indefinite | Q55: 32899 | R55: 36.712329 | S55: 4U4PSBZ | T55: Azerbaijan | U55: AZE 15010965 | W55: Full time | X55: Bachelor | Y55: Male | Z55: +994555050849 | AA55: +994707633363 | AB55: rafig.aliyev@pashapay.az | AD55: Lənkəran Ray.,Küvənil Kəndi | AE55: Lənkəran Ray.,Küvənil Kəndi | AF55: married | AG55: 2 | AI55: Lənkaran RİM
A56: Active | B56: ID-85 | C56: A | D56: Murad Hasanov, Fayaz | E56: Həsənov Murad Fayaz oğlu | F56: Terminal business support department | G56: Terminal biznesinə dəstək departamenti | H56: Terminal technical support division | I56: Terminallara texniki dəstək şöbəsi | J56: Technical worker on terminal payments | K56: Terminal ödənişləri üzrə texniki işçi | L56: Əlizadə Nicat Əşrəf oğlu | M56: 42999 | O56: Indefinite | Q56: 32655 | R56: 37.380822 | S56: 4KBZEB1 | T56: Azerbaijan | U56: AZE 14313617 | W56: Full time | Y56: Male | Z56: +994555050894 | AB56: - | AD56: Lənkəran Ray.,Aşağı-Nüvədi Qəs. | AE56: Lənkəran Ray.,Aşağı-Nüvədi Qəs. | AF56: married | AG56: 0 | AI56: Lənkaran RİM
A57: Active | B57: ID-86 | C57: S | D57: Samir Mammadov, Sabir | E57: Məmmədov Samir Sabir oğlu | F57: Terminal business support department | G57: Terminal biznesinə dəstək departamenti | H57: Terminal maintenance division | I57: Texniki təmir şöbəsi | J57: Leading Technician Specialist | K57: Texniki İşlər üzrə Aparıcı Mütəxəssis | L57: Nəbiyev Namiq Şahbəddin oğlu | M57: 43010 | O57: Indefinite | Q57: 29388 | R57: 46.331507 | S57: 1DCB2S7 | T57: Azerbaijan | U57: AZE16938273 | W57: Full time | Y57: Male | Z57: +994553192095 | AB57: samir.mammadov@pashapay.az | AD57: Bakı Şəh.,Sabunçu Ray.,Bakıxanov Qəs.,Rəhmanov Küç,Ev7,M.2 | AE57: Bakı Şəh.,Sabunçu Ray.,Bakıxanov Qəs.,Rəhmanov Küç,Ev7,M.2 | AF57: married | AG57: 2 | AI57: Sabail rayonu, Gülbala Əliyev 54C
A58: Active | B58: ID-88 | C58: A | D58: Umid Ibrahimov, Yunus | E58: İbrahimov Ümid Yunus oğlu | F58: Terminal business support department | G58: Terminal biznesinə dəstək departamenti | H58: Terminal technical support division | I58: Terminallara texniki dəstək şöbəsi | J58: Technical worker on terminal payments | K58: Terminal ödənişləri üzrə texniki işçi | L58: Əlizadə Nicat Əşrəf oğlu | M58: 43040 | O58: Indefinite | Q58: 33277 | R58: 35.676712 | S58: 53J5SYP | T58: Azerbaijan | U58: AZE 15287293 | W58: Full time | Y58: Male | Z58: +994555050825 | AB58: - | AD58: Azərbaycan,Balakən Ray.Hənifə Kəndi | AE58: Azərbaycan,Balakən Ray.Hənifə Kəndi | AF58: married | AG58: 2 | AI58: Şəki RİM
A59: Active | B59: ID-89 | C59: A | D59: Rahim Aliyev, Bakhtiyar | E59: Əliyev Rəhim Bəxtiyar oğlu | F59: - | G59: - | H59: - | I59: - | J59: Technical worker on terminal payments | K59: Terminal ödənişləri üzrə texniki işçi | L59: Abbasov Toğrul Vaqif oğlu | M59: 43070 | O59: Indefinite | Q59: 32306 | R59: 38.336986 | S59: 2HZWLYA | T59: Azerbaijan | U59: AZE 13582754 | W59: Full time | Y59: Male | Z59: +994555050862 | AB59: - | AD59: Bakı Şəh.Bakıxanov Qəs.,Sülh Küç.,Yat.,Ev7 | AE59: Bakı Şəh.,Zabrat Qəs.,R.Göyüşov Küç.,Ev2 ,M.77 | AF59: married | AG59: 0 | AI59: Sabail rayonu, Gülbala Əliyev 54C
A60: Active | B60: ID-92 | C60: S | D60: Nargiz Mustafayeva, Adil | E60: Mustafayeva Nərgiz Adil qızı | F60: Customer excellence department | G60: Müştəri mükəmməlliyi departamenti | H60: Customer care division | I60: Müştəri xidmətləri şöbəsi | J60: Senior Front Office Specialist | K60: Ön Masa üzrə Baş Mütəxəssis | L60: Əmirov Savalan İsrəfil oğlu | M60: 43108 | O60: 3 months | Q60: 32698 | R60: 37.263014 | S60: 4JFG7T6 | T60: Azerbaijan | U60: AZE 14846243 | W60: Full time | Y60: Female | Z60: +994517775907 | AA60: +994517775907 | AB60: nargiz.mustafayeva@pashapay.az | AD60: Bakı Şəh., Nizami Ray., Ə.Vəliyev Küç., Ev. 7 A, M.23 | AE60: Bakı Şəh., Nizami Ray., Ə.Vəliyev Küç., Ev. 7 A, M.23 | AF60: married | AG60: 1 | AI60: Elmlər-KB Filialı
A61: Active | B61: ID-95 | C61: A | D61: Vahid Orujzade, Daryagulu | E61: Oruczadə Vahid Dəryaqulu oğlu | F61: - | G61: - | H61: Encashment division | I61: İnkassasiya Şöbəsi | J61: Driver Incasator | K61: Sürücü inkassator | L61: Abbasova Nurlana Ramiz qızı | M61: 43192 | O61: 3 months | P61: Lənkaran RİM | Q61: 26574 | R61: 54.041096 | S61: 1CFBT16 | T61: Azerbaijan | U61: AZE 16115362 | W61: Full time | Y61: Male | Z61: +994503815450 | AB61: - | AD61: Lənkəran Ray., Velədi Kəndi | AE61: Lənkəran Ray., Velədi Kəndi | AF61: married | AG61: 0 | AI61: Lənkaran RİM
A62: Active | B62: ID-96 | C62: A | D62: Ulvi Mehnat, Mukhtar | E62: Mehnət Ülvi Muxtar oğlu | F62: Terminal business support department | G62: Terminal biznesinə dəstək departamenti | H62: Terminal technical support division | I62: Terminallara texniki dəstək şöbəsi | J62: Technical worker on terminal payments | K62: Terminal ödənişləri üzrə texniki işçi | L62: Əlizadə Nicat Əşrəf oğlu | M62: 43206 | O62: 3 months | Q62: 31555 | R62: 40.394521 | S62: 28VLDXU | T62: Azerbaijan | U62: AZE 13553710 | W62: Full time | Y62: Male | Z62: +994555050853 | AB62: - | AD62: Neftçala Şəh.M.Ə.Rəsulzadə Küçəsi | AE62: Neftçala Şəh.M.Ə.Rəsulzadə Küçəsi | AF62: married | AG62: 2 | AI62: Şirvan RİM
A63: Active | B63: ID-97 | C63: A | D63: Ramin Gurbanov, Akbar | E63: Qurbanov Ramin Əkbər oğlu | F63: - | G63: - | H63: Encashment division | I63: İnkassasiya Şöbəsi | J63: Cash Collector | K63: Kassir inkassator | L63: Abbasova Nurlana Ramiz qızı | M63: 43228 | O63: 6 months | P63: Baki | Q63: 29221 | R63: 46.789041 | S63: 31LKY4F | T63: Azerbaijan | U63: AZE 15005673 | W63: Full time | Y63: Male | Z63: +994555050744 | AB63: - | AD63: Gədəbəy Ray.,İsalı K | AE63: Suraxanı Ray.,Yefim Saratov Küç, Ev 62 | AF63: married | AG63: 2 | AI63: Sabail rayonu, Gülbala Əliyev 54C
A64: Active | B64: ID-99 | C64: A | D64: Rauf Asgarov, Vagif | E64: Əsgərov Rauf Vaqif oğlu | F64: Terminal business support department | G64: Terminal biznesinə dəstək departamenti | H64: Terminal technical support division | I64: Terminallara texniki dəstək şöbəsi | J64: Technical worker on terminal payments | K64: Terminal ödənişləri üzrə texniki işçi | L64: Əlizadə Nicat Əşrəf oğlu | M64: 43252 | O64: 3 months | Q64: 26333 | R64: 54.70137 | S64: 1PCNGPC | T64: Azerbaijan | U64: AZE 09852523 | W64: Full time | Y64: Male | Z64: +994555050889 | AB64: - | AD64: Bakı Şəh.,4 Mr.M.Cəlal Küç.,Ev.35,M.22 | AE64: Bakı Şəh.,4 Mr.M.Cəlal Küç.,Ev.35,M.22 | AF64: married | AG64: 2 | AI64: Sabail rayonu, Gülbala Əliyev 54C
A65: Active | B65: ID-100 | C65: TL | D65: Fuad Jamalzade, Sabir | E65: Camalzadə Fuad Sabir oğlu | F65: Terminal and ATM department | G65: Terminal və ATM şəbəkəsinin idarə edilməsi departamenti | H65: Sales support division | I65: Satışa dəstək | J65: Terminal Monitoring Team Lead | K65: Terminalların Monitorinqi üzrə Qrup Rəhbəri | L65: Zeynalova İlahə Əflatun qızı | M65: 43278 | O65: 6 months | Q65: 34228 | R65: 33.071233 | S65: 5NXQD05 | T65: Azerbaijan | U65: AA 0600587 | W65: Full time | X65: Bachelor | Y65: Male | Z65: +994555050740 | AA65: Active | AB65: fuad.camalzade@pashapay.az | AD65: Bakı, , Cabbar Qaryağdıoğlu, Ev 46, M. | AE65: Bakı Şəh.,Yasamal Ray.,C.Qaryağdıoğlu Küç.,Ev.46 | AF65: single | AG65: 0 | AI65: Port Baku 2
A66: Active | B66: ID-104 | C66: S | D66: Mehman Jafarov, Azer | E66: Cəfərov Mehman Azər oğlu | F66: - | G66: - | H66: - | I66: - | J66: Senior Accountant | K66: Böyük Mühasib | L66: Piriyev Abdulla Vaqif oğlu | M66: 43332 | O66: 1 year | Q66: 35135 | R66: 30.586301 | S66: 5VLV3RJ | T66: Azerbaijan | U66: AZE 09952836 | W66: Full time | Y66: Male | Z66: +994555050747 | AA66: +994505921639 | AB66: mehman.jafarov@pashapay.az | AD66: Bakı Şəh.,S.Mehdiyev Küç,Ev.3,M.43 | AE66: Bakı Şəh.,S.Mehdiyev Küç,Ev.3,M.43 | AF66: single | AG66: 0 | AI66: Port Baku 2
A67: Active | B67: ID-105 | C67: S | D67: Fidan Eyvazzade (Khaligova), Jeyhun | E67: Eyvazzade (Xalıqova) Fidan Ceyhun qızı | F67: - | G67: - | H67: Fraud prevention division | I67: Frauda qarşı mübarizə şöbəsi | J67: Senior Fraud Specialist | K67: Fraud Monitorinq üzrə Baş Mütəxəssis | L67: Tinatin Asadova | M67: 43342 | O67: 1 year | Q67: 35285 | R67: 30.175342 | S67: 145KR1Q | T67: Azerbaijan | U67: AZE 09723767 | W67: Full time | Y67: Female | Z67: +994559387500 | AA67: +994559387500 | AB67: fidan.khaligova@pashapay.az | AD67: Bakı Şəh.,Əmircan Qəs.,Z.Tağıyev Küç,Ev.2,M.8 | AE67: Bakı Şəh.,Əmircan Qəs.,Z.Tağıyev Küç,Ev.2,M.8 | AF67: married | AG67: 1 | AI67: Port Baku 2
A68: Active | B68: ID-108 | C68: M | D68: Murad Ahmadzade, Talibzade | E68: Əhmədzadə Murad Talıbzadə oğlu | F68: - | G68: - | H68: IT Division | I68: İT şöbəsi | J68: Customer Help Desk Manager | K68: Müştərilərə Texniki Dəstək üzrə Menecer | L68: Almaz Cavadova | M68: 43350 | O68: Indefinite | Q68: 34438 | R68: 32.49589 | S68: 5UB9ANF | T68: Azerbaijan | U68: AA 002930 | W68: Part time | Y68: Male | Z68: +994555050838 | AA68: +994555050838 | AB68: Murad.akhmadzada@pashapay.az | AD68: Bakı Şəh.,Məzahir Rüstəmov Mənzil 159 | AE68: Bakı Şəh.,Gəncə Prospekti,Ev.1 3,M.159 | AF68: married | AG68: 1 | AI68: Port Baku 2
A69: Active | B69: ID-112 | C69: M | D69: Nurlana Abbasova, Ramiz | E69: Abbasova Nurlana Ramiz qızı | F69: - | G69: - | H69: Encashment division | I69: İnkassasiya Şöbəsi | J69: Team Lead | K69: Qrup Rəhbəri | L69: Tağıyev Camal İlham oğlu | M69: 43375 | O69: Indefinite | Q69: 30019 | R69: 44.60274 | S69: 1M8URNM | T69: Azerbaijan | U69: AZE 17680067 | W69: Full time | Y69: Female | Z69: +994555050820 | AA69: +994553379119 | AB69: nurlana.abbasova@pashapay.az | AD69: Gəncə Şəh.,Kəpəz Ray.,D.Qorqud Küç.,Ev.24A,M.11 | AE69: Gəncə Şəh.,Kəpəz Ray.,D.Qorqud Küç.,Ev.24A,M.11 | AF69: married | AG69: 2 | AI69: Bakı-Nərimanov Kapital
A70: Active | B70: ID-113 | C70: A | D70: Hajiagha Aghamammadov, Bahruz | E70: Ağaməmmədov Hacıağa Bəhruz oğlu | F70: Terminal business support department | G70: Terminal biznesinə dəstək departamenti | H70: Encashment processes support division | I70: İnkassasiya proseslərinə dəstək şöbəsi | J70: Driver | K70: Sürücü | L70: Rüstəmzadə İlqar Vilayət oğlu | M70: 43383 | O70: 3 months | Q70: 31123 | R70: 41.578082 | S70: 12KRH5G | T70: Azerbaijan | U70: AA 2301147 | W70: Full time | Y70: Male | Z70: +994555050964 | AB70: - | AD70: Bakı Şəh.,Y/Suraxanı Qəs.,Kirov Küç.Ev.14 | AE70: Bakı Şəh.,Y/Suraxanı Qəs.,A.Şəfiyev Küç.Ev.14 | AF70: married | AG70: 2 | AI70: Sabail rayonu, Gülbala Əliyev 54C
A71: Active | B71: ID-115 | C71: S | D71: Sona Ahmadzade, Firidun | E71: Əhmədzadə Sona Firidun qızı | F71: Customer excellence department | G71: Müştəri mükəmməlliyi departamenti | H71: Customer complaints division | I71: Müştəri şikayətləri şöbəsi | J71: Leading Customer Complaints Specialist | K71: Müştəri Şikayətləri üzrə Aparıcı Mütəxəssis | L71: Ağazadə Bəhmən Zeynal oğli | M71: 43409 | O71: Indefinite | Q71: 34771 | R71: 31.583562 | S71: 5YZAMQP | T71: Azerbaijan | U71: AA 1886871 | W71: Full time | Y71: Female | Z71: +994505032772 | AA71: +994505032772 | AB71: sona.ahmadzada@pashapay.az | AD71: Abşeron Ray.,Xırdalan Şəh.,H Əliyev Pr,Məh.30,Ev.10,M.52 | AE71: Nizami Ray.,Özbəkistan Küç.1,M.78 | AF71: married | AG71: 1 | AI71: Azure
A72: Active | B72: ID-116 | C72: S | D72: Orkhan Karimov, Akif | E72: Kərimov Orxan Akif oğlu | F72: Terminal business support department | G72: Terminal biznesinə dəstək departamenti | H72: Terminal maintenance division | I72: Texniki təmir şöbəsi | J72: Leading Technician Spacialist | K72: Texniki İşlər üzrə Aparıcı Mütəxəssis | L72: Nəbiyev Namiq Şahbəddin oğlu | M72: 43410 | O72: Indefinite | Q72: 35898 | R72: 28.49589 | S72: 6B3LNEG | T72: Azerbaijan | U72: AA 0450281 | W72: Full time | Y72: Male | Z72: +994554911099 | AB72: orkhan.karimov@pashapay.az | AD72: Bakı Şəh.,Azadlıq Ev 103, Mənzil 58 | AE72: Nəsimi Ray..Dilarə Əliyeva Küç.,Ev.253,M.111 | AF72: single | AG72: 0 | AI72: Sabail rayonu, Gülbala Əliyev 54C
A73: Active | B73: ID-124 | C73: A | D73: Vidadi Alakbarov, Ilham | E73: Ələkbərov Vidadi İlham oğlu | F73: - | G73: - | H73: Encashment division | I73: İnkassasiya Şöbəsi | J73: Cash Collector | K73: Kassir inkassator | L73: Abbasova Nurlana Ramiz qızı | M73: 43435 | O73: indefinitely | P73: Tovuz RİM | Q73: 34839 | R73: 31.39726 | S73: 5XBMXRD | T73: Azerbaijan | U73: AA 1581128 | W73: Full time | Y73: Male | Z73: +994555486198 | AB73: - | AD73: Gəncə Şəh.,Bursa Ev.89 | AE73: Gəncə Şəh.,Kəpəz Ray.,N.Nərimanov Küç.,Ev 1/52,M.4 | AF73: married | AG73: 2 | AI73: Tovuz RİM
A74: Active | B74: ID-125 | C74: A | D74: Elshan Jumshudov, Shahin | E74: Cümşüdov Elşən Şahin oğlu | F74: - | G74: - | H74: Encashment division | I74: İnkassasiya Şöbəsi | J74: Cash Collector | K74: Kassir inkassator | L74: Abbasova Nurlana Ramiz qızı | M74: 43435 | O74: indefinitely | P74: Gəncə RİM | Q74: 33948 | R74: 33.838356 | S74: 5PUL4TA | T74: Azerbaijan | U74: AZE 18558400 | W74: Full time | Y74: Male | Z74: +994705156190 | AB74: - | AD74: Göygöl Ray.,Üçtəpə K. | AE74: Göygöl Ray.,Üçtəpə K. | AF74: married | AG74: 0 | AI74: Gəncə RİM
A75: Active | B75: ID-123 | C75: A | D75: Bahram Shukurov, Hidayat | E75: Şükürov Bəhram Hidayət oğlu | F75: - | G75: - | H75: Encashment division | I75: İnkassasiya Şöbəsi | J75: Cash Collector | K75: Kassir inkassator | L75: Abbasova Nurlana Ramiz qızı | M75: 43435 | O75: indefinitely | P75: Bilasuvar RİM | Q75: 33562 | R75: 34.89589 | S75: 5YGM2J2 | T75: Azerbaijan | U75: AZE 16930674 | W75: Full time | Y75: Male | Z75: +994514545669 | AB75: - | AD75: Masallı Ray.,Mololon K | AE75: Masalli Ray.,Mololon K | AF75: married | AG75: 2 | AI75: Bilasuvar RİM
A76: Active | B76: ID-128 | C76: A | D76: Ibrahim Nasrullayev, Amil | E76: Nəsrullayev İbrahim Amil oğlu | F76: - | G76: - | H76: Encashment division | I76: İnkassasiya Şöbəsi | J76: Cash Collector | K76: Kassir inkassator | L76: Abbasova Nurlana Ramiz qızı | M76: 43435 | O76: indefinitely | P76: Tovuz RİM | Q76: 33377 | R76: 35.40274 | S76: 5J0Q30U | T76: Azerbaijan | U76: AA 0271504 | W76: Full time | Y76: Male | Z76: +994552955566 | AB76: - | AD76: Göygöl Şəh.,M.11 | AE76: Göygöl Şəh.,13 Saylı Hərbi Şəhərcik,Ev.216,M.11 | AF76: married | AG76: 1 | AI76: Tovuz RİM
A77: Active | B77: ID-131 | C77: A | D77: Rza Mammadov, Shahmirza | E77: Məmmədov Rza Şahmirzə oğlu | F77: - | G77: - | H77: Encashment division | I77: İnkassasiya Şöbəsi | J77: Cash Collector | K77: Kassir inkassator | L77: Abbasova Nurlana Ramiz qızı | M77: 43435 | O77: 3 months | P77: Lənkaran RİM | Q77: 33150 | R77: 36.024658 | S77: 4X0C934 | T77: Azerbaijan | U77: AZE 15341483 | W77: Full time | Y77: Male | Z77: +994504906850 | AB77: - | AD77: Lənkəran Ray.,Parakənd Kəndi | AE77: Lənkəran Ray.,Parakənd Kəndi | AF77: married | AG77: 2 | AI77: Lənkaran RİM
A78: Active | B78: ID-132 | C78: A | D78: Azer Aliyev, Fizuli | E78: Əliyev Azər Fizuli oğlu | F78: - | G78: - | H78: Encashment division | I78: İnkassasiya Şöbəsi | J78: Driver Incasator | K78: Sürücü inkassator | L78: Abbasova Nurlana Ramiz qızı | M78: 43435 | O78: indefinitely | P78: Gəncə RİM | Q78: 32976 | R78: 36.50137 | S78: 4V8FTJ7 | T78: Azerbaijan | U78: AZE 15926639 | W78: Full time | Y78: Male | Z78: +994554622220 | AB78: - | AD78: Gəncə Şəh.,Kəpəz Ray.,M.Hüseynzadə Küç.,Ev.102 | AE78: Gəncə Şəh.,Məhsəti Qəs.11 | AF78: married | AG78: 2 | AI78: Gəncə RİM
A79: Active | B79: ID-129 | C79: A | D79: Sadig Imanov, Mohubbat | E79: İmanov Sadiq Möhübbət oğlu | F79: - | G79: - | H79: Encashment division | I79: İnkassasiya Şöbəsi | J79: Cash Collector | K79: Kassir inkassator | L79: Abbasova Nurlana Ramiz qızı | M79: 43435 | O79: indefinitely | P79: Lənkaran RİM | Q79: 28517 | R79: 48.717808 | S79: 46276RV | T79: Azerbaijan | U79: AZE 13657270 | W79: Full time | Y79: Male | Z79: +994555254584 | AB79: - | AD79: Lənkəran Ray.,Xolmili Kəndi | AE79: Lənkəran Ray.,Xolmili Kəndi | AF79: married | AG79: 2 | AI79: Lənkaran RİM
A80: Active | B80: ID-119 | C80: A | D80: Furad Abasov, Intigam | E80: Abasov Furad İntiqam oğlu | F80: Terminal business support department | G80: Terminal biznesinə dəstək departamenti | H80: Terminal technical support division | I80: Terminallara texniki dəstək şöbəsi | J80: Technical worker on terminal payments | K80: Terminal ödənişləri üzrə texniki işçi | L80: Əlizadə Nicat Əşrəf oğlu | M80: 43435 | O80: 6 months | Q80: 34900 | R80: 31.230137 | S80: 622LM19 | T80: Azerbaijan | U80: AZE 09955098 | W80: Full time | Y80: Male | Z80: +994555050781 | AB80: - | AD80: Bakı Şəh.,Ə.Ələkbərov Küç.,Ev.4 | AE80: Bakı Şəh.,Ə.Ələkbərov Küç.,Ev.4 | AF80: married | AI80: Sabail rayonu, Gülbala Əliyev 54C
A81: Active | B81: ID-126 | C81: A | D81: Aliniyaz Mammadzade, Mehman | E81: Məmmədzadə Əliniyaz Mehman oğlu | F81: Terminal business support department | G81: Terminal biznesinə dəstək departamenti | H81: Terminal technical support division | I81: Terminallara texniki dəstək şöbəsi | J81: Technical worker on terminal payments | K81: Terminal ödənişləri üzrə texniki işçi | L81: Əlizadə Nicat Əşrəf oğlu | M81: 43435 | O81: indefinitely | Q81: 34574 | R81: 32.123288 | S81: 5MUZYWH | T81: Azerbaijan | U81: AA 0634839 | W81: Full time | Y81: Male | Z81: +994557911117 | AB81: - | AD81: Bakı Şəh.,Bakıxanov Qəs.,S.Mehmandarov Küç.,Ev.26,M.48 | AE81: Bakı Şəh.,Sabunçu Ray.,Bakıxanov Qəs.,S.Mehmandarov Küç.,Ev.26,M.48 | AF81: married | AG81: 1 | AI81: Sabail rayonu, Gülbala Əliyev 54C
A82: Active | B82: ID-127 | C82: A | D82: Ilgar Pashazade, Famil | E82: Paşazadə İlqar Famil oğlu | F82: Terminal business support department | G82: Terminal biznesinə dəstək departamenti | H82: Terminal technical support division | I82: Terminallara texniki dəstək şöbəsi | J82: Technical worker on terminal payments | K82: Terminal ödənişləri üzrə texniki işçi | L82: Əlizadə Nicat Əşrəf oğlu | M82: 43435 | O82: 6 months | Q82: 34062 | R82: 33.526027 | S82: 5J5G8K6 | T82: Azerbaijan | U82: AZE 18582208 | W82: Full time | Y82: Male | Z82: +994555050848 | AB82: - | AD82: Şuşa Şəh.,Dədə Qorxud Küç.,Ev.40 | AE82: Bakı Şəh., Yasamal Ray.M.Müşfiq Küç.,Məh.5 Bina 4,M.1 | AF82: single | AG82: 0 | AI82: Sabail rayonu, Gülbala Əliyev 54C
A83: Active | B83: ID-122 | C83: A | D83: Elnur Aliyev, Movlan | E83: Əliyev Elnur Mövlan oğlu | F83: - | G83: - | H83: Encashment division | I83: İnkassasiya Şöbəsi | J83: Cash Collector | K83: Kassir inkassator | L83: Abbasova Nurlana Ramiz qızı | M83: 43435 | O83: Indefinite | P83: Sumqayıt RİM | Q83: 32094 | R83: 38.917808 | S83: 507N5GM | T83: Azerbaijan | U83: AA4690217 | W83: Full time | Y83: Male | Z83: +994555777580 | AB83: - | AD83: Abşeron Ray.,Masazır Qəs. | AE83: Abşeron Ray.,Masazır Qəs. | AF83: married | AG83: 1 | AI83: Sumqayıt RİM
A84: Active | B84: ID-134 | C84: A | D84: Sadi Allahverdiyev, Zahid | E84: Allahverdiyev Sədi Zahid oğlu | F84: - | G84: - | H84: Encashment division | I84: İnkassasiya Şöbəsi | J84: Cash Collector | K84: Kassir inkassator | L84: Abbasova Nurlana Ramiz qızı | M84: 43435 | O84: indefinitely | P84: Baki | Q84: 30351 | R84: 43.693151 | S84: 23YCQA1 | T84: Azerbaijan | U84: AZE 18374371 | W84: Full time | Y84: Male | Z84: +994555083493 | AB84: - | AD84: Ağdam Şəh.,20 Yanvar Küç.,Ev.98,M.9 | AE84: Bakı Şəh., 1 Nömrəli İqdisadiyyat Universitetinin Yataqxanası | AF84: married | AG84: 2 | AI84: Sabail rayonu, Gülbala Əliyev 54C
A85: Active | B85: ID-121 | C85: A | D85: Tural Shirinov, Shami | E85: Şirinov Tural Şəmi oğlu | F85: - | G85: - | H85: Encashment division | I85: İnkassasiya Şöbəsi | J85: Cash Collector | K85: Kassir inkassator | L85: Abbasova Nurlana Ramiz qızı | M85: 43435 | O85: 6 months | P85: Sumqayıt RİM | Q85: 36052 | R85: 28.073973 | S85: 6BYGKPE | T85: Azerbaijan | U85: AZE 00157711 | W85: Full time | Y85: Male | Z85: +994555050902 | AB85: - | AD85: Ağsu Ray.,Kalva Kəndi. | AE85: Abşeron Ray.,Müşviqabad Qəs. | AF85: single | AG85: 0 | AI85: Sumqayıt RİM
A86: Active | B86: ID-118 | C86: A | D86: Rafik Azizov, Namig | E86: Əzizov Rafik Namiq oğlu | F86: - | G86: - | H86: Encashment division | I86: İnkassasiya Şöbəsi | J86: Cash Collector | K86: Kassir inkassator | L86: Abbasova Nurlana Ramiz qızı | M86: 43435 | O86: 6 months | P86: Baki | Q86: 35688 | R86: 29.071233 | S86: 6418T5W | T86: Azerbaijan | U86: AZE 14154469 | W86: Full time | Y86: Male | Z86: +994555050812 | AB86: - | AD86: Bakı Şəh.,Bakıxanov Qəs.,Sülh Küç.8,İnz.Bina | AE86: Bakı Şəh.,Sabunçu Ray., Zabrat 1,Çapayev Küç. 8 | AF86: married | AI86: Sabail rayonu, Gülbala Əliyev 54C
A87: Active | B87: ID-120 | C87: A | D87: Kamran Jamalov, Kamil | E87: Camalov Kamran Kamil oğlu | F87: - | G87: - | H87: Encashment division | I87: İnkassasiya Şöbəsi | J87: Cash Collector | K87: Kassir inkassator | L87: Abbasova Nurlana Ramiz qızı | M87: 43435 | O87: Indefinite | P87: Baki | Q87: 34944 | R87: 31.109589 | S87: 60A34DT | T87: Azerbaijan | U87: AA 2772539 | W87: Full time | Y87: Male | Z87: +994503157125 | AB87: - | AD87: Bakı Şəh.,Nərimanov Ray.,X.R.Ulutürk Küç.,Ev.85A | AE87: Bakı Şəh.,Nərimanov Ray.,X.R.Ulutürk Küç.,Ev.165A | AF87: single | AG87: 0 | AI87: Sabail rayonu, Gülbala Əliyev 54C
A88: Active | B88: ID-130 | C88: A | D88: Murad Mammadov, Sari | E88: Məmmədov Murad Sarı oğlu | F88: - | G88: - | H88: Encashment division | I88: İnkassasiya Şöbəsi | J88: Cash Collector | K88: Kassir inkassator | L88: Abbasova Nurlana Ramiz qızı | M88: 43435 | O88: 6 months | P88: Sumqayıt RİM | Q88: 33187 | R88: 35.923288 | S88: 4ZFKERT | T88: Azerbaijan | U88: AZE 15470481 | W88: Full time | Y88: Male | Z88: +994555050903 | AB88: - | AD88: Bakı Şəh.,Yasamal Ray.,2-Ci Alatava,Ev.80J | AE88: Bakı Şəh.,Yasamal Ray.,2-Ci Alatava,Ev.8 J | AF88: married | AG88: 1 | AI88: Sumqayıt RİM
A89: Active | B89: ID-136 | C89: A | D89: Mehman Hasanov, Mahir | E89: Həsənov Mehman Mahir oğlu | F89: - | G89: - | H89: Encashment division | I89: İnkassasiya Şöbəsi | J89: Cash Collector | K89: Kassir inkassator | L89: Abbasova Nurlana Ramiz qızı | M89: 43435 | O89: indefinitely | P89: Xaçmaz RİM | Q89: 32968 | R89: 36.523288 | S89: 2ETM9U7 | T89: Azerbaijan | U89: AZE 14340694 | W89: Full time | Y89: Male | Z89: +994555050901 | AB89: - | AD89: Bakı Şəh., Nəsimi Ray.,4 Mkr M.Cəlal Küç.,Ev 38,M.37. | AE89: Bakı Şəh., Nəsimi Ray.,4 Mkr M.Cəlal Küç.,Ev 38,M.37. | AF89: married | AG89: 1 | AI89: Xaçmaz RİM
A90: Active | B90: ID-139 | C90: A | D90: Jeyhun Musazade, Famil | E90: Musazadə Ceyhun Famil oğlu | F90: - | G90: - | H90: Encashment division | I90: İnkassasiya Şöbəsi | J90: Driver Incasator | K90: Kassir inkassator | L90: Abbasova Nurlana Ramiz qızı | M90: 43451 | O90: Indefinite | P90: İsmayılli RİM | Q90: 33800 | R90: 34.243836 | S90: 5LGHDHX | T90: Azerbaijan | U90: AZE 16951091 | W90: Full time | Y90: Male | Z90: +994777247700 | AB90: - | AD90: Qəbələ Şəh.,C.Yusibov Küç.,Ev.24 | AE90: Qəbələ Şəh.,C.Yusibov Küç.,Ev.24 | AF90: married | AG90: 0 | AI90: İsmayılli RİM
A91: Active | B91: ID-138 | C91: A | D91: Yagut Abdulazizova, Shahbuz | E91: Abduləzizova Yaqut Şahbuz qızı | F91: - | G91: - | H91: - | I91: - | J91: Cleaning Lady | K91: Xidmətçi | L91: KB-yə Kassa və inkassasiya prosesləri departamentinə keçirilir, rəsmiləşmədədirlər. | M91: 43451 | O91: Indefinite | Q91: 32750 | R91: 37.120548 | S91: 5SRPH14 | T91: Azerbaijan | U91: AZE 16810489 | W91: Full time | Y91: Female | Z91: +994517910098 | AB91: - | AD91: Qəbələ Ray.,Qəbələ-2,A.Vasilyev Küç,Ev.41,M.3 | AE91: Qəbələ Ray.,Qəbələ-2,A.Vasilyev Küç,Ev.41,M.3 | AF91: married | AG91: 2 | AI91: İsmayılli RİM
A92: Active | B92: ID-144 | C92: S | D92: Zaur Alakbarov, Jahangir | E92: Ələkbərov Zaur Cahangir oğlu | F92: Terminal and ATM department | G92: Terminal və ATM şəbəkəsinin idarə edilməsi departamenti | H92: Terminal and ATM distibution division | I92: Terminal və ATM-lərin yerləşdirilməsi | J92: Senior Sales Representative | K92: Baş Satış Təmsilçisi | L92: Ramazanov Rəşad Cəfər oğlu | M92: 43468 | O92: 6 months | Q92: 29074 | R92: 47.191781 | S92: 2X0XJ58 | T92: Azerbaijan | U92: AZE 14700027 | W92: Full time | X92: Bachelor | Y92: Male | Z92: +994555050721 | AA92: +994555050721 | AB92: zaur.alakbarov@pashapay.az | AD92: Gəncə Şəh.,Kəpəz Ray.,Lermontov Küç.,1-Dal,Ev.4 | AE92: Gəncə Şəh.,Kəpəz Ray.,Lermontov Küç.,1-Dal,Ev.4 | AF92: married | AG92: 3 | AI92: Gəncə RİM
A93: Active | B93: ID-145 | C93: S | D93: Sakina Ibrahimova, Bayram | E93: İbrahimova Səkinə Bayram qızı | F93: Terminal business support department | G93: Terminal biznesinə dəstək departamenti | H93: Encashment processes support division | I93: İnkassasiya proseslərinə dəstək şöbəsi | J93: Security Specialist | K93: Təhlükəsizlik üzrə Mütəxəssis | L93: Rüstəmzadə İlqar Vilayət oğlu | M93: 43469 | O93: Indefinite | Q93: 30196 | R93: 44.117808 | S93: 29GFCMC | T93: Azerbaijan | U93: AZE 17448910 | W93: Full time | Y93: Female | Z93: +994557434361 | AB93: - | AD93: Bakı Şəh.,Binəqədi Ray.,Sulu-Təpə Qəs,R.Allahverdyev Küç.,Ev.21 | AE93: Bakı Şəh.,Binəqədi Ray.,Sulu-Təpə Qəs,R.Allahverdyev Küç.,Ev.21 | AF93: married | AG93: 3 | AI93: Sabail rayonu, Gülbala Əliyev 54C
A94: Active | B94: ID-146 | C94: A | D94: Majid Huseynli, Arastun | E94: Hüseynli Məcid Ərəstun oğlu | F94: Terminal business support department | G94: Terminal biznesinə dəstək departamenti | H94: Terminal technical support division | I94: Terminallara texniki dəstək şöbəsi | J94: Technical worker on terminal payments | K94: Terminal ödənişləri üzrə texniki işçi | L94: Əlizadə Nicat Əşrəf oğlu | M94: 43497 | O94: 3 months | Q94: 34196 | R94: 33.158904 | S94: 5N1AHSZ | T94: Azerbaijan | U94: AZE 18132058 | W94: Full time | Y94: Male | Z94: +994555050702 | AB94: - | AD94: Göygol Şəh.,A.Hacıyev Küç.,Ev.43 | AE94: Gəncə Şəh.,Qızıl Aslan Küç.,Ev.9 | AF94: single | AG94: 0 | AI94: Gəncə RİM
A95: Active | B95: ID-150 | C95: A | D95: Elmar Babazade, Eldar | E95: Babazadə Elmar Eldar oğlu | F95: Terminal business support department | G95: Terminal biznesinə dəstək departamenti | H95: Terminal technical support division | I95: Terminallara texniki dəstək şöbəsi | J95: Technical worker on terminal payments | K95: Terminal ödənişləri üzrə texniki işçi | L95: Əlizadə Nicat Əşrəf oğlu | M95: 43521 | O95: 6 months | Q95: 30801 | R95: 42.460274 | S95: 0W4Z8BF | T95: Azerbaijan | U95: AA 0265637 | W95: Full time | Y95: Male | Z95: +994555050870 | AB95: - | AD95: Lənkəran Şəh.,Şəhidlər Xiyabanı,M.15 | AE95: Lənkəran Şəh.,Şəhidlər Xiyabanı,Ev.46/1 ,M.15 | AF95: married | AG95: 3 | AI95: Lənkaran RİM
A96: Active | B96: ID-152 | C96: S | D96: Gani Taghiyev, Saadat | E96: Tağıyev Qəni Səadət oğlu | F96: Security department | G96: Təhlükəsizlik departamenti | H96: - | I96: - | J96: Senior Security Specialist | K96: Baş mütəxəssis | L96: Məmmədov Kənan Eldar oğlu | M96: 43586 | O96: 3 months | Q96: 25859 | R96: 56 | S96: 1BKHM5V | T96: Azerbaijan | U96: AZE 06429308 | W96: Full time | Y96: Male | Z96: +994555050797 | AA96: +994512771070 | AB96: qani.tagiyev@pashapay.az | AD96: Lənkəran Ray.,Serapadi Kəndi | AE96: Lənkəran Ray.,Serapadi Kəndi | AF96: married | AG96: 2 | AI96: Sabail rayonu, Gülbala Əliyev 54C
A97: Active | B97: ID-154 | C97: A | D97: Rasim Rustamov, Javid | E97: Rüstəmov Rasim Cavid oğlu | F97: - | G97: - | H97: Encashment division | I97: İnkassasiya Şöbəsi | J97: Driver Incasator | K97: Sürücü inkassator | L97: Abbasova Nurlana Ramiz qızı | M97: 43595 | O97: 3 months | P97: Baki | Q97: 31038 | R97: 41.810959 | S97: 10RZBV2 | T97: Azerbaijan | U97: AZE 08781764 | W97: Full time | Y97: Male | Z97: +994774221535 | AB97: - | AD97: Bakı Şəh.,Şərifzadə Küç.,Ev.110, M.32 | AE97: Bakı Şəh.,Şərifzadə Küç.,Ev.11 , M.32 | AF97: married | AG97: 1 | AI97: Sabail rayonu, Gülbala Əliyev 54C
A98: Active | B98: ID-157 | C98: A | D98: Toghrul Aghazade, Javanshir | E98: Ağazadə Toğrul Cavanşir oğlu | F98: - | G98: - | H98: Encashment division | I98: İnkassasiya Şöbəsi | J98: Cash Collector | K98: Kassir inkassator | L98: Abbasova Nurlana Ramiz qızı | M98: 43617 | O98: 6 months | P98: Xaçmaz RİM | Q98: 34241 | R98: 33.035616 | S98: 5RAFBXS | T98: Azerbaijan | U98: AA 0359950 | W98: Full time | Y98: Male | Z98: +994708111214 | AB98: - | AD98: Bakı, , Ağa Neymətulla, Ev 69, M. | AE98: Bakı, , Ağa Neymətulla, Ev 69, M. | AF98: married | AI98: Xaçmaz RİM
A99: Active | B99: ID-160 | C99: M | D99: Fakhraddin Ahmadov, Firidun | E99: Əhmədov Fəxrəddin Firidun oğlu | F99: - | G99: - | H99: Encashment division | I99: İnkassasiya Şöbəsi | J99: Gabala Branch Manager | K99: Qəbələ RXM-nin Meneceri | L99: Abbasova Nurlana Ramiz qızı | M99: 43634 | O99: 6 months | Q99: 25249 | R99: 57.671233 | S99: 3D49CL9 | T99: Azerbaijan | U99: AA 0233538 | W99: Full time | Y99: Male | Z99: +994555050801 | AA99: +994555050801 | AB99: ahmadov.faxraddin@pashapay.az | AD99: Qəbələ, Zarağan, , Ev , M. | AE99: Qəbələ Şəh.,H.Əliyev Pr.175 | AF99: married | AG99: 2 | AI99: İsmayılli RİM
A100: Active | B100: ID-164 | C100: A | D100: Gulu Taghizade, Vusat | E100: Tağızadə Qulu Vüsət oğlu | F100: Terminal business support department | G100: Terminal biznesinə dəstək departamenti | H100: Encashment processes support division | I100: İnkassasiya proseslərinə dəstək şöbəsi | J100: Security | K100: Mühafizəçi | L100: Rüstəmzadə İlqar Vilayət oğlu | M100: 43643 | O100: 3 months | Q100: 34669 | R100: 31.863014 | S100: 2PU9WKA | T100: Azerbaijan | U100: AA 0305276 | W100: Full time | Y100: Male | Z100: +994502990585 | AB100: - | AD100: Bakı Şəh., İnqilab İsmayılov, Ev 58, M. 34 | AE100: Bakı Şəh., İnqilab İsmayılov, Ev 58, M. 34 | AF100: married | AG100: 0 | AI100: Sabail rayonu, Gülbala Əliyev 54C
...

Sheet Birmarket-local labor
A1: Badge | B1: Employee (En) | C1: Employee (Az) | D1: Department (Az) | E1: Department (En) | F1: Division (En) | G1: Division (Az) | H1: Position (Az) | I1: Position (En)
A2: COM3 | B2: Mammadov Zaur | C2: Məmmədov Zaur Elçin oğlu | D2: İnkişaf bloku | E2: Growth block | F2: Buyer Experience Product Tribe/Post-Checkout and Reviews team | G2: Alıcı Təcrübəsi Məhsul departamenti/Ödənişdən Sonrakı Proseslər və Rəylər bölməsi | H2: Məhsul meneceri | I2: Product manager
A3: COM4 | B3: Maharramli Orkhan | C3: Məhərrəmli Orxan Ziyəddin oğlu | D3: Məhsul və Texnologiyalar bloku/Mühəndislik departamenti | E3: Product Technology block/Engineering department | F3: Engineering department/Seller Experience Technology division | G3: Mühəndislik departamenti/Satıcı tərəfdaşların təcrübəsi texnologiyaları şöbəsi | H3: Texniki lider | I3: Technical Lead
A4: COM8 | B4: Mammadov Chingiz | C4: Məmmədov Çingiz Ramiz oğlu | D4: Məhsul və Texnologiyalar bloku/Mühəndislik departamenti | E4: Product Technology block/Engineering department | F4: Technical Practice/Frontend Practice Team | G4: Texniki Təcrübə şöbəsi/Frontend Texnologiyaları bölməsi | H4: Frontend təcrübəsi rəhbəri | I4: Frontend Practice Lead
A5: COM 2560 | B5: Alasgarli Aysel | C5: Ələsgərli̇ Aysel Bəxti̇yar qızı | D5: Kommersiya blok/Elektronika sahəsi | E5: Commercial block/Electronics vertical | F5: Commercial block/Electronics vertical | G5: Kommersiya blok/Elektronika sahəsi | H5: Kateqoriya üzrə direktor | I5: Category General Manager
A6: COM 2561 | B6: Aghayeva Manisa | C6: Ağayeva Manisə Şahlar qızı | D6: Müştəri xidməti və marketpleys əməliyyatları departamenti | E6: Client Care and Marketplace Operations department | F6: Clinent Care division/Online Support team | G6: Müştəri xidməti şöbəsi/Onlayn dəstək bölməsi | H6: Onlayn dəstək bölməsinin təmsilçisi | I6: Online Support Representative
A7: COM 2563 | B7: Rzali Teymur | C7: Rzali Teymur Mahi̇r oğlu | D7: Data və analitika departamenti | E7: Data and analytics department | F7: Data Science CoE division | G7: Data elmi ekspert mərkəzi | H7: Data elmi üzrə mütəxəssis | I7: Data Scientist
A8: COM 2564 | B8: Huseynov Ibrahim | C8: Hüseynov İbrahi̇m Kami̇l oğlu | D8: Data və analitika departamenti | E8: Data and analytics department | F8: Data Science CoE division | G8: Data elmi ekspert mərkəzi | H8: Data elmi üzrə kiçik mütəxəssis | I8: Junior Data Scientist
A9: COM 2565 | B9: Samadov Nijat | C9: Səmədov Ni̇cat Asi̇m oğlu | D9: Data və analitika departamenti | E9: Data and analytics department | F9: Data Science CoE division | G9: Data elmi ekspert mərkəzi | H9: Data elmi üzrə kiçik mütəxəssis | I9: Junior Data Scientist
A10: COM 2566 | B10: Ahmadov Mammad | C10: Əhmədov Məmməd Seyran oğlu | D10: Təchizat Zənciri bloku | E10: Supply Chain block | F10: Maintenenance$Facility division | G10: Texniki xidmət və inzibati təsərrüfat şöbəsi | H10: Anbar və ehtiyatların uçotu üzrə mütəxəssis | I10: Stock Keeper
A11: COM 2569 | B11: Agharahimova Naila | C11: Ağarəhimova Nailə İlyasovna | D11: İşçi Performansının Təkmilləşdirilməsi Departamenti | E11: Performance Excellence department | F11: Performance Excellence department | G11: İşçi Performansının Təkmilləşdirilməsi Departamenti | H11: İşçi performansının təkmilləşdirilməsi üzrə baş mütəxəssis | I11: Performance Lead
A12: COM 2570 | B12: Dunyamaliyev Nazim | C12: Dünyamalıyev Nazim Samir oğlu | D12: Kommersiya bloku/Satışların təkmilləşdirilməsi departamenti | E12: Commercial block/Seller Excellence Department | F12: Merchant Support and Operation division/Operational support team | G12: Tərəfdaş əməliyyatları və dəstək şöbəsi/Əməliyyat dəstəyi bölməsi | H12: Əməliyyat Dəstəyi üzrə Mütəxəssis | I12: Operations Support Specialist
... A639: COM 2557 | B639: Akbarzade Fatima | C639: Əkbərzadə Fatimə Vüqar qızı | D639: Müştəri xidməti və marketpleys əməliyyatları departamenti | E639: Client Care and Marketplace Operations department | F639: Clinent Care division/Online Support team | G639: Müştəri xidməti şöbəsi/Onlayn dəstək bölməsi | H639: Onlayn dəstək bölməsinin təmsilçisi | I639: Online Support Representative

Sheet Birmarket-Local service
A1: Badge | B1: Employee (En) | C1: Employee (Az) | D1: Department (Az) | E1: Department (En) | F1: Division (En) | G1: Division (Az) | H1: Position (Az) | I1: Position (En)
A2: XM-480 | B2: Jafarova Jala | C2: Cəfərova Jalə Tahir qızı | D2: Logistika Departamenti | E2: Logistics Department | F2: Courier-driver division | G2: Kuryer-sürücü şöbəsi | H2: Sürücü MP | I2: Driver
A3: XM-481 | B3: Azizov Namig | C3: Əzizov Namiq Arzu oğlu | D3: Logistika Departamenti | E3: Logistics Department | F3: Courier-driver division | G3: Kuryer-sürücü şöbəsi | H3: Sürücü MP | I3: Driver
A4: XM-479 | B4: İsmayılov İbrahim | C4: İsmayılov İbrahim Rasim oğlu | D4: Logistika Departamenti | E4: Logistics Department | F4: Courier-driver division | G4: Kuryer-sürücü şöbəsi | H4: Sürücü MP | I4: Driver
A5: XM-487 | B5: Karimov Rashid | C5: Kərimov Rəşid Məlik oğlu | D5: Logistika Departamenti | E5: Logistics Department | F5: Driver-courier division MP | G5: Sürücü-kuryer şöbəsi MP | H5: Sürücü MP | I5: Driver
A6: XM-482 | B6: Zakaryayev Ismail | C6: Zəkəryəyev İsmayıl Qabil oğlu | D6: Logistika Departamenti | E6: Logistics Department | F6: Driver-courier division MP | G6: Sürücü-kuryer şöbəsi MP | H6: Sürücü MP | I6: Driver
A7: XM-478 | B7: Abbasquliyev Rasim | C7: Abbasquliyev Rasim Ramiz oğlu | D7: Logistika Departamenti | E7: Logistics Department | F7: Driver-courier division MP | G7: Sürücü-kuryer şöbəsi MP | H7: Sürücü MP | I7: Driver
A8: XM-484 | B8: Dadashov Oguzkhan | C8: Dadaşov Oğuzxan Mehmed oğlu | D8: Logistika Departamenti | E8: Logistics Department | F8: Driver-courier division MP | G8: Sürücü-kuryer şöbəsi MP | H8: Sürücü MP | I8: Driver
A9: XM-483 | B9: Amiraslanov Elgun | C9: Əmiraslanov Elgün Əmiraslan oğlu | D9: Logistika Departamenti | E9: Logistics Department | F9: Driver-courier division MP | G9: Sürücü-kuryer şöbəsi MP | H9: Sürücü MP | I9: Driver
A10: XM-495 | B10: Baghirov Tarlan | C10: Bağırov Tərlan Tahir oğlu | D10: Logistika Departamenti | E10: Logistics Department | F10: Driver-courier division MP | G10: Sürücü-kuryer şöbəsi MP | H10: Sürücü MP | I10: Driver
A11: XM-489 | B11: Huseynov Firuz | C11: Hüseynov Firuz Mehman oğlu | D11: Logistika Departamenti | E11: Logistics Department | F11: Driver-courier division MP | G11: Sürücü-kuryer şöbəsi MP | H11: Sürücü MP | I11: Driver
A12: XM-496 | B12: Mammadov Elvin | C12: Məmmədov Elvin Abdulla oğlu | D12: Logistika Departamenti | E12: Logistics Department | F12: Driver-courier division MP | G12: Sürücü-kuryer şöbəsi MP | H12: Sürücü MP | I12: Driver
... A31: XM-508 | B31: Naghiyev Turan | C31: Nağıyev Turan Məzahir oğlu | D31: Logistika Departamenti | E31: Logistics Department | F31: Driver-courier division MP | G31: Sürücü-kuryer şöbəsi MP | H31: Sürücü MP | I31: Driver
A32: XM-514 | C32: Ağayev Qaraxan Çingiz oğlu | D32: Logistika Departamenti | E32: Logistics Department | F32: Driver-courier division MP | G32: Sürücü-kuryer şöbəsi MP | H32: Sürücü MP | I32: Driver
A33: XM-515 | C33: Əhlimanzadə Asəf Azər oğlu | D33: Logistika Departamenti | E33: Logistics Department | F33: Driver-courier division MP | G33: Sürücü-kuryer şöbəsi MP | H33: Sürücü MP | I33: Driver
A34: XM-516 | C34: Abbasov Orxan Məzahir oğlu | D34: Logistika Departamenti | E34: Logistics Department | F34: Driver-courier division MP | G34: Sürücü-kuryer şöbəsi MP | H34: Sürücü MP | I34: Driver
A35: XM-517 | C35: Heydərli Əmrah Vaqif oğlu | D35: Logistika Departamenti | E35: Logistics Department | F35: Driver-courier division MP | G35: Sürücü-kuryer şöbəsi MP | H35: Sürücü MP | I35: Driver
A36: XM-518 | C36: Əkbərov Rasim İmran oğlu | D36: Logistika Departamenti | E36: Logistics Department | F36: Driver-courier division MP | G36: Sürücü-kuryer şöbəsi MP | H36: Sürücü MP | I36: Driver
A37: XM-519 | C37: Abidov Elməddin Eldəniz oğlu | D37: Logistika Departamenti | E37: Logistics Department | F37: Driver-courier division MP | G37: Sürücü-kuryer şöbəsi MP | H37: Sürücü MP | I37: Driver
A38: XM-521 | C38: Tariyev Ravil Tari oğlu | D38: Logistika Departamenti | E38: Logistics Department | F38: Driver-courier division MP | G38: Sürücü-kuryer şöbəsi MP | H38: Sürücü MP | I38: Driver
A39: XM-523 | C39: Əliyev Adil Hikmət oğlu | D39: Logistika Departamenti | E39: Logistics Department | F39: Driver-courier division MP | G39: Sürücü-kuryer şöbəsi MP | H39: Sürücü MP | I39: Driver
A40: XM-64 | B40: Dilbazov Ilkin | C40: Di̇lbazov İlki̇n Fərman oğlu | D40: Logistika Departamenti | E40: Logistics Department | F40: Driver-courier division MP | G40: Sürücü-kuryer şöbəsi MP | H40: Sürücü MP | I40: Driver
A41: XM-123 | B41: Abdullayev Orkhan | C41: Abdullayev Orxan Çi̇ngi̇z oğlu | D41: Logistika Departamenti | E41: Logistics Department | F41: Driver-courier division MP | G41: Sürücü-kuryer şöbəsi MP | H41: Sürücü MP | I41: Driver
A42: XM-5 | B42: DASHDAMIROV AGHABAY | C42: DAŞDƏMİROV AĞABƏY ƏBDÜLƏMİN OĞLU | D42: Logistika Departamenti | E42: Logistics Department | F42: Driver-courier division MP | G42: Sürücü-kuryer şöbəsi MP | H42: Sürücü MP | I42: Driver
A43: XM-1 | B43: JAFAROV ASLAN | C43: CƏFƏROV ASLAN ZAKİR OĞLU | D43: Logistika Departamenti | E43: Logistics Department | F43: Driver-courier division MP | G43: Sürücü-kuryer şöbəsi MP | H43: Sürücü MP | I43: Driver
A44: XM-18 | B44: IBRAHIMOV ATIN | C44: İBRAHİMOV ATİN SALƏDDİN OĞLU | D44: Logistika Departamenti | E44: Logistics Department | F44: Driver-courier division MP | G44: Sürücü-kuryer şöbəsi MP | H44: Sürücü MP | I44: Driver
A45: XM-19 | B45: Mukhtarov Azar | C45: Muxtarov Azər Kamil oğlu | D45: Logistika Departamenti | E45: Logistics Department | F45: Driver-courier division MP | G45: Sürücü-kuryer şöbəsi MP | H45: Sürücü MP | I45: Driver
A46: XM-8 | B46: Majıdzada Bahruz | C46: Məcidzadə Bəhruz Bəhram oğlu | D46: Logistika Departamenti | E46: Logistics Department | F46: Driver-courier division MP | G46: Sürücü-kuryer şöbəsi MP | H46: Sürücü MP | I46: Driver
A47: XM-21 | B47: ALLAHVERDIYEV AKBAR | C47: ALLAHVERDİYEV ƏKBƏR RƏŞİD OĞLU | D47: Logistika Departamenti | E47: Logistics Department | F47: Driver-courier division MP | G47: Sürücü-kuryer şöbəsi MP | H47: Sürücü MP | I47: Driver
A48: XM-20 | B48: KARIMOV ELCHIN | C48: KƏRİMOV ELÇİN NİZAMİ OĞLU | D48: Logistika Departamenti | E48: Logistics Department | F48: Driver-courier division MP | G48: Sürücü-kuryer şöbəsi MP | H48: Sürücü MP | I48: Driver
A49: XM-447 | B49: Dunyamaliyev Eldeniz | C49: Dünyamalıyev Eldəniz Dünyamalı oğlu | D49: Logistika Departamenti | E49: Logistics Department | F49: Driver-courier division MP | G49: Sürücü-kuryer şöbəsi MP | H49: Sürücü MP | I49: Driver
A50: XM-7 | B50: AGHAYEV ALI | C50: Ağayev Əli Məhəmmədəli oğlu | D50: Logistika Departamenti | E50: Logistics Department | F50: Driver-courier division MP | G50: Sürücü-kuryer şöbəsi MP | H50: Sürücü MP | I50: Driver
A51: XM-26 | B51: GADIRLI ELNUR | C51: QƏDİRLİ ELNUR MÜZƏFFƏR OĞLU | D51: Logistika Departamenti | E51: Logistics Department | F51: Driver-courier division MP | G51: Sürücü-kuryer şöbəsi MP | H51: Sürücü MP | I51: Driver
... A456: XM-476 | B456: Anvarov Mammad | C456: Ənvərov Məmməd Əbdülvahidoviç | D456: Logistika Departamenti | E456: Logistics Department | F456: Driver-courier division MP | G456: Sürücü-kuryer şöbəsi MP | H456: Sürücü MP | I456: Driver

Sheet Birmarket-service expat
A1: Badge | B1: Employee (En) | C1: Employee (Az) | D1: Department (Az) | E1: Department (En) | F1: Division (En) | G1: Division (Az) | H1: Position (Az) | I1: Position (En)
A2: Bir-171 | B2: Mlynarczyk Marcin Tomasz | C2: Mlynarczyk Marcin Tomasz | D2: Təchizat Zənciri bloku/Logistika Məhsul departamenti | E2: Supply Chain block/Logistics Product Tribe | F2: Logistics Product Tribe | G2: Logistika Məhsul departamenti | H2: Layihələrin İcrası üzrə Rəhbər | I2: Project Delivery Lead
A3: Bir-173 | B3: Zakirov Renat Takherovich | C3: Закиров Ренат Тахерович | D3: Məhsul və Texnologiyalar bloku/Mühəndislik departamenti | E3: Product Technology block/Engineering department | F3: IT Marketing | G3: İT Marketinqi bölməsi | H3: Baş Proqram Tərtibatçı | I3: Senior Software Developer
A4: Bir-174 | B4: Dolgov Aleksei | C4: Долгов Алексей Валентинович | D4: Məhsul və Texnologiyalar bloku/Mühəndislik departamenti | E4: Product Technology block/Engineering department | F4: Buyer Experience Technology divison | G4: Alıcı Təcrübəsi Texnologiyaları şöbəsi | H4: Backend Developer (middle) | I4: Backend Developer (middle)
A5: Bir-175 | B5: Shiriaev Egor Vladimirovich | C5: Ширяев Егор Владимирович | D5: Məhsul və Texnologiyalar bloku/Mühəndislik departamenti | E5: Product Technology block/Engineering department | F5: Buyer Experience Technology divison/Client Care division | G5: Alıcı Təcrübəsi Texnologiyaları şöbəsi/Müştəri Xidməti bölməsi | H5: Baş Backend Developer | I5: Senior Backend Developer
A6: Bir-23 | B6: Chalov Artem Arkadievich | C6: Чалов Артем Аркадьевич | D6: Məhsul və Texnologiyalar bloku/Mühəndislik departamenti | E6: Product Technology block/Engineering department | F6: Logistics&Platform Technology division/ Order-Returns Flow Team | G6: Logistika və Platforma Texnologiyaları şöbəsi/Sifarişlərin-Qaytarma Proseslərinin İdarəedilməsi bölməsi | H6: Sistem analitiki | I6: System analysts
A7: Bir-81 | B7: Lapitski Pavel Aleksandrovich | C7: Лапицкий Павел Александрович | D7: Məhsul və Texnologiyalar bloku | E7: Product Technology block | F7: Infrastructure Technology Division/DevOps Team | G7: İnfrastruktur Texnologiyaları şöbəsi/DevOps bölməsi | H7: DevOps mühəndis | I7: DevOps Engineer
A8: Bir-117 | B8: Rudenko Kirill Anatolevich | C8: Руденко Кирилл Анатолійович | D8: Məhsul və Texnologiyalar bloku/Mühəndislik departamenti | E8: Product Technology block/Engineering department | F8: Buyer Experience Technology divison/Billing team | G8: Alıcı Təcrübəsi Texnologiyaları şöbəsi/Hesablaşmalar bölməsi | H8: IOS Developer | I8: IOS Developer
A9: Bir-13 | B9: Bespalov Anton Sergijovych | C9: Беспалов Антон Сергійович | D9: Məhsul və Texnologiyalar bloku/Mühəndislik departamenti | E9: Product Technology block/Engineering department | F9: Buyer Experience Technology divison/Billing team | G9: Alıcı Təcrübəsi Texnologiyaları şöbəsi/Hesablaşmalar bölməsi | H9: IOS Developer | I9: IOS Developer
A10: Bir-17 | B10: Bolgarov Dmytro Valerievich | C10: Болгаров Дмитро Валерiйович | D10: Məhsul və Texnologiyalar bloku/Mühəndislik departamenti | E10: Product Technology block/Engineering department | F10: Technical Practice/QA Practice Team | G10: Texniki Təcrübə şöbəsi/Keyfiyyət Təminatı Təcrübə bölməsi | H10: QA mühəndisi | I10: QA Engineer
A11: Bir-44 | B11: Haliatkin Oleksandr Anatolievich | C11: Галяткін Олександр Анатолійович | D11: Məhsul və Texnologiyalar bloku/Mühəndislik departamenti | E11: Product Technology block/Engineering department | F11: IT Marketing | G11: İT Marketinqi bölməsi | H11: IOS Developer | I11: IOS Developer
A12: Bir-48 | B12: Horbachevskyi Valerii Vitalievich | C12: Горбачевський Валерій Віталійович | D12: Məhsul və Texnologiyalar bloku/Mühəndislik departamenti | E12: Product Technology block/Engineering department | F12: Logistics&Platform Technology division | G12: Logistika və Platforma Texnologiyaları şöbəsi | H12: Web developer | I12: Web developer
... A140: Bir-170 | B140: Moldokasymov Iskhak | C140: Молдокасымов Исхак Кыясович | D140: Mühəndisllik departamenti | E140: Engineering department | F140: Infrastructure Technology Division | G140: İnfrastruktur texnologiyalar şöbəsi | H140: DevOps mühəndis | I140: DevOps Engineer
