Workbook

Sheet ştat sayları
A1: Keçmiş Struktur adı | B1: Keçmiş Ştat sayı | C1: Yeni Struktur adı | D1: Yeni Ştat sayı | E1: Müxtəlif mənbələrdən əlavə edilmiş ştat sayı | F1: Cəm ştat sayı | G1: Pashapay | H1: Birmarket | I1: Paşa holding | J1: Future lab | K1: Keçid cəm | L1: Fərq səbəbi | M1: Səbəb | N1: Qeyd | R1: 46279
A2: Arxitektura ekspert mərkəzi | B2: 14 | C2: Arxitektura ekspert mərkəzi | D2: 8 | E2: - | F2: 8 | G2: =COUNTIFS(baza!B:B,'ştat sayları'!C:C,baza!H:H,"Bir Payment") -> 0 | H2: =COUNTIFS(baza!B:B,'ştat sayları'!C:C,baza!H:H,"BirMarket") -> 0 | I2: =COUNTIFS(baza!B:B,'ştat sayları'!C:C,baza!H:H,"Paşa Holding") -> 0 | J2: =COUNTIFS(baza!B:B,'ştat sayları'!C:C,baza!H:H,"Future lab") -> 0 | K2: =G2+H2+I2+J2 -> 0 | L2: 2 si Ödəniş biznesinin arxitektura və İT idarəetmə prosesi prosesi, 4 İT proseslərinin idarə edilməsi funksional sahəsi | M2: Struktur dəyişiklik
A3: Dizayn ekspert mərkəzi | B3: 45 | C3: Dizayn ekspert mərkəzi | D3: 59 | E3: 1 pashapay, 3 future lab keçid | F3: 63 | G3: =COUNTIFS(baza!B:B,'ştat sayları'!C:C,baza!H:H,"Bir Payment") -> 10 | H3: =COUNTIFS(baza!B:B,'ştat sayları'!C:C,baza!H:H,"BirMarket") -> 6 | I3: =COUNTIFS(baza!B:B,'ştat sayları'!C:C,baza!H:H,"Paşa Holding") -> 0 | J3: =COUNTIFS(baza!B:B,'ştat sayları'!C:C,baza!H:H,"Future lab") -> 3 | K3: =G3+H3+I3+J3 -> 19 | L3: 1- müştəri təcrübəsi ekspert mərkəzinə geri verilib | M3: Keçidlər
A4: İnzibati idarəetmə departamenti | B4: 141 | C4: İnzibati idarəetmə departamenti | D4: 161 | E4: 1 pashapay | F4: 162 | G4: 19 | H4: =COUNTIFS(baza!B:B,'ştat sayları'!C:C,baza!H:H,"BirMarket") -> 2 | I4: =COUNTIFS(baza!B:B,'ştat sayları'!C:C,baza!H:H,"Paşa Holding") -> 0 | J4: =COUNTIFS(baza!B:B,'ştat sayları'!C:C,baza!H:H,"Future lab") -> 0 | K4: =G4+H4+I4+J4 -> 21 | M4: Keçidlər
A5: Komplayens departamenti | B5: 48 | C5: Komplayens departamenti | D5: 52 | E5: - | F5: 52 | G5: =COUNTIFS(baza!B:B,'ştat sayları'!C:C,baza!H:H,"Bir Payment") -> 3 | H5: =COUNTIFS(baza!B:B,'ştat sayları'!C:C,baza!H:H,"BirMarket") -> 1 | I5: =COUNTIFS(baza!B:B,'ştat sayları'!C:C,baza!H:H,"Paşa Holding") -> 0 | J5: =COUNTIFS(baza!B:B,'ştat sayları'!C:C,baza!H:H,"Future lab") -> 0 | K5: =G5+H5+I5+J5 -> 4 | M5: Keçidlər
A6: Korporativ katiblik şöbəsi | B6: 34.5 | C6: Korporativ katiblik şöbəsi | D6: 36.5 | E6: 1 future lab | F6: 37.5 | G6: 1 | H6: 1 | I6: =COUNTIFS(baza!B:B,'ştat sayları'!C:C,baza!H:H,"Paşa Holding") -> 0 | J6: 1 | K6: =G6+H6+I6+J6 -> 3 | M6: Keçidlər
A7: Ekosistemin partnyor şəbəkəsi departamenti | B7: 74 | C7: Biznes sahələrinin inkişafı və partnyor şəbəkəsi departamenti | D7: 99 | E7: - | F7: 99 | G7: =COUNTIFS(baza!B:B,'ştat sayları'!C:C,baza!H:H,"Bir Payment") -> 24 | H7: =COUNTIFS(baza!B:B,'ştat sayları'!C:C,baza!H:H,"BirMarket") -> 1 | I7: =COUNTIFS(baza!B:B,'ştat sayları'!C:C,baza!H:H,"Paşa Holding") -> 1 | J7: =COUNTIFS(baza!B:B,'ştat sayları'!C:C,baza!H:H,"Future lab") -> 0 | K7: =G7+H7+I7+J7 -> 26 | L7: 1-nağd pulların idarə edilməsi dep verilib | M7: Struktur dəyişiklik və keçidlər
A8: Müştəri təcrübəsi ekspert mərkəzi | B8: 13 | C8: Müştəri təcrübəsi ekspert mərkəzi | D8: 16 | E8: 2 future lab, 7 payment | F8: 25 | G8: =COUNTIFS(baza!B:B,'ştat sayları'!C:C,baza!H:H,"Bir Payment") -> 7 | H8: =COUNTIFS(baza!B:B,'ştat sayları'!C:C,baza!H:H,"BirMarket") -> 0 | I8: =COUNTIFS(baza!B:B,'ştat sayları'!C:C,baza!H:H,"Paşa Holding") -> 0 | J8: =COUNTIFS(baza!B:B,'ştat sayları'!C:C,baza!H:H,"Future lab") -> 2 | K8: =G8+H8+I8+J8 -> 9 | L8: 3-marketinqdən,pashapaydan , dizayn ekspert mərkəzindən | M8: Keçidlər
A9: yeni struktur | B9: 0 | C9: Kredit portfelinə nəzarət departamenti | D9: 35 | E9: 1 i fintech analitika və ai verildi | F9: 34 | G9: =COUNTIFS(baza!B:B,'ştat sayları'!C:C,baza!H:H,"Bir Payment") -> 0 | H9: =COUNTIFS(baza!B:B,'ştat sayları'!C:C,baza!H:H,"BirMarket") -> 0 | I9: =COUNTIFS(baza!B:B,'ştat sayları'!C:C,baza!H:H,"Paşa Holding") -> 0 | J9: =COUNTIFS(baza!B:B,'ştat sayları'!C:C,baza!H:H,"Future lab") -> 0 | K9: =G9+H9+I9+J9 -> 0 | L9: 31 nəzarət,+3 maliyyə risk id ed, +1 biznes risk texnologiyaları sahəsi, +1 pərakəndə risk texnologiyaları sahəsi, -1 fintech mühəndislik , -1 fintech analitika | M9: Struktur dəyişiklik
A10: başqa sahənin parçalanması | B10: 0 | C10: FinTech TechOps funksional sahəsi | D10: 16 | E10: - | F10: 16 | G10: =COUNTIFS(baza!B:B,'ştat sayları'!C:C,baza!H:H,"Bir Payment") -> 0 | H10: =COUNTIFS(baza!B:B,'ştat sayları'!C:C,baza!H:H,"BirMarket") -> 0 | I10: =COUNTIFS(baza!B:B,'ştat sayları'!C:C,baza!H:H,"Paşa Holding") -> 0 | J10: =COUNTIFS(baza!B:B,'ştat sayları'!C:C,baza!H:H,"Future lab") -> 0 | K10: =G10+H10+I10+J10 -> 0 | L10: 15 devops ekspert mərkəzi, 1 fintech mühəndislik | M10: Struktur dəyişiklik
A11: Biznesə dəstək departamenti | B11: 190 | C11: Biznesə dəstək departamenti | D11: 116 | E11: - | F11: 116 | G11: =COUNTIFS(baza!B:B,'ştat sayları'!C:C,baza!H:H,"Bir Payment") -> 0 | H11: =COUNTIFS(baza!B:B,'ştat sayları'!C:C,baza!H:H,"BirMarket") -> 0 | I11: =COUNTIFS(baza!B:B,'ştat sayları'!C:C,baza!H:H,"Paşa Holding") -> 0 | J11: =COUNTIFS(baza!B:B,'ştat sayları'!C:C,baza!H:H,"Future lab") -> 0 | K11: =G11+H11+I11+J11 -> 0 | L11: 18 verildi xkied, -35 nağd pulların id edilməsi, -8 kart klirinqi və hesablaşmalar, -30 texniki dəstək, +11 satış kanalları, +6 maliyyə hesabatlıq | M11: Struktur dəyişiklik
A12: Məhsulların rəsmiləşdirilməsi sahəsi | B12: 5 | C12: Məhsulların rəsmiləşdirilməsi sahəsi | D12: 5 | E12: - | F12: 5 | G12: =COUNTIFS(baza!B:B,'ştat sayları'!C:C,baza!H:H,"Bir Payment") -> 0 | H12: =COUNTIFS(baza!B:B,'ştat sayları'!C:C,baza!H:H,"BirMarket") -> 0 | I12: =COUNTIFS(baza!B:B,'ştat sayları'!C:C,baza!H:H,"Paşa Holding") -> 0 | J12: =COUNTIFS(baza!B:B,'ştat sayları'!C:C,baza!H:H,"Future lab") -> 0 | K12: =G12+H12+I12+J12 -> 0 | M12: Struktur dəyişiklik
A13: Kart biznesi ekspert mərkəzi | B13: 23 | C13: Kart biznesi ekspert mərkəzi | D13: 12 | E13: - | F13: 12 | G13: =COUNTIFS(baza!B:B,'ştat sayları'!C:C,baza!H:H,"Bir Payment") -> 0 | H13: =COUNTIFS(baza!B:B,'ştat sayları'!C:C,baza!H:H,"BirMarket") -> 0 | I13: =COUNTIFS(baza!B:B,'ştat sayları'!C:C,baza!H:H,"Paşa Holding") -> 0 | J13: =COUNTIFS(baza!B:B,'ştat sayları'!C:C,baza!H:H,"Future lab") -> 0 | K13: =G13+H13+I13+J13 -> 0 | L13: 11 rəqəmsal dələduzluğa qarşı mübarizə dep | M13: Struktur dəyişiklik
A14: Təhlükəsizlik departamenti | B14: 70 | C14: Təhlükəsizlik departamenti | D14: 79 | E14: - | F14: 79 | G14: =COUNTIFS(baza!B:B,'ştat sayları'!C:C,baza!H:H,"Bir Payment") -> 3 | H14: =COUNTIFS(baza!B:B,'ştat sayları'!C:C,baza!H:H,"BirMarket") -> 4 | I14: =COUNTIFS(baza!B:B,'ştat sayları'!C:C,baza!H:H,"Paşa Holding") -> 0 | J14: =COUNTIFS(baza!B:B,'ştat sayları'!C:C,baza!H:H,"Future lab") -> 0 | K14: =G14+H14+I14+J14 -> 7 | L14: 1 birmarket boş ştat, 1 nəzarət dep verilib | M14: Keçidlər | N14: 5 birmarket ştatı verilib, 4 ü istifade edilib
A15: başqa sahənin parçalanması | B15: 0 | C15: İT proseslərinin idarə edilməsi funksional sahəsi | D15: 5 | E15: - | F15: 5 | G15: =COUNTIFS(baza!B:B,'ştat sayları'!C:C,baza!H:H,"Bir Payment") -> 0 | H15: =COUNTIFS(baza!B:B,'ştat sayları'!C:C,baza!H:H,"BirMarket") -> 0 | I15: =COUNTIFS(baza!B:B,'ştat sayları'!C:C,baza!H:H,"Paşa Holding") -> 0 | J15: =COUNTIFS(baza!B:B,'ştat sayları'!C:C,baza!H:H,"Future lab") -> 0 | K15: =G15+H15+I15+J15 -> 0 | L15: 4 arxitektura ekspert mərkəzindən,1 ödəniş biznesinin analitika və ai sahəsindən | M15: Struktur dəyişiklik
A16: İşçi təcrübəsi sahəsi | B16: 6 | C16: Rəqəmsal həllər sahəsi | D16: 6 | E16: - | F16: 6 | G16: =COUNTIFS(baza!B:B,'ştat sayları'!C:C,baza!H:H,"Bir Payment") -> 0 | H16: =COUNTIFS(baza!B:B,'ştat sayları'!C:C,baza!H:H,"BirMarket") -> 0 | I16: =COUNTIFS(baza!B:B,'ştat sayları'!C:C,baza!H:H,"Paşa Holding") -> 0 | J16: =COUNTIFS(baza!B:B,'ştat sayları'!C:C,baza!H:H,"Future lab") -> 0 | K16: =G16+H16+I16+J16 -> 0 | M16: Struktur dəyişiklik
A17: yeni struktur | B17: 0 | C17: Strategiya və layihələrin idarə edilməsi departamenti | D17: 28 | E17: - | F17: 28 | G17: =COUNTIFS(baza!B:B,'ştat sayları'!C:C,baza!H:H,"Bir Payment") -> 3 | H17: =COUNTIFS(baza!B:B,'ştat sayları'!C:C,baza!H:H,"BirMarket") -> 0 | I17: =COUNTIFS(baza!B:B,'ştat sayları'!C:C,baza!H:H,"Paşa Holding") -> 4 | J17: =COUNTIFS(baza!B:B,'ştat sayları'!C:C,baza!H:H,"Future lab") -> 0 | K17: =G17+H17+I17+J17 -> 7 | L17: 2 agile və məhsul eksp m, 10 layihələrin id ed eksp m,5 maliyyə menecmenti dep, +1 agile və məhs eksp m(orxan), 3 boş ştat(1 pashapay,1 holdinq, 1 birmarket) | M17: yeni sahə və keçid
A18: Ekosistem platforma və İD sahəsi | B18: 4 | C18: Ekosistem platforma və İD sahəsi | D18: 5 | E18: - | F18: 5 | G18: =COUNTIFS(baza!B:B,'ştat sayları'!C:C,baza!H:H,"Bir Payment") -> 0 | H18: =COUNTIFS(baza!B:B,'ştat sayları'!C:C,baza!H:H,"BirMarket") -> 0 | I18: =COUNTIFS(baza!B:B,'ştat sayları'!C:C,baza!H:H,"Paşa Holding") -> 0 | J18: =COUNTIFS(baza!B:B,'ştat sayları'!C:C,baza!H:H,"Future lab") -> 0 | K18: =G18+H18+I18+J18 -> 0 | L18: 1 pashapay işdən çıxan əməkdaşın ştatı əlavə edildi | M18: struktur dəyişikliyi yoxdur
A19: Filial | B19: 2018 | C19: Filial | D19: 2008 | E19: 1 vip verildi, -57 ştat ixtisar olunmalı | F19: 1950 | G19: =COUNTIFS(baza!B:B,'ştat sayları'!C:C,baza!H:H,"Bir Payment") -> 0 | H19: =COUNTIFS(baza!B:B,'ştat sayları'!C:C,baza!H:H,"BirMarket") -> 0 | I19: =COUNTIFS(baza!B:B,'ştat sayları'!C:C,baza!H:H,"Paşa Holding") -> 0 | J19: =COUNTIFS(baza!B:B,'ştat sayları'!C:C,baza!H:H,"Future lab") -> 0 | K19: =G19+H19+I19+J19 -> 0 | L19: 1 biznesə dəstək, -2 proqram müh coe(mikro biznes),-1 QA(mikro biznes dep), -1 Fintech analitika(xkied), -1 Təhlükəsizlik, -4 fintech müh(rəqəmsal həllər), -1 vip şöbəsi | M19: struktur dəyişikliyi yoxdur | N19: 57 ştat ləğv olunsun
A20: Ekosistem korporativ maliyyə və investor əlaqələri departamenti | B20: 6 | C20: Korporativ inkişaf və investor əlaqələri departamenti | D20: 6 | E20: - | F20: 6 | G20: =COUNTIFS(baza!B:B,'ştat sayları'!C:C,baza!H:H,"Bir Payment") -> 0 | H20: =COUNTIFS(baza!B:B,'ştat sayları'!C:C,baza!H:H,"BirMarket") -> 0 | I20: =COUNTIFS(baza!B:B,'ştat sayları'!C:C,baza!H:H,"Paşa Holding") -> 0 | J20: =COUNTIFS(baza!B:B,'ştat sayları'!C:C,baza!H:H,"Future lab") -> 0 | K20: =G20+H20+I20+J20 -> 0 | M20: Struktur dəyişiklik
A21: Satış kanalları departamenti | B21: 656 | C21: Satış kanalları departamenti | D21: 669 | E21: - | F21: 669 | G21: =COUNTIFS(baza!B:B,'ştat sayları'!C:C,baza!H:H,"Bir Payment") -> 0 | H21: =COUNTIFS(baza!B:B,'ştat sayları'!C:C,baza!H:H,"BirMarket") -> 0 | I21: =COUNTIFS(baza!B:B,'ştat sayları'!C:C,baza!H:H,"Paşa Holding") -> 0 | J21: =COUNTIFS(baza!B:B,'ştat sayları'!C:C,baza!H:H,"Future lab") -> 0 | K21: =G21+H21+I21+J21 -> 0 | L21: 41mikro biznes dep, -11 Biznesə dəstək dep, -2 Fintech marketinq(müştəri dəyərləri), -2 Fintech Analitika və Aİ(müştəri dəyərləri),-3 Fintech mühəndislik (müştəri dəyərləri),-1 Müştəri dəyərləri, -4 fintech mühəndislik məhsulların rəsmiləşd.sahəsi, -1 Fintech analitika və ai(skd), -2 Rəqəmsal dələduzluğa qarşı mübarizə dep, +1 Fintech analitika və ai(skd)(lazım olmadı geri qaytarıldı), -3 Mühəndislik və texnoloji platform | M21: struktur dəyişikliyi yoxdur
A22: Xəzinədarlıq departamenti | B22: 20 | C22: Xəzinədarlıq departamenti | D22: 21 | E22: - | F22: 21 | G22: =COUNTIFS(baza!B:B,'ştat sayları'!C:C,baza!H:H,"Bir Payment") -> 0 | H22: =COUNTIFS(baza!B:B,'ştat sayları'!C:C,baza!H:H,"BirMarket") -> 0 | I22: =COUNTIFS(baza!B:B,'ştat sayları'!C:C,baza!H:H,"Paşa Holding") -> 0 | J22: =COUNTIFS(baza!B:B,'ştat sayları'!C:C,baza!H:H,"Future lab") -> 0 | K22: =G22+H22+I22+J22 -> 0 | L22: 1OPCO 13N 14.06.2026 | M22: struktur dəyişikliyi yoxdur
A23: İT infrastruktur departamenti | B23: 91 | C23: İT infrastruktur departamenti | D23: 99 | E23: - | F23: 99 | G23: 5 | H23: =COUNTIFS(baza!B:B,'ştat sayları'!C:C,baza!H:H,"BirMarket") -> 1 | I23: =COUNTIFS(baza!B:B,'ştat sayları'!C:C,baza!H:H,"Paşa Holding") -> 0 | J23: =COUNTIFS(baza!B:B,'ştat sayları'!C:C,baza!H:H,"Future lab") -> 0 | K23: =G23+H23+I23+J23 -> 6 | L23: 11 Pashapay, +5 devops coe, +1 analitika coe, -10 İnformasiya təhlükəsizliyi, +1Birmarket keçid üçün | M23: Keçidlər | N23: 11 pashapay ştatı verilib, hələki 5 i keçib
A24: Pərakəndə biznes platformaları sahəsi | B24: 6 | C24: Pərakəndə biznes platformaları sahəsi | D24: 7 | E24: - | F24: 7 | G24: =COUNTIFS(baza!B:B,'ştat sayları'!C:C,baza!H:H,"Bir Payment") -> 0 | H24: =COUNTIFS(baza!B:B,'ştat sayları'!C:C,baza!H:H,"BirMarket") -> 0 | I24: =COUNTIFS(baza!B:B,'ştat sayları'!C:C,baza!H:H,"Paşa Holding") -> 0 | J24: =COUNTIFS(baza!B:B,'ştat sayları'!C:C,baza!H:H,"Future lab") -> 0 | K24: =G24+H24+I24+J24 -> 0 | L24: 1 Fintech müh(pərakəndə biznes platform)-OPCO N 20, 27.07.2026 | M24: struktur dəyişikliyi yoxdur
A25: yeni struktur | B25: 0 | C25: Ekosistemin inkişafı və analitikası departamenti | D25: 11 | E25: - | F25: 11 | G25: =COUNTIFS(baza!B:B,'ştat sayları'!C:C,baza!H:H,"Bir Payment") -> 1 | H25: =COUNTIFS(baza!B:B,'ştat sayları'!C:C,baza!H:H,"BirMarket") -> 0 | I25: =COUNTIFS(baza!B:B,'ştat sayları'!C:C,baza!H:H,"Paşa Holding") -> 8 | J25: =COUNTIFS(baza!B:B,'ştat sayları'!C:C,baza!H:H,"Future lab") -> 0 | K25: =G25+H25+I25+J25 -> 9 | L25: 2 paşa holdinq boş ştat | M25: yeni sahə və keçid
A26: yeni struktur | B26: 0 | C26: Beynəlxalq hesabatlıq və MİS departamenti | D26: 13 | E26: - | F26: 13 | G26: =COUNTIFS(baza!B:B,'ştat sayları'!C:C,baza!H:H,"Bir Payment") -> 0 | H26: =COUNTIFS(baza!B:B,'ştat sayları'!C:C,baza!H:H,"BirMarket") -> 0 | I26: =COUNTIFS(baza!B:B,'ştat sayları'!C:C,baza!H:H,"Paşa Holding") -> 0 | J26: =COUNTIFS(baza!B:B,'ştat sayları'!C:C,baza!H:H,"Future lab") -> 0 | K26: =G26+H26+I26+J26 -> 0 | L26: dəqiqləşməli | M26: yeni sahə
A27: başqa sahənin parçalanması | B27: 0 | C27: FinTech arxitektura və İT idarəetmə prosesi | D27: 3 | E27: - | F27: 3 | G27: =COUNTIFS(baza!B:B,'ştat sayları'!C:C,baza!H:H,"Bir Payment") -> 0 | H27: =COUNTIFS(baza!B:B,'ştat sayları'!C:C,baza!H:H,"BirMarket") -> 0 | I27: =COUNTIFS(baza!B:B,'ştat sayları'!C:C,baza!H:H,"Paşa Holding") -> 0 | J27: =COUNTIFS(baza!B:B,'ştat sayları'!C:C,baza!H:H,"Future lab") -> 0 | K27: =G27+H27+I27+J27 -> 0 | L27: 1 asiman ştatı pmem dən,1 Fintech mühəndislik(texnoloji platformalar)(MF İD 11988), +1 Fintech müh(fintech platform)(MF İD = 11987 nin relokasiyası) | M27: yeni sahə
A28: başqa sahənin parçalanması | B28: 0 | C28: Ödəniş biznesinin arxitektura və İT idarəetmə prosesi | D28: 5 | E28: - | F28: 5 | G28: =COUNTIFS(baza!B:B,'ştat sayları'!C:C,baza!H:H,"Bir Payment") -> 0 | H28: =COUNTIFS(baza!B:B,'ştat sayları'!C:C,baza!H:H,"BirMarket") -> 0 | I28: =COUNTIFS(baza!B:B,'ştat sayları'!C:C,baza!H:H,"Paşa Holding") -> 0 | J28: =COUNTIFS(baza!B:B,'ştat sayları'!C:C,baza!H:H,"Future lab") -> 0 | K28: =G28+H28+I28+J28 -> 0 | L28: 2 arxitektura coe, +3 IT Governance Expert,Area Lead ,Architect ştat alındı | M28: yeni sahə
A29: Daxili audit departamenti | B29: 55 | C29: Daxili audit departamenti | D29: 55 | E29: - | F29: 55 | G29: =COUNTIFS(baza!B:B,'ştat sayları'!C:C,baza!H:H,"Bir Payment") -> 0 | H29: =COUNTIFS(baza!B:B,'ştat sayları'!C:C,baza!H:H,"BirMarket") -> 0 | I29: =COUNTIFS(baza!B:B,'ştat sayları'!C:C,baza!H:H,"Paşa Holding") -> 0 | J29: =COUNTIFS(baza!B:B,'ştat sayları'!C:C,baza!H:H,"Future lab") -> 0 | K29: =G29+H29+I29+J29 -> 0 | M29: struktur dəyişikliyi yoxdur
A30: Korporativ satışlar departamenti | B30: 30 | C30: Korporativ satışlar departamenti | D30: 29 | E30: - | F30: 29 | G30: =COUNTIFS(baza!B:B,'ştat sayları'!C:C,baza!H:H,"Bir Payment") -> 0 | H30: =COUNTIFS(baza!B:B,'ştat sayları'!C:C,baza!H:H,"BirMarket") -> 0 | I30: =COUNTIFS(baza!B:B,'ştat sayları'!C:C,baza!H:H,"Paşa Holding") -> 0 | J30: =COUNTIFS(baza!B:B,'ştat sayları'!C:C,baza!H:H,"Future lab") -> 0 | K30: =G30+H30+I30+J30 -> 0 | L30: 1 xkied | M30: struktur dəyişikliyi yoxdur
A31: Kredit risklərinin təhlili departamenti | B31: 133 | C31: Kredit risklərinin təhlili departamenti | D31: 133 | E31: - | F31: 133 | G31: =COUNTIFS(baza!B:B,'ştat sayları'!C:C,baza!H:H,"Bir Payment") -> 0 | H31: =COUNTIFS(baza!B:B,'ştat sayları'!C:C,baza!H:H,"BirMarket") -> 0 | I31: =COUNTIFS(baza!B:B,'ştat sayları'!C:C,baza!H:H,"Paşa Holding") -> 0 | J31: =COUNTIFS(baza!B:B,'ştat sayları'!C:C,baza!H:H,"Future lab") -> 0 | K31: =G31+H31+I31+J31 -> 0 | M31: struktur dəyişikliyi yoxdur
A32: Kreditlərin hüquqi təqibi departamenti | B32: 58 | C32: Kreditlərin hüquqi təqibi departamenti | D32: 58 | E32: - | F32: 58 | G32: =COUNTIFS(baza!B:B,'ştat sayları'!C:C,baza!H:H,"Bir Payment") -> 0 | H32: =COUNTIFS(baza!B:B,'ştat sayları'!C:C,baza!H:H,"BirMarket") -> 0 | I32: =COUNTIFS(baza!B:B,'ştat sayları'!C:C,baza!H:H,"Paşa Holding") -> 0 | J32: =COUNTIFS(baza!B:B,'ştat sayları'!C:C,baza!H:H,"Future lab") -> 0 | K32: =G32+H32+I32+J32 -> 0 | M32: struktur dəyişikliyi yoxdur
A33: Maliyyə menecmenti departamenti | B33: 33 | C33: Maliyyə menecmenti departamenti | D33: 28 | E33: - | F33: 28 | G33: =COUNTIFS(baza!B:B,'ştat sayları'!C:C,baza!H:H,"Bir Payment") -> 0 | H33: =COUNTIFS(baza!B:B,'ştat sayları'!C:C,baza!H:H,"BirMarket") -> 0 | I33: =COUNTIFS(baza!B:B,'ştat sayları'!C:C,baza!H:H,"Paşa Holding") -> 0 | J33: =COUNTIFS(baza!B:B,'ştat sayları'!C:C,baza!H:H,"Future lab") -> 0 | K33: =G33+H33+I33+J33 -> 0 | L33: 5 strategiya və layihələrin id ed | M33: struktur dəyişikliyi yoxdur
A34: Model risklərinin idarəedilməsi ekspert mərkəzi | B34: 12 | C34: Model risklərinin idarəedilməsi ekspert mərkəzi | D34: 12 | E34: - | F34: 12 | G34: =COUNTIFS(baza!B:B,'ştat sayları'!C:C,baza!H:H,"Bir Payment") -> 0 | H34: =COUNTIFS(baza!B:B,'ştat sayları'!C:C,baza!H:H,"BirMarket") -> 0 | I34: =COUNTIFS(baza!B:B,'ştat sayları'!C:C,baza!H:H,"Paşa Holding") -> 0 | J34: =COUNTIFS(baza!B:B,'ştat sayları'!C:C,baza!H:H,"Future lab") -> 0 | K34: =G34+H34+I34+J34 -> 0 | M34: struktur dəyişikliyi yoxdur
A35: İstedadların idarə edilməsi departamenti | B35: 72 | C35: İstedadların idarə edilməsi departamenti | D35: 23 | E35: - | F35: 23 | G35: =COUNTIFS(baza!B:B,'ştat sayları'!C:C,baza!H:H,"Bir Payment") -> 0 | H35: =COUNTIFS(baza!B:B,'ştat sayları'!C:C,baza!H:H,"BirMarket") -> 1 | I35: =COUNTIFS(baza!B:B,'ştat sayları'!C:C,baza!H:H,"Paşa Holding") -> 0 | J35: =COUNTIFS(baza!B:B,'ştat sayları'!C:C,baza!H:H,"Future lab") -> 0 | K35: =G35+H35+I35+J35 -> 1 | L35: 1 Daxili komm və korp sosial məs verildi, +1 birmarket, -48 təşkilati inkişaf və hr texn, -1 Təşkilati inkişaf və HR(xuraman həsənova), -1 Müjgan Rüstəmli ştatı(Təşkilati inkişaf və HR verildi) | M35: Keçidlər
A36: başqa sahənin parçalanması | B36: 0 | C36: Təşkilati inkişaf və HR texnologiyaları departamenti | D36: 83 | E36: - | F36: 83 | G36: =COUNTIFS(baza!B:B,'ştat sayları'!C:C,baza!H:H,"Bir Payment") -> 9 | H36: =COUNTIFS(baza!B:B,'ştat sayları'!C:C,baza!H:H,"BirMarket") -> 12 | I36: =COUNTIFS(baza!B:B,'ştat sayları'!C:C,baza!H:H,"Paşa Holding") -> 2 | J36: =COUNTIFS(baza!B:B,'ştat sayları'!C:C,baza!H:H,"Future lab") -> 1 | K36: =G36+H36+I36+J36 -> 24 | L36: 48 iied, 8 daxili komm, +1İstedadların idarə edilməsi dep, +1 Pashapaydan Zabeta ştatı, +1 İİEDdən(Müjgan Rüstəmli ştatı), | M36: Struktur dəyişiklik və keçidlər
A37: Hüquq departamenti | B37: 53.5 | C37: Hüquq departamenti | D37: 71.5 | E37: - | F37: 71.5 | G37: =COUNTIFS(baza!B:B,'ştat sayları'!C:C,baza!H:H,"Bir Payment") -> 7 | H37: =COUNTIFS(baza!B:B,'ştat sayları'!C:C,baza!H:H,"BirMarket") -> 8 | I37: =COUNTIFS(baza!B:B,'ştat sayları'!C:C,baza!H:H,"Paşa Holding") -> 0 | J37: =COUNTIFS(baza!B:B,'ştat sayları'!C:C,baza!H:H,"Future lab") -> 0 | K37: =G37+H37+I37+J37 -> 15 | L37: 2 birmarket, 1 pashapay ştat boş | M37: Keçidlər | N37: 10 birmarket, 8 pashapay ştatı verilib
A38: Kiçik və orta sahibkarlarla iş departamenti | B38: 94 | C38: Kiçik və orta sahibkarlarla iş departamenti | D38: 94 | E38: - | F38: 94 | G38: =COUNTIFS(baza!B:B,'ştat sayları'!C:C,baza!H:H,"Bir Payment") -> 0 | H38: =COUNTIFS(baza!B:B,'ştat sayları'!C:C,baza!H:H,"BirMarket") -> 0 | I38: =COUNTIFS(baza!B:B,'ştat sayları'!C:C,baza!H:H,"Paşa Holding") -> 0 | J38: =COUNTIFS(baza!B:B,'ştat sayları'!C:C,baza!H:H,"Future lab") -> 0 | K38: =G38+H38+I38+J38 -> 0 | M38: struktur dəyişikliyi yoxdur
A39: Kreditlərin ilkin təqibi departamenti | B39: 207 | C39: Kreditlərin ilkin təqibi departamenti | D39: 204 | E39: - | F39: 204 | G39: =COUNTIFS(baza!B:B,'ştat sayları'!C:C,baza!H:H,"Bir Payment") -> 0 | H39: =COUNTIFS(baza!B:B,'ştat sayları'!C:C,baza!H:H,"BirMarket") -> 0 | I39: =COUNTIFS(baza!B:B,'ştat sayları'!C:C,baza!H:H,"Paşa Holding") -> 0 | J39: =COUNTIFS(baza!B:B,'ştat sayları'!C:C,baza!H:H,"Future lab") -> 0 | K39: =G39+H39+I39+J39 -> 0 | L39: 2 Fintech müh(kredit portf nəzarət dep) verildi, -1 Maliyyə risk.id.olunması | M39: struktur dəyişikliyi yoxdur
A40: Prosessinq sahəsi | B40: 3 | C40: Prosessinq sahəsi | D40: 3 | E40: - | F40: 3 | G40: =COUNTIFS(baza!B:B,'ştat sayları'!C:C,baza!H:H,"Bir Payment") -> 0 | H40: =COUNTIFS(baza!B:B,'ştat sayları'!C:C,baza!H:H,"BirMarket") -> 0 | I40: =COUNTIFS(baza!B:B,'ştat sayları'!C:C,baza!H:H,"Paşa Holding") -> 0 | J40: =COUNTIFS(baza!B:B,'ştat sayları'!C:C,baza!H:H,"Future lab") -> 0 | K40: =G40+H40+I40+J40 -> 0 | M40: struktur dəyişikliyi yoxdur
A41: VİP müştərilərlə iş şöbəsi | B41: 8 | C41: VİP müştərilərlə iş şöbəsi | D41: 8 | E41: 1 filialdan ştat | F41: 9 | G41: =COUNTIFS(baza!B:B,'ştat sayları'!C:C,baza!H:H,"Bir Payment") -> 0 | H41: =COUNTIFS(baza!B:B,'ştat sayları'!C:C,baza!H:H,"BirMarket") -> 0 | I41: =COUNTIFS(baza!B:B,'ştat sayları'!C:C,baza!H:H,"Paşa Holding") -> 0 | J41: =COUNTIFS(baza!B:B,'ştat sayları'!C:C,baza!H:H,"Future lab") -> 0 | K41: =G41+H41+I41+J41 -> 0 | L41: 1 filialdan bura | M41: struktur dəyişikliyi yoxdur
A42: Maliyyə risklərinin idarə edilməsi departamenti | B42: 39 | C42: Maliyyə risklərinin idarə edilməsi departamenti | D42: 41 | E42: - | F42: 41 | G42: =COUNTIFS(baza!B:B,'ştat sayları'!C:C,baza!H:H,"Bir Payment") -> 1 | H42: =COUNTIFS(baza!B:B,'ştat sayları'!C:C,baza!H:H,"BirMarket") -> 0 | I42: =COUNTIFS(baza!B:B,'ştat sayları'!C:C,baza!H:H,"Paşa Holding") -> 0 | J42: =COUNTIFS(baza!B:B,'ştat sayları'!C:C,baza!H:H,"Future lab") -> 0 | K42: =G42+H42+I42+J42 -> 1 | L42: 1 kreditlərin ilkin təqibindən | M42: Keçidlər
A43: Təşkilati risklərin idarə edilməsi departamenti | B43: 27 | C43: Təşkilati və qeyri-maliyyə risklərinin idarə edilməsi departamenti | D43: 57 | E43: - | F43: 57 | G43: =COUNTIFS(baza!B:B,'ştat sayları'!C:C,baza!H:H,"Bir Payment") -> 2 | H43: =COUNTIFS(baza!B:B,'ştat sayları'!C:C,baza!H:H,"BirMarket") -> 0 | I43: =COUNTIFS(baza!B:B,'ştat sayları'!C:C,baza!H:H,"Paşa Holding") -> 0 | J43: =COUNTIFS(baza!B:B,'ştat sayları'!C:C,baza!H:H,"Future lab") -> 0 | K43: =G43+H43+I43+J43 -> 2 | L43: 4 pashapay boş ştat, 24 nəzarət depdən | M43: Struktur dəyişiklik və keçidlər | N43: 6 pashapay ştatı verilib
A44: yeni struktur | B44: 0 | C44: Data governance ekspert mərkəzi | D44: 19 | E44: - | F44: 19 | G44: =COUNTIFS(baza!B:B,'ştat sayları'!C:C,baza!H:H,"Bir Payment") -> 0 | H44: =COUNTIFS(baza!B:B,'ştat sayları'!C:C,baza!H:H,"BirMarket") -> 5 | I44: =COUNTIFS(baza!B:B,'ştat sayları'!C:C,baza!H:H,"Paşa Holding") -> 1 | J44: =COUNTIFS(baza!B:B,'ştat sayları'!C:C,baza!H:H,"Future lab") -> 0 | K44: =G44+H44+I44+J44 -> 6 | L44: 13 data tranformasiyasından | M44: Struktur dəyişiklik və keçidlər
A45: yeni struktur | B45: 0 | C45: Aİ governance ekspert mərkəzi | D45: 14 | E45: - | F45: 14 | G45: =COUNTIFS(baza!B:B,'ştat sayları'!C:C,baza!H:H,"Bir Payment") -> 0 | H45: =COUNTIFS(baza!B:B,'ştat sayları'!C:C,baza!H:H,"BirMarket") -> 0 | I45: =COUNTIFS(baza!B:B,'ştat sayları'!C:C,baza!H:H,"Paşa Holding") -> 0 | J45: =COUNTIFS(baza!B:B,'ştat sayları'!C:C,baza!H:H,"Future lab") -> 1 | K45: =G45+H45+I45+J45 -> 1 | L45: 1 fintech analitika(fintech marketinq), 10 analitika, 2 agile | M45: yeni sahə və keçid
A46: Mikro məhsullar sahəsi, KOS və korporativ məhsullar sahəsi | B46: 12 | C46: Birbank biznes sahəsi | D46: 12 | E46: - | F46: 12 | G46: =COUNTIFS(baza!B:B,'ştat sayları'!C:C,baza!H:H,"Bir Payment") -> 0 | H46: =COUNTIFS(baza!B:B,'ştat sayları'!C:C,baza!H:H,"BirMarket") -> 0 | I46: =COUNTIFS(baza!B:B,'ştat sayları'!C:C,baza!H:H,"Paşa Holding") -> 0 | J46: =COUNTIFS(baza!B:B,'ştat sayları'!C:C,baza!H:H,"Future lab") -> 0 | K46: =G46+H46+I46+J46 -> 0 | M46: Struktur dəyişiklik
A47: Texnoloji platformalar sahəsi | B47: 4 | C47: FinTech platformalar sahəsi | D47: 3 | E47: - | F47: 3 | G47: =COUNTIFS(baza!B:B,'ştat sayları'!C:C,baza!H:H,"Bir Payment") -> 0 | H47: =COUNTIFS(baza!B:B,'ştat sayları'!C:C,baza!H:H,"BirMarket") -> 0 | I47: =COUNTIFS(baza!B:B,'ştat sayları'!C:C,baza!H:H,"Paşa Holding") -> 0 | J47: =COUNTIFS(baza!B:B,'ştat sayları'!C:C,baza!H:H,"Future lab") -> 0 | K47: =G47+H47+I47+J47 -> 0 | L47: 1 i ödəniş platformaları | M47: Struktur dəyişiklik
A48: Ödənişlər sahəsi | B48: 5 | C48: Ödəniş və transferlər sahəsi | D48: 3 | E48: - | F48: 3 | G48: =COUNTIFS(baza!B:B,'ştat sayları'!C:C,baza!H:H,"Bir Payment") -> 0 | H48: =COUNTIFS(baza!B:B,'ştat sayları'!C:C,baza!H:H,"BirMarket") -> 0 | I48: =COUNTIFS(baza!B:B,'ştat sayları'!C:C,baza!H:H,"Paşa Holding") -> 0 | J48: =COUNTIFS(baza!B:B,'ştat sayları'!C:C,baza!H:H,"Future lab") -> 0 | K48: =G48+H48+I48+J48 -> 0 | L48: 1i özünə xidmət terminalları, 1 birapp | M48: Struktur dəyişiklik
A49: Xidmət keyfiyyətinin idarə edilməsi departamenti | B49: 376 | C49: Xidmət keyfiyyətinin idarə edilməsi departamenti | D49: 152 | E49: - | F49: 152 | G49: =COUNTIFS(baza!B:B,'ştat sayları'!C:C,baza!H:H,"Bir Payment") -> 0 | H49: =COUNTIFS(baza!B:B,'ştat sayları'!C:C,baza!H:H,"BirMarket") -> 0 | I49: =COUNTIFS(baza!B:B,'ştat sayları'!C:C,baza!H:H,"Paşa Holding") -> 0 | J49: =COUNTIFS(baza!B:B,'ştat sayları'!C:C,baza!H:H,"Future lab") -> 0 | K49: =G49+H49+I49+J49 -> 0 | L49: 1 Korporativ satış dep, -244(kassa və inkassasiya dep, struktur dəyişiklik),-2 Nağd pull id ed(struktur dəyişiklik),+18 Biznesə dəstək dep(struktur d), +3 Kassa və inkassasiya(keçmiş QƏLD dən verilən) | M49: Keçidlər
A50: Ekvayrinq texnologiyaları sahəsi | B50: 3 | C50: Ekvayrinq texnologiyaları sahəsi | D50: 3 | E50: - | F50: 3 | G50: =COUNTIFS(baza!B:B,'ştat sayları'!C:C,baza!H:H,"Bir Payment") -> 0 | H50: =COUNTIFS(baza!B:B,'ştat sayları'!C:C,baza!H:H,"BirMarket") -> 0 | I50: =COUNTIFS(baza!B:B,'ştat sayları'!C:C,baza!H:H,"Paşa Holding") -> 0 | J50: =COUNTIFS(baza!B:B,'ştat sayları'!C:C,baza!H:H,"Future lab") -> 0 | K50: =G50+H50+I50+J50 -> 0 | M50: struktur dəyişikliyi yoxdur
A51: başqa sahənin parçalanması | B51: 0 | C51: FinTech Analitika və Aİ ekspert mərkəzi | D51: 153 | E51: 1 kredit portfelinə nəzarət | F51: 154 | G51: =COUNTIFS(baza!B:B,'ştat sayları'!C:C,baza!H:H,"Bir Payment") -> 0 | H51: =COUNTIFS(baza!B:B,'ştat sayları'!C:C,baza!H:H,"BirMarket") -> 0 | I51: =COUNTIFS(baza!B:B,'ştat sayları'!C:C,baza!H:H,"Paşa Holding") -> 1 | J51: =COUNTIFS(baza!B:B,'ştat sayları'!C:C,baza!H:H,"Future lab") -> 0 | K51: =G51+H51+I51+J51 -> 1 | L51: 151 Aİ və Analitika ekspert mərkəzlərindən keçidlər | M51: Struktur dəyişiklik
A52: Mikro biznes departamenti | B52: 58 | C52: Mikro biznes departamenti | D52: 19 | E52: - | F52: 19 | G52: =COUNTIFS(baza!B:B,'ştat sayları'!C:C,baza!H:H,"Bir Payment") -> 0 | H52: =COUNTIFS(baza!B:B,'ştat sayları'!C:C,baza!H:H,"BirMarket") -> 0 | I52: =COUNTIFS(baza!B:B,'ştat sayları'!C:C,baza!H:H,"Paşa Holding") -> 0 | J52: =COUNTIFS(baza!B:B,'ştat sayları'!C:C,baza!H:H,"Future lab") -> 0 | K52: =G52+H52+I52+J52 -> 0 | L52: 41 satış kanallarına verildi, +2 mikro məhsullar | M52: struktur dəyişikliyi yoxdur
A53: başqa sahənin parçalanması | B53: 0 | C53: Mühəndislik və texnoloji platformalar ekspert mərkəzi | D53: 168 | E53: - | F53: 168 | G53: =COUNTIFS(baza!B:B,'ştat sayları'!C:C,baza!H:H,"Bir Payment") -> 0 | H53: =COUNTIFS(baza!B:B,'ştat sayları'!C:C,baza!H:H,"BirMarket") -> 2 | I53: =COUNTIFS(baza!B:B,'ştat sayları'!C:C,baza!H:H,"Paşa Holding") -> 0 | J53: =COUNTIFS(baza!B:B,'ştat sayları'!C:C,baza!H:H,"Future lab") -> 0 | K53: =G53+H53+I53+J53 -> 2 | L53: 161 struktur dəyişikliyi zamanı(it ba, qa, programming coedən), +5 fintech müh(fintech marketinq), +3 OPCO N 21, -1 birapp sahəsi | M53: yeni sahə və keçid
A54: başqa sahənin parçalanması | B54: 0 | C54: Rəqəmsal dələduzluğa qarşı mübarizə departamenti | D54: 22 | E54: - | F54: 22 | G54: =COUNTIFS(baza!B:B,'ştat sayları'!C:C,baza!H:H,"Bir Payment") -> 2 | H54: =COUNTIFS(baza!B:B,'ştat sayları'!C:C,baza!H:H,"BirMarket") -> 0 | I54: =COUNTIFS(baza!B:B,'ştat sayları'!C:C,baza!H:H,"Paşa Holding") -> 0 | J54: =COUNTIFS(baza!B:B,'ştat sayları'!C:C,baza!H:H,"Future lab") -> 0 | K54: =G54+H54+I54+J54 -> 2 | L54: 11 Kart biznesi ekspert mərkəzindən, 2 si Nəzarət dep, +2SKD, +3 Analitika şöbəsinə, +2 developer | M54: yeni sahə və keçid
A55: Data texnologiyaları ekspert mərkəzi | B55: 23 | C55: Data mühəndisliyi və texnologiyaları ekspert mərkəzi | D55: 27 | E55: - | F55: 27 | G55: =COUNTIFS(baza!B:B,'ştat sayları'!C:C,baza!H:H,"Bir Payment") -> 4 | H55: =COUNTIFS(baza!B:B,'ştat sayları'!C:C,baza!H:H,"BirMarket") -> 0 | I55: =COUNTIFS(baza!B:B,'ştat sayları'!C:C,baza!H:H,"Paşa Holding") -> 0 | J55: =COUNTIFS(baza!B:B,'ştat sayları'!C:C,baza!H:H,"Future lab") -> 0 | K55: =G55+H55+I55+J55 -> 4 | M55: Struktur dəyişiklik və keçidlər
A56: başqa sahənin parçalanması | B56: 0 | C56: Nağd pulların idarə edilməsi departamenti | D56: 42 | E56: - | F56: 42 | G56: =COUNTIFS(baza!B:B,'ştat sayları'!C:C,baza!H:H,"Bir Payment") -> 1 | H56: =COUNTIFS(baza!B:B,'ştat sayları'!C:C,baza!H:H,"BirMarket") -> 0 | I56: =COUNTIFS(baza!B:B,'ştat sayları'!C:C,baza!H:H,"Paşa Holding") -> 0 | J56: =COUNTIFS(baza!B:B,'ştat sayları'!C:C,baza!H:H,"Future lab") -> 0 | K56: =G56+H56+I56+J56 -> 1 | L56: 2 ştat pashapaydan bura boş verilib,35 BDD, 2 xkied, +1 Biznes sah inkişafi və partn,+1 orxan yeni excel, | M56: yeni sahə və keçid
A57: başqa sahənin parçalanması | B57: 0 | C57: Risk texnologiyaları sahəsi | D57: 9 | E57: - | F57: 9 | G57: =COUNTIFS(baza!B:B,'ştat sayları'!C:C,baza!H:H,"Bir Payment") -> 0 | H57: =COUNTIFS(baza!B:B,'ştat sayları'!C:C,baza!H:H,"BirMarket") -> 0 | I57: =COUNTIFS(baza!B:B,'ştat sayları'!C:C,baza!H:H,"Paşa Holding") -> 0 | J57: =COUNTIFS(baza!B:B,'ştat sayları'!C:C,baza!H:H,"Future lab") -> 0 | K57: =G57+H57+I57+J57 -> 0 | L57: 4 biznes risk texn, 5 pərakəndə risk tex sah | M57: yeni sahə
A58: başqa sahənin parçalanması | B58: 0 | C58: FinTech mühəndislik ekspert mərkəzi | D58: 366 | E58: - | F58: 366 | G58: =COUNTIFS(baza!B:B,'ştat sayları'!C:C,baza!H:H,"Bir Payment") -> 1 | H58: =COUNTIFS(baza!B:B,'ştat sayları'!C:C,baza!H:H,"BirMarket") -> 0 | I58: =COUNTIFS(baza!B:B,'ştat sayları'!C:C,baza!H:H,"Paşa Holding") -> 0 | J58: =COUNTIFS(baza!B:B,'ştat sayları'!C:C,baza!H:H,"Future lab") -> 0 | K58: =G58+H58+I58+J58 -> 1 | L58: 366 struktur dəyişiklik | M58: Struktur dəyişiklik və keçidlər
A59: başqa sahənin parçalanması | B59: 0 | C59: Birbonus sahəsi | D59: 6 | E59: - | F59: 6 | G59: =COUNTIFS(baza!B:B,'ştat sayları'!C:C,baza!H:H,"Bir Payment") -> 0 | H59: =COUNTIFS(baza!B:B,'ştat sayları'!C:C,baza!H:H,"BirMarket") -> 0 | I59: =COUNTIFS(baza!B:B,'ştat sayları'!C:C,baza!H:H,"Paşa Holding") -> 0 | J59: =COUNTIFS(baza!B:B,'ştat sayları'!C:C,baza!H:H,"Future lab") -> 0 | K59: =G59+H59+I59+J59 -> 0 | L59: 6 loyallıq məhsullar | M59: Struktur dəyişiklik
A60: başqa sahənin parçalanması | B60: 0 | C60: BirApp texnologiyası sahəsi | D60: 3 | E60: - | F60: 3 | G60: =COUNTIFS(baza!B:B,'ştat sayları'!C:C,baza!H:H,"Bir Payment") -> 0 | H60: =COUNTIFS(baza!B:B,'ştat sayları'!C:C,baza!H:H,"BirMarket") -> 0 | I60: =COUNTIFS(baza!B:B,'ştat sayları'!C:C,baza!H:H,"Paşa Holding") -> 0 | J60: =COUNTIFS(baza!B:B,'ştat sayları'!C:C,baza!H:H,"Future lab") -> 0 | K60: =G60+H60+I60+J60 -> 0 | L60: 2 birbank platforma, 1 texnoloji həllər | M60: Struktur dəyişiklik
A61: Marketinq ekspert mərkəzi | B61: 56 | C61: Marketinq ekspert mərkəzi | D61: 91 | E61: 1 əlavə ştat əsaslandırma | F61: 92 | G61: =COUNTIFS(baza!B:B,'ştat sayları'!C:C,baza!H:H,"Bir Payment") -> 22 | H61: =COUNTIFS(baza!B:B,'ştat sayları'!C:C,baza!H:H,"BirMarket") -> 13 | I61: =COUNTIFS(baza!B:B,'ştat sayları'!C:C,baza!H:H,"Paşa Holding") -> 0 | J61: =COUNTIFS(baza!B:B,'ştat sayları'!C:C,baza!H:H,"Future lab") -> 0 | K61: =G61+H61+I61+J61 -> 35 | L61: 1 əlavə ştat tamilla x əsaslandırma | M61: Keçidlər | N61: 1 əlavə ştat yazdıq orxan qeyd
A62: İnformasiya təhlükəsizliyi departamenti | B62: 34 | C62: İnformasiya təhlükəsizliyi departamenti | D62: 70 | E62: - | F62: 70 | G62: 4 | H62: =COUNTIFS(baza!B:B,'ştat sayları'!C:C,baza!H:H,"BirMarket") -> 1 | I62: =COUNTIFS(baza!B:B,'ştat sayları'!C:C,baza!H:H,"Paşa Holding") -> 0 | J62: =COUNTIFS(baza!B:B,'ştat sayları'!C:C,baza!H:H,"Future lab") -> 0 | K62: =G62+H62+I62+J62 -> 5 | L62: 4 boş pashapay ştat, 10 İT infrastruktur, 17 OPCO N 38 | M62: Keçidlər | N62: 8 pashapay,1 birmarket
A63: Maliyyə hesabatlığı və mühasibatlıq departamenti | B63: 53 | C63: Maliyyə hesabatlığı və mühasibatlıq departamenti | D63: 48 | E63: 2 pashapay | F63: 50 | G63: =COUNTIFS(baza!B:B,'ştat sayları'!C:C,baza!H:H,"Bir Payment") -> 3 | H63: =COUNTIFS(baza!B:B,'ştat sayları'!C:C,baza!H:H,"BirMarket") -> 1 | I63: =COUNTIFS(baza!B:B,'ştat sayları'!C:C,baza!H:H,"Paşa Holding") -> 0 | J63: =COUNTIFS(baza!B:B,'ştat sayları'!C:C,baza!H:H,"Future lab") -> 0 | K63: =G63+H63+I63+J63 -> 4 | L63: dəqiqləşməli | M63: Keçidlər | N63: danışılmalıdı, burdan 13 u beynəlxalq hesabatlıq və MİS
A64: Müştəri dəyərləri sahəsi | B64: 7 | C64: Müştəri dəyərləri sahəsi | D64: 7 | E64: - | F64: 7 | G64: =COUNTIFS(baza!B:B,'ştat sayları'!C:C,baza!H:H,"Bir Payment") -> 0 | H64: =COUNTIFS(baza!B:B,'ştat sayları'!C:C,baza!H:H,"BirMarket") -> 0 | I64: =COUNTIFS(baza!B:B,'ştat sayları'!C:C,baza!H:H,"Paşa Holding") -> 0 | J64: =COUNTIFS(baza!B:B,'ştat sayları'!C:C,baza!H:H,"Future lab") -> 0 | K64: =G64+H64+I64+J64 -> 0 | M64: struktur dəyişikliyi yoxdur
A65: başqa sahənin parçalanması | B65: 0 | C65: BirApp sahəsi | D65: 6 | E65: 1 pashapay | F65: 7 | G65: =COUNTIFS(baza!B:B,'ştat sayları'!C:C,baza!H:H,"Bir Payment") -> 1 | H65: =COUNTIFS(baza!B:B,'ştat sayları'!C:C,baza!H:H,"BirMarket") -> 0 | I65: =COUNTIFS(baza!B:B,'ştat sayları'!C:C,baza!H:H,"Paşa Holding") -> 0 | J65: =COUNTIFS(baza!B:B,'ştat sayları'!C:C,baza!H:H,"Future lab") -> 0 | K65: =G65+H65+I65+J65 -> 1 | L65: 3 müştərinin rəqəmsal təc, 1 ödənişlər sahısi, 1 texnoloji həllər ofis, +1 mühəndislik və texn pl | M65: Struktur dəyişiklik və keçidlər
A66: yeni struktur | B66: 0 | C66: Kart məhsulları sahəsi | D66: 7 | E66: - | F66: 7 | G66: =COUNTIFS(baza!B:B,'ştat sayları'!C:C,baza!H:H,"Bir Payment") -> 0 | H66: =COUNTIFS(baza!B:B,'ştat sayları'!C:C,baza!H:H,"BirMarket") -> 0 | I66: =COUNTIFS(baza!B:B,'ştat sayları'!C:C,baza!H:H,"Paşa Holding") -> 0 | J66: =COUNTIFS(baza!B:B,'ştat sayları'!C:C,baza!H:H,"Future lab") -> 0 | K66: =G66+H66+I66+J66 -> 0 | L66: 2 Müştərinin rəqəmsal təcrübəsi sahəsi, 1 cvm, 1 məhs rəsmil,1 kos və korp m, 1 orxan yekun excele esasen, +1 ödəniş bizn müh(kart məhs) | M66: yeni sahə
A67: yeni struktur | B67: 0 | C67: Özünəxidmət terminalları sahəsi | D67: 2 | E67: - | F67: 2 | G67: =COUNTIFS(baza!B:B,'ştat sayları'!C:C,baza!H:H,"Bir Payment") -> 1 | H67: =COUNTIFS(baza!B:B,'ştat sayları'!C:C,baza!H:H,"BirMarket") -> 0 | I67: =COUNTIFS(baza!B:B,'ştat sayları'!C:C,baza!H:H,"Paşa Holding") -> 0 | J67: =COUNTIFS(baza!B:B,'ştat sayları'!C:C,baza!H:H,"Future lab") -> 0 | K67: =G67+H67+I67+J67 -> 1 | L67: 1 ödənişlər sahəsindən | M67: yeni sahə və keçid
A68: başqa sahənin parçalanması | B68: 0 | C68: Kassa və inkassasiya prosesləri departamenti | D68: 444 | E68: - | F68: 444 | G68: =COUNTIFS(baza!B:B,'ştat sayları'!C:C,baza!H:H,"Bir Payment") -> 202 | H68: =COUNTIFS(baza!B:B,'ştat sayları'!C:C,baza!H:H,"BirMarket") -> 0 | I68: =COUNTIFS(baza!B:B,'ştat sayları'!C:C,baza!H:H,"Paşa Holding") -> 0 | J68: =COUNTIFS(baza!B:B,'ştat sayları'!C:C,baza!H:H,"Future lab") -> 0 | K68: =G68+H68+I68+J68 -> 202 | L68: 244 xkied, -3 XKİED(köhnə QƏLD dən verilən ştat), 1 xkieddəki kassir inkassatorun ştatı, +5 keçid pashapay sonradan | M68: yeni sahə və keçid
A69: başqa sahənin parçalanması | B69: 0 | C69: Texniki dəstək departamenti | D69: 61 | E69: - | F69: 61 | G69: =COUNTIFS(baza!B:B,'ştat sayları'!C:C,baza!H:H,"Bir Payment") -> 31 | H69: =COUNTIFS(baza!B:B,'ştat sayları'!C:C,baza!H:H,"BirMarket") -> 0 | I69: =COUNTIFS(baza!B:B,'ştat sayları'!C:C,baza!H:H,"Paşa Holding") -> 0 | J69: =COUNTIFS(baza!B:B,'ştat sayları'!C:C,baza!H:H,"Future lab") -> 0 | K69: =G69+H69+I69+J69 -> 31 | L69: 30 biznsə dəstək dep | M69: yeni sahə və keçid
A70: yeni struktur | B70: 0 | C70: Kart klirinqi və hesablaşmalar şöbəsi | D70: 12 | E70: - | F70: 12 | G70: =COUNTIFS(baza!B:B,'ştat sayları'!C:C,baza!H:H,"Bir Payment") -> 0 | H70: =COUNTIFS(baza!B:B,'ştat sayları'!C:C,baza!H:H,"BirMarket") -> 0 | I70: =COUNTIFS(baza!B:B,'ştat sayları'!C:C,baza!H:H,"Paşa Holding") -> 0 | J70: =COUNTIFS(baza!B:B,'ştat sayları'!C:C,baza!H:H,"Future lab") -> 0 | K70: =G70+H70+I70+J70 -> 0 | L70: 8 biznesə dəstək, 4 maliyyə hesabatlığı | M70: yeni sahə
A71: Loyallıq platformaları sahəsi | B71: 2 | C71: Ödəniş platformaları sahəsi | D71: 4 | E71: - | F71: 4 | G71: =COUNTIFS(baza!B:B,'ştat sayları'!C:C,baza!H:H,"Bir Payment") -> 0 | H71: =COUNTIFS(baza!B:B,'ştat sayları'!C:C,baza!H:H,"BirMarket") -> 0 | I71: =COUNTIFS(baza!B:B,'ştat sayları'!C:C,baza!H:H,"Paşa Holding") -> 0 | J71: =COUNTIFS(baza!B:B,'ştat sayları'!C:C,baza!H:H,"Future lab") -> 0 | K71: =G71+H71+I71+J71 -> 0 | L71: 1 fintech platform, 1 texnoloji həllər | M71: Struktur dəyişiklik
A72: başqa sahənin parçalanması | B72: 0 | C72: Ödəniş biznesinin mühəndislik ekspert mərkəzi | D72: 270 | E72: - | F72: 270 | G72: =COUNTIFS(baza!B:B,'ştat sayları'!C:C,baza!H:H,"Bir Payment") -> 15 | H72: =COUNTIFS(baza!B:B,'ştat sayları'!C:C,baza!H:H,"BirMarket") -> 0 | I72: =COUNTIFS(baza!B:B,'ştat sayları'!C:C,baza!H:H,"Paşa Holding") -> 0 | J72: =COUNTIFS(baza!B:B,'ştat sayları'!C:C,baza!H:H,"Future lab") -> 0 | K72: =G72+H72+I72+J72 -> 15 | L72: struktur dəyişikliyi | M72: Struktur dəyişiklik və keçidlər
A73: başqa sahənin parçalanması | B73: 0 | C73: Ödəniş biznesinin TechOps funksional sahəsi | D73: 21 | E73: 1 pashapay | F73: 22 | G73: =COUNTIFS(baza!B:B,'ştat sayları'!C:C,baza!H:H,"Bir Payment") -> 4 | H73: =COUNTIFS(baza!B:B,'ştat sayları'!C:C,baza!H:H,"BirMarket") -> 0 | I73: =COUNTIFS(baza!B:B,'ştat sayları'!C:C,baza!H:H,"Paşa Holding") -> 0 | J73: =COUNTIFS(baza!B:B,'ştat sayları'!C:C,baza!H:H,"Future lab") -> 0 | K73: =G73+H73+I73+J73 -> 4 | L73: 8 devops eks mərkəzi, 5 əlavə pashapaydan, +5 (4SRE,1 devops), | M73: yeni sahə və keçid
A74: Agile və məhsul ekspert mərkəzi | B74: 27 | C74: Agile və məhsul ekspert mərkəzi | D74: 22 | E74: 3 pashapay keçid | F74: 25 | G74: =COUNTIFS(baza!B:B,'ştat sayları'!C:C,baza!H:H,"Bir Payment") -> 3 | H74: =COUNTIFS(baza!B:B,'ştat sayları'!C:C,baza!H:H,"BirMarket") -> 0 | I74: =COUNTIFS(baza!B:B,'ştat sayları'!C:C,baza!H:H,"Paşa Holding") -> 0 | J74: =COUNTIFS(baza!B:B,'ştat sayları'!C:C,baza!H:H,"Future lab") -> 0 | K74: =G74+H74+I74+J74 -> 3 | L74: 2 si ai governance verilib, 3 ü strategiya və layihələr | M74: Keçidlər
A75: başqa sahənin parçalanması | B75: 0 | C75: Ödəniş biznesinin Analitika və Aİ ekspert mərkəzi | D75: 44 | E75: - | F75: 44 | G75: =COUNTIFS(baza!B:B,'ştat sayları'!C:C,baza!H:H,"Bir Payment") -> 10 | H75: =COUNTIFS(baza!B:B,'ştat sayları'!C:C,baza!H:H,"BirMarket") -> 0 | I75: =COUNTIFS(baza!B:B,'ştat sayları'!C:C,baza!H:H,"Paşa Holding") -> 0 | J75: =COUNTIFS(baza!B:B,'ştat sayları'!C:C,baza!H:H,"Future lab") -> 0 | K75: =G75+H75+I75+J75 -> 10 | L75: struktur dəyişikliyi | M75: Struktur dəyişiklik və keçidlər
A76: Audit komitəsi | B76: 2 | C76: Audit komitəsi | D76: 2 | E76: - | F76: 2 | G76: =COUNTIFS(baza!B:B,'ştat sayları'!C:C,baza!H:H,"Bir Payment") -> 0 | H76: =COUNTIFS(baza!B:B,'ştat sayları'!C:C,baza!H:H,"BirMarket") -> 0 | I76: =COUNTIFS(baza!B:B,'ştat sayları'!C:C,baza!H:H,"Paşa Holding") -> 0 | J76: =COUNTIFS(baza!B:B,'ştat sayları'!C:C,baza!H:H,"Future lab") -> 0 | K76: =G76+H76+I76+J76 -> 0
A77: Bank əməliyyatları ofisi | B77: 1 | C77: Əməliyyatlar ofisi | D77: 1 | E77: - | F77: 1 | G77: =COUNTIFS(baza!B:B,'ştat sayları'!C:C,baza!H:H,"Bir Payment") -> 0 | H77: =COUNTIFS(baza!B:B,'ştat sayları'!C:C,baza!H:H,"BirMarket") -> 0 | I77: =COUNTIFS(baza!B:B,'ştat sayları'!C:C,baza!H:H,"Paşa Holding") -> 0 | J77: =COUNTIFS(baza!B:B,'ştat sayları'!C:C,baza!H:H,"Future lab") -> 0 | K77: =G77+H77+I77+J77 -> 0
A78: İnformasiya texnologiyaları idarəsi | B78: 2 | C78: İnformasiya texnologiyaları idarəsi | D78: 2 | E78: - | F78: 2 | G78: =COUNTIFS(baza!B:B,'ştat sayları'!C:C,baza!H:H,"Bir Payment") -> 0 | H78: =COUNTIFS(baza!B:B,'ştat sayları'!C:C,baza!H:H,"BirMarket") -> 0 | I78: =COUNTIFS(baza!B:B,'ştat sayları'!C:C,baza!H:H,"Paşa Holding") -> 0 | J78: =COUNTIFS(baza!B:B,'ştat sayları'!C:C,baza!H:H,"Future lab") -> 0 | K78: =G78+H78+I78+J78 -> 0
A79: Məhsul və marketinq idarəsi | B79: 2 | C79: Məhsul və marketinq idarəsi | D79: 2 | E79: - | F79: 2 | G79: =COUNTIFS(baza!B:B,'ştat sayları'!C:C,baza!H:H,"Bir Payment") -> 0 | H79: =COUNTIFS(baza!B:B,'ştat sayları'!C:C,baza!H:H,"BirMarket") -> 0 | I79: =COUNTIFS(baza!B:B,'ştat sayları'!C:C,baza!H:H,"Paşa Holding") -> 0 | J79: =COUNTIFS(baza!B:B,'ştat sayları'!C:C,baza!H:H,"Future lab") -> 0 | K79: =G79+H79+I79+J79 -> 0
A80: Müşahidə şurası | B80: 4 | C80: Müşahidə şurası | D80: 4 | E80: - | F80: 4 | G80: =COUNTIFS(baza!B:B,'ştat sayları'!C:C,baza!H:H,"Bir Payment") -> 0 | H80: =COUNTIFS(baza!B:B,'ştat sayları'!C:C,baza!H:H,"BirMarket") -> 0 | I80: =COUNTIFS(baza!B:B,'ştat sayları'!C:C,baza!H:H,"Paşa Holding") -> 0 | J80: =COUNTIFS(baza!B:B,'ştat sayları'!C:C,baza!H:H,"Future lab") -> 0 | K80: =G80+H80+I80+J80 -> 0
A81: Rəhbərlik | B81: 13 | C81: Rəhbərlik | D81: 15 | E81: - | F81: 15 | G81: =COUNTIFS(baza!B:B,'ştat sayları'!C:C,baza!H:H,"Bir Payment") -> 1 | H81: =COUNTIFS(baza!B:B,'ştat sayları'!C:C,baza!H:H,"BirMarket") -> 2 | I81: =COUNTIFS(baza!B:B,'ştat sayları'!C:C,baza!H:H,"Paşa Holding") -> 0 | J81: =COUNTIFS(baza!B:B,'ştat sayları'!C:C,baza!H:H,"Future lab") -> 0 | K81: =G81+H81+I81+J81 -> 3 | L81: 2 yeni rəhbər lukasz və rauf atakişiyev
A82: Maliyyə risklərinin idarə edilməsi ofisi | B82: 1 | C82: Maliyyə risklərinin idarə edilməsi ofisi | D82: 1 | E82: - | F82: 1 | G82: =COUNTIFS(baza!B:B,'ştat sayları'!C:C,baza!H:H,"Bir Payment") -> 0 | H82: =COUNTIFS(baza!B:B,'ştat sayları'!C:C,baza!H:H,"BirMarket") -> 0 | I82: =COUNTIFS(baza!B:B,'ştat sayları'!C:C,baza!H:H,"Paşa Holding") -> 0 | J82: =COUNTIFS(baza!B:B,'ştat sayları'!C:C,baza!H:H,"Future lab") -> 0 | K82: =G82+H82+I82+J82 -> 0
A83: yeni struktur | B83: 0 | C83: Strategiya idarəsi | D83: 1 | E83: - | F83: 1 | G83: =COUNTIFS(baza!B:B,'ştat sayları'!C:C,baza!H:H,"Bir Payment") -> 0 | H83: =COUNTIFS(baza!B:B,'ştat sayları'!C:C,baza!H:H,"BirMarket") -> 0 | I83: =COUNTIFS(baza!B:B,'ştat sayları'!C:C,baza!H:H,"Paşa Holding") -> 1 | J83: =COUNTIFS(baza!B:B,'ştat sayları'!C:C,baza!H:H,"Future lab") -> 0 | K83: =G83+H83+I83+J83 -> 1
A84: yeni struktur | B84: 0 | C84: Data və Aİ idarəsi | D84: 1 | E84: - | F84: 1 | G84: =COUNTIFS(baza!B:B,'ştat sayları'!C:C,baza!H:H,"Bir Payment") -> 0 | H84: =COUNTIFS(baza!B:B,'ştat sayları'!C:C,baza!H:H,"BirMarket") -> 0 | I84: =COUNTIFS(baza!B:B,'ştat sayları'!C:C,baza!H:H,"Paşa Holding") -> 1 | J84: =COUNTIFS(baza!B:B,'ştat sayları'!C:C,baza!H:H,"Future lab") -> 0 | K84: =G84+H84+I84+J84 -> 1
A85: yeni struktur | B85: 0 | C85: Maliyyə ofisi | D85: 1 | E85: - | F85: 1 | G85: =COUNTIFS(baza!B:B,'ştat sayları'!C:C,baza!H:H,"Bir Payment") -> 0 | H85: =COUNTIFS(baza!B:B,'ştat sayları'!C:C,baza!H:H,"BirMarket") -> 0 | I85: =COUNTIFS(baza!B:B,'ştat sayları'!C:C,baza!H:H,"Paşa Holding") -> 0 | J85: =COUNTIFS(baza!B:B,'ştat sayları'!C:C,baza!H:H,"Future lab") -> 0 | K85: =G85+H85+I85+J85 -> 0 | L85: Pərvin Məmmədovun rəhbərlikdən bura keçməsi
A86: Pərakəndə biznes ofisi | B86: 1 | C86: Pərakəndə məhsullar ofisi | D86: 1 | E86: - | F86: 1 | G86: =COUNTIFS(baza!B:B,'ştat sayları'!C:C,baza!H:H,"Bir Payment") -> 0 | H86: =COUNTIFS(baza!B:B,'ştat sayları'!C:C,baza!H:H,"BirMarket") -> 0 | I86: =COUNTIFS(baza!B:B,'ştat sayları'!C:C,baza!H:H,"Paşa Holding") -> 0 | J86: =COUNTIFS(baza!B:B,'ştat sayları'!C:C,baza!H:H,"Future lab") -> 0 | K86: =G86+H86+I86+J86 -> 0
A87: Gündəlik bankçılıq ofisi | B87: 1 | C87: Ödəniş məhsulları ofisi | D87: 1 | E87: - | F87: 1 | G87: =COUNTIFS(baza!B:B,'ştat sayları'!C:C,baza!H:H,"Bir Payment") -> 0 | H87: =COUNTIFS(baza!B:B,'ştat sayları'!C:C,baza!H:H,"BirMarket") -> 0 | I87: =COUNTIFS(baza!B:B,'ştat sayları'!C:C,baza!H:H,"Paşa Holding") -> 0 | J87: =COUNTIFS(baza!B:B,'ştat sayları'!C:C,baza!H:H,"Future lab") -> 0 | K87: =G87+H87+I87+J87 -> 0
A88: yeni struktur | B88: 0 | C88: Ödəniş əməliyyatları ofisi | D88: 2 | E88: - | F88: 2 | G88: =COUNTIFS(baza!B:B,'ştat sayları'!C:C,baza!H:H,"Bir Payment") -> 0 | H88: =COUNTIFS(baza!B:B,'ştat sayları'!C:C,baza!H:H,"BirMarket") -> 0 | I88: =COUNTIFS(baza!B:B,'ştat sayları'!C:C,baza!H:H,"Paşa Holding") -> 0 | J88: =COUNTIFS(baza!B:B,'ştat sayları'!C:C,baza!H:H,"Future lab") -> 0 | K88: =G88+H88+I88+J88 -> 0 | L88: 1 i nağd pullardan, 1i opco(axtarılır)
A89: Texnoloji həllər ofisi | B89: 1 | C89: Ödəniş texnologiyaları ofisi | D89: 1 | E89: - | F89: 1 | G89: =COUNTIFS(baza!B:B,'ştat sayları'!C:C,baza!H:H,"Bir Payment") -> 0 | H89: =COUNTIFS(baza!B:B,'ştat sayları'!C:C,baza!H:H,"BirMarket") -> 0 | I89: =COUNTIFS(baza!B:B,'ştat sayları'!C:C,baza!H:H,"Paşa Holding") -> 0 | J89: =COUNTIFS(baza!B:B,'ştat sayları'!C:C,baza!H:H,"Future lab") -> 0 | K89: =G89+H89+I89+J89 -> 0
A90: Analitika ekspert mərkəzi | B90: 0 | C90: Analitika ekspert mərkəzi | D90: 4 | E90: - | F90: 4 | G90: =COUNTIFS(baza!B:B,'ştat sayları'!C:C,baza!H:H,"Bir Payment") -> 0 | H90: =COUNTIFS(baza!B:B,'ştat sayları'!C:C,baza!H:H,"BirMarket") -> 0 | I90: =COUNTIFS(baza!B:B,'ştat sayları'!C:C,baza!H:H,"Paşa Holding") -> 0 | J90: =COUNTIFS(baza!B:B,'ştat sayları'!C:C,baza!H:H,"Future lab") -> 0 | K90: =G90+H90+I90+J90 -> 0 | L90: köhnə strukturda qalanlar
A91: Aİ və Data elmi ekspert mərkəzi | B91: 0 | C91: Aİ və Data elmi ekspert mərkəzi | D91: 5 | E91: - | F91: 5 | G91: =COUNTIFS(baza!B:B,'ştat sayları'!C:C,baza!H:H,"Bir Payment") -> 0 | H91: =COUNTIFS(baza!B:B,'ştat sayları'!C:C,baza!H:H,"BirMarket") -> 0 | I91: =COUNTIFS(baza!B:B,'ştat sayları'!C:C,baza!H:H,"Paşa Holding") -> 0 | J91: =COUNTIFS(baza!B:B,'ştat sayları'!C:C,baza!H:H,"Future lab") -> 0 | K91: =G91+H91+I91+J91 -> 0 | L91: köhnə strukturda qalanlar
A92: Loyallıq məhsulları sahəsi | B92: 0 | C92: Loyallıq məhsulları sahəsi | D92: 1 | E92: - | F92: 1 | G92: =COUNTIFS(baza!B:B,'ştat sayları'!C:C,baza!H:H,"Bir Payment") -> 0 | H92: =COUNTIFS(baza!B:B,'ştat sayları'!C:C,baza!H:H,"BirMarket") -> 0 | I92: =COUNTIFS(baza!B:B,'ştat sayları'!C:C,baza!H:H,"Paşa Holding") -> 0 | J92: =COUNTIFS(baza!B:B,'ştat sayları'!C:C,baza!H:H,"Future lab") -> 0 | K92: =G92+H92+I92+J92 -> 0 | L92: köhnə strukturda qalanlar
A93: Data menecment ofisi | B93: 0 | C93: Data menecment ofisi | D93: 1 | E93: - | F93: 1 | G93: =COUNTIFS(baza!B:B,'ştat sayları'!C:C,baza!H:H,"Bir Payment") -> 0 | H93: =COUNTIFS(baza!B:B,'ştat sayları'!C:C,baza!H:H,"BirMarket") -> 0 | I93: =COUNTIFS(baza!B:B,'ştat sayları'!C:C,baza!H:H,"Paşa Holding") -> 0 | J93: =COUNTIFS(baza!B:B,'ştat sayları'!C:C,baza!H:H,"Future lab") -> 0 | K93: =G93+H93+I93+J93 -> 0 | L93: köhnə strukturda qalanlar
B94: 4977 | F94: =SUM(F2:F93) -> 6622 | G94: =SUM(G2:G93) -> 400 | H94: =SUM(H2:H93) -> 61 | I94: =SUM(I2:I93) -> 19 | J94: =SUM(J2:J93) -> 8 | K94: =SUM(K2:K93) -> 488
H96: =SUM(G94:J94) -> 488

Sheet əlavə ştat
A1: OPCO | F1: 85 | L1: Digər ştat məsələləri | M1: Keçid edən ştat | N1: Qeyd | O1: Əsas
A2: Hansı sahə | B2: Neçə ştat | C2: Tarix | D2: Protokol/ təsdiq | L2: Ekosistemin inkişafı və analitikası departamenti | M2: 2 | N2: holdinq
A3: Paymentsə verilən | B3: 23 | C3: 46239 | D3: OPCO N 22 | L3: Hüquq departamenti | M3: 3 | N3: 1 pashapay, 2 birmarket boş
A4: İnformasiya təhlükəsizliyi | B4: 17 | C4: 46157 | D4: OPCO N 38 | L4: İnformasiya təhlükəsizliyi departamenti | M4: 4 | N4: pashapay
A5: Mühəndislik və texnoloji platform, data və Aİ | B5: 7 | C5: 46177 | D5: OPCO N 15 | L5: İT infrastruktur departamenti | M5: 6 | N5: pashapay
A6: Birapp, Bir search | B6: 2 | C6: 46160 | D6: OPCO N14 | L6: Müştəri təcrübəsi ekspert mərkəzi | M6: 1 | N6: pashapaydan bura | O6: 07.07.2026 tamillla x ok
A7: Birinvest | B7: 1 | C7: 46156 | D7: OPCO N 13 | L7: Nağd pulların idarə edilməsi departamenti | M7: 2 | N7: pashapaydan bura | O7: 11.09.2026 tamilla x ok
A8: Cəmi | B8: 50 | L8: Ödəniş biznesinin mühəndislik ekspert mərkəzi | M8: 6 | N8: pashapaydan bura | O8: aylin maillər-pavel varapai,yuliya və.s
L9: Strategiya və layihələrin idarə edilməsi departamenti | M9: 3 | N9: 1 pashapay, 1 holdinq, 1 birmarket
L10: Təhlükəsizlik departamenti | M10: 1 | N10: Birmarket
L11: Təşkilati və qeyri-maliyyə risklərinin idarə edilməsi departamenti | M11: 4 | N11: pashapay
L12: Marketinq ekspert mərkəzi | M12: 1 | N12: əsaslandırılmalı
L13: Beynəlxalq hesabatlıq MİS | M13: 13 | N13: Maliyyədən silinməli idi
L14: Rəqəmsal dələduzluq | M14: 5
L16: Cəmi | M16: =SUM(M2:M14) -> 51

Sheet yekun ştat və vakant
A1: New | B1: Cəmi | C1: İşçi sayı | D1: müvəqqəti | E1: vakant | F1: Non agile, agile, filial
A2: Arxitektura ekspert mərkəzi | B2: 8 | C2: 7 | D2: 0 | E2: 1 | F2: Agile | I2: Agile | J2: =SUMIFS(E:E,F:F,"Agile") -> 198
A3: Dizayn ekspert mərkəzi | B3: 63 | C3: 57 | D3: 0 | E3: 6 | F3: Agile | I3: Non-Agile | J3: =SUMIFS(E:E,F:F,"Non-Agile") -> 236 | L3: =J3+J4+J2 -> 482
A4: İnzibati idarəetmə departamenti | B4: 162 | C4: 158 | D4: 2 | E4: 6 | F4: Non-Agile | I4: Filial | J4: =SUMIFS(E:E,F:F,"Filial") -> 48
A5: Komplayens departamenti | B5: 52 | C5: 54 | D5: 2 | E5: 0 | F5: Non-Agile
A6: Korporativ katiblik şöbəsi | B6: 37.5 | C6: 30 | D6: 0 | E6: 7.5 | F6: Non-Agile
A7: Biznes sahələrinin inkişafı və partnyor şəbəkəsi departamenti | B7: 99 | C7: 84 | D7: 0 | E7: 15 | F7: Non-Agile
A8: Müştəri təcrübəsi ekspert mərkəzi | B8: 25 | C8: 23 | D8: 0 | E8: 2 | F8: Agile
A9: Kredit portfelinə nəzarət departamenti | B9: 34 | C9: 31 | D9: 0 | E9: 3 | F9: Agile
A10: FinTech TechOps funksional sahəsi | B10: 16 | C10: 14 | D10: 0 | E10: 2 | F10: Agile
A11: Biznesə dəstək departamenti | B11: 116 | C11: 109 | D11: 0 | E11: 7 | F11: Non-Agile
A12: Məhsulların rəsmiləşdirilməsi sahəsi | B12: 5 | C12: 4 | D12: 0 | E12: 1 | F12: Agile
A13: Kart biznesi ekspert mərkəzi | B13: 12 | C13: 12 | D13: 0 | E13: 0 | F13: Agile
A14: Təhlükəsizlik departamenti | B14: 79 | C14: 74 | D14: 0 | E14: 5 | F14: Non-Agile
A15: İT proseslərinin idarə edilməsi funksional sahəsi | B15: 5 | C15: 4 | D15: 0 | E15: 1 | F15: Agile
A16: Rəqəmsal həllər sahəsi | B16: 6 | C16: 6 | D16: 0 | E16: 0 | F16: Agile
... A93: Data menecment ofisi | B93: 1 | C93: 1 | D93: 0 | E93: 0 | F93: Agile
B94: 6622 | C94: 6288 | D94: 148 | E94: 482

Sheet baza
A1: Personal kod | B1: Departament (Department) | C1: Şöbə (Section) | D1: Bölmə (Subsection) | E1: Vəzifə (Position) | F1: Aktiv, Passiv, HX, SM (Active, Passive,Social vacation) | G1: Kapital Banka işə qəbul olunduğu tarix (Hire date) | H1: keçid etdiyi şirkət | I1: Qeyd | J1: Non agile filial | N1: keçid etdiyi şirkət
A2: 16457 | B2: Müşahidə Şurası | C2: # | D2: # | E2: Müşahidə şurasının sədri (əvəzçilik qaydasında) | F2: A | G2: 45405 | J2: Non-Agile
A3: 10843 | B3: Müşahidə Şurası | C3: # | D3: # | E3: Müşahidə şurasının üzvü, Audit komitəsinin sədri (əvəzçilik qaydasında) | F3: A | G3: 41654 | J3: Non-Agile | N3: BirMarket
A4: 10925 | B4: Rəhbərlik | C4: # | D4: # | E4: İdarə Heyətinin sədri, Baş icraçı direktor | F4: A | G4: 42125 | J4: Non-Agile | N4: Bir Payment
A5: 10722 | B5: Rəhbərlik | C5: # | D5: # | E5: İdarə Heyəti sədrinin I müavini | F5: A | G5: 41736 | J5: Non-Agile | N5: Paşa Holding
A6: 10610 | B6: Rəhbərlik | C6: # | D6: # | E6: İdarə Heyəti sədrinin müavini, Baş Korporativ satış inzibatçısı | F6: A | G6: 41484 | J6: Non-Agile | N6: Future lab
A7: 18167 | B7: Rəhbərlik | C7: # | D7: # | E7: İdarə Heyəti sədrinin müavini | F7: A | G7: 46027 | J7: Non-Agile
A8: 10002 | B8: Rəhbərlik | C8: # | D8: # | E8: İdarə Heyəti sədrinin müavini | F8: A | G8: 37893 | J8: Non-Agile
A9: 10611 | B9: Rəhbərlik | C9: # | D9: # | E9: Baş komplayens inzibatçısı | F9: A | G9: 41484 | J9: Non-Agile
A10: 10963 | B10: Rəhbərlik | C10: # | D10: # | E10: Baş Risk inzibatçısı | F10: A | G10: 42219 | J10: Non-Agile
A11: 18369 | B11: Rəhbərlik | C11: # | D11: # | E11: Baş Maliyyə inzibatçısı | F11: A | G11: 46113 | J11: Non-Agile
A12: 10658 | B12: Rəhbərlik | C12: # | D12: # | E12: İdarə Heyəti sədrinin müşaviri | F12: A | G12: 41611 | J12: Non-Agile
A13: 18916 | B13: Rəhbərlik | C13: # | D13: # | E13: İdarə Heyəti sədrinin müşaviri | F13: A | G13: 46237 | J13: Non-Agile
A14: 18890 | B14: Rəhbərlik | C14: # | D14: # | E14: İdarə Heyəti sədrinin müşaviri | F14: A | G14: 46241 | H14: BirMarket | J14: Non-Agile
A15: 18188 | B15: Rəhbərlik | C15: # | D15: # | E15: İdarə Heyəti sədrinin müşaviri (əvəzçilik qaydasında) | F15: A | G15: 46034 | H15: BirMarket | J15: Non-Agile
A16: 15131 | B16: Rəhbərlik | C16: # | D16: # | E16: Müşavir (İdarə Heyətinin sədri/baş icraçı direktorun ekosistem üzrə) (əvəzçilik üzrə) | F16: A | G16: 44958 | J16: Non-Agile
A17: 11584 | B17: Rəhbərlik | C17: # | D17: # | E17: Ofis lideri | F17: A | G17: 42877 | J17: Agile
A18: 19018 | B18: Rəhbərlik | C18: # | D18: # | E18: Aparat rəhbəri | F18: A | G18: 46254 | H18: Bir Payment | J18: Agile
A19: 15541 | B19: İnformasiya texnologiyaları idarəsi | C19: # | D19: # | E19: Baş direktor | F19: A | G19: 45114 | J19: Agile
A20: 16327 | B20: Məhsul və marketinq idarəsi | C20: # | D20: # | E20: Baş direktor | F20: A | G20: 45344 | J20: Agile
A21: 18522 | B21: Data və Aİ idarəsi | C21: # | D21: # | E21: Baş direktor | F21: A | G21: 46143 | H21: Paşa Holding | J21: Agile
A22: 18523 | B22: Strategiya idarəsi | C22: # | D22: # | E22: Baş direktor | F22: A | G22: 46143 | H22: Paşa Holding | J22: Non-Agile
A23: 160032 | B23: Əməliyyatlar ofisi | C23: # | D23: # | E23: Ofis lideri | F23: A | G23: 42311 | J23: Non-Agile
A24: 10431 | B24: Ödəniş məhsulları ofisi | C24: # | D24: # | E24: Ofis lideri | F24: A | G24: 40253 | J24: Agile
A25: 13317 | B25: Data menecment ofisi | C25: # | D25: # | E25: Ofis lideri | F25: A | G25: 44382 | J25: Agile
A26: 10967 | B26: Ödəniş texnologiyaları ofisi | C26: # | D26: # | E26: Ofis lideri | F26: A | G26: 42222 | J26: Agile
A27: 10516 | B27: Maliyyə ofisi | C27: # | D27: # | E27: Ofis lideri | F27: A | G27: 41022 | J27: Non-Agile
A28: 13059 | B28: Maliyyə risklərinin idarə edilməsi ofisi | C28: # | D28: # | E28: Ofis lideri | F28: A | G28: 44228 | J28: Non-Agile
A29: 16326 | B29: İnformasiya texnologiyaları idarəsi | C29: # | D29: # | E29: Tribe tech lead | F29: A | G29: 45344 | J29: Agile
A30: 16075 | B30: Ödəniş biznesinin mühəndislik ekspert mərkəzi | C30: # | D30: # | E30: Tribe tech lead | F30: A | G30: 45278 | J30: Agile
A31: 18483 | B31: Ödəniş biznesinin mühəndislik ekspert mərkəzi | C31: softwate chapter | D31: # | E31: Tech lead | F31: A | G31: 46146 | J31: Agile
A32: 18815 | B32: Ödəniş biznesinin mühəndislik ekspert mərkəzi | C32: softwate chapter | D32: # | E32: Tech lead (0,5 ştat vahidi üzrə əvəzçilik qaydasında) | F32: A | G32: 46213 | H32: Bir Payment | J32: Agile
A33: 18182 | B33: Kart məhsulları sahəsi | C33: # | D33: # | E33: Tribe tech lead | F33: A | G33: 46035 | J33: Agile
A34: 11886 | B34: FinTech mühəndislik ekspert mərkəzi | C34: # | D34: # | E34: Tribe tech lead | F34: A | G34: 43242 | J34: Agile
A35: 17254 | B35: Ödəniş biznesinin mühəndislik ekspert mərkəzi | C35: # | D35: # | E35: Ekspert mərkəzinin lideri | F35: A | G35: 45691 | J35: Agile
A36: 16234 | B36: Ödəniş biznesinin TechOps funksional sahəsi | C36: # | D36: # | E36: Servis dayanıqlığı üzrə mühəndis | F36: A | G36: 45323 | J36: Agile
A37: 17485 | B37: BirApp texnologiyası sahəsi | C37: # | D37: # | E37: Tribe tech lead | F37: A | G37: 45762 | J37: Agile
A38: 11527 | B38: BirApp texnologiyası sahəsi | C38: Birbank Platform | D38: # | E38: Məhsul sahibi | F38: A | G38: 42797 | J38: Agile
A39: 11536 | B39: Ödəniş biznesinin mühəndislik ekspert mərkəzi | C39: # | D39: # | E39: Tribe tech lead | F39: A | G39: 42808 | J39: Agile
A40: 18202 | B40: Korporativ inkişaf və investor əlaqələri departamenti | C40: # | D40: # | E40: Menecer | F40: A | G40: 46055 | J40: Non-Agile
A41: 18268 | B41: Korporativ inkişaf və investor əlaqələri departamenti | C41: # | D41: # | E41: Direktor müavini | F41: A | G41: 46084 | J41: Non-Agile
A42: 10944 | B42: # | C42: Korporativ katiblik şöbəsi | D42: # | E42: Şöbə müdiri | F42: A | G42: 42171 | J42: Non-Agile
A43: 10568 | B43: # | C43: Korporativ katiblik şöbəsi | D43: İdarəetmə orqanları və komitələrlə iş bölməsi | E43: Korporativ katib | F43: A | G43: 41246 | J43: Non-Agile
A44: 13399 | B44: # | C44: Korporativ katiblik şöbəsi | D44: İdarəetmə orqanları və komitələrlə iş bölməsi | E44: Aparıcı mütəxəssis | F44: A | G44: 44425 | J44: Non-Agile
... A57: 15659 | B57: # | C57: Korporativ katiblik şöbəsi | D57: Katiblik bölməsi | E57: Şəxsi köməkçi | F57: A | G57: 45154 | J57: Non-Agile
A58: 19126 | B58: # | C58: Korporativ katiblik şöbəsi | D58: Katiblik bölməsi | E58: Şəxsi köməkçi | F58: A | G58: 46268 | H58: Future lab | J58: Non-Agile
A59: 17763 | B59: # | C59: Korporativ katiblik şöbəsi | D59: Katiblik bölməsi | E59: Şəxsi köməkçi | F59: A | G59: 45873 | J59: Non-Agile
A60: 17835 | B60: # | C60: Korporativ katiblik şöbəsi | D60: Katiblik bölməsi | E60: Şəxsi köməkçi | F60: A | G60: 45888 | J60: Non-Agile
A61: 12584 | B61: # | C61: Korporativ katiblik şöbəsi | D61: Katiblik bölməsi | E61: Şəxsi köməkçi | F61: A | G61: 43827 | J61: Non-Agile
A62: 10603 | B62: # | C62: Korporativ katiblik şöbəsi | D62: Katiblik bölməsi | E62: Şəxsi köməkçi (əvəzçilik qaydasında) | F62: A | G62: 39727 | J62: Non-Agile
A63: 10015 | B63: # | C63: Korporativ katiblik şöbəsi | D63: Sənədlərin qeydiyyatı və dövriyyəsi bölməsi | E63: Menecer | F63: A | G63: 36714 | J63: Non-Agile
A64: 13006 | B64: # | C64: Korporativ katiblik şöbəsi | D64: Sənədlərin qeydiyyatı və dövriyyəsi bölməsi | E64: Aparıcı mütəxəssis | F64: A | G64: 44187 | J64: Non-Agile
A65: 14147 | B65: # | C65: Korporativ katiblik şöbəsi | D65: Sənədlərin qeydiyyatı və dövriyyəsi bölməsi | E65: Aparıcı mütəxəssis | F65: A | G65: 44673 | J65: Non-Agile
A66: 18467 | B66: # | C66: Korporativ katiblik şöbəsi | D66: Sənədlərin qeydiyyatı və dövriyyəsi bölməsi | E66: Aparıcı mütəxəssis | F66: A | G66: 46134 | J66: Non-Agile
A67: 13414 | B67: # | C67: Korporativ katiblik şöbəsi | D67: Sənədlərin qeydiyyatı və dövriyyəsi bölməsi | E67: Mütəxəssis | F67: A | G67: 44431 | J67: Non-Agile
A68: 16636 | B68: # | C68: Korporativ katiblik şöbəsi | D68: Sənədlərin qeydiyyatı və dövriyyəsi bölməsi | E68: Mütəxəssis | F68: A | G68: 45505 | J68: Non-Agile
A69: 17180 | B69: # | C69: Korporativ katiblik şöbəsi | D69: Sənədlərin qeydiyyatı və dövriyyəsi bölməsi | E69: Mütəxəssis | F69: A | G69: 45670 | J69: Non-Agile
A70: 17316 | B70: # | C70: Korporativ katiblik şöbəsi | D70: Sənədlərin qeydiyyatı və dövriyyəsi bölməsi | E70: Mütəxəssis | F70: A | G70: 45709 | J70: Non-Agile
... A72: 16969 | B72: Təşkilati inkişaf və HR texnologiyaları departamenti | C72: İşəgötürən brendi və KSM funksional sahəsi | D72: # | E72: Funksional sahə lideri | F72: A | G72: 45580 | J72: Non-Agile
A73: 18277 | B73: Təşkilati inkişaf və HR texnologiyaları departamenti | C73: İşəgötürən brendi və KSM funksional sahəsi | D73: # | E73: Menecer | F73: A | G73: 46072 | H73: BirMarket | J73: Non-Agile
A74: 18281 | B74: Təşkilati inkişaf və HR texnologiyaları departamenti | C74: İşəgötürən brendi və KSM funksional sahəsi | D74: İnternal communications function | E74: Menecer | F74: A | G74: 46072 | H74: BirMarket | J74: Non-Agile
A75: 18362 | B75: Təşkilati inkişaf və HR texnologiyaları departamenti | C75: İşəgötürən brendi və KSM funksional sahəsi | D75: # | E75: Baş mütəxəssis | F75: A | G75: 46113 | J75: Non-Agile
A76: 19206 | B76: Təşkilati inkişaf və HR texnologiyaları departamenti | C76: İşəgötürən brendi və KSM funksional sahəsi | D76: # | E76: Baş mütəxəssis | F76: A | G76: 46276 | H76: Future lab | J76: Non-Agile
A77: 15580 | B77: Təşkilati inkişaf və HR texnologiyaları departamenti | C77: İşəgötürən brendi və KSM funksional sahəsi | D77: İnternal communications function | E77: Aparıcı mütəxəssis | F77: A | G77: 45124 | J77: Non-Agile
A78: 18243 | B78: Təşkilati inkişaf və HR texnologiyaları departamenti | C78: İşəgötürən brendi və KSM funksional sahəsi | D78: İnternal communications function | E78: Aparıcı mütəxəssis | F78: A | G78: 46069 | J78: Non-Agile
A79: 19232 | B79: Təşkilati inkişaf və HR texnologiyaları departamenti | C79: İşəgötürən brendi və KSM funksional sahəsi | D79: İnternal communications function | E79: Aparıcı mütəxəssis | F79: A | G79: 46281 | J79: Non-Agile
A80: 17948 | B80: Təşkilati inkişaf və HR texnologiyaları departamenti | C80: İşəgötürən brendi və KSM funksional sahəsi | D80: # | E80: Mütəxəssis | F80: A | G80: 45933 | J80: Non-Agile
A81: 13116 | B81: Təşkilati inkişaf və HR texnologiyaları departamenti | C81: İşəgötürən brendi və KSM funksional sahəsi | D81: # | E81: Baş mütəxəssis | F81: A | G81: 44265 | J81: Non-Agile
A82: 17466 | B82: Təşkilati inkişaf və HR texnologiyaları departamenti | C82: İşəgötürən brendi və KSM funksional sahəsi | D82: # | E82: Mütəxəssis | F82: A | G82: 45758 | J82: Non-Agile
A83: 17978 | B83: Təşkilati inkişaf və HR texnologiyaları departamenti | C83: İşəgötürən brendi və KSM funksional sahəsi | D83: # | E83: Mütəxəssis | F83: A | G83: 45944 | J83: Non-Agile
A84: 18399 | B84: Təşkilati inkişaf və HR texnologiyaları departamenti | C84: İşəgötürən brendi və KSM funksional sahəsi | D84: # | E84: Aparıcı mütəxəssis | F84: A | G84: 46120 | H84: BirMarket | J84: Non-Agile
A85: 12835 | B85: # | C85: VİP müştərilərlə iş şöbəsi | D85: # | E85: Şöbə müdiri | F85: A | G85: 44004 | J85: Non-Agile
A86: 600034 | B86: # | C86: VİP müştərilərlə iş şöbəsi | D86: # | E86: Menecer | F86: A | G86: 42676 | J86: Non-Agile
A87: 770021 | B87: # | C87: VİP müştərilərlə iş şöbəsi | D87: # | E87: Baş mütəxəssis | F87: A | G87: 42731 | J87: Non-Agile
A88: 12638 | B88: # | C88: VİP müştərilərlə iş şöbəsi | D88: # | E88: Baş mütəxəssis | F88: A | G88: 43847 | J88: Non-Agile
A89: 12738 | B89: # | C89: VİP müştərilərlə iş şöbəsi | D89: # | E89: Baş mütəxəssis | F89: A | G89: 43885 | J89: Non-Agile
A90: 300223 | B90: # | C90: VİP müştərilərlə iş şöbəsi | D90: # | E90: Aparıcı mütəxəssis | F90: A | G90: 44203 | J90: Non-Agile
A91: 13285 | B91: # | C91: VİP müştərilərlə iş şöbəsi | D91: # | E91: Aparıcı mütəxəssis | F91: A | G91: 44368 | J91: Non-Agile
A92: 18961 | B92: # | C92: VİP müştərilərlə iş şöbəsi | D92: # | E92: Kiçik mütəxəssis | F92: A | G92: 46248 | J92: Non-Agile
A93: 17215 | B93: Daxili audit departamenti | C93: # | D93: # | E93: Direktor müavini | F93: A | G93: 45663 | J93: Non-Agile
A94: 210029 | B94: Daxili audit departamenti | C94: Əməliyyat,komplayens və davamlı audit üzrə ekspert mərkəzi | D94: # | E94: Audit meneceri | F94: A | G94: 42075 | J94: Non-Agile
A95: 10765 | B95: Daxili audit departamenti | C95: Əməliyyat,komplayens və davamlı audit üzrə ekspert mərkəzi | D95: # | E95: Audit meneceri | F95: A | G95: 41841 | J95: Non-Agile
A96: 10338 | B96: Daxili audit departamenti | C96: Əməliyyat,komplayens və davamlı audit üzrə ekspert mərkəzi | D96: # | E96: Audit meneceri | F96: A | G96: 38783 | J96: Non-Agile
... A148: 15499 | B148: Hüquq departamenti | C148: Məhkəmələr və hüquqi təminat şöbəsi | D148: # | E148: Aparıcı hüquqşünas | F148: A | G148: 45099 | J148: Non-Agile
A149: 18318 | B149: Hüquq departamenti | C149: Məhkəmələr və hüquqi təminat şöbəsi | D149: # | E149: Hüquqşünas (əvəzçilik qaydasında) | F149: A | G149: 46084 | H149: BirMarket | J149: Non-Agile
A150: 18319 | B150: Hüquq departamenti | C150: Məhkəmələr və hüquqi təminat şöbəsi | D150: # | E150: Mütəxəssis(əvəzçilik qaydasında) | F150: A | G150: 46084 | H150: Bir Payment | J150: Non-Agile
A151: 18335 | B151: Hüquq departamenti | C151: Məhkəmələr və hüquqi təminat şöbəsi | D151: # | E151: Mütəxəssis | F151: A | G151: 46091 | H151: Bir Payment | J151: Non-Agile
A152: 14355 | B152: Hüquq departamenti | C152: Məhkəmələr və hüquqi təminat şöbəsi | D152: # | E152: Mütəxəssis | F152: A | G152: 44743 | J152: Non-Agile
A153: 17456 | B153: Hüquq departamenti | C153: Məhkəmələr və hüquqi təminat şöbəsi | D153: # | E153: Aparıcı hüquqşünas | F153: A | G153: 45757 | J153: Non-Agile
A154: 18375 | B154: Hüquq departamenti | C154: Ödəniş biznesinə hüquqi dəstək şöbəsi | D154: # | E154: Şöbə müdiri | F154: A | G154: 46113 | H154: Bir Payment | J154: Non-Agile
A155: 18376 | B155: Hüquq departamenti | C155: Ödəniş biznesinə hüquqi dəstək şöbəsi | D155: # | E155: Baş hüquqşünas | F155: A | G155: 46113 | H155: Bir Payment | J155: Non-Agile
A156: 18379 | B156: Hüquq departamenti | C156: Ödəniş biznesinə hüquqi dəstək şöbəsi | D156: # | E156: Baş hüquqşünas | F156: A | G156: 46113 | H156: Bir Payment | J156: Non-Agile
A157: 18377 | B157: Hüquq departamenti | C157: Ödəniş biznesinə hüquqi dəstək şöbəsi | D157: # | E157: Aparıcı hüquqşünas | F157: A | G157: 46113 | H157: Bir Payment | J157: Non-Agile
A158: 18381 | B158: Hüquq departamenti | C158: E-ticarət biznesinə hüquqi dəstək şöbəsi | D158: # | E158: Baş hüquqşünas | F158: A | G158: 46113 | H158: BirMarket | J158: Non-Agile
A159: 18382 | B159: Hüquq departamenti | C159: E-ticarət biznesinə hüquqi dəstək şöbəsi | D159: # | E159: Baş hüquqşünas (0,5 ştat vahidi üzrə) | F159: A | G159: 46113 | H159: BirMarket | J159: Non-Agile
A160: 18380 | B160: Hüquq departamenti | C160: E-ticarət biznesinə hüquqi dəstək şöbəsi | D160: # | E160: Aparıcı hüquqşünas | F160: A | G160: 46113 | H160: BirMarket | J160: Non-Agile
A161: 18384 | B161: Hüquq departamenti | C161: E-ticarət biznesinə hüquqi dəstək şöbəsi | D161: # | E161: Baş mütəxəssis | F161: HX | G161: 46113 | H161: BirMarket | J161: Non-Agile
A162: 18383 | B162: Hüquq departamenti | C162: E-ticarət biznesinə hüquqi dəstək şöbəsi | D162: # | E162: Mütəxəssis | F162: A | G162: 46113 | H162: BirMarket | J162: Non-Agile
A163: 18378 | B163: Hüquq departamenti | C163: E-ticarət biznesinə hüquqi dəstək şöbəsi | D163: # | E163: Hüquqşunas | F163: A | G163: 46113 | H163: BirMarket | J163: Non-Agile
A164: 12207 | B164: Hüquq departamenti | C164: Arxiv şöbəsi | D164: # | E164: Şöbə müdiri | F164: A | G164: 43587 | J164: Non-Agile
...

Sheet birmarket
A1: Unit | B1: Number of employee
A3: Commercial Block | B3: 1
A4: Electronics Vertical | B4: 10
A5: Beauty Vertical | B5: 6
A6: Home goods Vertical | B6: 8
A7: FMCG Vertical | B7: 8
A8: Seller Excellence Department | B8: 46
A9: Content Operations Division | B9: 37
A10: Seller Product tribe | B10: 5
A11: C-level | B11: 1
A12: Vacant HCs | B12: 7
A14: Supply Chain Block | B14: 1
A15: Routes planning&Delivery division | B15: 38
... A59: HSE Division | B59: 1

Sheet pashapay
A3: Struktur adı | B3: Staff | C3: Vacant | D3: Qeyd | E3: qeyd
A4: Audit komitəsi | B4: 3 | C4: 1
A5: Baş Komplayens inzibatçısı | B5: 1 | C5: 0
A6: Biznesin optimallaşdırılması şöbəsi | B6: 1 | C6: 0
A7: Daxili audit departamenti | B7: 2 | C7: 0
A8: Daxili nəzarət şöbəsi | B8: 3 | C8: 0
A9: Frauda qarşı mübarizə şöbəsi | B9: 10 | C9: 0
A10: Hesablaşmalar departamenti | B10: 11 | C10: 2
A11: Hüquq Şöbəsi | B11: 3 | C11: 1
A12: İnformasiya təhlükəsizliyi şöbəsi | B12: 3 | C12: 0
A13: İnkassasiya Şöbəsi | B13: 162 | C13: 26 | D13: 86 vakant yerdən 60 FTE-in relokasiyasına icazə verilmişdir. Bu vakantlar 34 FTE-in relokasiyası üçün istifadə olunacaqdır. İnkassasiya şöbəsində 26 vakant qalacaq.
A14: İstedadların idarə edilməsi departamenti | B14: 4 | C14: 2
A15: İT şöbəsi | B15: 11 | C15: 0
A16: Kross-sərhəd və satış sahəsi | B16: 10 | C16: 3
A17: Maliyyə menecmenti departamenti | B17: 13 | C17: =1+3 -> 4 | D17: Hazırda 1 vakant var, lakin 3 FTE də bura relokasiya olunacaqdır. 34 FTE excelinin içində bu barədə məlumat var.
A18: Məhsullar Şöbəsi | B18: 26 | C18: 5
A19: Mühasibatlıq departamenti | B19: 2 | C19: 0
A20: Müştəri mükəmməlliyi departamenti | B20: 117 | C20: =10+3 -> 13 | D20: 3 FTE relokasiya olunacaq bura, 34 FTE-in içində qeyd olunub.
A21: none structure | B21: 38
A22: Təhlükəsizlik departamenti | B22: 8 | C22: 0
A23: Terminal biznesinə dəstək departamenti | B23: 141 | C23: 0
A24: Terminal və ATM şəbəkəsinin idarə edilməsi departamenti | B24: 28 | C24: 0
A25: Grand Total | B25: 597 | C25: =SUM(C4:C24) -> 57
