Workbook

Sheet Summary
B1: Summary by Department
B4: Summary by Department (Horizontal) | C4: 31 August 2026 (actual) | G4: 31 Dec 2027 (plan) | H4: Change in Active
B5: Department | C5: Active | D5: Passive | E5: Vacant | F5: Total | G5: Active | H5: Absolute | I5: %
B6: Management | C6: =SUMIFS('Summary by Division'!$D$6:$D$297,'Summary by Division'!$B$6:$B$297,$B6,'Summary by Division'!$A$6:$A$297,"<>"&$B$38,'Summary by Division'!$A$6:$A$297,"<>"&$B$73) -> 0 | D6: =SUMIFS('Summary by Division'!$E$6:$E$297,'Summary by Division'!$B$6:$B$297,$B6,'Summary by Division'!$A$6:$A$297,"<>"&$B$38,'Summary by Division'!$A$6:$A$297,"<>"&$B$73) -> 0 | E6: =SUMIFS('Summary by Division'!$F$6:$F$297,'Summary by Division'!$B$6:$B$297,$B6,'Summary by Division'!$A$6:$A$297,"<>"&$B$38,'Summary by Division'!$A$6:$A$297,"<>"&$B$73) -> 0 | F6: =SUMIFS('Summary by Division'!$G$6:$G$297,'Summary by Division'!$B$6:$B$297,$B6,'Summary by Division'!$A$6:$A$297,"<>"&$B$38,'Summary by Division'!$A$6:$A$297,"<>"&$B$73) -> 0 | G6: =SUMIFS('Summary by Division'!$H$6:$H$297,'Summary by Division'!$B$6:$B$297,$B6,'Summary by Division'!$A$6:$A$297,"<>"&$B$38,'Summary by Division'!$A$6:$A$297,"<>"&$B$73) -> 0 | H6: =G6-C6 -> 0 | I6: =IF(C6=0,0,H6/C6) -> 0
B7: Corporate Secretary Division | C7: =SUMIFS('Summary by Division'!$D$6:$D$297,'Summary by Division'!$B$6:$B$297,$B7,'Summary by Division'!$A$6:$A$297,"<>"&$B$38,'Summary by Division'!$A$6:$A$297,"<>"&$B$73) -> 30 | D7: =SUMIFS('Summary by Division'!$E$6:$E$297,'Summary by Division'!$B$6:$B$297,$B7,'Summary by Division'!$A$6:$A$297,"<>"&$B$38,'Summary by Division'!$A$6:$A$297,"<>"&$B$73) -> 2 | E7: =SUMIFS('Summary by Division'!$F$6:$F$297,'Summary by Division'!$B$6:$B$297,$B7,'Summary by Division'!$A$6:$A$297,"<>"&$B$38,'Summary by Division'!$A$6:$A$297,"<>"&$B$73) -> 7.5 | F7: =SUMIFS('Summary by Division'!$G$6:$G$297,'Summary by Division'!$B$6:$B$297,$B7,'Summary by Division'!$A$6:$A$297,"<>"&$B$38,'Summary by Division'!$A$6:$A$297,"<>"&$B$73) -> 39.5 | G7: =SUMIFS('Summary by Division'!$H$6:$H$297,'Summary by Division'!$B$6:$B$297,$B7,'Summary by Division'!$A$6:$A$297,"<>"&$B$38,'Summary by Division'!$A$6:$A$297,"<>"&$B$73) -> 37.5 | H7: =G7-C7 -> 7.5 | I7: =IF(C7=0,0,H7/C7) -> 0.25
B8: Agile and Product Center of Expertise | C8: =SUMIFS('Summary by Division'!$D$6:$D$297,'Summary by Division'!$B$6:$B$297,$B8,'Summary by Division'!$A$6:$A$297,"<>"&$B$38,'Summary by Division'!$A$6:$A$297,"<>"&$B$73) -> 19 | D8: =SUMIFS('Summary by Division'!$E$6:$E$297,'Summary by Division'!$B$6:$B$297,$B8,'Summary by Division'!$A$6:$A$297,"<>"&$B$38,'Summary by Division'!$A$6:$A$297,"<>"&$B$73) -> 2 | E8: =SUMIFS('Summary by Division'!$F$6:$F$297,'Summary by Division'!$B$6:$B$297,$B8,'Summary by Division'!$A$6:$A$297,"<>"&$B$38,'Summary by Division'!$A$6:$A$297,"<>"&$B$73) -> 4 | F8: =SUMIFS('Summary by Division'!$G$6:$G$297,'Summary by Division'!$B$6:$B$297,$B8,'Summary by Division'!$A$6:$A$297,"<>"&$B$38,'Summary by Division'!$A$6:$A$297,"<>"&$B$73) -> 25 | G8: =SUMIFS('Summary by Division'!$H$6:$H$297,'Summary by Division'!$B$6:$B$297,$B8,'Summary by Division'!$A$6:$A$297,"<>"&$B$38,'Summary by Division'!$A$6:$A$297,"<>"&$B$73) -> 26 | H8: =G8-C8 -> 7 | I8: =IF(C8=0,0,H8/C8) -> 0.36842105
B9: AI Governance Center of Expertise | C9: =SUMIFS('Summary by Division'!$D$6:$D$297,'Summary by Division'!$B$6:$B$297,$B9,'Summary by Division'!$A$6:$A$297,"<>"&$B$38,'Summary by Division'!$A$6:$A$297,"<>"&$B$73) -> 16 | D9: =SUMIFS('Summary by Division'!$E$6:$E$297,'Summary by Division'!$B$6:$B$297,$B9,'Summary by Division'!$A$6:$A$297,"<>"&$B$38,'Summary by Division'!$A$6:$A$297,"<>"&$B$73) -> 0 | E9: =SUMIFS('Summary by Division'!$F$6:$F$297,'Summary by Division'!$B$6:$B$297,$B9,'Summary by Division'!$A$6:$A$297,"<>"&$B$38,'Summary by Division'!$A$6:$A$297,"<>"&$B$73) -> 27 | F9: =SUMIFS('Summary by Division'!$G$6:$G$297,'Summary by Division'!$B$6:$B$297,$B9,'Summary by Division'!$A$6:$A$297,"<>"&$B$38,'Summary by Division'!$A$6:$A$297,"<>"&$B$73) -> 43 | G9: =SUMIFS('Summary by Division'!$H$6:$H$297,'Summary by Division'!$B$6:$B$297,$B9,'Summary by Division'!$A$6:$A$297,"<>"&$B$38,'Summary by Division'!$A$6:$A$297,"<>"&$B$73) -> 48 | H9: =G9-C9 -> 32 | I9: =IF(C9=0,0,H9/C9) -> 2
B10: Architecture Center of Expertise | C10: =SUMIFS('Summary by Division'!$D$6:$D$297,'Summary by Division'!$B$6:$B$297,$B10,'Summary by Division'!$A$6:$A$297,"<>"&$B$38,'Summary by Division'!$A$6:$A$297,"<>"&$B$73) -> 7 | D10: =SUMIFS('Summary by Division'!$E$6:$E$297,'Summary by Division'!$B$6:$B$297,$B10,'Summary by Division'!$A$6:$A$297,"<>"&$B$38,'Summary by Division'!$A$6:$A$297,"<>"&$B$73) -> 0 | E10: =SUMIFS('Summary by Division'!$F$6:$F$297,'Summary by Division'!$B$6:$B$297,$B10,'Summary by Division'!$A$6:$A$297,"<>"&$B$38,'Summary by Division'!$A$6:$A$297,"<>"&$B$73) -> 2 | F10: =SUMIFS('Summary by Division'!$G$6:$G$297,'Summary by Division'!$B$6:$B$297,$B10,'Summary by Division'!$A$6:$A$297,"<>"&$B$38,'Summary by Division'!$A$6:$A$297,"<>"&$B$73) -> 9 | G10: =SUMIFS('Summary by Division'!$H$6:$H$297,'Summary by Division'!$B$6:$B$297,$B10,'Summary by Division'!$A$6:$A$297,"<>"&$B$38,'Summary by Division'!$A$6:$A$297,"<>"&$B$73) -> 9 | H10: =G10-C10 -> 2 | I10: =IF(C10=0,0,H10/C10) -> 0.28571429
B11: International Reporting and MIS Department | C11: =SUMIFS('Summary by Division'!$D$6:$D$297,'Summary by Division'!$B$6:$B$297,$B11,'Summary by Division'!$A$6:$A$297,"<>"&$B$38,'Summary by Division'!$A$6:$A$297,"<>"&$B$73) -> 11 | D11: =SUMIFS('Summary by Division'!$E$6:$E$297,'Summary by Division'!$B$6:$B$297,$B11,'Summary by Division'!$A$6:$A$297,"<>"&$B$38,'Summary by Division'!$A$6:$A$297,"<>"&$B$73) -> 3 | E11: =SUMIFS('Summary by Division'!$F$6:$F$297,'Summary by Division'!$B$6:$B$297,$B11,'Summary by Division'!$A$6:$A$297,"<>"&$B$38,'Summary by Division'!$A$6:$A$297,"<>"&$B$73) -> 8 | F11: =SUMIFS('Summary by Division'!$G$6:$G$297,'Summary by Division'!$B$6:$B$297,$B11,'Summary by Division'!$A$6:$A$297,"<>"&$B$38,'Summary by Division'!$A$6:$A$297,"<>"&$B$73) -> 22 | G11: =SUMIFS('Summary by Division'!$H$6:$H$297,'Summary by Division'!$B$6:$B$297,$B11,'Summary by Division'!$A$6:$A$297,"<>"&$B$38,'Summary by Division'!$A$6:$A$297,"<>"&$B$73) -> 22 | H11: =G11-C11 -> 11 | I11: =IF(C11=0,0,H11/C11) -> 1
B12: BirApp Area | C12: =SUMIFS('Summary by Division'!$D$6:$D$297,'Summary by Division'!$B$6:$B$297,$B12,'Summary by Division'!$A$6:$A$297,"<>"&$B$38,'Summary by Division'!$A$6:$A$297,"<>"&$B$73) -> 5 | D12: =SUMIFS('Summary by Division'!$E$6:$E$297,'Summary by Division'!$B$6:$B$297,$B12,'Summary by Division'!$A$6:$A$297,"<>"&$B$38,'Summary by Division'!$A$6:$A$297,"<>"&$B$73) -> 0 | E12: =SUMIFS('Summary by Division'!$F$6:$F$297,'Summary by Division'!$B$6:$B$297,$B12,'Summary by Division'!$A$6:$A$297,"<>"&$B$38,'Summary by Division'!$A$6:$A$297,"<>"&$B$73) -> 0 | F12: =SUMIFS('Summary by Division'!$G$6:$G$297,'Summary by Division'!$B$6:$B$297,$B12,'Summary by Division'!$A$6:$A$297,"<>"&$B$38,'Summary by Division'!$A$6:$A$297,"<>"&$B$73) -> 5 | G12: =SUMIFS('Summary by Division'!$H$6:$H$297,'Summary by Division'!$B$6:$B$297,$B12,'Summary by Division'!$A$6:$A$297,"<>"&$B$38,'Summary by Division'!$A$6:$A$297,"<>"&$B$73) -> 4 | H12: =G12-C12 -> -1 | I12: =IF(C12=0,0,H12/C12) -> -0.2
B13: BirApp Technology Area | C13: =SUMIFS('Summary by Division'!$D$6:$D$297,'Summary by Division'!$B$6:$B$297,$B13,'Summary by Division'!$A$6:$A$297,"<>"&$B$38,'Summary by Division'!$A$6:$A$297,"<>"&$B$73) -> 2 | D13: =SUMIFS('Summary by Division'!$E$6:$E$297,'Summary by Division'!$B$6:$B$297,$B13,'Summary by Division'!$A$6:$A$297,"<>"&$B$38,'Summary by Division'!$A$6:$A$297,"<>"&$B$73) -> 0 | E13: =SUMIFS('Summary by Division'!$F$6:$F$297,'Summary by Division'!$B$6:$B$297,$B13,'Summary by Division'!$A$6:$A$297,"<>"&$B$38,'Summary by Division'!$A$6:$A$297,"<>"&$B$73) -> 1 | F13: =SUMIFS('Summary by Division'!$G$6:$G$297,'Summary by Division'!$B$6:$B$297,$B13,'Summary by Division'!$A$6:$A$297,"<>"&$B$38,'Summary by Division'!$A$6:$A$297,"<>"&$B$73) -> 3 | G13: =SUMIFS('Summary by Division'!$H$6:$H$297,'Summary by Division'!$B$6:$B$297,$B13,'Summary by Division'!$A$6:$A$297,"<>"&$B$38,'Summary by Division'!$A$6:$A$297,"<>"&$B$73) -> 3 | H13: =G13-C13 -> 1 | I13: =IF(C13=0,0,H13/C13) -> 0.5
B14: Data Governance Center of Expertise | C14: =SUMIFS('Summary by Division'!$D$6:$D$297,'Summary by Division'!$B$6:$B$297,$B14,'Summary by Division'!$A$6:$A$297,"<>"&$B$38,'Summary by Division'!$A$6:$A$297,"<>"&$B$73) -> 20 | D14: =SUMIFS('Summary by Division'!$E$6:$E$297,'Summary by Division'!$B$6:$B$297,$B14,'Summary by Division'!$A$6:$A$297,"<>"&$B$38,'Summary by Division'!$A$6:$A$297,"<>"&$B$73) -> 0 | E14: =SUMIFS('Summary by Division'!$F$6:$F$297,'Summary by Division'!$B$6:$B$297,$B14,'Summary by Division'!$A$6:$A$297,"<>"&$B$38,'Summary by Division'!$A$6:$A$297,"<>"&$B$73) -> 10 | F14: =SUMIFS('Summary by Division'!$G$6:$G$297,'Summary by Division'!$B$6:$B$297,$B14,'Summary by Division'!$A$6:$A$297,"<>"&$B$38,'Summary by Division'!$A$6:$A$297,"<>"&$B$73) -> 30 | G14: =SUMIFS('Summary by Division'!$H$6:$H$297,'Summary by Division'!$B$6:$B$297,$B14,'Summary by Division'!$A$6:$A$297,"<>"&$B$38,'Summary by Division'!$A$6:$A$297,"<>"&$B$73) -> 30 | H14: =G14-C14 -> 10 | I14: =IF(C14=0,0,H14/C14) -> 0.5
B15: Data mühəndisliyi və texnologiyaları ekspert mərkəzi | C15: =SUMIFS('Summary by Division'!$D$6:$D$297,'Summary by Division'!$B$6:$B$297,$B15,'Summary by Division'!$A$6:$A$297,"<>"&$B$38,'Summary by Division'!$A$6:$A$297,"<>"&$B$73) -> 23 | D15: =SUMIFS('Summary by Division'!$E$6:$E$297,'Summary by Division'!$B$6:$B$297,$B15,'Summary by Division'!$A$6:$A$297,"<>"&$B$38,'Summary by Division'!$A$6:$A$297,"<>"&$B$73) -> 1 | E15: =SUMIFS('Summary by Division'!$F$6:$F$297,'Summary by Division'!$B$6:$B$297,$B15,'Summary by Division'!$A$6:$A$297,"<>"&$B$38,'Summary by Division'!$A$6:$A$297,"<>"&$B$73) -> 4 | F15: =SUMIFS('Summary by Division'!$G$6:$G$297,'Summary by Division'!$B$6:$B$297,$B15,'Summary by Division'!$A$6:$A$297,"<>"&$B$38,'Summary by Division'!$A$6:$A$297,"<>"&$B$73) -> 28 | G15: =SUMIFS('Summary by Division'!$H$6:$H$297,'Summary by Division'!$B$6:$B$297,$B15,'Summary by Division'!$A$6:$A$297,"<>"&$B$38,'Summary by Division'!$A$6:$A$297,"<>"&$B$73) -> 26 | H15: =G15-C15 -> 3 | I15: =IF(C15=0,0,H15/C15) -> 0.13043478
B16: Data və Analitika departamenti(Marketplace) | C16: =SUMIFS('Summary by Division'!$D$6:$D$297,'Summary by Division'!$B$6:$B$297,$B16,'Summary by Division'!$A$6:$A$297,"<>"&$B$38,'Summary by Division'!$A$6:$A$297,"<>"&$B$73) -> 4 | D16: =SUMIFS('Summary by Division'!$E$6:$E$297,'Summary by Division'!$B$6:$B$297,$B16,'Summary by Division'!$A$6:$A$297,"<>"&$B$38,'Summary by Division'!$A$6:$A$297,"<>"&$B$73) -> 0 | E16: =SUMIFS('Summary by Division'!$F$6:$F$297,'Summary by Division'!$B$6:$B$297,$B16,'Summary by Division'!$A$6:$A$297,"<>"&$B$38,'Summary by Division'!$A$6:$A$297,"<>"&$B$73) -> 0 | F16: =SUMIFS('Summary by Division'!$G$6:$G$297,'Summary by Division'!$B$6:$B$297,$B16,'Summary by Division'!$A$6:$A$297,"<>"&$B$38,'Summary by Division'!$A$6:$A$297,"<>"&$B$73) -> 4 | G16: =SUMIFS('Summary by Division'!$H$6:$H$297,'Summary by Division'!$B$6:$B$297,$B16,'Summary by Division'!$A$6:$A$297,"<>"&$B$38,'Summary by Division'!$A$6:$A$297,"<>"&$B$73) -> 4 | H16: =G16-C16 -> 0 | I16: =IF(C16=0,0,H16/C16) -> 0
B17: Design Center of Expertise | C17: =SUMIFS('Summary by Division'!$D$6:$D$297,'Summary by Division'!$B$6:$B$297,$B17,'Summary by Division'!$A$6:$A$297,"<>"&$B$38,'Summary by Division'!$A$6:$A$297,"<>"&$B$73) -> 53 | D17: =SUMIFS('Summary by Division'!$E$6:$E$297,'Summary by Division'!$B$6:$B$297,$B17,'Summary by Division'!$A$6:$A$297,"<>"&$B$38,'Summary by Division'!$A$6:$A$297,"<>"&$B$73) -> 1 | E17: =SUMIFS('Summary by Division'!$F$6:$F$297,'Summary by Division'!$B$6:$B$297,$B17,'Summary by Division'!$A$6:$A$297,"<>"&$B$38,'Summary by Division'!$A$6:$A$297,"<>"&$B$73) -> 9 | F17: =SUMIFS('Summary by Division'!$G$6:$G$297,'Summary by Division'!$B$6:$B$297,$B17,'Summary by Division'!$A$6:$A$297,"<>"&$B$38,'Summary by Division'!$A$6:$A$297,"<>"&$B$73) -> 63 | G17: =SUMIFS('Summary by Division'!$H$6:$H$297,'Summary by Division'!$B$6:$B$297,$B17,'Summary by Division'!$A$6:$A$297,"<>"&$B$38,'Summary by Division'!$A$6:$A$297,"<>"&$B$73) -> 63 | H17: =G17-C17 -> 10 | I17: =IF(C17=0,0,H17/C17) -> 0.18867925
... B34: Organizational and Non-Financial Risk Management Department | C34: =SUMIFS('Summary by Division'!$D$6:$D$297,'Summary by Division'!$B$6:$B$297,$B34,'Summary by Division'!$A$6:$A$297,"<>"&$B$38,'Summary by Division'!$A$6:$A$297,"<>"&$B$73) -> 58 | D34: =SUMIFS('Summary by Division'!$E$6:$E$297,'Summary by Division'!$B$6:$B$297,$B34,'Summary by Division'!$A$6:$A$297,"<>"&$B$38,'Summary by Division'!$A$6:$A$297,"<>"&$B$73) -> 1 | E34: =SUMIFS('Summary by Division'!$F$6:$F$297,'Summary by Division'!$B$6:$B$297,$B34,'Summary by Division'!$A$6:$A$297,"<>"&$B$38,'Summary by Division'!$A$6:$A$297,"<>"&$B$73) -> 5 | F34: =SUMIFS('Summary by Division'!$G$6:$G$297,'Summary by Division'!$B$6:$B$297,$B34,'Summary by Division'!$A$6:$A$297,"<>"&$B$38,'Summary by Division'!$A$6:$A$297,"<>"&$B$73) -> 64 | G34: =SUMIFS('Summary by Division'!$H$6:$H$297,'Summary by Division'!$B$6:$B$297,$B34,'Summary by Division'!$A$6:$A$297,"<>"&$B$38,'Summary by Division'!$A$6:$A$297,"<>"&$B$73) -> 70 | H34: =G34-C34 -> 12 | I34: =IF(C34=0,0,H34/C34) -> 0.20689655
B35: Total | C35: =SUM(C6:C34) -> 1169 | D35: =SUM(D6:D34) -> 34 | E35: =SUM(E6:E34) -> 181 | F35: =SUM(F6:F34) -> 1384 | G35: =SUM(G6:G34) -> 1384 | H35: =SUM(H6:H34) -> 215 | I35: =IF(C35=0,0,H35/C35) -> 0.18391788
C36: =C35-SUMIFS('Summary by Division'!$D$6:$D$261,'Summary by Division'!$A$6:$A$261,"<>"&$B$38) -> 0 | D36: =D35-SUMIFS('Summary by Division'!$E$6:$E$261,'Summary by Division'!$A$6:$A$261,"<>"&$B$38) -> 0 | E36: =E35-SUMIFS('Summary by Division'!$F$6:$F$261,'Summary by Division'!$A$6:$A$261,"<>"&$B$38) -> 0 | F36: =F35-SUMIFS('Summary by Division'!$G$6:$G$261,'Summary by Division'!$A$6:$A$261,"<>"&$B$38) -> 0 | G36: =G35-SUMIFS('Summary by Division'!$H$6:$H$261,'Summary by Division'!$A$6:$A$261,"<>"&$B$38) -> 0
B38: Fintech | C38: 31 August 2026 (actual) | G38: 31 Dec 2027 (plan) | H38: Change in Active
B39: Department | C39: Active | D39: Passive | E39: Vacant | F39: Total | G39: Active | H39: Absolute | I39: %
B40: Management | C40: =SUMIFS('Summary by Division'!$D$6:$D$297,'Summary by Division'!$B$6:$B$297,$B40,'Summary by Division'!$A$6:$A$297,$B$38) -> 43 | D40: =SUMIFS('Summary by Division'!$E$6:$E$297,'Summary by Division'!$B$6:$B$297,$B40,'Summary by Division'!$A$6:$A$297,$B$38) -> 0 | E40: =SUMIFS('Summary by Division'!$F$6:$F$297,'Summary by Division'!$B$6:$B$297,$B40,'Summary by Division'!$A$6:$A$297,$B$38) -> 0 | F40: =SUMIFS('Summary by Division'!$G$6:$G$297,'Summary by Division'!$B$6:$B$297,$B40,'Summary by Division'!$A$6:$A$297,$B$38) -> 43 | G40: =SUMIFS('Summary by Division'!$H$6:$H$297,'Summary by Division'!$B$6:$B$297,$B40,'Summary by Division'!$A$6:$A$297,$B$38) -> 43 | H40: =G40-C40 -> 0 | I40: =IF(C40=0,0,H40/C40) -> 0
B41: VİP müştərilərlə iş şöbəsi | C41: =SUMIFS('Summary by Division'!$D$6:$D$297,'Summary by Division'!$B$6:$B$297,$B41,'Summary by Division'!$A$6:$A$297,$B$38) -> 8 | D41: =SUMIFS('Summary by Division'!$E$6:$E$297,'Summary by Division'!$B$6:$B$297,$B41,'Summary by Division'!$A$6:$A$297,$B$38) -> 0 | E41: =SUMIFS('Summary by Division'!$F$6:$F$297,'Summary by Division'!$B$6:$B$297,$B41,'Summary by Division'!$A$6:$A$297,$B$38) -> 0 | F41: =SUMIFS('Summary by Division'!$G$6:$G$297,'Summary by Division'!$B$6:$B$297,$B41,'Summary by Division'!$A$6:$A$297,$B$38) -> 8 | G41: =SUMIFS('Summary by Division'!$H$6:$H$297,'Summary by Division'!$B$6:$B$297,$B41,'Summary by Division'!$A$6:$A$297,$B$38) -> 4 | H41: =G41-C41 -> -4 | I41: =IF(C41=0,0,H41/C41) -> -0.5
B42: Birbank biznes sahəsi | C42: =SUMIFS('Summary by Division'!$D$6:$D$297,'Summary by Division'!$B$6:$B$297,$B42,'Summary by Division'!$A$6:$A$297,$B$38) -> 7 | D42: =SUMIFS('Summary by Division'!$E$6:$E$297,'Summary by Division'!$B$6:$B$297,$B42,'Summary by Division'!$A$6:$A$297,$B$38) -> 0 | E42: =SUMIFS('Summary by Division'!$F$6:$F$297,'Summary by Division'!$B$6:$B$297,$B42,'Summary by Division'!$A$6:$A$297,$B$38) -> 2 | F42: =SUMIFS('Summary by Division'!$G$6:$G$297,'Summary by Division'!$B$6:$B$297,$B42,'Summary by Division'!$A$6:$A$297,$B$38) -> 9 | G42: =SUMIFS('Summary by Division'!$H$6:$H$297,'Summary by Division'!$B$6:$B$297,$B42,'Summary by Division'!$A$6:$A$297,$B$38) -> 9 | H42: =G42-C42 -> 2 | I42: =IF(C42=0,0,H42/C42) -> 0.28571429
B43: Biznesə dəstək departamenti | C43: =SUMIFS('Summary by Division'!$D$6:$D$297,'Summary by Division'!$B$6:$B$297,$B43,'Summary by Division'!$A$6:$A$297,$B$38) -> 99 | D43: =SUMIFS('Summary by Division'!$E$6:$E$297,'Summary by Division'!$B$6:$B$297,$B43,'Summary by Division'!$A$6:$A$297,$B$38) -> 0 | E43: =SUMIFS('Summary by Division'!$F$6:$F$297,'Summary by Division'!$B$6:$B$297,$B43,'Summary by Division'!$A$6:$A$297,$B$38) -> 17 | F43: =SUMIFS('Summary by Division'!$G$6:$G$297,'Summary by Division'!$B$6:$B$297,$B43,'Summary by Division'!$A$6:$A$297,$B$38) -> 116 | G43: =SUMIFS('Summary by Division'!$H$6:$H$297,'Summary by Division'!$B$6:$B$297,$B43,'Summary by Division'!$A$6:$A$297,$B$38) -> 116 | H43: =G43-C43 -> 17 | I43: =IF(C43=0,0,H43/C43) -> 0.17171717
B44: Daxili audit departamenti | C44: =SUMIFS('Summary by Division'!$D$6:$D$297,'Summary by Division'!$B$6:$B$297,$B44,'Summary by Division'!$A$6:$A$297,$B$38) -> 39 | D44: =SUMIFS('Summary by Division'!$E$6:$E$297,'Summary by Division'!$B$6:$B$297,$B44,'Summary by Division'!$A$6:$A$297,$B$38) -> 0 | E44: =SUMIFS('Summary by Division'!$F$6:$F$297,'Summary by Division'!$B$6:$B$297,$B44,'Summary by Division'!$A$6:$A$297,$B$38) -> 11 | F44: =SUMIFS('Summary by Division'!$G$6:$G$297,'Summary by Division'!$B$6:$B$297,$B44,'Summary by Division'!$A$6:$A$297,$B$38) -> 50 | G44: =SUMIFS('Summary by Division'!$H$6:$H$297,'Summary by Division'!$B$6:$B$297,$B44,'Summary by Division'!$A$6:$A$297,$B$38) -> 50 | H44: =G44-C44 -> 11 | I44: =IF(C44=0,0,H44/C44) -> 0.28205128
B45: FinTech Agile funksional sahəsi | C45: =SUMIFS('Summary by Division'!$D$6:$D$297,'Summary by Division'!$B$6:$B$297,$B45,'Summary by Division'!$A$6:$A$297,$B$38) -> 3 | D45: =SUMIFS('Summary by Division'!$E$6:$E$297,'Summary by Division'!$B$6:$B$297,$B45,'Summary by Division'!$A$6:$A$297,$B$38) -> 0 | E45: =SUMIFS('Summary by Division'!$F$6:$F$297,'Summary by Division'!$B$6:$B$297,$B45,'Summary by Division'!$A$6:$A$297,$B$38) -> 4 | F45: =SUMIFS('Summary by Division'!$G$6:$G$297,'Summary by Division'!$B$6:$B$297,$B45,'Summary by Division'!$A$6:$A$297,$B$38) -> 7 | G45: =SUMIFS('Summary by Division'!$H$6:$H$297,'Summary by Division'!$B$6:$B$297,$B45,'Summary by Division'!$A$6:$A$297,$B$38) -> 7 | H45: =G45-C45 -> 4 | I45: =IF(C45=0,0,H45/C45) -> 1.3333333
B46: Fintech Analitika və Aİ ekspert mərkəzi | C46: =SUMIFS('Summary by Division'!$D$6:$D$297,'Summary by Division'!$B$6:$B$297,$B46,'Summary by Division'!$A$6:$A$297,$B$38) -> 30 | D46: =SUMIFS('Summary by Division'!$E$6:$E$297,'Summary by Division'!$B$6:$B$297,$B46,'Summary by Division'!$A$6:$A$297,$B$38) -> 0 | E46: =SUMIFS('Summary by Division'!$F$6:$F$297,'Summary by Division'!$B$6:$B$297,$B46,'Summary by Division'!$A$6:$A$297,$B$38) -> 0 | F46: =SUMIFS('Summary by Division'!$G$6:$G$297,'Summary by Division'!$B$6:$B$297,$B46,'Summary by Division'!$A$6:$A$297,$B$38) -> 30 | G46: =SUMIFS('Summary by Division'!$H$6:$H$297,'Summary by Division'!$B$6:$B$297,$B46,'Summary by Division'!$A$6:$A$297,$B$38) -> 30 | H46: =G46-C46 -> 0 | I46: =IF(C46=0,0,H46/C46) -> 0
B47: FinTech arxitektura və İT idarəetmə prosesi | C47: =SUMIFS('Summary by Division'!$D$6:$D$297,'Summary by Division'!$B$6:$B$297,$B47,'Summary by Division'!$A$6:$A$297,$B$38) -> 3 | D47: =SUMIFS('Summary by Division'!$E$6:$E$297,'Summary by Division'!$B$6:$B$297,$B47,'Summary by Division'!$A$6:$A$297,$B$38) -> 0 | E47: =SUMIFS('Summary by Division'!$F$6:$F$297,'Summary by Division'!$B$6:$B$297,$B47,'Summary by Division'!$A$6:$A$297,$B$38) -> 2 | F47: =SUMIFS('Summary by Division'!$G$6:$G$297,'Summary by Division'!$B$6:$B$297,$B47,'Summary by Division'!$A$6:$A$297,$B$38) -> 5 | G47: =SUMIFS('Summary by Division'!$H$6:$H$297,'Summary by Division'!$B$6:$B$297,$B47,'Summary by Division'!$A$6:$A$297,$B$38) -> 5 | H47: =G47-C47 -> 2 | I47: =IF(C47=0,0,H47/C47) -> 0.66666667
B48: FinTech mühəndislik ekspert mərkəzi | C48: =SUMIFS('Summary by Division'!$D$6:$D$297,'Summary by Division'!$B$6:$B$297,$B48,'Summary by Division'!$A$6:$A$297,$B$38) -> 19 | D48: =SUMIFS('Summary by Division'!$E$6:$E$297,'Summary by Division'!$B$6:$B$297,$B48,'Summary by Division'!$A$6:$A$297,$B$38) -> 0 | E48: =SUMIFS('Summary by Division'!$F$6:$F$297,'Summary by Division'!$B$6:$B$297,$B48,'Summary by Division'!$A$6:$A$297,$B$38) -> 0 | F48: =SUMIFS('Summary by Division'!$G$6:$G$297,'Summary by Division'!$B$6:$B$297,$B48,'Summary by Division'!$A$6:$A$297,$B$38) -> 19 | G48: =SUMIFS('Summary by Division'!$H$6:$H$297,'Summary by Division'!$B$6:$B$297,$B48,'Summary by Division'!$A$6:$A$297,$B$38) -> 19 | H48: =G48-C48 -> 0 | I48: =IF(C48=0,0,H48/C48) -> 0
B49: FinTech platformalar sahəsi | C49: =SUMIFS('Summary by Division'!$D$6:$D$297,'Summary by Division'!$B$6:$B$297,$B49,'Summary by Division'!$A$6:$A$297,$B$38) -> 2 | D49: =SUMIFS('Summary by Division'!$E$6:$E$297,'Summary by Division'!$B$6:$B$297,$B49,'Summary by Division'!$A$6:$A$297,$B$38) -> 0 | E49: =SUMIFS('Summary by Division'!$F$6:$F$297,'Summary by Division'!$B$6:$B$297,$B49,'Summary by Division'!$A$6:$A$297,$B$38) -> 0 | F49: =SUMIFS('Summary by Division'!$G$6:$G$297,'Summary by Division'!$B$6:$B$297,$B49,'Summary by Division'!$A$6:$A$297,$B$38) -> 2 | G49: =SUMIFS('Summary by Division'!$H$6:$H$297,'Summary by Division'!$B$6:$B$297,$B49,'Summary by Division'!$A$6:$A$297,$B$38) -> 2 | H49: =G49-C49 -> 0 | I49: =IF(C49=0,0,H49/C49) -> 0
B50: FinTech TechOps funksional sahəsi | C50: =SUMIFS('Summary by Division'!$D$6:$D$297,'Summary by Division'!$B$6:$B$297,$B50,'Summary by Division'!$A$6:$A$297,$B$38) -> 14 | D50: =SUMIFS('Summary by Division'!$E$6:$E$297,'Summary by Division'!$B$6:$B$297,$B50,'Summary by Division'!$A$6:$A$297,$B$38) -> 0 | E50: =SUMIFS('Summary by Division'!$F$6:$F$297,'Summary by Division'!$B$6:$B$297,$B50,'Summary by Division'!$A$6:$A$297,$B$38) -> 5 | F50: =SUMIFS('Summary by Division'!$G$6:$G$297,'Summary by Division'!$B$6:$B$297,$B50,'Summary by Division'!$A$6:$A$297,$B$38) -> 19 | G50: =SUMIFS('Summary by Division'!$H$6:$H$297,'Summary by Division'!$B$6:$B$297,$B50,'Summary by Division'!$A$6:$A$297,$B$38) -> 19 | H50: =G50-C50 -> 5 | I50: =IF(C50=0,0,H50/C50) -> 0.35714286
B51: İstedadların idarə edilməsi departamenti | C51: =SUMIFS('Summary by Division'!$D$6:$D$297,'Summary by Division'!$B$6:$B$297,$B51,'Summary by Division'!$A$6:$A$297,$B$38) -> 21 | D51: =SUMIFS('Summary by Division'!$E$6:$E$297,'Summary by Division'!$B$6:$B$297,$B51,'Summary by Division'!$A$6:$A$297,$B$38) -> 0 | E51: =SUMIFS('Summary by Division'!$F$6:$F$297,'Summary by Division'!$B$6:$B$297,$B51,'Summary by Division'!$A$6:$A$297,$B$38) -> 0 | F51: =SUMIFS('Summary by Division'!$G$6:$G$297,'Summary by Division'!$B$6:$B$297,$B51,'Summary by Division'!$A$6:$A$297,$B$38) -> 21 | G51: =SUMIFS('Summary by Division'!$H$6:$H$297,'Summary by Division'!$B$6:$B$297,$B51,'Summary by Division'!$A$6:$A$297,$B$38) -> 21 | H51: =G51-C51 -> 0 | I51: =IF(C51=0,0,H51/C51) -> 0
... B69: Branches | C69: =SUMIFS('Summary by Division'!$D$6:$D$297,'Summary by Division'!$B$6:$B$297,$B69,'Summary by Division'!$A$6:$A$297,$B$38) -> 1860 | D69: =SUMIFS('Summary by Division'!$E$6:$E$297,'Summary by Division'!$B$6:$B$297,$B69,'Summary by Division'!$A$6:$A$297,$B$38) -> 0 | E69: =SUMIFS('Summary by Division'!$F$6:$F$297,'Summary by Division'!$B$6:$B$297,$B69,'Summary by Division'!$A$6:$A$297,$B$38) -> 6 | F69: =SUMIFS('Summary by Division'!$G$6:$G$297,'Summary by Division'!$B$6:$B$297,$B69,'Summary by Division'!$A$6:$A$297,$B$38) -> 1866 | G69: =SUMIFS('Summary by Division'!$H$6:$H$297,'Summary by Division'!$B$6:$B$297,$B69,'Summary by Division'!$A$6:$A$297,$B$38) -> 1860 | H69: =G69-C69 -> 0 | I69: =IF(C69=0,0,H69/C69) -> 0
B70: Fintech total | C70: =SUM(C40:C69) -> 3431 | D70: =SUM(D40:D69) -> 0 | E70: =SUM(E40:E69) -> 158 | F70: =SUM(F40:F69) -> 3589 | G70: =SUM(G40:G69) -> 3559 | H70: =SUM(H40:H69) -> 128 | I70: =IF(C70=0,0,H70/C70) -> 0.037306908
C71: =C70-SUMIFS('Summary by Division'!$D$6:$D$261,'Summary by Division'!$A$6:$A$261,$B$38) -> 0 | D71: =D70-SUMIFS('Summary by Division'!$E$6:$E$261,'Summary by Division'!$A$6:$A$261,$B$38) -> 0 | E71: =E70-SUMIFS('Summary by Division'!$F$6:$F$261,'Summary by Division'!$A$6:$A$261,$B$38) -> 0 | F71: =F70-SUMIFS('Summary by Division'!$G$6:$G$261,'Summary by Division'!$A$6:$A$261,$B$38) -> 0 | G71: =G70-SUMIFS('Summary by Division'!$H$6:$H$261,'Summary by Division'!$A$6:$A$261,$B$38) -> 0
B73: Payment | C73: =C38 -> 31 August 2026 (actual) | G73: =G38 -> 31 Dec 2027 (plan) | H73: =H38 -> Change in Active
B74: Department | C74: =C39 -> Active | D74: =D39 -> Passive | E74: =E39 -> Vacant | F74: =F39 -> Total | G74: =G39 -> Active | H74: =H39 -> Absolute | I74: =I39 -> %
B75: ='Summary by Division'!B262 -> Management | C75: =SUMIFS('Summary by Division'!$D$6:$D$297,'Summary by Division'!$B$6:$B$297,$B75,'Summary by Division'!$A$6:$A$297,$B$73) -> 11 | D75: =SUMIFS('Summary by Division'!$E$6:$E$297,'Summary by Division'!$B$6:$B$297,$B75,'Summary by Division'!$A$6:$A$297,$B$73) -> 0 | E75: =SUMIFS('Summary by Division'!$F$6:$F$297,'Summary by Division'!$B$6:$B$297,$B75,'Summary by Division'!$A$6:$A$297,$B$73) -> 0 | F75: =SUMIFS('Summary by Division'!$G$6:$G$297,'Summary by Division'!$B$6:$B$297,$B75,'Summary by Division'!$A$6:$A$297,$B$73) -> 11 | G75: =SUMIFS('Summary by Division'!$H$6:$H$297,'Summary by Division'!$B$6:$B$297,$B75,'Summary by Division'!$A$6:$A$297,$B$73) -> 11 | H75: =G75-C75 -> 0 | I75: =IF(C75=0,0,H75/C75) -> 0
B76: ='Summary by Division'!B263 -> Birbonus sahəsi | C76: =SUMIFS('Summary by Division'!$D$6:$D$297,'Summary by Division'!$B$6:$B$297,$B76,'Summary by Division'!$A$6:$A$297,$B$73) -> 4 | D76: =SUMIFS('Summary by Division'!$E$6:$E$297,'Summary by Division'!$B$6:$B$297,$B76,'Summary by Division'!$A$6:$A$297,$B$73) -> 0 | E76: =SUMIFS('Summary by Division'!$F$6:$F$297,'Summary by Division'!$B$6:$B$297,$B76,'Summary by Division'!$A$6:$A$297,$B$73) -> 0 | F76: =SUMIFS('Summary by Division'!$G$6:$G$297,'Summary by Division'!$B$6:$B$297,$B76,'Summary by Division'!$A$6:$A$297,$B$73) -> 4 | G76: =SUMIFS('Summary by Division'!$H$6:$H$297,'Summary by Division'!$B$6:$B$297,$B76,'Summary by Division'!$A$6:$A$297,$B$73) -> 4 | H76: =G76-C76 -> 0 | I76: =IF(C76=0,0,H76/C76) -> 0
B77: ='Summary by Division'!B264 -> Biznes sahələrinin inkişafı və partnyor şəbəkəsi departamenti | C77: =SUMIFS('Summary by Division'!$D$6:$D$297,'Summary by Division'!$B$6:$B$297,$B77,'Summary by Division'!$A$6:$A$297,$B$73) -> 82 | D77: =SUMIFS('Summary by Division'!$E$6:$E$297,'Summary by Division'!$B$6:$B$297,$B77,'Summary by Division'!$A$6:$A$297,$B$73) -> 0 | E77: =SUMIFS('Summary by Division'!$F$6:$F$297,'Summary by Division'!$B$6:$B$297,$B77,'Summary by Division'!$A$6:$A$297,$B$73) -> 0 | F77: =SUMIFS('Summary by Division'!$G$6:$G$297,'Summary by Division'!$B$6:$B$297,$B77,'Summary by Division'!$A$6:$A$297,$B$73) -> 82 | G77: =SUMIFS('Summary by Division'!$H$6:$H$297,'Summary by Division'!$B$6:$B$297,$B77,'Summary by Division'!$A$6:$A$297,$B$73) -> 89 | H77: =G77-C77 -> 7 | I77: =IF(C77=0,0,H77/C77) -> 0.085365854
B78: ='Summary by Division'!B265 -> Ekvayrinq texnologiyaları sahəsi | C78: =SUMIFS('Summary by Division'!$D$6:$D$297,'Summary by Division'!$B$6:$B$297,$B78,'Summary by Division'!$A$6:$A$297,$B$73) -> 3 | D78: =SUMIFS('Summary by Division'!$E$6:$E$297,'Summary by Division'!$B$6:$B$297,$B78,'Summary by Division'!$A$6:$A$297,$B$73) -> 0 | E78: =SUMIFS('Summary by Division'!$F$6:$F$297,'Summary by Division'!$B$6:$B$297,$B78,'Summary by Division'!$A$6:$A$297,$B$73) -> 0 | F78: =SUMIFS('Summary by Division'!$G$6:$G$297,'Summary by Division'!$B$6:$B$297,$B78,'Summary by Division'!$A$6:$A$297,$B$73) -> 3 | G78: =SUMIFS('Summary by Division'!$H$6:$H$297,'Summary by Division'!$B$6:$B$297,$B78,'Summary by Division'!$A$6:$A$297,$B$73) -> 5 | H78: =G78-C78 -> 2 | I78: =IF(C78=0,0,H78/C78) -> 0.66666667
B79: ='Summary by Division'!B266 -> Kart biznesi ekspert mərkəzi | C79: =SUMIFS('Summary by Division'!$D$6:$D$297,'Summary by Division'!$B$6:$B$297,$B79,'Summary by Division'!$A$6:$A$297,$B$73) -> 11 | D79: =SUMIFS('Summary by Division'!$E$6:$E$297,'Summary by Division'!$B$6:$B$297,$B79,'Summary by Division'!$A$6:$A$297,$B$73) -> 0 | E79: =SUMIFS('Summary by Division'!$F$6:$F$297,'Summary by Division'!$B$6:$B$297,$B79,'Summary by Division'!$A$6:$A$297,$B$73) -> 0 | F79: =SUMIFS('Summary by Division'!$G$6:$G$297,'Summary by Division'!$B$6:$B$297,$B79,'Summary by Division'!$A$6:$A$297,$B$73) -> 11 | G79: =SUMIFS('Summary by Division'!$H$6:$H$297,'Summary by Division'!$B$6:$B$297,$B79,'Summary by Division'!$A$6:$A$297,$B$73) -> 14 | H79: =G79-C79 -> 3 | I79: =IF(C79=0,0,H79/C79) -> 0.27272727
B80: ='Summary by Division'!B267 -> Kart məhsulları sahəsi | C80: =SUMIFS('Summary by Division'!$D$6:$D$297,'Summary by Division'!$B$6:$B$297,$B80,'Summary by Division'!$A$6:$A$297,$B$73) -> 5 | D80: =SUMIFS('Summary by Division'!$E$6:$E$297,'Summary by Division'!$B$6:$B$297,$B80,'Summary by Division'!$A$6:$A$297,$B$73) -> 0 | E80: =SUMIFS('Summary by Division'!$F$6:$F$297,'Summary by Division'!$B$6:$B$297,$B80,'Summary by Division'!$A$6:$A$297,$B$73) -> 0 | F80: =SUMIFS('Summary by Division'!$G$6:$G$297,'Summary by Division'!$B$6:$B$297,$B80,'Summary by Division'!$A$6:$A$297,$B$73) -> 5 | G80: =SUMIFS('Summary by Division'!$H$6:$H$297,'Summary by Division'!$B$6:$B$297,$B80,'Summary by Division'!$A$6:$A$297,$B$73) -> 5 | H80: =G80-C80 -> 0 | I80: =IF(C80=0,0,H80/C80) -> 0
B81: ='Summary by Division'!B268 -> Kassa və inkassasiya prosesləri departamenti | C81: =SUMIFS('Summary by Division'!$D$6:$D$297,'Summary by Division'!$B$6:$B$297,$B81,'Summary by Division'!$A$6:$A$297,$B$73) -> 440 | D81: =SUMIFS('Summary by Division'!$E$6:$E$297,'Summary by Division'!$B$6:$B$297,$B81,'Summary by Division'!$A$6:$A$297,$B$73) -> 0 | E81: =SUMIFS('Summary by Division'!$F$6:$F$297,'Summary by Division'!$B$6:$B$297,$B81,'Summary by Division'!$A$6:$A$297,$B$73) -> 0 | F81: =SUMIFS('Summary by Division'!$G$6:$G$297,'Summary by Division'!$B$6:$B$297,$B81,'Summary by Division'!$A$6:$A$297,$B$73) -> 440 | G81: =SUMIFS('Summary by Division'!$H$6:$H$297,'Summary by Division'!$B$6:$B$297,$B81,'Summary by Division'!$A$6:$A$297,$B$73) -> 470 | H81: =G81-C81 -> 30 | I81: =IF(C81=0,0,H81/C81) -> 0.068181818
B82: ='Summary by Division'!B269 -> Nağd pulların idarə edilməsi departamenti | C82: =SUMIFS('Summary by Division'!$D$6:$D$297,'Summary by Division'!$B$6:$B$297,$B82,'Summary by Division'!$A$6:$A$297,$B$73) -> 36 | D82: =SUMIFS('Summary by Division'!$E$6:$E$297,'Summary by Division'!$B$6:$B$297,$B82,'Summary by Division'!$A$6:$A$297,$B$73) -> 0 | E82: =SUMIFS('Summary by Division'!$F$6:$F$297,'Summary by Division'!$B$6:$B$297,$B82,'Summary by Division'!$A$6:$A$297,$B$73) -> 0 | F82: =SUMIFS('Summary by Division'!$G$6:$G$297,'Summary by Division'!$B$6:$B$297,$B82,'Summary by Division'!$A$6:$A$297,$B$73) -> 36 | G82: =SUMIFS('Summary by Division'!$H$6:$H$297,'Summary by Division'!$B$6:$B$297,$B82,'Summary by Division'!$A$6:$A$297,$B$73) -> 48 | H82: =G82-C82 -> 12 | I82: =IF(C82=0,0,H82/C82) -> 0.33333333
B83: ='Summary by Division'!B270 -> Ödəniş biznesinin Agile funksional sahəsi | C83: =SUMIFS('Summary by Division'!$D$6:$D$297,'Summary by Division'!$B$6:$B$297,$B83,'Summary by Division'!$A$6:$A$297,$B$73) -> 15 | D83: =SUMIFS('Summary by Division'!$E$6:$E$297,'Summary by Division'!$B$6:$B$297,$B83,'Summary by Division'!$A$6:$A$297,$B$73) -> 0 | E83: =SUMIFS('Summary by Division'!$F$6:$F$297,'Summary by Division'!$B$6:$B$297,$B83,'Summary by Division'!$A$6:$A$297,$B$73) -> 0 | F83: =SUMIFS('Summary by Division'!$G$6:$G$297,'Summary by Division'!$B$6:$B$297,$B83,'Summary by Division'!$A$6:$A$297,$B$73) -> 15 | G83: =SUMIFS('Summary by Division'!$H$6:$H$297,'Summary by Division'!$B$6:$B$297,$B83,'Summary by Division'!$A$6:$A$297,$B$73) -> 15 | H83: =G83-C83 -> 0 | I83: =IF(C83=0,0,H83/C83) -> 0
B84: ='Summary by Division'!B271 -> Ödəniş biznesinin Analitika və Aİ ekspert mərkəzi | C84: =SUMIFS('Summary by Division'!$D$6:$D$297,'Summary by Division'!$B$6:$B$297,$B84,'Summary by Division'!$A$6:$A$297,$B$73) -> 40 | D84: =SUMIFS('Summary by Division'!$E$6:$E$297,'Summary by Division'!$B$6:$B$297,$B84,'Summary by Division'!$A$6:$A$297,$B$73) -> 0 | E84: =SUMIFS('Summary by Division'!$F$6:$F$297,'Summary by Division'!$B$6:$B$297,$B84,'Summary by Division'!$A$6:$A$297,$B$73) -> 0 | F84: =SUMIFS('Summary by Division'!$G$6:$G$297,'Summary by Division'!$B$6:$B$297,$B84,'Summary by Division'!$A$6:$A$297,$B$73) -> 40 | G84: =SUMIFS('Summary by Division'!$H$6:$H$297,'Summary by Division'!$B$6:$B$297,$B84,'Summary by Division'!$A$6:$A$297,$B$73) -> 59 | H84: =G84-C84 -> 19 | I84: =IF(C84=0,0,H84/C84) -> 0.475
B85: ='Summary by Division'!B272 -> Ödəniş biznesinin arxitektura və İT idarəetmə prosesi | C85: =SUMIFS('Summary by Division'!$D$6:$D$297,'Summary by Division'!$B$6:$B$297,$B85,'Summary by Division'!$A$6:$A$297,$B$73) -> 4 | D85: =SUMIFS('Summary by Division'!$E$6:$E$297,'Summary by Division'!$B$6:$B$297,$B85,'Summary by Division'!$A$6:$A$297,$B$73) -> 0 | E85: =SUMIFS('Summary by Division'!$F$6:$F$297,'Summary by Division'!$B$6:$B$297,$B85,'Summary by Division'!$A$6:$A$297,$B$73) -> 0 | F85: =SUMIFS('Summary by Division'!$G$6:$G$297,'Summary by Division'!$B$6:$B$297,$B85,'Summary by Division'!$A$6:$A$297,$B$73) -> 4 | G85: =SUMIFS('Summary by Division'!$H$6:$H$297,'Summary by Division'!$B$6:$B$297,$B85,'Summary by Division'!$A$6:$A$297,$B$73) -> 4 | H85: =G85-C85 -> 0 | I85: =IF(C85=0,0,H85/C85) -> 0
B86: ='Summary by Division'!B273 -> Ödəniş biznesinin mühəndislik ekspert mərkəzi | C86: =SUMIFS('Summary by Division'!$D$6:$D$297,'Summary by Division'!$B$6:$B$297,$B86,'Summary by Division'!$A$6:$A$297,$B$73) -> 243 | D86: =SUMIFS('Summary by Division'!$E$6:$E$297,'Summary by Division'!$B$6:$B$297,$B86,'Summary by Division'!$A$6:$A$297,$B$73) -> 0 | E86: =SUMIFS('Summary by Division'!$F$6:$F$297,'Summary by Division'!$B$6:$B$297,$B86,'Summary by Division'!$A$6:$A$297,$B$73) -> 0 | F86: =SUMIFS('Summary by Division'!$G$6:$G$297,'Summary by Division'!$B$6:$B$297,$B86,'Summary by Division'!$A$6:$A$297,$B$73) -> 243 | G86: =SUMIFS('Summary by Division'!$H$6:$H$297,'Summary by Division'!$B$6:$B$297,$B86,'Summary by Division'!$A$6:$A$297,$B$73) -> 267 | H86: =G86-C86 -> 24 | I86: =IF(C86=0,0,H86/C86) -> 0.098765432
... B110: ='Summary by Division'!B297 -> Information security division | C110: =SUMIFS('Summary by Division'!$D$6:$D$297,'Summary by Division'!$B$6:$B$297,$B110,'Summary by Division'!$A$6:$A$297,$B$73) -> 3 | D110: =SUMIFS('Summary by Division'!$E$6:$E$297,'Summary by Division'!$B$6:$B$297,$B110,'Summary by Division'!$A$6:$A$297,$B$73) -> 0 | E110: =SUMIFS('Summary by Division'!$F$6:$F$297,'Summary by Division'!$B$6:$B$297,$B110,'Summary by Division'!$A$6:$A$297,$B$73) -> 0 | F110: =SUMIFS('Summary by Division'!$G$6:$G$297,'Summary by Division'!$B$6:$B$297,$B110,'Summary by Division'!$A$6:$A$297,$B$73) -> 3 | G110: =SUMIFS('Summary by Division'!$H$6:$H$297,'Summary by Division'!$B$6:$B$297,$B110,'Summary by Division'!$A$6:$A$297,$B$73) -> 3 | H110: =G110-C110 -> 0 | I110: =IF(C110=0,0,H110/C110) -> 0
B111: ='Summary by Division'!B298 -> C-level | C111: =SUMIFS('Summary by Division'!$D$6:$D$298,'Summary by Division'!$B$6:$B$298,$B111,'Summary by Division'!$A$6:$A$298,$B$73) -> 3 | D111: =SUMIFS('Summary by Division'!$E$6:$E$298,'Summary by Division'!$B$6:$B$298,$B111,'Summary by Division'!$A$6:$A$298,$B$73) -> 0 | E111: =SUMIFS('Summary by Division'!$F$6:$F$298,'Summary by Division'!$B$6:$B$298,$B111,'Summary by Division'!$A$6:$A$298,$B$73) -> 0 | F111: =SUMIFS('Summary by Division'!$G$6:$G$298,'Summary by Division'!$B$6:$B$298,$B111,'Summary by Division'!$A$6:$A$298,$B$73) -> 3 | G111: =SUMIFS('Summary by Division'!$H$6:$H$298,'Summary by Division'!$B$6:$B$298,$B111,'Summary by Division'!$A$6:$A$298,$B$73) -> 3 | H111: =G111-C111 -> 0 | I111: =IF(C111=0,0,H111/C111) -> 0
B112: Payment total | C112: =SUM(C75:C111) -> 1536 | D112: =SUM(D75:D111) -> 0 | E112: =SUM(E75:E111) -> 47 | F112: =SUM(F75:F111) -> 1583 | G112: =SUM(G75:G111) -> 1701 | H112: =SUM(H75:H111) -> 165 | I112: =IF(C112=0,0,H112/C112) -> 0.10742188
C113: =C112-SUMIFS('Summary by Division'!$D$6:$D$298,'Summary by Division'!$A$6:$A$298,$B$73) -> 0 | D113: =D112-SUMIFS('Summary by Division'!$E$6:$E$298,'Summary by Division'!$A$6:$A$298,$B$73) -> 0 | E113: =E112-SUMIFS('Summary by Division'!$F$6:$F$297,'Summary by Division'!$A$6:$A$297,$B$73) -> 0 | F113: =F112-SUMIFS('Summary by Division'!$G$6:$G$298,'Summary by Division'!$A$6:$A$298,$B$73) -> 0 | G113: =G112-SUMIFS('Summary by Division'!$H$6:$H$298,'Summary by Division'!$A$6:$A$298,$B$73) -> 0
B115: Grand total (all) | C115: =C35+C70+C112 -> 6136 | D115: =D35+D70+D112 -> 34 | E115: =E35+E70+E112 -> 386 | F115: =F35+F70+F112 -> 6556 | G115: =G35+G70+G112 -> 6644 | H115: =H35+H70+H112 -> 508 | I115: =IF(C115=0,0,H115/C115) -> 0.082790091
C116: =C115-'Summary by Division'!D299 -> 0 | D116: =D115-'Summary by Division'!E299 -> 0 | E116: =E115-'Summary by Division'!F299 -> 0 | F116: =F115-'Summary by Division'!G299 -> 0 | G116: =G115-'Summary by Division'!H299 -> 0

Sheet Summary by Division
A1: Summary by Division
D4: 31 August 2026 (actual) | H4: 31 December 2027 (plan) | I4: Change in Active
B5: Department | C5: Division | D5: Active | E5: Passive | F5: Vacant | G5: Total | H5: Active | I5: Absolute | J5: % | L5: Qeydlər
A6: Horizontal | B6: ='2027'!C4 -> Management | C6: ='2027'!D4 -> C-level, Director, Deputy Director | D6: ='2027'!F4 -> 0 | E6: ='2027'!G4 -> 0 | F6: ='2027'!H4 -> 0 | G6: =SUM(D6:F6) -> 0 | H6: ='2027'!V4 -> 0 | I6: =H6-D6 -> 0 | J6: =IF(D6=0,0,I6/D6) -> 0
A7: Horizontal | B7: ='2027'!C5 -> Corporate Secretary Division | C7: ='2027'!D5 -> # | D7: ='2027'!F5 -> 1 | E7: ='2027'!G5 -> 0 | F7: ='2027'!H5 -> 0 | G7: =SUM(D7:F7) -> 1 | H7: ='2027'!V5 -> 1 | I7: =H7-D7 -> 0 | J7: =IF(D7=0,0,I7/D7) -> 0 | L7: Əlavə 7.5 vakant yer nəzərdə tutulub.
A8: Horizontal | B8: ='2027'!C6 -> Corporate Secretary Division | C8: ='2027'!D6 -> Corporate Secretary Division | D8: ='2027'!F6 -> 29 | E8: ='2027'!G6 -> 2 | F8: ='2027'!H6 -> 7.5 | G8: =SUM(D8:F8) -> 38.5 | H8: ='2027'!V6 -> 36.5 | I8: =H8-D8 -> 7.5 | J8: =IF(D8=0,0,I8/D8) -> 0.25862069
A9: Horizontal | B9: ='2027'!C7 -> Agile and Product Center of Expertise | C9: ='2027'!D7 -> Agile and product development chapter | D9: ='2027'!F7 -> 3 | E9: ='2027'!G7 -> 0 | F9: ='2027'!H7 -> 1 | G9: =SUM(D9:F9) -> 4 | H9: ='2027'!V7 -> 4 | I9: =H9-D9 -> 1 | J9: =IF(D9=0,0,I9/D9) -> 0.33333333 | L9: Əlavə 4 vakant yer nəzərdə tutulub.
A10: Horizontal | B10: ='2027'!C8 -> Agile and Product Center of Expertise | C10: ='2027'!D8 -> Fintech chapter | D10: ='2027'!F8 -> 4 | E10: ='2027'!G8 -> 1 | F10: ='2027'!H8 -> 2 | G10: =SUM(D10:F10) -> 7 | H10: ='2027'!V8 -> 7 | I10: =H10-D10 -> 3 | J10: =IF(D10=0,0,I10/D10) -> 0.75
A11: Horizontal | B11: ='2027'!C9 -> Agile and Product Center of Expertise | C11: ='2027'!D9 -> Payment Chapter | D11: ='2027'!F9 -> 12 | E11: ='2027'!G9 -> 1 | F11: ='2027'!H9 -> 1 | G11: =SUM(D11:F11) -> 14 | H11: ='2027'!V9 -> 15 | I11: =H11-D11 -> 3 | J11: =IF(D11=0,0,I11/D11) -> 0.25
A12: Horizontal | B12: ='2027'!C11 -> AI Governance Center of Expertise | C12: ='2027'!D11 -> # | D12: ='2027'!F11 -> 1 | E12: ='2027'!G11 -> 0 | F12: ='2027'!H11 -> 0 | G12: =SUM(D12:F12) -> 1 | H12: ='2027'!V11 -> 0 | I12: =H12-D12 -> -1 | J12: =IF(D12=0,0,I12/D12) -> -1 | L12: Əlavə 27 vakant yer nəzərdə tutulub. HR tərəfindən təqdim olunan faylda sadəcə bir vakant və 3 müvəqqəti nəzərə alınıb.
A13: Horizontal | B13: ='2027'!C10 -> AI Governance Center of Expertise | C13: ='2027'!D10 -> Ecosystem Analytics | D13: ='2027'!F10 -> 13 | E13: ='2027'!G10 -> 0 | F13: ='2027'!H10 -> 16 | G13: =SUM(D13:F13) -> 29 | H13: ='2027'!V10 -> 29 | I13: =H13-D13 -> 16 | J13: =IF(D13=0,0,I13/D13) -> 1.2307692
A14: Horizontal | B14: ='2027'!C12 -> AI Governance Center of Expertise | C14: ='2027'!D12 -> AI Engineering | D14: ='2027'!F12 -> 1 | E14: ='2027'!G12 -> 0 | F14: ='2027'!H12 -> 8 | G14: =SUM(D14:F14) -> 9 | H14: ='2027'!V12 -> 15 | I14: =H14-D14 -> 14 | J14: =IF(D14=0,0,I14/D14) -> 14
A15: Horizontal | B15: ='2027'!C13 -> AI Governance Center of Expertise | C15: ='2027'!D13 -> AI Governance | D15: ='2027'!F13 -> 0 | E15: ='2027'!G13 -> 0 | F15: ='2027'!H13 -> 2 | G15: =SUM(D15:F15) -> 2 | H15: ='2027'!V13 -> 2 | I15: =H15-D15 -> 2 | J15: =IF(D15=0,0,I15/D15) -> 0
A16: Horizontal | B16: ='2027'!C14 -> AI Governance Center of Expertise | C16: ='2027'!D14 -> AI Platforms | D16: ='2027'!F14 -> 1 | E16: ='2027'!G14 -> 0 | F16: ='2027'!H14 -> 1 | G16: =SUM(D16:F16) -> 2 | H16: ='2027'!V14 -> 2 | I16: =H16-D16 -> 1 | J16: =IF(D16=0,0,I16/D16) -> 1
A17: Horizontal | B17: ='2027'!C15 -> Architecture Center of Expertise | C17: ='2027'!D15 -> # | D17: ='2027'!F15 -> 1 | E17: ='2027'!G15 -> 0 | F17: ='2027'!H15 -> 0 | G17: =SUM(D17:F17) -> 1 | H17: ='2027'!V15 -> 1 | I17: =H17-D17 -> 0 | J17: =IF(D17=0,0,I17/D17) -> 0 | L17: Əlavə 2 vakant yer nəzərdə tutulub.
A18: Horizontal | B18: ='2027'!C16 -> Architecture Center of Expertise | C18: ='2027'!D16 -> Architecture Center of Expertise | D18: ='2027'!F16 -> 6 | E18: ='2027'!G16 -> 0 | F18: ='2027'!H16 -> 2 | G18: =SUM(D18:F18) -> 8 | H18: ='2027'!V16 -> 8 | I18: =H18-D18 -> 2 | J18: =IF(D18=0,0,I18/D18) -> 0.33333333
A19: Horizontal | B19: ='2027'!C17 -> International Reporting and MIS Department | C19: ='2027'!D17 -> # | D19: ='2027'!F17 -> 1 | E19: ='2027'!G17 -> 0 | F19: ='2027'!H17 -> 0 | G19: =SUM(D19:F19) -> 1 | H19: ='2027'!U17 -> 1 | I19: =H19-D19 -> 0 | J19: =IF(D19=0,0,I19/D19) -> 0 | L19: Əlavə 8 vakant yer nəzərdə tutulub.
A20: Horizontal | B20: ='2027'!C18 -> International Reporting and MIS Department | C20: ='2027'!D18 -> MIS Reporting | D20: ='2027'!F18 -> 4 | E20: ='2027'!G18 -> 1 | F20: ='2027'!H18 -> 0 | G20: =SUM(D20:F20) -> 5 | H20: ='2027'!U18 -> 5 | I20: =H20-D20 -> 1 | J20: =IF(D20=0,0,I20/D20) -> 0.25
A21: Horizontal | B21: ='2027'!C19 -> International Reporting and MIS Department | C21: ='2027'!D19 -> IFRS Reporting | D21: ='2027'!F19 -> 2 | E21: ='2027'!G19 -> 2 | F21: ='2027'!H19 -> 4 | G21: =SUM(D21:F21) -> 8 | H21: ='2027'!U19 -> 9 | I21: =H21-D21 -> 7 | J21: =IF(D21=0,0,I21/D21) -> 3.5
A22: Horizontal | B22: ='2027'!C20 -> International Reporting and MIS Department | C22: ='2027'!D20 -> Modelling, Valuation and Consolidated Reporting | D22: ='2027'!F20 -> 4 | E22: ='2027'!G20 -> 0 | F22: ='2027'!H20 -> 4 | G22: =SUM(D22:F22) -> 8 | H22: ='2027'!U20 -> 7 | I22: =H22-D22 -> 3 | J22: =IF(D22=0,0,I22/D22) -> 0.75
A23: Horizontal | B23: ='2027'!C21 -> BirApp Area | C23: ='2027'!D21 -> # | D23: ='2027'!F21 -> 1 | E23: ='2027'!G21 -> 0 | F23: ='2027'!H21 -> 0 | G23: =SUM(D23:F23) -> 1 | H23: ='2027'!V21 -> 1 | I23: =H23-D23 -> 0 | J23: =IF(D23=0,0,I23/D23) -> 0 | K23: =IF('2027'!A21="","",'2027'!A21) | L23: Vakant yer nəzərdə tutulmayıb. HR tərəfindən təqdim olunan faylda 6 əməkdaş və bir vakant gosterir.
A24: Horizontal | B24: ='2027'!C22 -> BirApp Area | C24: ='2027'!D22 -> Bir Enabler | D24: ='2027'!F22 -> 1 | E24: ='2027'!G22 -> 0 | F24: ='2027'!H22 -> 0 | G24: =SUM(D24:F24) -> 1 | H24: ='2027'!V22 -> 1 | I24: =H24-D24 -> 0 | J24: =IF(D24=0,0,I24/D24) -> 0
A25: Horizontal | B25: ='2027'!C23 -> BirApp Area | C25: ='2027'!D23 -> Birbank Mainpage | D25: ='2027'!F23 -> 1 | E25: ='2027'!G23 -> 0 | F25: ='2027'!H23 -> 0 | G25: =SUM(D25:F25) -> 1 | H25: ='2027'!V23 -> 1 | I25: =H25-D25 -> 0 | J25: =IF(D25=0,0,I25/D25) -> 0
A26: Horizontal | B26: ='2027'!C24 -> BirApp Area | C26: ='2027'!D24 -> Travel | D26: ='2027'!F24 -> 1 | E26: ='2027'!G24 -> 0 | F26: ='2027'!H24 -> 0 | G26: =SUM(D26:F26) -> 1 | H26: ='2027'!V24 -> 0 | I26: =H26-D26 -> -1 | J26: =IF(D26=0,0,I26/D26) -> -1
A27: Horizontal | B27: ='2027'!C25 -> BirApp Area | C27: ='2027'!D25 -> Bir Search | D27: ='2027'!F25 -> 1 | E27: ='2027'!G25 -> 0 | F27: ='2027'!H25 -> 0 | G27: =SUM(D27:F27) -> 1 | H27: ='2027'!V25 -> 1 | I27: =H27-D27 -> 0 | J27: =IF(D27=0,0,I27/D27) -> 0
A28: Horizontal | B28: ='2027'!C26 -> BirApp Technology Area | C28: ='2027'!D26 -> # | D28: ='2027'!F26 -> 1 | E28: ='2027'!G26 -> 0 | F28: ='2027'!H26 -> 0 | G28: =SUM(D28:F28) -> 1 | H28: ='2027'!V26 -> 1 | I28: =H28-D28 -> 0 | J28: =IF(D28=0,0,I28/D28) -> 0 | L28: Əlavə 1 vakant yer nəzərdə tutulub.
A29: Horizontal | B29: ='2027'!C27 -> BirApp Technology Area | C29: ='2027'!D27 -> Birbank Platform | D29: ='2027'!F27 -> 1 | E29: ='2027'!G27 -> 0 | F29: ='2027'!H27 -> 1 | G29: =SUM(D29:F29) -> 2 | H29: ='2027'!V27 -> 2 | I29: =H29-D29 -> 1 | J29: =IF(D29=0,0,I29/D29) -> 1
A30: Horizontal | B30: ='2027'!C28 -> BirApp Technology Area | C30: ='2027'!D28 -> Birbank SRE | D30: ='2027'!F28 -> 0 | E30: ='2027'!G28 -> 0 | F30: ='2027'!H28 -> 0 | G30: =SUM(D30:F30) -> 0 | H30: ='2027'!V28 -> 0 | I30: =H30-D30 -> 0 | J30: =IF(D30=0,0,I30/D30) -> 0
A31: Horizontal | B31: ='2027'!C29 -> Data Governance Center of Expertise | C31: ='2027'!D29 -> # | D31: ='2027'!F29 -> 1 | E31: ='2027'!G29 -> 0 | F31: ='2027'!H29 -> 0 | G31: =SUM(D31:F31) -> 1 | H31: ='2027'!V29 -> 1 | I31: =H31-D31 -> 0 | J31: =IF(D31=0,0,I31/D31) -> 0 | K31: =IF('2027'!A29="","",'2027'!A29) | L31: Əlavə 8 vakant yer nəzərdə tutulub. Lakin HR-ın təqdim etdiyi sənəddə vakant qeyd olunmayıb.
A32: Horizontal | B32: ='2027'!C30 -> Data Governance Center of Expertise | C32: ='2027'!D30 -> Data Process Management | D32: ='2027'!F30 -> 3 | E32: ='2027'!G30 -> 0 | F32: ='2027'!H30 -> 2 | G32: =SUM(D32:F32) -> 5 | H32: ='2027'!V30 -> 5 | I32: =H32-D32 -> 2 | J32: =IF(D32=0,0,I32/D32) -> 0.66666667 | K32: =IF('2027'!A30="","",'2027'!A30)
A33: Horizontal | B33: ='2027'!C31 -> Data Governance Center of Expertise | C33: ='2027'!D31 -> Data Quality | D33: ='2027'!F31 -> 6 | E33: ='2027'!G31 -> 0 | F33: ='2027'!H31 -> 2 | G33: =SUM(D33:F33) -> 8 | H33: ='2027'!V31 -> 8 | I33: =H33-D33 -> 2 | J33: =IF(D33=0,0,I33/D33) -> 0.33333333 | K33: =IF('2027'!A31="","",'2027'!A31)
A34: Horizontal | B34: ='2027'!C32 -> Data Governance Center of Expertise | C34: ='2027'!D32 -> Data Steward | D34: ='2027'!F32 -> 10 | E34: ='2027'!G32 -> 0 | F34: ='2027'!H32 -> 6 | G34: =SUM(D34:F34) -> 16 | H34: ='2027'!V32 -> 16 | I34: =H34-D34 -> 6 | J34: =IF(D34=0,0,I34/D34) -> 0.6 | K34: =IF('2027'!A32="","",'2027'!A32)
A35: Horizontal | B35: ='2027'!C33 -> Data mühəndisliyi və texnologiyaları ekspert mərkəzi | C35: ='2027'!D33 -> # | D35: ='2027'!F33 -> 1 | E35: ='2027'!G33 -> 0 | F35: ='2027'!H33 -> 0 | G35: =SUM(D35:F35) -> 1 | H35: ='2027'!V33 -> 1 | I35: =H35-D35 -> 0 | J35: =IF(D35=0,0,I35/D35) -> 0 | L35: Əlavə 4 vakant yer nəzərdə tutulub.
A36: Horizontal | B36: ='2027'!C34 -> Data mühəndisliyi və texnologiyaları ekspert mərkəzi | C36: ='2027'!D34 -> Data engineering 1 | D36: ='2027'!F34 -> 6 | E36: ='2027'!G34 -> 0 | F36: ='2027'!H34 -> 1 | G36: =SUM(D36:F36) -> 7 | H36: ='2027'!V34 -> 7 | I36: =H36-D36 -> 1 | J36: =IF(D36=0,0,I36/D36) -> 0.16666667
A37: Horizontal | B37: ='2027'!C35 -> Data mühəndisliyi və texnologiyaları ekspert mərkəzi | C37: ='2027'!D35 -> Data engineering 2 | D37: ='2027'!F35 -> 6 | E37: ='2027'!G35 -> 1 | F37: ='2027'!H35 -> 2 | G37: =SUM(D37:F37) -> 9 | H37: ='2027'!V35 -> 7 | I37: =H37-D37 -> 1 | J37: =IF(D37=0,0,I37/D37) -> 0.16666667
A38: Horizontal | B38: ='2027'!C36 -> Data mühəndisliyi və texnologiyaları ekspert mərkəzi | C38: ='2027'!D36 -> Data engineering 3 | D38: ='2027'!F36 -> 5 | E38: ='2027'!G36 -> 0 | F38: ='2027'!H36 -> 1 | G38: =SUM(D38:F38) -> 6 | H38: ='2027'!V36 -> 6 | I38: =H38-D38 -> 1 | J38: =IF(D38=0,0,I38/D38) -> 0.2
A39: Horizontal | B39: ='2027'!C37 -> Data mühəndisliyi və texnologiyaları ekspert mərkəzi | C39: ='2027'!D37 -> Data engineering 4 | D39: ='2027'!F37 -> 5 | E39: ='2027'!G37 -> 0 | F39: ='2027'!H37 -> 0 | G39: =SUM(D39:F39) -> 5 | H39: ='2027'!V37 -> 5 | I39: =H39-D39 -> 0 | J39: =IF(D39=0,0,I39/D39) -> 0
A40: Horizontal | B40: ='2027'!C38 -> Data və Analitika departamenti(Marketplace) | C40: ='2027'!D38 -> Data Engineering | D40: ='2027'!F38 -> 4 | E40: ='2027'!G38 -> 0 | F40: ='2027'!H38 -> 0 | G40: =SUM(D40:F40) -> 4 | H40: ='2027'!V38 -> 4 | I40: =H40-D40 -> 0 | J40: =IF(D40=0,0,I40/D40) -> 0 | L40: Vakant yer nəzərdə tutulmayıb.
A41: Horizontal | B41: ='2027'!C39 -> Design Center of Expertise | C41: ='2027'!D39 -> # | D41: ='2027'!F39 -> 4 | E41: ='2027'!G39 -> 0 | F41: ='2027'!H39 -> 4 | G41: =SUM(D41:F41) -> 8 | H41: ='2027'!V39 -> 8 | I41: =H41-D41 -> 4 | J41: =IF(D41=0,0,I41/D41) -> 1 | L41: Əlavə 9 vakant yer nəzərdə tutulub.
A42: Horizontal | B42: ='2027'!C40 -> Design Center of Expertise | C42: ='2027'!D40 -> Product Designer 1 | D42: ='2027'!F40 -> 9 | E42: ='2027'!G40 -> 1 | F42: ='2027'!H40 -> 0 | G42: =SUM(D42:F42) -> 10 | H42: ='2027'!V40 -> 10 | I42: =H42-D42 -> 1 | J42: =IF(D42=0,0,I42/D42) -> 0.11111111
A43: Horizontal | B43: ='2027'!C41 -> Design Center of Expertise | C43: ='2027'!D41 -> Graphic Design | D43: ='2027'!F41 -> 20 | E43: ='2027'!G41 -> 0 | F43: ='2027'!H41 -> 1 | G43: =SUM(D43:F43) -> 21 | H43: ='2027'!V41 -> 21 | I43: =H43-D43 -> 1 | J43: =IF(D43=0,0,I43/D43) -> 0.05
A44: Horizontal | B44: ='2027'!C42 -> Design Center of Expertise | C44: ='2027'!D42 -> Product Designer 2 | D44: ='2027'!F42 -> 5 | E44: ='2027'!G42 -> 0 | F44: ='2027'!H42 -> 1 | G44: =SUM(D44:F44) -> 6 | H44: ='2027'!V42 -> 6 | I44: =H44-D44 -> 1 | J44: =IF(D44=0,0,I44/D44) -> 0.2
A45: Horizontal | B45: ='2027'!C43 -> Design Center of Expertise | C45: ='2027'!D43 -> Product Designer 3 | D45: ='2027'!F43 -> 6 | E45: ='2027'!G43 -> 0 | F45: ='2027'!H43 -> 1 | G45: =SUM(D45:F45) -> 7 | H45: ='2027'!V43 -> 7 | I45: =H45-D45 -> 1 | J45: =IF(D45=0,0,I45/D45) -> 0.16666667
A46: Horizontal | B46: ='2027'!C44 -> Design Center of Expertise | C46: ='2027'!D44 -> Product Designer 4 | D46: ='2027'!F44 -> 6 | E46: ='2027'!G44 -> 0 | F46: ='2027'!H44 -> 2 | G46: =SUM(D46:F46) -> 8 | H46: ='2027'!V44 -> 8 | I46: =H46-D46 -> 2 | J46: =IF(D46=0,0,I46/D46) -> 0.33333333
A47: Horizontal | B47: ='2027'!C45 -> Design Center of Expertise | C47: ='2027'!D45 -> UX Researcher | D47: ='2027'!F45 -> 3 | E47: ='2027'!G45 -> 0 | F47: ='2027'!H45 -> 0 | G47: =SUM(D47:F47) -> 3 | H47: ='2027'!V45 -> 3 | I47: =H47-D47 -> 0 | J47: =IF(D47=0,0,I47/D47) -> 0
A48: Horizontal | B48: ='2027'!C46 -> Ecosystem Platform and ID Area | C48: ='2027'!D46 -> # | D48: ='2027'!F46 -> 1 | E48: ='2027'!G46 -> 0 | F48: ='2027'!H46 -> 0 | G48: =SUM(D48:F48) -> 1 | H48: ='2027'!V46 -> 1 | I48: =H48-D48 -> 0 | J48: =IF(D48=0,0,I48/D48) -> 0 | L48: Vakant yer nəzərdə tutulmayıb.
A49: Horizontal | B49: ='2027'!C47 -> Ecosystem Platform and ID Area | C49: ='2027'!D47 -> BirID | D49: ='2027'!F47 -> 1 | E49: ='2027'!G47 -> 0 | F49: ='2027'!H47 -> 0 | G49: =SUM(D49:F49) -> 1 | H49: ='2027'!V47 -> 1 | I49: =H49-D49 -> 0 | J49: =IF(D49=0,0,I49/D49) -> 0
A50: Horizontal | B50: ='2027'!C48 -> Ecosystem Platform and ID Area | C50: ='2027'!D48 -> Business ID | D50: ='2027'!F48 -> 1 | E50: ='2027'!G48 -> 0 | F50: ='2027'!H48 -> 0 | G50: =SUM(D50:F50) -> 1 | H50: ='2027'!V48 -> 1 | I50: =H50-D50 -> 0 | J50: =IF(D50=0,0,I50/D50) -> 0
A51: Horizontal | B51: ='2027'!C49 -> Ecosystem Platform and ID Area | C51: ='2027'!D49 -> DVS | D51: ='2027'!F49 -> 1 | E51: ='2027'!G49 -> 0 | F51: ='2027'!H49 -> 0 | G51: =SUM(D51:F51) -> 1 | H51: ='2027'!V49 -> 1 | I51: =H51-D51 -> 0 | J51: =IF(D51=0,0,I51/D51) -> 0
A52: Horizontal | B52: ='2027'!C50 -> Legal Department | C52: ='2027'!D50 -> # | D52: ='2027'!F50 -> 2 | E52: ='2027'!G50 -> 0 | F52: ='2027'!H50 -> 0 | G52: =SUM(D52:F52) -> 2 | H52: ='2027'!V50 -> 2 | I52: =H52-D52 -> 0 | J52: =IF(D52=0,0,I52/D52) -> 0 | L52: Əlavə 5.5 vakant yer nəzərdə tutulub.
A53: Horizontal | B53: ='2027'!C51 -> Legal Department | C53: ='2027'!D51 -> Litigation and Legal Support Division | D53: ='2027'!F51 -> 15 | E53: ='2027'!G51 -> 0 | F53: ='2027'!H51 -> 5.5 | G53: =SUM(D53:F53) -> 20.5 | H53: ='2027'!V51 -> 20.5 | I53: =H53-D53 -> 5.5 | J53: =IF(D53=0,0,I53/D53) -> 0.36666667
A54: Horizontal | B54: ='2027'!C52 -> Legal Department | C54: ='2027'!D52 -> Payment Business Legal Support Division | D54: ='2027'!F52 -> 4 | E54: ='2027'!G52 -> 0 | F54: ='2027'!H52 -> 0 | G54: =SUM(D54:F54) -> 4 | H54: ='2027'!V52 -> 4 | I54: =H54-D54 -> 0 | J54: =IF(D54=0,0,I54/D54) -> 0
A55: Horizontal | B55: ='2027'!C53 -> Legal Department | C55: ='2027'!D53 -> E-commerce Business Legal Support Division | D55: ='2027'!F53 -> 6 | E55: ='2027'!G53 -> 0 | F55: ='2027'!H53 -> 0 | G55: =SUM(D55:F55) -> 6 | H55: ='2027'!V53 -> 6 | I55: =H55-D55 -> 0 | J55: =IF(D55=0,0,I55/D55) -> 0
A56: Horizontal | B56: ='2027'!C54 -> Legal Department | C56: ='2027'!D54 -> Archive Division | D56: ='2027'!F54 -> 12 | E56: ='2027'!G54 -> 0 | F56: ='2027'!H54 -> 0 | G56: =SUM(D56:F56) -> 12 | H56: ='2027'!V54 -> 12 | I56: =H56-D56 -> 0 | J56: =IF(D56=0,0,I56/D56) -> 0
A57: Horizontal | B57: ='2027'!C55 -> Legal Department | C57: ='2027'!D55 -> Banking Products Legal Support Division | D57: ='2027'!F55 -> 10 | E57: ='2027'!G55 -> 0 | F57: ='2027'!H55 -> 0 | G57: =SUM(D57:F57) -> 10 | H57: ='2027'!V55 -> 10 | I57: =H57-D57 -> 0 | J57: =IF(D57=0,0,I57/D57) -> 0
A58: Horizontal | B58: ='2027'!C56 -> Legal Department | C58: ='2027'!D56 -> Corporate Law and Corporate Governance Legal Support Division | D58: ='2027'!F56 -> 10 | E58: ='2027'!G56 -> 0 | F58: ='2027'!H56 -> 0 | G58: =SUM(D58:F58) -> 10 | H58: ='2027'!V56 -> 10 | I58: =H58-D58 -> 0 | J58: =IF(D58=0,0,I58/D58) -> 0
A59: Horizontal | B59: ='2027'!C57 -> Legal Department | C59: ='2027'!D57 -> Methodology Division | D59: ='2027'!F57 -> 7 | E59: ='2027'!G57 -> 2 | F59: ='2027'!H57 -> 0 | G59: =SUM(D59:F59) -> 9 | H59: ='2027'!V57 -> 7 | I59: =H59-D59 -> 0 | J59: =IF(D59=0,0,I59/D59) -> 0
A60: Horizontal | B60: ='2027'!C58 -> Information Security Department | C60: ='2027'!D58 -> # | D60: ='2027'!F58 -> 4 | E60: ='2027'!G58 -> 0 | F60: ='2027'!H58 -> 0 | G60: =SUM(D60:F60) -> 4 | H60: ='2027'!V58 -> 4 | I60: =H60-D60 -> 0 | J60: =IF(D60=0,0,I60/D60) -> 0 | L60: Əlavə 10 vakant yer nəzərdə tutulub.
A61: Horizontal | B61: ='2027'!C59 -> Information Security Department | C61: ='2027'!D59 -> Platform Security Division | D61: ='2027'!F59 -> 9.5 | E61: ='2027'!G59 -> 0 | F61: ='2027'!H59 -> 0 | G61: =SUM(D61:F61) -> 9.5 | H61: ='2027'!V59 -> 9.5 | I61: =H61-D61 -> 0 | J61: =IF(D61=0,0,I61/D61) -> 0
A62: Horizontal | B62: ='2027'!C60 -> Information Security Department | C62: ='2027'!D60 -> Network Security Division | D62: ='2027'!F60 -> 5 | E62: ='2027'!G60 -> 0 | F62: ='2027'!H60 -> 0 | G62: =SUM(D62:F62) -> 5 | H62: ='2027'!V60 -> 5 | I62: =H62-D62 -> 0 | J62: =IF(D62=0,0,I62/D62) -> 0
A63: Horizontal | B63: ='2027'!C61 -> Information Security Department | C63: ='2027'!D61 -> Information Security GRC Division | D63: ='2027'!F61 -> 6 | E63: ='2027'!G61 -> 0 | F63: ='2027'!H61 -> 6 | G63: =SUM(D63:F63) -> 12 | H63: ='2027'!V61 -> 12 | I63: =H63-D63 -> 6 | J63: =IF(D63=0,0,I63/D63) -> 1
A64: Horizontal | B64: ='2027'!C62 -> Information Security Department | C64: ='2027'!D62 -> Cyber Defense Division | D64: ='2027'!F62 -> 17 | E64: ='2027'!G62 -> 0 | F64: ='2027'!H62 -> 1 | G64: =SUM(D64:F64) -> 18 | H64: ='2027'!V62 -> 18 | I64: =H64-D64 -> 1 | J64: =IF(D64=0,0,I64/D64) -> 0.058823529
A65: Horizontal | B65: ='2027'!C63 -> Information Security Department | C65: ='2027'!D63 -> Product Security Division | D65: ='2027'!F63 -> 10.5 | E65: ='2027'!G63 -> 0 | F65: ='2027'!H63 -> 3 | G65: =SUM(D65:F65) -> 13.5 | H65: ='2027'!V63 -> 13.5 | I65: =H65-D65 -> 3 | J65: =IF(D65=0,0,I65/D65) -> 0.28571429
A66: Horizontal | B66: ='2027'!C64 -> Information Security Department | C66: ='2027'!D64 -> IT Risk Management Division | D66: ='2027'!F64 -> 4 | E66: ='2027'!G64 -> 0 | F66: ='2027'!H64 -> 0 | G66: =SUM(D66:F66) -> 4 | H66: ='2027'!V64 -> 4 | I66: =H66-D66 -> 0 | J66: =IF(D66=0,0,I66/D66) -> 0
A67: Horizontal | B67: ='2027'!C65 -> Administrative Management Department | C67: ='2027'!D65 -> # | D67: ='2027'!F65 -> 3 | E67: ='2027'!G65 -> 0 | F67: ='2027'!H65 -> 0 | G67: =SUM(D67:F67) -> 3 | H67: ='2027'!V65 -> 3 | I67: =H67-D67 -> 0 | J67: =IF(D67=0,0,I67/D67) -> 0 | L67: Vakant yer nəzərdə tutulmayıb.
A68: Horizontal | B68: ='2027'!C66 -> Administrative Management Department | C68: ='2027'!D66 -> Repair and Maintenance Division | D68: ='2027'!F66 -> 67 | E68: ='2027'!G66 -> 1 | F68: ='2027'!H66 -> 0 | G68: =SUM(D68:F68) -> 68 | H68: ='2027'!V66 -> 68 | I68: =H68-D68 -> 1 | J68: =IF(D68=0,0,I68/D68) -> 0.014925373
A69: Horizontal | B69: ='2027'!C67 -> Administrative Management Department | C69: ='2027'!D67 -> Transport Division | D69: ='2027'!F67 -> 36 | E69: ='2027'!G67 -> 1 | F69: ='2027'!H67 -> 0 | G69: =SUM(D69:F69) -> 37 | H69: ='2027'!V67 -> 37 | I69: =H69-D69 -> 1 | J69: =IF(D69=0,0,I69/D69) -> 0.027777778
A70: Horizontal | B70: ='2027'!C68 -> Administrative Management Department | C70: ='2027'!D68 -> Procurement and Supply Division | D70: ='2027'!F68 -> 27 | E70: ='2027'!G68 -> 4 | F70: ='2027'!H68 -> 0 | G70: =SUM(D70:F70) -> 31 | H70: ='2027'!V68 -> 31 | I70: =H70-D70 -> 4 | J70: =IF(D70=0,0,I70/D70) -> 0.14814815
A71: Horizontal | B71: ='2027'!C69 -> Administrative Management Department | C71: ='2027'!D69 -> Administrative Operations Division | D71: ='2027'!F69 -> 23 | E71: ='2027'!G69 -> 1 | F71: ='2027'!H69 -> 0 | G71: =SUM(D71:F71) -> 24 | H71: ='2027'!V69 -> 21 | I71: =H71-D71 -> -2 | J71: =IF(D71=0,0,I71/D71) -> -0.086956522
A72: Horizontal | B72: ='2027'!C70 -> IT Infrastructure Department | C72: ='2027'!D70 -> # | D72: ='2027'!F70 -> 2 | E72: ='2027'!G70 -> 0 | F72: ='2027'!H70 -> 0 | G72: =SUM(D72:F72) -> 2 | H72: ='2027'!V70 -> 2 | I72: =H72-D72 -> 0 | J72: =IF(D72=0,0,I72/D72) -> 0 | L72: Əlavə 10 vakant yer nəzərdə tutulub.
A73: Horizontal | B73: ='2027'!C71 -> IT Infrastructure Department | C73: ='2027'!D71 -> IT Access Management and Technical Support Division | D73: ='2027'!F71 -> 44 | E73: ='2027'!G71 -> 0 | F73: ='2027'!H71 -> 4 | G73: =SUM(D73:F73) -> 48 | H73: ='2027'!V71 -> 48 | I73: =H73-D73 -> 4 | J73: =IF(D73=0,0,I73/D73) -> 0.090909091
A74: Horizontal | B74: ='2027'!C72 -> IT Infrastructure Department | C74: ='2027'!D72 -> IT Service Management Division | D74: ='2027'!F72 -> 5 | E74: ='2027'!G72 -> 0 | F74: ='2027'!H72 -> 1 | G74: =SUM(D74:F74) -> 6 | H74: ='2027'!V72 -> 6 | I74: =H74-D74 -> 1 | J74: =IF(D74=0,0,I74/D74) -> 0.2
A75: Horizontal | B75: ='2027'!C73 -> IT Infrastructure Department | C75: ='2027'!D73 -> Network Operations Division | D75: ='2027'!F73 -> 13 | E75: ='2027'!G73 -> 0 | F75: ='2027'!H73 -> 3 | G75: =SUM(D75:F75) -> 16 | H75: ='2027'!V73 -> 16 | I75: =H75-D75 -> 3 | J75: =IF(D75=0,0,I75/D75) -> 0.23076923
A76: Horizontal | B76: ='2027'!C74 -> IT Infrastructure Department | C76: ='2027'!D74 -> System and Network Administration Division | D76: ='2027'!F74 -> 18 | E76: ='2027'!G74 -> 1 | F76: ='2027'!H74 -> 2 | G76: =SUM(D76:F76) -> 21 | H76: ='2027'!V74 -> 20 | I76: =H76-D76 -> 2 | J76: =IF(D76=0,0,I76/D76) -> 0.11111111
A77: Horizontal | B77: ='2027'!C75 -> IT Infrastructure Department | C77: ='2027'!D75 -> IT Service Monitoring and Incident Management Division | D77: ='2027'!F75 -> 7 | E77: ='2027'!G75 -> 0 | F77: ='2027'!H75 -> 0 | G77: =SUM(D77:F77) -> 7 | H77: ='2027'!V75 -> 7 | I77: =H77-D77 -> 0 | J77: =IF(D77=0,0,I77/D77) -> 0
A78: Horizontal | B78: ='2027'!C76 -> IT Process Management Functional Area | C78: ='2027'!D76 -> IT Process Management Functional Area | D78: ='2027'!F76 -> 4 | E78: ='2027'!G76 -> 0 | F78: ='2027'!H76 -> 0 | G78: =SUM(D78:F78) -> 4 | H78: ='2027'!V76 -> 4 | I78: =H78-D78 -> 0 | J78: =IF(D78=0,0,I78/D78) -> 0 | L78: Vakant yer nəzərdə tutulmayıb.
A79: Horizontal | B79: ='2027'!C77 -> Compliance Department | C79: ='2027'!D77 -> # | D79: ='2027'!F77 -> 3 | E79: ='2027'!G77 -> 0 | F79: ='2027'!H77 -> 0 | G79: =SUM(D79:F79) -> 3 | H79: ='2027'!V77 -> 3 | I79: =H79-D79 -> 0 | J79: =IF(D79=0,0,I79/D79) -> 0 | L79: Əlavə 5 vakant yer nəzərdə tutulub. Lakin HR-ın təqdim etdiyi sənəddə isə vakant yer nəzərə alınmamışdır.
A80: Horizontal | B80: ='2027'!C78 -> Compliance Department | C80: ='2027'!D78 -> AML and CFT Division | D80: ='2027'!F78 -> 14 | E80: ='2027'!G78 -> 1 | F80: ='2027'!H78 -> 0 | G80: =SUM(D80:F80) -> 15 | H80: ='2027'!V78 -> 16 | I80: =H80-D80 -> 2 | J80: =IF(D80=0,0,I80/D80) -> 0.14285714
A81: Horizontal | B81: ='2027'!C79 -> Compliance Department | C81: ='2027'!D79 -> Compliance Risk Management and Monitoring Division | D81: ='2027'!F79 -> 10 | E81: ='2027'!G79 -> 0 | F81: ='2027'!H79 -> 0 | G81: =SUM(D81:F81) -> 10 | H81: 10 | I81: =H81-D81 -> 0 | J81: =IF(D81=0,0,I81/D81) -> 0
A82: Horizontal | B82: ='2027'!C80 -> Compliance Department | C82: ='2027'!D80 -> Compliance Reporting Division | D82: ='2027'!F80 -> 6 | E82: ='2027'!G80 -> 0 | F82: ='2027'!H80 -> 0 | G82: =SUM(D82:F82) -> 6 | H82: 6 | I82: =H82-D82 -> 0 | J82: =IF(D82=0,0,I82/D82) -> 0
A83: Horizontal | B83: ='2027'!C81 -> Compliance Department | C83: ='2027'!D81 -> Compliance Function Management Division | D83: ='2027'!F81 -> 6 | E83: ='2027'!G81 -> 0 | F83: ='2027'!H81 -> 3 | G83: =SUM(D83:F83) -> 9 | H83: 8 | I83: =H83-D83 -> 2 | J83: =IF(D83=0,0,I83/D83) -> 0.33333333
A84: Horizontal | B84: ='2027'!C82 -> Compliance Department | C84: ='2027'!D82 -> Data and AI Compliance Control Division | D84: ='2027'!F82 -> 2 | E84: ='2027'!G82 -> 0 | F84: ='2027'!H82 -> 2 | G84: =SUM(D84:F84) -> 4 | H84: 4 | I84: =H84-D84 -> 2 | J84: =IF(D84=0,0,I84/D84) -> 1
A85: Horizontal | B85: ='2027'!C83 -> Compliance Department | C85: ='2027'!D83 -> Ecosystem Product and Process Compliance Support Division | D85: ='2027'!F83 -> 4 | E85: ='2027'!G83 -> 0 | F85: ='2027'!H83 -> 0 | G85: =SUM(D85:F85) -> 4 | H85: 4 | I85: =H85-D85 -> 0 | J85: =IF(D85=0,0,I85/D85) -> 0
A86: Horizontal | B86: ='2027'!C84 -> Compliance Department | C86: ='2027'!D84 -> Regulatory Compliance Division | D86: ='2027'!F84 -> 5 | E86: ='2027'!G84 -> 0 | F86: ='2027'!H84 -> 0 | G86: =SUM(D86:F86) -> 5 | H86: 5 | I86: =H86-D86 -> 0 | J86: =IF(D86=0,0,I86/D86) -> 0
A87: Horizontal | B87: ='2027'!C86 -> Corporate Development and Investor Relations Department | C87: ='2027'!D86 -> # | D87: ='2027'!F86 -> 1 | E87: ='2027'!G86 -> 0 | F87: ='2027'!H86 -> 1 | G87: =SUM(D87:F87) -> 2 | H87: ='2027'!V86 -> 2 | I87: =H87-D87 -> 1 | J87: =IF(D87=0,0,I87/D87) -> 1 | L87: Əlavə 1 vakant yer nəzərdə tutulub.
A88: Horizontal | B88: ='2027'!C85 -> Corporate Development and Investor Relations Department | C88: ='2027'!D85 -> Director, Deputy Director | D88: ='2027'!F85 -> 1 | E88: ='2027'!G85 -> 0 | F88: ='2027'!H85 -> 0 | G88: =SUM(D88:F88) -> 1 | H88: ='2027'!V85 -> 1 | I88: =H88-D88 -> 0 | J88: =IF(D88=0,0,I88/D88) -> 0
A89: Horizontal | B89: ='2027'!C87 -> Financial Reporting and Accounting Department | C89: ='2027'!D87 -> # | D89: ='2027'!F87 -> 4 | E89: ='2027'!G87 -> 0 | F89: ='2027'!H87 -> 0 | G89: =SUM(D89:F89) -> 4 | H89: ='2027'!V87 -> 4 | I89: =H89-D89 -> 0 | J89: =IF(D89=0,0,I89/D89) -> 0 | L89: Əlavə 5 vakant yer nəzərdə tutulub.
A90: Horizontal | B90: ='2027'!C93 -> Financial Reporting and Accounting Department | C90: ='2027'!D93 -> # | D90: ='2027'!F93 -> 1 | E90: ='2027'!G93 -> 0 | F90: ='2027'!H93 -> 0 | G90: =SUM(D90:F90) -> 1 | H90: ='2027'!V93 -> 1 | I90: =H90-D90 -> 0 | J90: =IF(D90=0,0,I90/D90) -> 0
A91: Horizontal | B91: ='2027'!C88 -> Financial Reporting and Accounting Department | C91: ='2027'!D88 -> Internal Accounting Division | D91: ='2027'!F88 -> 10 | E91: ='2027'!G88 -> 0 | F91: ='2027'!H88 -> 4 | G91: =SUM(D91:F91) -> 14 | H91: ='2027'!V88 -> 14 | I91: =H91-D91 -> 4 | J91: =IF(D91=0,0,I91/D91) -> 0.4
A92: Horizontal | B92: ='2027'!C89 -> Financial Reporting and Accounting Department | C92: ='2027'!D89 -> Regulatory Reporting Division | D92: ='2027'!F89 -> 7 | E92: ='2027'!G89 -> 0 | F92: ='2027'!H89 -> 1 | G92: =SUM(D92:F92) -> 8 | H92: ='2027'!V89 -> 8 | I92: =H92-D92 -> 1 | J92: =IF(D92=0,0,I92/D92) -> 0.14285714
A93: Horizontal | B93: ='2027'!C90 -> Financial Reporting and Accounting Department | C93: ='2027'!D90 -> Compensation Calculation Division | D93: ='2027'!F90 -> 5 | E93: ='2027'!G90 -> 1 | F93: ='2027'!H90 -> 0 | G93: =SUM(D93:F93) -> 6 | H93: ='2027'!V90 -> 6 | I93: =H93-D93 -> 1 | J93: =IF(D93=0,0,I93/D93) -> 0.2
A94: Horizontal | B94: ='2027'!C91 -> Financial Reporting and Accounting Department | C94: ='2027'!D91 -> Financial Control and Accounting Division | D94: ='2027'!F91 -> 10 | E94: ='2027'!G91 -> 0 | F94: ='2027'!H91 -> 0 | G94: =SUM(D94:F94) -> 10 | H94: ='2027'!V91 -> 10 | I94: =H94-D94 -> 0 | J94: =IF(D94=0,0,I94/D94) -> 0
A95: Horizontal | B95: ='2027'!C92 -> Financial Reporting and Accounting Department | C95: ='2027'!D92 -> Accounting Division | D95: ='2027'!F92 -> 8 | E95: ='2027'!G92 -> 2 | F95: ='2027'!H92 -> 0 | G95: =SUM(D95:F95) -> 10 | H95: ='2027'!V92 -> 11 | I95: =H95-D95 -> 3 | J95: =IF(D95=0,0,I95/D95) -> 0.375
A96: Horizontal | B96: ='2027'!C94 -> Financial Reporting and Accounting Department | C96: ='2027'!D94 -> Operations Accounting and Processing Division | D96: ='2027'!F94 -> 11 | E96: ='2027'!G94 -> 0 | F96: ='2027'!H94 -> 0 | G96: =SUM(D96:F96) -> 11 | H96: ='2027'!V94 -> 11 | I96: =H96-D96 -> 0 | J96: =IF(D96=0,0,I96/D96) -> 0
A97: Horizontal | B97: ='2027'!C95 -> Financial Reporting and Accounting Department | C97: ='2027'!D95 -> Administrative Accounting and Taxation Division | D97: ='2027'!F95 -> 7 | E97: ='2027'!G95 -> 0 | F97: ='2027'!H95 -> 0 | G97: =SUM(D97:F97) -> 7 | H97: ='2027'!V95 -> 7 | I97: =H97-D97 -> 0 | J97: =IF(D97=0,0,I97/D97) -> 0
A98: Horizontal | B98: ='2027'!C96 -> Financial Reporting and Accounting Department | C98: ='2027'!D96 -> Payments Management Division | D98: ='2027'!F96 -> 3 | E98: ='2027'!G96 -> 1 | F98: ='2027'!H96 -> 0 | G98: =SUM(D98:F98) -> 4 | H98: ='2027'!V96 -> 4 | I98: =H98-D98 -> 1 | J98: =IF(D98=0,0,I98/D98) -> 0.33333333
A99: Horizontal | B99: ='2027'!C97 -> Financial Reporting and Accounting Department | C99: ='2027'!D97 -> Expense Control Division | D99: ='2027'!F97 -> 2 | E99: ='2027'!G97 -> 0 | F99: ='2027'!H97 -> 0 | G99: =SUM(D99:F99) -> 2 | H99: ='2027'!V97 -> 2 | I99: =H99-D99 -> 0 | J99: =IF(D99=0,0,I99/D99) -> 0
A100: Horizontal | B100: ='2027'!C98 -> Marketing Center of Expertise | C100: ='2027'!D98 -> # | D100: ='2027'!F98 -> 3 | E100: ='2027'!G98 -> 0 | F100: ='2027'!H98 -> 0 | G100: =SUM(D100:F100) -> 3 | H100: ='2027'!V98 -> 3 | I100: =H100-D100 -> 0 | J100: =IF(D100=0,0,I100/D100) -> 0 | L100: Əlavə 10 vakant yer nəzərdə tutulub. Lakin HR -ın təqdim etdiyi faylda 5 vakant nəzərdə tutulmuşdur.
A101: Horizontal | B101: ='2027'!C99 -> Marketing Center of Expertise | C101: ='2027'!D99 -> Public Relations Process | D101: ='2027'!F99 -> 3 | E101: ='2027'!G99 -> 0 | F101: ='2027'!H99 -> 0 | G101: =SUM(D101:F101) -> 3 | H101: ='2027'!V99 -> 3 | I101: =H101-D101 -> 0 | J101: =IF(D101=0,0,I101/D101) -> 0
A102: Horizontal | B102: ='2027'!C100 -> Marketing Center of Expertise | C102: ='2027'!D100 -> Marketing Communications Process | D102: ='2027'!F100 -> 14 | E102: ='2027'!G100 -> 0 | F102: ='2027'!H100 -> 0 | G102: =SUM(D102:F102) -> 14 | H102: ='2027'!V100 -> 14 | I102: =H102-D102 -> 0 | J102: =IF(D102=0,0,I102/D102) -> 0
...

Sheet 2027
C1: 2027 Headcount Plan – Source Data (by Department and Division)
F2: 31/08/2026 | I2: 31/12/2026 | K2: Number of Employees
A3: Additional notes | B3: Horizontal/Vertical | C3: Departament | D3: Division | E3: Out-seconded FTEs | F3: Active current employee | G3: Passive current employees | H3: Number of vacant positions | I3: 2026 YE (active current employee) | J3: Number of vacant positions | K3: January | L3: February | M3: March | N3: April | O3: May | P3: June | Q3: July | R3: August | S3: September | T3: October | U3: November | V3: December
B4: Horizontal | C4: Management | D4: C-level, Director, Deputy Director | E4: 0 | F4: 0 | G4: 0 | H4: 0 | I4: 0 | J4: 0 | K4: 0 | L4: 0 | M4: 0 | N4: 0 | O4: 0 | P4: 0 | Q4: 0 | R4: 0 | S4: 0 | T4: 0 | U4: 0 | V4: 0
B5: Horizontal | C5: Corporate Secretary Division | D5: # | E5: 0 | F5: 1 | G5: 0 | H5: 0 | I5: 1 | J5: 0 | K5: 1 | L5: 1 | M5: 1 | N5: 1 | O5: 1 | P5: 1 | Q5: 1 | R5: 1 | S5: 1 | T5: 1 | U5: 1 | V5: 1
B6: Horizontal | C6: Corporate Secretary Division | D6: Corporate Secretary Division | E6: 0 | F6: 29 | G6: 2 | H6: 7.5 | I6: 31 | J6: 5.5 | K6: 31 | L6: 31 | M6: 31 | N6: 31 | O6: 31 | P6: 31 | Q6: 31 | R6: 31 | S6: 31 | T6: 31 | U6: 31 | V6: =31+5.5 -> 36.5
B7: Horizontal | C7: Agile and Product Center of Expertise | D7: Agile and product development chapter | E7: 0 | F7: 3 | G7: 0 | H7: 1 | I7: 3 | J7: 1 | K7: 4 | L7: 4 | M7: 4 | N7: 4 | O7: 4 | P7: 4 | Q7: 4 | R7: 4 | S7: 4 | T7: 3 | U7: 3 | V7: 4
B8: Horizontal | C8: Agile and Product Center of Expertise | D8: Fintech chapter | E8: 0 | F8: 4 | G8: 1 | H8: 2 | I8: 7 | J8: 0 | K8: 7 | L8: 7 | M8: 7 | N8: 7 | O8: 7 | P8: 7 | Q8: 7 | R8: 7 | S8: 7 | T8: 7 | U8: 7 | V8: 7
B9: Horizontal | C9: Agile and Product Center of Expertise | D9: Payment Chapter | E9: 0 | F9: 12 | G9: 1 | H9: 1 | I9: 14 | J9: 1 | K9: 14 | L9: 14 | M9: 14 | N9: 14 | O9: 14 | P9: 14 | Q9: 14 | R9: 14 | S9: 14 | T9: 14 | U9: 14 | V9: 15
B10: Horizontal | C10: AI Governance Center of Expertise | D10: Ecosystem Analytics | E10: 0 | F10: 13 | G10: 0 | H10: 16 | I10: 16 | J10: 13 | K10: 13 | L10: 14 | M10: 18 | N10: 22 | O10: 24 | P10: 26 | Q10: 28 | R10: 29 | S10: 29 | T10: 29 | U10: 29 | V10: 29
B11: Horizontal | C11: AI Governance Center of Expertise | D11: # | E11: 0 | F11: 1 | G11: 0 | H11: 0 | I11: 0 | J11: 0 | K11: 0 | L11: 0 | M11: 0 | N11: 0 | O11: 0 | P11: 0 | Q11: 0 | R11: 0 | S11: 0 | T11: 0 | U11: 0 | V11: 0
B12: Horizontal | C12: AI Governance Center of Expertise | D12: AI Engineering | E12: 0 | F12: 1 | G12: 0 | H12: 8 | I12: 1 | J12: 8 | K12: 8 | L12: 10 | M12: 10 | N12: 12 | O12: 12 | P12: 15 | Q12: 15 | R12: 15 | S12: 15 | T12: 15 | U12: 15 | V12: 15
B13: Horizontal | C13: AI Governance Center of Expertise | D13: AI Governance | E13: 0 | F13: 0 | G13: 0 | H13: 2 | I13: 0 | J13: 2 | K13: 2 | L13: 2 | M13: 2 | N13: 2 | O13: 2 | P13: 2 | Q13: 2 | R13: 2 | S13: 2 | T13: 2 | U13: 2 | V13: 2
B14: Horizontal | C14: AI Governance Center of Expertise | D14: AI Platforms | E14: 0 | F14: 1 | G14: 0 | H14: 1 | I14: 1 | J14: 1 | K14: 2 | L14: 2 | M14: 2 | N14: 2 | O14: 2 | P14: 2 | Q14: 2 | R14: 2 | S14: 2 | T14: 2 | U14: 2 | V14: 2
B15: Horizontal | C15: Architecture Center of Expertise | D15: # | E15: 0 | F15: 1 | G15: 0 | H15: 0 | I15: 1 | J15: 0 | K15: 1 | L15: 1 | M15: 1 | N15: 1 | O15: 1 | P15: 1 | Q15: 1 | R15: 1 | S15: 1 | T15: 1 | U15: 1 | V15: 1
B16: Horizontal | C16: Architecture Center of Expertise | D16: Architecture Center of Expertise | E16: 0 | F16: 6 | G16: 0 | H16: 2 | I16: 6 | J16: 2 | K16: 6 | L16: 6 | M16: 7 | N16: 7 | O16: 7 | P16: 8 | Q16: 8 | R16: 8 | S16: 8 | T16: 8 | U16: 8 | V16: 8
B17: Horizontal | C17: International Reporting and MIS Department | D17: # | E17: 0 | F17: 1 | H17: 0 | I17: 1 | J17: 0 | K17: 1 | L17: 1 | M17: 1 | N17: 1 | O17: 1 | P17: 1 | Q17: 1 | R17: 1 | S17: 1 | T17: 1 | U17: 1 | V17: 1
B18: Horizontal | C18: International Reporting and MIS Department | D18: MIS Reporting | E18: 0 | F18: 4 | G18: 1 | H18: 0 | I18: 4 | J18: 0 | K18: 4 | L18: 4 | M18: 4 | N18: 4 | O18: 4 | P18: 4 | Q18: 5 | R18: 5 | S18: 5 | T18: 5 | U18: 5 | V18: 5
B19: Horizontal | C19: International Reporting and MIS Department | D19: IFRS Reporting | E19: 0 | F19: 2 | G19: 2 | H19: 4 | I19: 7 | J19: 0 | K19: 6 | L19: 6 | M19: 6 | N19: 6 | O19: 6 | P19: 6 | Q19: 7 | R19: 7 | S19: 7 | T19: 9 | U19: 9 | V19: 9
B20: Horizontal | C20: International Reporting and MIS Department | D20: Modelling, Valuation and Consolidated Reporting | E20: 0 | F20: 4 | G20: 0 | H20: 4 | I20: 6 | J20: 2 | K20: 7 | L20: 7 | M20: 7 | N20: 7 | O20: 7 | P20: 7 | Q20: 7 | R20: 7 | S20: 7 | T20: 7 | U20: 7 | V20: 7
B21: Horizontal | C21: BirApp Area | D21: # | E21: 0 | F21: 1 | G21: 0 | H21: 0 | I21: 1 | J21: 0 | K21: 1 | L21: 1 | M21: 1 | N21: 1 | O21: 1 | P21: 1 | Q21: 1 | R21: 1 | S21: 1 | T21: 1 | U21: 1 | V21: 1
B22: Horizontal | C22: BirApp Area | D22: Bir Enabler | E22: 0 | F22: 1 | G22: 0 | H22: 0 | I22: 1 | J22: 0 | K22: 1 | L22: 1 | M22: 1 | N22: 1 | O22: 1 | P22: 1 | Q22: 1 | R22: 1 | S22: 1 | T22: 1 | U22: 1 | V22: 1
B23: Horizontal | C23: BirApp Area | D23: Birbank Mainpage | E23: 0 | F23: 1 | G23: 0 | H23: 0 | I23: 1 | J23: 0 | K23: 1 | L23: 1 | M23: 1 | N23: 1 | O23: 1 | P23: 1 | Q23: 1 | R23: 1 | S23: 1 | T23: 1 | U23: 1 | V23: 1
B24: Horizontal | C24: BirApp Area | D24: Travel | E24: 0 | F24: 1 | G24: 0 | H24: 0 | I24: 1 | J24: 0 | K24: 0 | L24: 0 | M24: 0 | N24: 0 | O24: 0 | P24: 0 | Q24: 0 | R24: 0 | S24: 0 | T24: 0 | U24: 0 | V24: 0
B25: Horizontal | C25: BirApp Area | D25: Bir Search | E25: 0 | F25: 1 | G25: 0 | H25: 0 | I25: 1 | J25: 0 | K25: 1 | L25: 1 | M25: 1 | N25: 1 | O25: 1 | P25: 1 | Q25: 1 | R25: 1 | S25: 1 | T25: 1 | U25: 1 | V25: 1
B26: Horizontal | C26: BirApp Technology Area | D26: # | F26: 1 | I26: 1 | K26: 1 | L26: 1 | M26: 1 | N26: 1 | O26: 1 | P26: 1 | Q26: 1 | R26: 1 | S26: 1 | T26: 1 | U26: 1 | V26: 1
B27: Horizontal | C27: BirApp Technology Area | D27: Birbank Platform | E27: 0 | F27: 1 | G27: 0 | H27: 1 | I27: 1 | J27: 1 | K27: =I27 -> 1 | L27: =K27 -> 1 | M27: =L27 -> 1 | N27: =M27 -> 1 | O27: =N27 -> 1 | P27: =O27 -> 1 | Q27: =P27+J27 -> 2 | R27: =Q27 -> 2 | S27: =R27 -> 2 | T27: =S27 -> 2 | U27: =T27 -> 2 | V27: =U27 -> 2
B28: Horizontal | C28: BirApp Technology Area | D28: Birbank SRE | E28: 0 | F28: 0 | G28: 0 | H28: 0 | I28: 0 | J28: 0 | K28: 0 | L28: 0 | M28: 0 | N28: 0 | O28: 0 | P28: 0 | Q28: 0 | R28: 0 | S28: 0 | T28: 0 | U28: 0 | V28: 0
B29: Horizontal | C29: Data Governance Center of Expertise | D29: # | E29: 0 | F29: 1 | G29: 0 | H29: 0 | I29: 1 | J29: 0 | K29: 1 | L29: 1 | M29: 1 | N29: 1 | O29: 1 | P29: 1 | Q29: 1 | R29: 1 | S29: 1 | T29: 1 | U29: 1 | V29: 1
B30: Horizontal | C30: Data Governance Center of Expertise | D30: Data Process Management | E30: 0 | F30: 3 | G30: 0 | H30: 2 | I30: 3 | J30: 2 | K30: 3 | L30: 3 | M30: 4 | N30: 4 | O30: 5 | P30: 5 | Q30: 5 | R30: 5 | S30: 5 | T30: 5 | U30: 5 | V30: 5
B31: Horizontal | C31: Data Governance Center of Expertise | D31: Data Quality | E31: 0 | F31: 6 | G31: 0 | H31: 2 | I31: 6 | J31: 2 | K31: 6 | L31: 6 | M31: 6 | N31: 7 | O31: 7 | P31: 8 | Q31: 8 | R31: 8 | S31: 8 | T31: 8 | U31: 8 | V31: 8
B32: Horizontal | C32: Data Governance Center of Expertise | D32: Data Steward | E32: 0 | F32: 10 | G32: 0 | H32: 6 | I32: 10 | J32: 6 | K32: 10 | L32: 10 | M32: 12 | N32: 14 | O32: 14 | P32: 16 | Q32: 16 | R32: 16 | S32: 16 | T32: 16 | U32: 16 | V32: 16
B33: Horizontal | C33: Data mühəndisliyi və texnologiyaları ekspert mərkəzi | D33: # | E33: 0 | F33: 1 | G33: 0 | H33: 0 | I33: 1 | J33: 0 | K33: 1 | L33: =K33 -> 1 | M33: =L33 -> 1 | N33: =M33 -> 1 | O33: =N33 -> 1 | P33: =O33 -> 1 | Q33: =P33 -> 1 | R33: =Q33 -> 1 | S33: =R33 -> 1 | ... U33: =T33 -> 1 | V33: 1
B34: Horizontal | C34: Data mühəndisliyi və texnologiyaları ekspert mərkəzi | D34: Data engineering 1 | E34: 0 | F34: 6 | G34: 0 | H34: 1 | I34: 6 | J34: 1 | K34: 7 | L34: 7 | M34: 7 | N34: 7 | O34: 7 | P34: 7 | Q34: 7 | R34: 7 | S34: 7 | T34: 7 | U34: 7 | V34: 7
B35: Horizontal | C35: Data mühəndisliyi və texnologiyaları ekspert mərkəzi | D35: Data engineering 2 | E35: 0 | F35: 6 | G35: 1 | H35: 2 | I35: 6 | J35: 1 | K35: 7 | L35: 7 | M35: 7 | N35: 7 | O35: 7 | P35: 7 | Q35: 7 | R35: 7 | S35: 7 | T35: 7 | U35: 7 | V35: 7
B36: Horizontal | C36: Data mühəndisliyi və texnologiyaları ekspert mərkəzi | D36: Data engineering 3 | E36: 0 | F36: 5 | G36: 0 | H36: 1 | I36: 5 | J36: 1 | K36: 6 | L36: 6 | M36: 6 | N36: 6 | O36: 6 | P36: 6 | Q36: 6 | R36: 6 | S36: 6 | T36: 6 | U36: 6 | V36: 6
B37: Horizontal | C37: Data mühəndisliyi və texnologiyaları ekspert mərkəzi | D37: Data engineering 4 | E37: 0 | F37: 5 | G37: 0 | H37: 0 | I37: 5 | J37: 0 | K37: 5 | L37: 5 | M37: 5 | N37: 5 | O37: 5 | P37: 5 | Q37: 5 | R37: 5 | S37: 5 | T37: 5 | U37: 5 | V37: 5
B38: Horizontal | C38: Data və Analitika departamenti(Marketplace) | D38: Data Engineering | E38: 0 | F38: 4 | G38: 0 | H38: 0 | I38: 4 | J38: 0 | K38: 4 | L38: 4 | M38: 4 | N38: 4 | O38: 4 | P38: 4 | Q38: 4 | R38: 4 | S38: 4 | T38: 4 | U38: 4 | V38: 4
B39: Horizontal | C39: Design Center of Expertise | D39: # | E39: 0 | F39: 4 | G39: 0 | H39: 4 | I39: 7 | J39: 1 | K39: 0 | L39: 0 | M39: 0 | N39: 0 | O39: 0 | P39: 0 | Q39: 0 | R39: 0 | S39: 0 | T39: 0 | U39: 0 | V39: 8
B40: Horizontal | C40: Design Center of Expertise | D40: Product Designer 1 | E40: 0 | F40: 9 | G40: 1 | H40: 0 | I40: 9 | J40: 1 | K40: 0 | L40: 0 | M40: 0 | N40: 0 | O40: 0 | P40: 0 | Q40: 0 | R40: 0 | S40: 0 | T40: 0 | U40: 0 | V40: 10
B41: Horizontal | C41: Design Center of Expertise | D41: Graphic Design | E41: 0 | F41: 20 | G41: 0 | H41: 1 | I41: 20 | J41: 1 | K41: 0 | L41: 0 | M41: 0 | N41: 0 | O41: 0 | P41: 0 | Q41: 0 | R41: 0 | S41: 0 | T41: 0 | U41: 0 | V41: 21
B42: Horizontal | C42: Design Center of Expertise | D42: Product Designer 2 | E42: 0 | F42: 5 | G42: 0 | H42: 1 | I42: 5 | J42: 1 | K42: 0 | L42: 0 | M42: 0 | N42: 0 | O42: 0 | P42: 0 | Q42: 0 | R42: 0 | S42: 0 | T42: 0 | U42: 0 | V42: 6
B43: Horizontal | C43: Design Center of Expertise | D43: Product Designer 3 | E43: 0 | F43: 6 | G43: 0 | H43: 1 | I43: 6 | J43: 1 | K43: 0 | L43: 0 | M43: 0 | N43: 0 | O43: 0 | P43: 0 | Q43: 0 | R43: 0 | S43: 0 | T43: 0 | U43: 0 | V43: 7
B44: Horizontal | C44: Design Center of Expertise | D44: Product Designer 4 | E44: 0 | F44: 6 | G44: 0 | H44: 2 | I44: 7 | J44: 1 | K44: 0 | L44: 0 | M44: 0 | N44: 0 | O44: 0 | P44: 0 | Q44: 0 | R44: 0 | S44: 0 | T44: 0 | U44: 0 | V44: 8
B45: Horizontal | C45: Design Center of Expertise | D45: UX Researcher | E45: 0 | F45: 3 | G45: 0 | H45: 0 | I45: 3 | J45: 0 | K45: 0 | L45: 0 | M45: 0 | N45: 0 | O45: 0 | P45: 0 | Q45: 0 | R45: 0 | S45: 0 | T45: 0 | U45: 0 | V45: 3
... B50: Horizontal | C50: Legal Department | D50: # | E50: 0 | F50: 2 | G50: 0 | H50: 0 | I50: 2 | J50: 0 | K50: 2 | L50: 2 | M50: 2 | N50: 2 | O50: 2 | P50: 2 | Q50: 2 | R50: 2 | S50: 2 | T50: 2 | U50: 2 | V50: 2
B51: Horizontal | C51: Legal Department | D51: Litigation and Legal Support Division | E51: 0 | F51: 15 | G51: 0 | H51: 5.5 | I51: 15 | J51: 5.5 | K51: =I51+J51 -> 20.5 | L51: =K51 -> 20.5 | M51: =L51 -> 20.5 | N51: =M51 -> 20.5 | O51: =N51 -> 20.5 | P51: =O51 -> 20.5 | Q51: =P51 -> 20.5 | R51: =Q51 -> 20.5 | S51: =R51 -> 20.5 | ... V51: =U51 -> 20.5
B52: Horizontal | C52: Legal Department | D52: Payment Business Legal Support Division | E52: 0 | F52: 4 | G52: 0 | H52: 0 | I52: 4 | J52: 0 | K52: 4 | L52: 4 | M52: 4 | N52: 4 | O52: 4 | P52: 4 | Q52: 4 | R52: 4 | S52: 4 | T52: 4 | U52: 4 | V52: 4
B53: Horizontal | C53: Legal Department | D53: E-commerce Business Legal Support Division | E53: 0 | F53: 6 | G53: 0 | H53: 0 | I53: 6 | J53: 0 | K53: 6 | L53: 6 | M53: 6 | N53: 6 | O53: 6 | P53: 6 | Q53: 6 | R53: 6 | S53: 6 | T53: 6 | U53: 6 | V53: 6
B54: Horizontal | C54: Legal Department | D54: Archive Division | E54: 0 | F54: 12 | G54: 0 | H54: 0 | I54: 12 | J54: 0 | K54: 12 | L54: 12 | M54: 12 | N54: 12 | O54: 12 | P54: 12 | Q54: 12 | R54: 12 | S54: 12 | T54: 12 | U54: 12 | V54: 12
B55: Horizontal | C55: Legal Department | D55: Banking Products Legal Support Division | E55: 0 | F55: 10 | G55: 0 | H55: 0 | I55: 10 | J55: 0 | K55: 10 | L55: 10 | M55: 10 | N55: 10 | O55: 10 | P55: 10 | Q55: 10 | R55: 10 | S55: 10 | T55: 10 | U55: 10 | V55: 10
B56: Horizontal | C56: Legal Department | D56: Corporate Law and Corporate Governance Legal Support Division | E56: 0 | F56: 10 | G56: 0 | H56: 0 | I56: 10 | J56: 0 | K56: 10 | L56: 10 | M56: 10 | N56: 10 | O56: 10 | P56: 10 | Q56: 10 | R56: 10 | S56: 10 | T56: 10 | U56: 10 | V56: 10
B57: Horizontal | C57: Legal Department | D57: Methodology Division | E57: 0 | F57: 7 | G57: 2 | H57: 0 | I57: 7 | J57: 0 | K57: 7 | L57: 7 | M57: 7 | N57: 7 | O57: 7 | P57: 7 | Q57: 7 | R57: 7 | S57: 7 | T57: 7 | U57: 7 | V57: 7
B58: Horizontal | C58: Information Security Department | D58: # | E58: 0 | F58: 4 | G58: 0 | H58: 0 | I58: =F58 -> 4 | J58: 0 | K58: 4 | L58: 4 | M58: 4 | N58: 4 | O58: 4 | P58: 4 | Q58: 4 | R58: 4 | S58: 4 | T58: 4 | U58: 4 | V58: 4
B59: Horizontal | C59: Information Security Department | D59: Platform Security Division | E59: 0 | F59: 9.5 | G59: 0 | H59: 0 | I59: =F59 -> 9.5 | J59: 0 | K59: =I59 -> 9.5 | L59: =K59 -> 9.5 | M59: =L59 -> 9.5 | N59: =M59 -> 9.5 | O59: =N59 -> 9.5 | P59: =O59 -> 9.5 | Q59: =P59 -> 9.5 | R59: =Q59 -> 9.5 | S59: =R59 -> 9.5 | ... V59: =U59 -> 9.5
B60: Horizontal | C60: Information Security Department | D60: Network Security Division | E60: 0 | F60: 5 | G60: 0 | H60: 0 | I60: 5 | J60: 0 | K60: 5 | L60: 5 | M60: 5 | N60: 5 | O60: 5 | P60: 5 | Q60: 5 | R60: 5 | S60: 5 | T60: 5 | U60: 5 | V60: 5
B61: Horizontal | C61: Information Security Department | D61: Information Security GRC Division | E61: 0 | F61: 6 | G61: 0 | H61: 6 | I61: 8 | J61: 4 | K61: =I61+J61 -> 12 | L61: =K61 -> 12 | M61: =L61 -> 12 | N61: =M61 -> 12 | O61: =N61 -> 12 | P61: =O61 -> 12 | Q61: =P61 -> 12 | R61: =Q61 -> 12 | S61: =R61 -> 12 | ... V61: =U61 -> 12
B62: Horizontal | C62: Information Security Department | D62: Cyber Defense Division | E62: 0 | F62: 17 | G62: 0 | H62: 1 | I62: 18 | J62: 0 | K62: 18 | L62: 18 | M62: 18 | N62: 18 | O62: 18 | P62: 18 | Q62: 18 | R62: 18 | S62: 18 | T62: 18 | U62: 18 | V62: 18
B63: Horizontal | C63: Information Security Department | D63: Product Security Division | E63: 0 | F63: 10.5 | G63: 0 | H63: 3 | I63: 10.5 | J63: 3 | K63: =I63+J63 -> 13.5 | L63: =K63 -> 13.5 | M63: =L63 -> 13.5 | N63: =M63 -> 13.5 | O63: =N63 -> 13.5 | P63: =O63 -> 13.5 | Q63: =P63 -> 13.5 | R63: =Q63 -> 13.5 | S63: =R63 -> 13.5 | ... V63: =U63 -> 13.5
B64: Horizontal | C64: Information Security Department | D64: IT Risk Management Division | E64: 0 | F64: 4 | G64: 0 | H64: 0 | I64: 4 | J64: 0 | K64: =I64+J64 -> 4 | L64: =K64 -> 4 | M64: =L64 -> 4 | N64: =M64 -> 4 | O64: =N64 -> 4 | P64: =O64 -> 4 | Q64: =P64 -> 4 | R64: =Q64 -> 4 | S64: =R64 -> 4 | ... V64: =U64 -> 4
B65: Horizontal | C65: Administrative Management Department | D65: # | F65: 3 | G65: 0 | H65: 0 | I65: 3 | J65: 0 | K65: 3 | L65: 3 | M65: 3 | N65: 3 | O65: 3 | P65: 3 | Q65: 3 | R65: 3 | S65: 3 | T65: 3 | U65: 3 | V65: 3
B66: Horizontal | C66: Administrative Management Department | D66: Repair and Maintenance Division | E66: 0 | F66: 67 | G66: 1 | H66: 0 | I66: 67 | J66: 1 | K66: 68 | L66: 68 | M66: 68 | N66: 68 | O66: 68 | P66: 68 | Q66: 68 | R66: 68 | S66: 68 | T66: 68 | U66: 68 | V66: 68
B67: Horizontal | C67: Administrative Management Department | D67: Transport Division | E67: 0 | F67: 36 | G67: 1 | H67: 0 | I67: 36 | J67: 1 | K67: 37 | L67: 37 | M67: 37 | N67: 37 | O67: 37 | P67: 37 | Q67: 37 | R67: 37 | S67: 37 | T67: 37 | U67: 37 | V67: 37
B68: Horizontal | C68: Administrative Management Department | D68: Procurement and Supply Division | E68: 0 | F68: 27 | G68: 4 | H68: 0 | I68: 27 | J68: 4 | K68: 27 | L68: 27 | M68: 29 | N68: 30 | O68: 30 | P68: 30 | Q68: 30 | R68: 31 | S68: 31 | T68: 31 | U68: 31 | V68: 31
B69: Horizontal | C69: Administrative Management Department | D69: Administrative Operations Division | E69: 0 | F69: 23 | G69: 1 | H69: 0 | I69: 20 | J69: 1 | K69: 21 | L69: 21 | M69: 21 | N69: 21 | O69: 21 | P69: 21 | Q69: 21 | R69: 21 | S69: 21 | T69: 21 | U69: 21 | V69: 21
B70: Horizontal | C70: IT Infrastructure Department | D70: # | E70: 0 | F70: 2 | G70: 0 | H70: 0 | I70: 2 | J70: 0 | K70: 2 | L70: 2 | M70: 2 | N70: 2 | O70: 2 | P70: 2 | Q70: 2 | R70: 2 | S70: 2 | T70: 2 | U70: 2 | V70: 2
B71: Horizontal | C71: IT Infrastructure Department | D71: IT Access Management and Technical Support Division | E71: 0 | F71: 44 | G71: 0 | H71: 4 | I71: 48 | J71: 0 | K71: 48 | L71: 48 | M71: 48 | N71: 48 | O71: 48 | P71: 48 | Q71: 48 | R71: 48 | S71: 48 | T71: 48 | U71: 48 | V71: 48
B72: Horizontal | C72: IT Infrastructure Department | D72: IT Service Management Division | E72: 0 | F72: 5 | G72: 0 | H72: 1 | I72: 5 | J72: 1 | K72: 6 | L72: 6 | M72: 6 | N72: 6 | O72: 6 | P72: 6 | Q72: 6 | R72: 6 | S72: 6 | T72: 6 | U72: 6 | V72: 6
B73: Horizontal | C73: IT Infrastructure Department | D73: Network Operations Division | E73: 0 | F73: 13 | G73: 0 | H73: 3 | I73: 15 | J73: 1 | K73: 16 | L73: 16 | M73: 16 | N73: 16 | O73: 16 | P73: 16 | Q73: 16 | R73: 16 | S73: 16 | T73: 16 | U73: 16 | V73: 16
B74: Horizontal | C74: IT Infrastructure Department | D74: System and Network Administration Division | E74: 0 | F74: 18 | G74: 1 | H74: 2 | I74: 19 | J74: 1 | K74: 20 | L74: 20 | M74: 20 | N74: 20 | O74: 20 | P74: 20 | Q74: 20 | R74: 20 | S74: 20 | T74: 20 | U74: 20 | V74: 20
B75: Horizontal | C75: IT Infrastructure Department | D75: IT Service Monitoring and Incident Management Division | E75: 0 | F75: 7 | G75: 0 | H75: 0 | I75: 7 | J75: 0 | K75: 7 | L75: 7 | M75: 7 | N75: 7 | O75: 7 | P75: 7 | Q75: 7 | R75: 7 | S75: 7 | T75: 7 | U75: 7 | V75: 7
B76: Horizontal | C76: IT Process Management Functional Area | D76: IT Process Management Functional Area | E76: 0 | F76: 4 | G76: 0 | H76: 0 | I76: 4 | J76: 0 | K76: 4 | L76: 4 | M76: 4 | N76: 4 | O76: 4 | P76: 4 | Q76: 4 | R76: 4 | S76: 4 | T76: 4 | U76: 4 | V76: 4
B77: Horizontal | C77: Compliance Department | D77: # | E77: 0 | F77: 3 | G77: 0 | H77: 0 | I77: 3 | J77: 0 | K77: 3 | L77: 3 | M77: 3 | N77: 3 | O77: 3 | P77: 3 | Q77: 3 | R77: 3 | S77: 3 | T77: 3 | U77: 3 | V77: 3
... B80: Horizontal | C80: Compliance Department | D80: Compliance Reporting Division | E80: 0 | F80: 6 | G80: 0 | H80: 0 | I80: 6 | J80: 0 | K80: 6 | L80: 6 | M80: 6 | N80: 6 | O80: 6 | P80: 7 | Q80: 7 | R80: 7 | S80: 7 | T80: 7 | U80: 7 | V80: 7
B81: Horizontal | C81: Compliance Department | D81: Compliance Function Management Division | E81: 0 | F81: 6 | H81: 3 | I81: 6 | J81: 3 | K81: 9 | L81: 9 | M81: 9 | N81: 9 | O81: 9 | P81: 9 | Q81: 9 | R81: 9 | S81: 9 | T81: 9 | U81: 9 | V81: 9
B82: Horizontal | C82: Compliance Department | D82: Data and AI Compliance Control Division | E82: 0 | F82: 2 | G82: 0 | H82: 2 | I82: 4 | J82: 0 | K82: 4 | L82: 4 | M82: 4 | N82: 4 | O82: 4 | P82: 4 | Q82: 4 | R82: 4 | S82: 4 | T82: 4 | U82: 4 | V82: 4
B83: Horizontal | C83: Compliance Department | D83: Ecosystem Product and Process Compliance Support Division | E83: 0 | F83: 4 | G83: 0 | H83: 0 | I83: 4 | J83: 2 | K83: 6 | L83: 6 | M83: 6 | N83: 6 | O83: 7 | P83: 8 | Q83: 9 | R83: 9 | S83: 9 | T83: 9 | U83: 9 | V83: 9
B84: Horizontal | C84: Compliance Department | D84: Regulatory Compliance Division | E84: 0 | F84: 5 | G84: 0 | H84: 0 | I84: 5 | J84: 1 | K84: 6 | L84: 6 | M84: 6 | N84: 6 | O84: 6 | P84: 6 | Q84: 6 | R84: 6 | S84: 6 | T84: 6 | U84: 6 | V84: 6
B85: Horizontal | C85: Corporate Development and Investor Relations Department | D85: Director, Deputy Director | E85: 0 | F85: 1 | G85: 0 | H85: 0 | I85: 1 | J85: 0 | K85: 1 | L85: 1 | M85: 1 | N85: 1 | O85: 1 | P85: 1 | Q85: 1 | R85: 1 | S85: 1 | T85: 1 | U85: 1 | V85: 1
B86: Horizontal | C86: Corporate Development and Investor Relations Department | D86: # | E86: 0 | F86: 1 | G86: 0 | H86: 1 | I86: 2 | J86: 0 | K86: 2 | L86: 2 | M86: 2 | N86: 2 | O86: 2 | P86: 2 | Q86: 2 | R86: 2 | S86: 2 | T86: 2 | U86: 2 | V86: 2
A87: Kapital Bank | B87: Horizontal | C87: Financial Reporting and Accounting Department | D87: # | E87: 0 | F87: 4 | G87: 0 | H87: 0 | I87: 4 | J87: 0 | K87: 4 | L87: 4 | M87: 4 | N87: 4 | O87: 4 | P87: 4 | Q87: 4 | R87: 4 | S87: 4 | T87: 4 | U87: 4 | V87: 4
A88: Kapital Bank | B88: Horizontal | C88: Financial Reporting and Accounting Department | D88: Internal Accounting Division | E88: 0 | F88: 10 | G88: 0 | H88: 4 | I88: 14 | J88: 0 | K88: 14 | L88: 14 | M88: 14 | N88: 14 | O88: 14 | P88: 14 | Q88: 14 | R88: 14 | S88: 14 | T88: 14 | U88: 14 | V88: 14
A89: Kapital Bank | B89: Horizontal | C89: Financial Reporting and Accounting Department | D89: Regulatory Reporting Division | E89: 0 | F89: 7 | G89: 0 | H89: 1 | I89: 8 | J89: 0 | K89: 8 | L89: 8 | M89: 8 | N89: 8 | O89: 8 | P89: 8 | Q89: 8 | R89: 8 | S89: 8 | T89: 8 | U89: 8 | V89: 8
A90: Kapital Bank | B90: Horizontal | C90: Financial Reporting and Accounting Department | D90: Compensation Calculation Division | E90: 0 | F90: 5 | G90: 1 | H90: 0 | I90: 5 | J90: 0 | K90: 6 | L90: 6 | M90: 6 | N90: 6 | O90: 6 | P90: 6 | Q90: 6 | R90: 6 | S90: 6 | T90: 6 | U90: 6 | V90: 6
A91: Kapital Bank | B91: Horizontal | C91: Financial Reporting and Accounting Department | D91: Financial Control and Accounting Division | E91: 0 | F91: 10 | G91: 0 | H91: 0 | I91: 10 | J91: 0 | K91: 10 | L91: 10 | M91: 10 | N91: 10 | O91: 10 | P91: 10 | Q91: 10 | R91: 10 | S91: 10 | T91: 10 | U91: 10 | V91: 10
A92: PashaPay | B92: Horizontal | C92: Financial Reporting and Accounting Department | D92: Accounting Division | E92: 0 | F92: 8 | G92: 2 | H92: 0 | I92: 8 | J92: 0 | K92: 11 | L92: 11 | M92: 11 | N92: 11 | O92: 11 | P92: 11 | Q92: 11 | R92: 11 | S92: 11 | T92: 11 | U92: 11 | V92: 11
A93: Competo | B93: Horizontal | C93: Financial Reporting and Accounting Department | D93: # | E93: 0 | F93: 1 | G93: 0 | H93: 0 | I93: 1 | J93: 0 | K93: 1 | L93: 1 | M93: 1 | N93: 1 | O93: 1 | P93: 1 | Q93: 1 | R93: 1 | S93: 1 | T93: 1 | U93: 1 | V93: 1
A94: Competo | B94: Horizontal | C94: Financial Reporting and Accounting Department | D94: Operations Accounting and Processing Division | E94: 0 | F94: 11 | G94: 0 | H94: 0 | I94: 11 | J94: 0 | K94: 11 | L94: 11 | M94: 11 | N94: 11 | O94: 11 | P94: 11 | Q94: 11 | R94: 11 | S94: 11 | T94: 11 | U94: 11 | V94: 11
A95: Competo | B95: Horizontal | C95: Financial Reporting and Accounting Department | D95: Administrative Accounting and Taxation Division | E95: 0 | F95: 7 | G95: 0 | H95: 0 | I95: 7 | J95: 0 | K95: 7 | L95: 7 | M95: 7 | N95: 7 | O95: 7 | P95: 7 | Q95: 7 | R95: 7 | S95: 7 | T95: 7 | U95: 7 | V95: 7
A96: Competo | B96: Horizontal | C96: Financial Reporting and Accounting Department | D96: Payments Management Division | E96: 0 | F96: 3 | G96: 1 | H96: 0 | I96: 3 | J96: 0 | K96: 4 | L96: 4 | M96: 4 | N96: 4 | O96: 4 | P96: 4 | Q96: 4 | R96: 4 | S96: 4 | T96: 4 | U96: 4 | V96: 4
A97: Competo | B97: Horizontal | C97: Financial Reporting and Accounting Department | D97: Expense Control Division | E97: 0 | F97: 2 | G97: 0 | H97: 0 | I97: 2 | J97: 0 | K97: 2 | L97: 2 | M97: 2 | N97: 2 | O97: 2 | P97: 2 | Q97: 2 | R97: 2 | S97: 2 | T97: 2 | U97: 2 | V97: 2
B98: Horizontal | C98: Marketing Center of Expertise | D98: # | E98: 0 | F98: 3 | G98: 0 | H98: 0 | I98: 3 | J98: 0 | K98: 0 | L98: 0 | M98: 0 | N98: 0 | O98: 0 | P98: 0 | Q98: 0 | R98: 0 | S98: 0 | T98: 0 | U98: 0 | V98: 3
B99: Horizontal | C99: Marketing Center of Expertise | D99: Public Relations Process | E99: 0 | F99: 3 | G99: 0 | H99: 0 | I99: 3 | J99: 0 | K99: 0 | L99: 0 | M99: 0 | N99: 0 | O99: 0 | P99: 0 | Q99: 0 | R99: 0 | S99: 0 | T99: 0 | U99: 0 | V99: 3
B100: Horizontal | C100: Marketing Center of Expertise | D100: Marketing Communications Process | E100: 0 | F100: 14 | G100: 0 | H100: 0 | I100: 14 | J100: 0 | K100: 0 | L100: 0 | M100: 0 | N100: 0 | O100: 0 | P100: 0 | Q100: 0 | R100: 0 | S100: 0 | T100: 0 | U100: 0 | V100: 14
B101: Horizontal | C101: Marketing Center of Expertise | D101: Product Marketing Process | E101: 0 | F101: 22 | G101: 0 | H101: 2 | I101: 22 | J101: 2 | K101: 0 | L101: 0 | M101: 0 | N101: 0 | O101: 0 | P101: 0 | Q101: 0 | R101: 0 | S101: 0 | T101: 0 | U101: 0 | V101: 24
B102: Horizontal | C102: Marketing Center of Expertise | D102: Digital Marketing Process | E102: 0 | F102: 41 | G102: 0 | H102: 8 | I102: 46 | J102: 3 | K102: 0 | L102: 0 | M102: 0 | N102: 0 | O102: 0 | P102: 0 | Q102: 0 | R102: 0 | S102: 0 | T102: 0 | U102: 0 | V102: 49
B103: Horizontal | C103: Model Risk Management Center of Expertise | D103: Model Validation Chapter | E103: 0 | F103: 6 | G103: 0 | H103: 1 | I103: 6 | J103: 1 | K103: 8 | L103: 8 | M103: 8 | N103: 8 | O103: 8 | P103: 8 | Q103: 8 | R103: 8 | S103: 8 | T103: 8 | U103: 8 | V103: 8
B104: Horizontal | C104: Model Risk Management Center of Expertise | D104: MRM Chapter | E104: 0 | F104: 2 | G104: 0 | H104: 0 | I104: 2 | J104: 0 | K104: 3 | L104: 3 | M104: 3 | N104: 3 | O104: 3 | P104: 3 | Q104: 3 | R104: 3 | S104: 3 | T104: 3 | U104: 3 | V104: 3
B105: Horizontal | C105: Model Risk Management Center of Expertise | D105: # | E105: 0 | F105: 3 | G105: 0 | H105: 0 | I105: 3 | J105: 0 | K105: 4 | L105: 4 | M105: 4 | N105: 4 | O105: 4 | P105: 4 | Q105: 4 | R105: 4 | S105: 4 | T105: 4 | U105: 4 | V105: 4
B106: Horizontal | C106: Engineering and Technology Platforms Center of Expertise | D106: # | E106: 0 | F106: 1 | G106: 0 | H106: 0 | I106: 1 | J106: 0 | K106: 0 | L106: 0 | M106: 0 | N106: 0 | O106: 0 | P106: 0 | Q106: 0 | R106: 0 | S106: 0 | T106: 0 | U106: 0 | V106: =I106+J106 -> 1
...

Sheet Full list (horizontal)
B2: Company | C2: Full name | E2: Department | F2: Division | G2: Position | H2: Status
B3: Kapital Bank | C3: Ağayeva Aysel Babakişi | E3: Korporativ katiblik şöbəsi | F3: Korporativ katiblik şöbəsi | G3: Şöbə müdiri | H3: HR listinde var
B4: Kapital Bank | C4: Bayramova Aynur Zirəddin | E4: Korporativ katiblik şöbəsi | F4: Korporativ katiblik şöbəsi | G4: Korporativ katib | H4: HR listinde var
B5: Kapital Bank | C5: Qasımlı Nəsibə Etibar | E5: Korporativ katiblik şöbəsi | F5: Korporativ katiblik şöbəsi | G5: Aparıcı mütəxəssis | H5: HR listinde var
B6: Kapital Bank | C6: Vəliyeva Nəsrin İsmayıl | E6: Korporativ katiblik şöbəsi | F6: Korporativ katiblik şöbəsi | G6: Aparıcı mütəxəssis | H6: HR listinde var
B7: Kapital Bank | C7: Əliyeva Lalə Sənan | E7: Korporativ katiblik şöbəsi | F7: Korporativ katiblik şöbəsi | G7: Mütəxəssis | H7: HR listinde var
B8: Kapital Bank | C8: Ağayeva Xanım Çingiz | E8: Korporativ katiblik şöbəsi | F8: Korporativ katiblik şöbəsi | G8: Mütəxəssis | H8: HR listinde var
B9: Kapital Bank | C9: Teymurzadə Səma Bəylər | E9: Korporativ katiblik şöbəsi | F9: Korporativ katiblik şöbəsi | G9: Mütəxəssis | H9: HR listinde var
B10: Kapital Bank | C10: Abdullayeva Leyla Rüstəm | E10: Korporativ katiblik şöbəsi | F10: Korporativ katiblik şöbəsi | G10: Mütəxəssis | H10: HR listinde var
B11: Kapital Bank | C11: Mehdiyeva Fərəh Şahin | E11: Korporativ katiblik şöbəsi | F11: Korporativ katiblik şöbəsi | G11: Şəxsi köməkçi | H11: HR listinde var
B12: Kapital Bank | C12: Hacıyev Anar Nadir | E12: Korporativ katiblik şöbəsi | F12: Korporativ katiblik şöbəsi | G12: Şəxsi köməkçi | H12: HR listinde var
B13: Kapital Bank | C13: Tağıyeva Elnarə Əli | E13: Korporativ katiblik şöbəsi | F13: Korporativ katiblik şöbəsi | G13: Şəxsi köməkçi | H13: HR listinde var
... B18: Kapital Bank | C18: İsmayılova Şükufə Muxalif | E18: Korporativ katiblik şöbəsi | F18: Korporativ katiblik şöbəsi | G18: Şəxsi köməkçi | H18: HR listinde var
B19: Future Lab | C19: Məmmədova Xumar Elşən | D19: =VLOOKUP(C19,'[1]Birbank İşçi Siyahı'!$B:$I,8,) -> Future lab | E19: Korporativ katiblik şöbəsi | F19: Korporativ katiblik şöbəsi | G19: Şəxsi köməkçi | H19: HR listinde var
B20: Kapital Bank | C20: Yahyayeva Emiliya Rasim | E20: Korporativ katiblik şöbəsi | F20: Korporativ katiblik şöbəsi | G20: Şəxsi köməkçi | H20: HR listinde var
B21: Kapital Bank | C21: Məmmədova Nərgiz Aydın | E21: Korporativ katiblik şöbəsi | F21: Korporativ katiblik şöbəsi | G21: Şəxsi köməkçi | H21: HR listinde var
B22: Kapital Bank | C22: Vəlili İranə İlmas | E22: Korporativ katiblik şöbəsi | F22: Korporativ katiblik şöbəsi | G22: Şəxsi köməkçi | H22: HR listinde var
B23: Kapital Bank | C23: Məmmədova Fidan Tahir | E23: Korporativ katiblik şöbəsi | F23: Korporativ katiblik şöbəsi | G23: Şəxsi köməkçi (əvəzçilik qaydasında) | H23: HR listinde var
B24: Kapital Bank | C24: Kərimova Mehparə Məmmədsadıq | E24: Korporativ katiblik şöbəsi | F24: Korporativ katiblik şöbəsi | G24: Menecer | H24: HR listinde var
B25: Kapital Bank | C25: Rzayeva Ülkər Bəhram | E25: Korporativ katiblik şöbəsi | F25: Korporativ katiblik şöbəsi | G25: Aparıcı mütəxəssis | H25: HR listinde var
B26: Kapital Bank | C26: Məmmədova Ramilə Vaqif | E26: Korporativ katiblik şöbəsi | F26: Korporativ katiblik şöbəsi | G26: Aparıcı mütəxəssis | H26: HR listinde var
B27: Kapital Bank | C27: Səfərli Vüsalə Novruz | E27: Korporativ katiblik şöbəsi | F27: Korporativ katiblik şöbəsi | G27: Aparıcı mütəxəssis | H27: HR listinde var
B28: Kapital Bank | C28: Aslanlı Tərlan Yusif | E28: Korporativ katiblik şöbəsi | F28: Korporativ katiblik şöbəsi | G28: Mütəxəssis | H28: HR listinde var
B29: Kapital Bank | C29: İsmayılova Aysel Qələmdar | E29: Korporativ katiblik şöbəsi | F29: Korporativ katiblik şöbəsi | G29: Mütəxəssis | H29: HR listinde var
B30: Kapital Bank | C30: Şeydayeva Ceyla Zəki | E30: Korporativ katiblik şöbəsi | F30: Korporativ katiblik şöbəsi | G30: Mütəxəssis | H30: HR listinde var
B31: Kapital Bank | C31: Raşimov Süleyman Rafik | E31: Korporativ katiblik şöbəsi | F31: Korporativ katiblik şöbəsi | G31: Mütəxəssis | H31: HR listinde var
... B36: Competo | C36: Əliyeva Sona Azad | E36: Korporativ katiblik şöbəsi | F36: Korporativ katiblik şöbəsi | G36: Reception (Rəsmiləşmə mərhələsində) | H36: HR listinde yox idi
B37: Kapital Bank | C37: Kərimova Gülnar Sahib | D37: =VLOOKUP(C37,'[1]Birbank İşçi Siyahı'!$B:$I,8,) -> #N/A | E37: Korporativ katiblik şöbəsi | F37: Korporativ katiblik şöbəsi | G37: Şəxsi köməkçi | H37: HR listinde yox idi
B38: Kapital Bank | C38: Qarayeva Melisa İsmayil | D38: =VLOOKUP(C38,'[1]Birbank İşçi Siyahı'!$B:$I,8,) -> #N/A | E38: Korporativ katiblik şöbəsi | F38: Korporativ katiblik şöbəsi | G38: Şəxsi köməkçi | H38: Staff listində yoxdur
B39: Kapital Bank | C39: Nuri Şahnaz Səməd | E39: Agile və məhsul ekspert mərkəzi | F39: Agile və məhsul ekspert mərkəzi | G39: Funksional sahə lideri | H39: HR listinde var
B40: Kapital Bank | C40: Səidova Samirə Balasultan | E40: Agile və məhsul ekspert mərkəzi | F40: Agile və məhsul ekspert mərkəzi | G40: Funksional lider | H40: HR listinde var
B41: Kapital Bank | C41: Qurbanova Fatma Xasməmməd | E41: Agile və məhsul ekspert mərkəzi | F41: Agile və məhsul ekspert mərkəzi | G41: Proseslər üzrə ekspert | H41: HR listinde var
B42: Pashapay | C42: BARANOVSKAYA SVETLANA | D42: =VLOOKUP(C42,'[1]Birbank İşçi Siyahı'!$B:$I,8,) -> Bir Payment | E42: Agile və məhsul ekspert mərkəzi | F42: Agile və məhsul ekspert mərkəzi | G42: Agile kouç | H42: HR listinde var
B43: Kapital Bank | C43: Əlizadə Turqut Elşən | E43: Agile və məhsul ekspert mərkəzi | F43: Agile və məhsul ekspert mərkəzi | G43: Scrum master | H43: HR listinde var
B44: Pashapay | C44: Adilzadə Aysu Elnur | D44: =VLOOKUP(C44,'[1]Birbank İşçi Siyahı'!$B:$I,8,) -> Bir Payment | E44: Agile və məhsul ekspert mərkəzi | F44: Agile və məhsul ekspert mərkəzi | G44: Scrum master | H44: HR listinde var
B45: Kapital Bank | C45: FOMINA MARIIA | D45: =VLOOKUP(C45,'[1]Birbank İşçi Siyahı'!$B:$I,8,) -> #N/A | E45: Agile və məhsul ekspert mərkəzi | F45: Agile və məhsul ekspert mərkəzi | G45: Agile kouç | H45: HR listinde var
B46: Kapital Bank | C46: Əhmədov Azər Qabil | E46: Agile və məhsul ekspert mərkəzi | F46: Agile və məhsul ekspert mərkəzi | G46: Scrum master | H46: HR listinde var
B47: Kapital Bank | C47: Musayeva Səmanə Kəmaləddin | E47: Agile və məhsul ekspert mərkəzi | F47: Agile və məhsul ekspert mərkəzi | G47: Proseslər üzrə ekspert | H47: HR listinde var
B48: Kapital Bank | C48: Əkbərova Vəsilə Vidadi | E48: Agile və məhsul ekspert mərkəzi | F48: Agile və məhsul ekspert mərkəzi | G48: Scrum master(müvəqqəti) | H48: HR listinde var
B49: Kapital Bank | C49: Şirinov Azər Qafar | E49: Agile və məhsul ekspert mərkəzi | F49: Agile və məhsul ekspert mərkəzi | G49: Agile kouç | H49: HR listinde var
B50: Kapital Bank | C50: Həsənov Ramin Cabir | E50: Agile və məhsul ekspert mərkəzi | F50: Agile və məhsul ekspert mərkəzi | G50: Agile kouç | H50: HR listinde var
B51: Kapital Bank | C51: Fərəcova Sevinc Taleh | E51: Agile və məhsul ekspert mərkəzi | F51: Agile və məhsul ekspert mərkəzi | G51: Agile kouç | H51: HR listinde var
B52: Kapital Bank | C52: Surxayzadə Leyla Nizami | E52: Agile və məhsul ekspert mərkəzi | F52: Agile və məhsul ekspert mərkəzi | G52: Agile kouç | H52: HR listinde var
B53: Kapital Bank | C53: Ağayeva Mənsurə Şahmalı | E53: Agile və məhsul ekspert mərkəzi | F53: Agile və məhsul ekspert mərkəzi | G53: Scrum master | H53: HR listinde var
B54: Kapital Bank | C54: İslamova Zərifə Elçin | E54: Agile və məhsul ekspert mərkəzi | F54: Agile və məhsul ekspert mərkəzi | G54: Scrum master | H54: HR listinde var
B55: Kapital Bank | C55: Səmədzadə Günel Səyavuş | E55: Agile və məhsul ekspert mərkəzi | F55: Agile və məhsul ekspert mərkəzi | G55: Scrum master | H55: HR listinde var
B56: Kapital Bank | C56: İsgəndərova Aysel Xəyyam | E56: Agile və məhsul ekspert mərkəzi | F56: Agile və məhsul ekspert mərkəzi | G56: Scrum master | H56: HR listinde var
B57: Kapital Bank | C57: Qasımzadə Aydın Məmmədhəsən | E57: Agile və məhsul ekspert mərkəzi | F57: Agile və məhsul ekspert mərkəzi | G57: Agile kouç | H57: HR listinde var
... B66: Kapital Bank | C66: İsayev İsa Hafiz | E66: Aİ governance ekspert mərkəzi | F66: Aİ governance ekspert mərkəzi | G66: Biznes analitik | H66: HR listinde var
B67: Future Lab | C67: Məmmədzadə Elnarə Vüqar | D67: =VLOOKUP(C67,'[1]Birbank İşçi Siyahı'!$B:$I,8,) -> Future lab | E67: Aİ governance ekspert mərkəzi | F67: Aİ governance ekspert mərkəzi | G67: Aİ governance üzrə baş mütəxəssis | H67: HR listinde var
B68: Kapital Bank | C68: Süleymanova Lalə Baxış | E68: Aİ governance ekspert mərkəzi | F68: Aİ governance ekspert mərkəzi | G68: Biznes analitik | H68: HR listinde var
B69: Kapital Bank | C69: XXX Aygül Fəxrəddin | E69: Aİ governance ekspert mərkəzi | F69: Aİ governance ekspert mərkəzi | G69: Biznes analitik (müvəqqəti) | H69: HR listinde var
B70: Kapital Bank | C70: Ramazanova Faina Faiq | E70: Aİ governance ekspert mərkəzi | F70: Aİ governance ekspert mərkəzi | G70: Biznes analitik | H70: HR listinde var
B71: Kapital Bank | C71: Zeynal Bayramova Aysel Mahir | E71: Aİ governance ekspert mərkəzi | F71: Aİ governance ekspert mərkəzi | G71: Biznes analitik | H71: HR listinde var
B72: Kapital Bank | C72: Qurbanlı Nəzrin Rəşad | E72: Aİ governance ekspert mərkəzi | F72: Aİ governance ekspert mərkəzi | G72: Biznes analitik | H72: HR listinde var
B73: Kapital Bank | C73: Tağıyev Əli Baba | E73: Aİ governance ekspert mərkəzi | F73: Aİ governance ekspert mərkəzi | G73: Biznes analitik | H73: HR listinde var
B74: Kapital Bank | C74: Georgiy Davidov | D74: =VLOOKUP(C74,'[1]Birbank İşçi Siyahı'!$B:$I,8,) -> #N/A | E74: Architecture Center of Expertise | F74: Architecture Center of Expertise | G74: Centre Lead | H74: HR listinde var
B75: Kapital Bank | C75: Sviatoslav Murzin | D75: =VLOOKUP(C75,'[1]Birbank İşçi Siyahı'!$B:$I,8,) -> #N/A | E75: Architecture Center of Expertise | F75: Architecture Center of Expertise | G75: Corporate Architect | H75: HR listinde var
B76: Kapital Bank | C76: Andrey Kulikov | D76: =VLOOKUP(C76,'[1]Birbank İşçi Siyahı'!$B:$I,8,) -> #N/A | E76: Architecture Center of Expertise | F76: Architecture Center of Expertise | G76: Corporate Architect | H76: HR listinde var
B77: Kapital Bank | C77: Timur Muminov | D77: =VLOOKUP(C77,'[1]Birbank İşçi Siyahı'!$B:$I,8,) -> #N/A | E77: Architecture Center of Expertise | F77: Architecture Center of Expertise | G77: Corporate Architect | H77: HR listinde var
B78: Kapital Bank | C78: Rafi Rahimov | D78: =VLOOKUP(C78,'[1]Birbank İşçi Siyahı'!$B:$I,8,) -> #N/A | E78: Architecture Center of Expertise | F78: Architecture Center of Expertise | G78: Corporate Architect | H78: HR listinde var
B79: Kapital Bank | C79: Ivan Perov | D79: =VLOOKUP(C79,'[1]Birbank İşçi Siyahı'!$B:$I,8,) -> #N/A | E79: Architecture Center of Expertise | F79: Architecture Center of Expertise | G79: Corporate Architect | H79: HR listinde var
B80: Kapital Bank | C80: Elcin Qasimov | D80: =VLOOKUP(C80,'[1]Birbank İşçi Siyahı'!$B:$I,8,) -> #N/A | E80: Architecture Center of Expertise | F80: Architecture Center of Expertise | G80: Corporate Architect | H80: HR listinde var
B81: Kapital Bank | C81: Məmmədyarov Şakir Nazim | E81: Beynəlxalq hesabatlıq və MİS departamenti | F81: # | G81: Direktor v.i.e. | H81: HR listinde var
B82: Kapital Bank | C82: Əliyev Azər Azad | E82: Beynəlxalq hesabatlıq və MİS departamenti | F82: Modelləşdirmə,Qiymətləndirmə və Konsolidasiya olunmuş Hesabatliq | G82: Şöbə müdiri | H82: HR listinde var
B83: Kapital Bank | C83: Mustafazadə Novruz Anatoliy | E83: Beynəlxalq hesabatlıq və MİS departamenti | F83: MİS hesabatlıq | G83: Menecer | H83: HR listinde var
B84: Kapital Bank | C84: Hüseynova Fidan Ziyəddin | E84: Beynəlxalq hesabatlıq və MİS departamenti | F84: MİS hesabatlıq | G84: Aparıcı mütəxəssis | H84: HR listinde var
B85: Kapital Bank | C85: Süleymanzadə Rəşad Süleyman | E85: Beynəlxalq hesabatlıq və MİS departamenti | F85: MİS hesabatlıq | G85: Aparıcı mütəxəssis | H85: HR listinde var
B86: Kapital Bank | C86: Axundova Mayya Fuad | E86: Beynəlxalq hesabatlıq və MİS departamenti | F86: MİS hesabatlıq | G86: Aparıcı mütəxəssis | H86: HR listinde var
B87: Kapital Bank | C87: Rəfiyeva Rəna İmrəddinovna | E87: Beynəlxalq hesabatlıq və MİS departamenti | F87: İFRS hesabatlıq | G87: Menecer | H87: HR listinde var
B88: Kapital Bank | C88: Abdullayev Rauf Həsənağa | E88: Beynəlxalq hesabatlıq və MİS departamenti | F88: İFRS hesabatlıq | G88: Menecer | H88: HR listinde var
B89: Kapital Bank | C89: İskəndərova Səma Müsədin | E89: Beynəlxalq hesabatlıq və MİS departamenti | F89: İFRS hesabatlıq | G89: Baş mütəxəssis | H89: HR listinde var
B90: Kapital Bank | C90: Eyvazov Ülvi Sahib | E90: Beynəlxalq hesabatlıq və MİS departamenti | F90: Modelləşdirmə,Qiymətləndirmə və Konsolidasiya olunmuş Hesabatliq | G90: Menecer | H90: HR listinde var
B91: Kapital Bank | C91: Əlizadə Ləman Rəşad | E91: Beynəlxalq hesabatlıq və MİS departamenti | F91: Modelləşdirmə,Qiymətləndirmə və Konsolidasiya olunmuş Hesabatliq | G91: Baş mütəxəssis | H91: HR listinde var
B92: Kapital Bank | C92: Məmmədov Şahin Hümmət | E92: Beynəlxalq hesabatlıq və MİS departamenti | F92: İFRS hesabatlıq | G92: Baş mütəxəssis | H92: HR listinde var
... B102: Kapital Bank | C102: Scope increase | E102: Beynəlxalq hesabatlıq və MİS departamenti | F102: İFRS hesabatlıq | G102: Menecer / Şöbə müdiri | H102: HR listinde yox idi
B103: Kapital Bank | C103: Cabbarova Nigar | D103: =VLOOKUP(C103,'[1]Birbank İşçi Siyahı'!$B:$I,8,) -> #N/A | E103: BirApp | F103: # | G103: Tribe lead | H103: HR listinde var
B104: Kapital Bank | C104: Alıyeva Tahirə | D104: =VLOOKUP(C104,'[1]Birbank İşçi Siyahı'!$B:$I,8,) -> #N/A | E104: BirApp | F104: Birbank Mainpage | G104: Product owner | H104: HR listinde var
B105: Kapital Bank | C105: Kazımova Səidə | D105: =VLOOKUP(C105,'[1]Birbank İşçi Siyahı'!$B:$I,8,) -> #N/A | E105: BirApp | F105: BirSearch | G105: Product owner | H105: HR listinde var
B106: Kapital Bank | C106: Əlili Ləman | D106: =VLOOKUP(C106,'[1]Birbank İşçi Siyahı'!$B:$I,8,) -> #N/A | E106: BirApp | F106: Travel | G106: Product owner | H106: HR listinde var
B107: Kapital Bank | C107: Tağızadə Səbinə | D107: =VLOOKUP(C107,'[1]Birbank İşçi Siyahı'!$B:$I,8,) -> #N/A | E107: BirApp | F107: BirEnablers | G107: Product owner | H107: HR listinde var
B108: Kapital Bank | C108: JAMALOV SHAMIL | E108: BirApp | F108: # | G108: Tribe tech Lead | H108: Staff listində yoxdur
B109: Kapital Bank | C109: SHATUNOV MAKSIM | E109: BirApp Techonology | F109: Birbank Platform | G109: Tribe lead | H109: HR listinde var
B110: Kapital Bank | C110: Rəcəbova Samirə Fuad | E110: BirApp Techonology | F110: Birbank Platform | G110: PO | H110: HR listinde var
B111: Kapital Bank | C111: Cəfərov Renad Feyzulla | E111: Data Governance Center of Expertise | F111: # | G111: Head of Center of Expertise | H111: HR listinde var
B112: Kapital Bank | C112: Hacıyeva Aytən Firdovsi | E112: Data Governance Center of Expertise | F112: Data Process Management | G112: Data Methodology Expert | H112: HR listinde var
B113: Kapital Bank | C113: Lətifova Fidan Rüfət | E113: Data Governance Center of Expertise | F113: Data Process Management | G113: Data Methodology Expert | H113: HR listinde var
B114: Competo | C114: Asayev Camal Artur | D114: =VLOOKUP(C114,'[1]Birbank İşçi Siyahı'!$B:$I,8,) -> BirMarket | E114: Data Governance Center of Expertise | F114: Data Process Management | G114: Data Governance Analyst | H114: HR listinde var
B115: Kapital Bank | C115: Bağırov Azər Məzahir | D115: =VLOOKUP(C115,'[1]Birbank İşçi Siyahı'!$B:$I,8,) -> #N/A | E115: Data Governance Center of Expertise | F115: Data Quality | G115: Functional Lead | H115: HR listinde yox idi
B116: Kapital Bank | C116: Qasımzadə Murad İlham | E116: Data Governance Center of Expertise | F116: Data Quality | G116: Data Quality Engineer | H116: HR listinde var
B117: Kapital Bank | C117: Ağayeva Möhtərəm Sədrəddin | E117: Data Governance Center of Expertise | F117: Data Quality | G117: Data Quality Engineer | H117: HR listinde var
B118: Kapital Bank | C118: Fərzali Güllər Sadiq | E118: Data Governance Center of Expertise | F118: Data Quality | G118: Data Quality Engineer | H118: HR listinde var
B119: Competo | C119: Müzəffərli Tural Zakir | D119: =VLOOKUP(C119,'[1]Birbank İşçi Siyahı'!$B:$I,8,) -> BirMarket | E119: Data Governance Center of Expertise | F119: Data Quality | G119: Data Quality Engineer | H119: HR listinde var
B120: Competo | C120: Sərkarov Ayxan Məhəmməd | D120: =VLOOKUP(C120,'[1]Birbank İşçi Siyahı'!$B:$I,8,) -> BirMarket | E120: Data Governance Center of Expertise | F120: Data Quality | G120: Data Quality Engineer | H120: HR listinde var
B121: Kapital Bank | C121: Eyvazlı Xavər İntiqam | E121: Data Governance Center of Expertise | F121: Data Steward | G121: Functional Lead | H121: HR listinde var
B122: Kapital Bank | C122: ONYSHCHENKO ANASTASİİA | D122: =VLOOKUP(C122,'[1]Birbank İşçi Siyahı'!$B:$I,8,) -> #N/A | E122: Data Governance Center of Expertise | F122: Data Steward | G122: Functional Lead | H122: HR listinde yox idi
B123: Kapital Bank | C123: Abbasov Devid Yavər | E123: Data Governance Center of Expertise | F123: Data Steward | G123: Data Governance Analyst | H123: HR listinde var
B124: Kapital Bank | C124: Zeynallı Rəisə Uğur | E124: Data Governance Center of Expertise | F124: Data Steward | G124: Data Governance Analyst | H124: HR listinde var
B125: Kapital Bank | C125: Əsgərova Şəbnəm Ramil | E125: Data Governance Center of Expertise | F125: Data Steward | G125: Data Governance Analyst | H125: HR listinde var
B126: Kapital Bank | C126: Süleymanova Nuranə Şikar | E126: Data Governance Center of Expertise | F126: Data Steward | G126: Data Governance Analyst | H126: HR listinde var
...
